Workbook

Sheet HOME
A2: Tipo | B2: Capital | C2: Peso(%) | D2: Peso Ideal | F2: Selic
A3: Ações Nacionais | B3: =SUM(Ações_Nacionais[Financeiro]) -> 40893 | C3: =IFERROR((B3/$B$9), 0) -> 0.30647591 | D3: 0.45 | F3: =Indicadores!J3 -> 0.139
A4: FIIs | B4: =SUM(Fiis[Financeiro]) -> 51728 | C4: =IFERROR((B4/$B$9), 0) -> 0.3876797 | D4: 0.25 | F4: IPCA
A5: Renda_Fixa | B5: =SUM(Renda_Fixa[Financeiro]) -> 29920.864 | C5: =IFERROR((B5/$B$9), 0) -> 0.22424435 | D5: 0.12 | F5: =Indicadores!J4 -> 0.044430246
A6: Etfs | B6: =SUM(Etfs[financeiro]) -> 5747.3049 | C6: =IFERROR((B6/$B$9), 0) -> 0.043073644 | D6: 0.14
A7: Tesouro Renda | B7: =SUM(Tesouro[Financeiro]) -> 1908.4273 | C7: =IFERROR((B7/$B$9), 0) -> 0.014302864 | D7: 0.02
A8: Cripto | B8: =SUM(Cripto[financeiro]) -> 3232.1384 | C8: =IFERROR((B8/$B$9), 0) -> 0.024223524 | D8: 0.02
A9: Capital | B9: =SUM(B3:B8) -> 133429.73 | C9: =SUM(C3:C8) -> 1 | D9: =SUM(D3:D8) -> 1
A21: QTD | B21: Ação | C21: Peso | D21: Nota | E21: Peso Ideal | F21: Financeiro | G21: Fluxo_De_Caixa | H21: Margen_Seg | I21: Barato | J21: Margen | K21: Preço mercado | L21: Bazin | M21: DY | N21: DY Barato | O21: DPA | P21: Total
A22: 100 | B22: BBAS3 | C22: =IFERROR((F22/$B$9), 0) -> 0.013812513 | D22: 10 | E22: =(D22/SUM(Ações_Nacionais[Nota]))*$D$3 -> 0.0375 | F22: =A22*K22 -> 1843 | G22: =IFERROR(__xludf.DUMMYFUNCTION("IFERROR(QUERY(IMPORTRANGE(""https://docs.google.com/spreadsheets/d/1ujByqR8S8LRZ2kRtkvuCwCRPYw31ta3JdfXYcMP7NC4/edit?usp=sharing"", ""Indicadores_Ações!A30:B""), ""SELECT Col2 WHERE Col1 = '""&B22 &""'"", 0), 0)"),24.63079005370153) -> 24.63079 | H22: 0.2 | I22: =G22*(1-H22) -> 19.704632 | J22: =1-(K22/G22) -> 0.25174954 | K22: =IFERROR(__xludf.DUMMYFUNCTION("(GOOGLEFINANCE(""BVMF:"" & B22))"),18.43) -> 18.43 | L22: =O22/N22 -> 16.920824 | M22: =O22/K22 -> 0.055086786 | N22: 0.06 | O22: {=IFERROR(INDEX(DPA[], MATCH(B22, DPA[Ação], 0), MATCH(DPA[[#HEADERS],[Media_DPA_3Anos]], DPA[#HEADERS], 0)),"")} -> 1.0152495 | P22: =O22*A22 -> 101.52495
A23: 100 | B23: ITSA4 | C23: =IFERROR((F23/$B$9), 0) -> 0.0093682267 | D23: 10 | E23: =(D23/SUM(Ações_Nacionais[Nota]))*$D$3 -> 0.0375 | F23: =A23*K23 -> 1250 | G23: =IFERROR(__xludf.DUMMYFUNCTION("IFERROR(QUERY(IMPORTRANGE(""https://docs.google.com/spreadsheets/d/1ujByqR8S8LRZ2kRtkvuCwCRPYw31ta3JdfXYcMP7NC4/edit?usp=sharing"", ""Indicadores_Ações!A30:B""), ""SELECT Col2 WHERE Col1 = '""&B23 &""'"", 0), 0)"),15.042719947244418) -> 15.04272 | H23: 0.17 | I23: =G23*(1-H23) -> 12.485458 | J23: =1-(K23/G23) -> 0.16903326 | K23: =IFERROR(__xludf.DUMMYFUNCTION("(GOOGLEFINANCE(""BVMF:"" & B23))"),12.5) -> 12.5 | L23: =O23/N23 -> 10.454975 | M23: =O23/K23 -> 0.083639797 | N23: 0.1 | O23: {=IFERROR(INDEX(DPA[], MATCH(B23, DPA[Ação], 0), MATCH(DPA[[#HEADERS],[Media_DPA_3Anos]], DPA[#HEADERS], 0)),"")} -> 1.0454975 | P23: =O23*A23 -> 104.54975
A24: 100 | B24: BRBI11 | C24: =IFERROR((F24/$B$9), 0) -> 0.0091059163 | D24: 0 | E24: =(D24/SUM(Ações_Nacionais[Nota]))*$D$3 -> 0 | F24: =A24*K24 -> 1215 | G24: =IFERROR(__xludf.DUMMYFUNCTION("IFERROR(QUERY(IMPORTRANGE(""https://docs.google.com/spreadsheets/d/1ujByqR8S8LRZ2kRtkvuCwCRPYw31ta3JdfXYcMP7NC4/edit?usp=sharing"", ""Indicadores_Ações!A30:B""), ""SELECT Col2 WHERE Col1 = '""&B24 &""'"", 0), 0)"),14.327743339727128) -> 14.327743 | H24: 0.2 | I24: =G24*(1-H24) -> 11.462195 | J24: =1-(K24/G24) -> 0.15199486 | K24: =IFERROR(__xludf.DUMMYFUNCTION("(GOOGLEFINANCE(""BVMF:"" & B24))"),12.15) -> 12.15 | L24: =O24/N24 -> 15.5 | M24: =O24/K24 -> 0.15308642 | N24: 0.12 | O24: {=IFERROR(INDEX(DPA[], MATCH(B24, DPA[Ação], 0), MATCH(DPA[[#HEADERS],[Media_DPA_3Anos]], DPA[#HEADERS], 0)),"")} -> 1.86 | P24: =O24*A24 -> 186
A25: 100 | B25: ITUB4 | C25: =IFERROR((F25/$B$9), 0) -> 0.028929084 | D25: 10 | E25: =(D25/SUM(Ações_Nacionais[Nota]))*$D$3 -> 0.0375 | F25: =A25*K25 -> 3860 | G25: =IFERROR(__xludf.DUMMYFUNCTION("IFERROR(QUERY(IMPORTRANGE(""https://docs.google.com/spreadsheets/d/1ujByqR8S8LRZ2kRtkvuCwCRPYw31ta3JdfXYcMP7NC4/edit?usp=sharing"", ""Indicadores_Ações!A30:B""), ""SELECT Col2 WHERE Col1 = '""&""ITUB3"" &""'"", 0), 0)"),43.47196062603119) -> 43.471961 | H25: 0.15 | I25: =G25*(1-H25) -> 36.951167 | J25: =1-(K25/G25) -> 0.11207133 | K25: =IFERROR(__xludf.DUMMYFUNCTION("(GOOGLEFINANCE(""BVMF:"" & B25))"),38.6) -> 38.6 | L25: =O25/N25 -> 33.549067 | M25: =O25/K25 -> 0.086914683 | N25: 0.1 | O25: {=IFERROR(INDEX(DPA[], MATCH("ITUB3", DPA[Ação], 0), MATCH(DPA[[#HEADERS],[Media_DPA_3Anos]], DPA[#HEADERS], 0)),"")} -> 3.3549068 | P25: =O25*A25 -> 335.49068
A26: 100 | B26: PETR4 | C26: =IFERROR((F26/$B$9), 0) -> 0.033200995 | D26: 10 | E26: =(D26/SUM(Ações_Nacionais[Nota]))*$D$3 -> 0.0375 | F26: =A26*K26 -> 4430 | G26: =IFERROR(__xludf.DUMMYFUNCTION("IFERROR(QUERY(IMPORTRANGE(""https://docs.google.com/spreadsheets/d/1ujByqR8S8LRZ2kRtkvuCwCRPYw31ta3JdfXYcMP7NC4/edit?usp=sharing"", ""Indicadores_Ações!A30:B""), ""SELECT Col2 WHERE Col1 = '""&B26 &""'"", 0), 0)"),49.6828752076028) -> 49.682875 | H26: 0.2 | I26: =G26*(1-H26) -> 39.7463 | J26: =1-(K26/G26) -> 0.10834468 | K26: =IFERROR(__xludf.DUMMYFUNCTION("(GOOGLEFINANCE(""BVMF:"" & B26))"),44.3) -> 44.3 | L26: =O26/N26 -> 29.760672 | M26: =O26/K26 -> 0.067179846 | N26: 0.1 | O26: {=IFERROR(INDEX(DPA[], MATCH(B26, DPA[Ação], 0), MATCH(DPA[[#HEADERS],[Media_DPA_3Anos]], DPA[#HEADERS], 0)),"")} -> 2.9760672 | P26: =O26*A26 -> 297.60672
A27: 100 | B27: SAPR4 | C27: =IFERROR((F27/$B$9), 0) -> 0.0048265104 | D27: 10 | E27: =(D27/SUM(Ações_Nacionais[Nota]))*$D$3 -> 0.0375 | F27: =A27*K27 -> 644 | G27: =IFERROR(__xludf.DUMMYFUNCTION("IFERROR(QUERY(IMPORTRANGE(""https://docs.google.com/spreadsheets/d/1ujByqR8S8LRZ2kRtkvuCwCRPYw31ta3JdfXYcMP7NC4/edit?usp=sharing"", ""Indicadores_Ações!A30:B""), ""SELECT Col2 WHERE Col1 = '""&B27 &""'"", 0), 0)"),7.22573807968191) -> 7.2257381 | H27: 0.1 | I27: =G27*(1-H27) -> 6.5031643 | J27: =1-(K27/G27) -> 0.10874157 | K27: =IFERROR(__xludf.DUMMYFUNCTION("(GOOGLEFINANCE(""BVMF:"" & B27))"),6.44) -> 6.44 | L27: =O27/N27 -> 6.9076165 | M27: =O27/K27 -> 0.045049673 | N27: 0.042 | O27: {=IFERROR(INDEX(DPA[], MATCH(B27, DPA[Ação], 0), MATCH(DPA[[#HEADERS],[Media_DPA_3Anos]], DPA[#HEADERS], 0)),"")} -> 0.29011989 | P27: =O27*A27 -> 29.011989
A28: 100 | B28: CMIG4 | C28: =IFERROR((F28/$B$9), 0) -> 0.0075245597 | D28: 10 | E28: =(D28/SUM(Ações_Nacionais[Nota]))*$D$3 -> 0.0375 | F28: =A28*K28 -> 1004 | G28: =IFERROR(__xludf.DUMMYFUNCTION("IFERROR(QUERY(IMPORTRANGE(""https://docs.google.com/spreadsheets/d/1ujByqR8S8LRZ2kRtkvuCwCRPYw31ta3JdfXYcMP7NC4/edit?usp=sharing"", ""Indicadores_Ações!A30:B""), ""SELECT Col2 WHERE Col1 = '""&B28 &""'"", 0), 0)"),11.027542743522044) -> 11.027543 | H28: 0.17 | I28: =G28*(1-H28) -> 9.1528605 | J28: =1-(K28/G28) -> 0.089552384 | K28: =IFERROR(__xludf.DUMMYFUNCTION("(GOOGLEFINANCE(""BVMF:"" & B28))"),10.04) -> 10.04 | L28: =O28/N28 -> 10.560523 | M28: =O28/K28 -> 0.13148061 | N28: 0.125 | O28: {=IFERROR(INDEX(DPA[], MATCH(B28, DPA[Ação], 0), MATCH(DPA[[#HEADERS],[Media_DPA_3Anos]], DPA[#HEADERS], 0)),"")} -> 1.3200653 | P28: =O28*A28 -> 132.00653
A29: 100 | B29: BBSE3 | C29: =IFERROR((F29/$B$9), 0) -> 0.027872348 | D29: 10 | E29: =(D29/SUM(Ações_Nacionais[Nota]))*$D$3 -> 0.0375 | F29: =A29*K29 -> 3719 | G29: =IFERROR(__xludf.DUMMYFUNCTION("IFERROR(QUERY(IMPORTRANGE(""https://docs.google.com/spreadsheets/d/1ujByqR8S8LRZ2kRtkvuCwCRPYw31ta3JdfXYcMP7NC4/edit?usp=sharing"", ""Indicadores_Ações!A30:B""), ""SELECT Col2 WHERE Col1 = '""&B29 &""'"", 0), 0)"),40.20978014310791) -> 40.20978 | H29: 0.15 | I29: =G29*(1-H29) -> 34.178313 | J29: =1-(K29/G29) -> 0.075100638 | K29: =IFERROR(__xludf.DUMMYFUNCTION("(GOOGLEFINANCE(""BVMF:"" & B29))"),37.19) -> 37.19 | L29: =O29/N29 -> 34.236045 | M29: =O29/K29 -> 0.092057125 | N29: 0.1 | O29: {=IFERROR(INDEX(DPA[], MATCH(B29, DPA[Ação], 0), MATCH(DPA[[#HEADERS],[Media_DPA_3Anos]], DPA[#HEADERS], 0)),"")} -> 3.4236045 | P29: =O29*A29 -> 342.36045
A30: 100 | B30: ITUB3 | C30: =IFERROR((F30/$B$9), 0) -> 0.031020072 | D30: 10 | E30: =(D30/SUM(Ações_Nacionais[Nota]))*$D$3 -> 0.0375 | F30: =A30*K30 -> 4139 | G30: =IFERROR(__xludf.DUMMYFUNCTION("IFERROR(QUERY(IMPORTRANGE(""https://docs.google.com/spreadsheets/d/1ujByqR8S8LRZ2kRtkvuCwCRPYw31ta3JdfXYcMP7NC4/edit?usp=sharing"", ""Indicadores_Ações!A30:B""), ""SELECT Col2 WHERE Col1 = '""&B30 &""'"", 0), 0)"),43.47196062603119) -> 43.471961 | H30: 0.15 | I30: =G30*(1-H30) -> 36.951167 | J30: =1-(K30/G30) -> 0.047892034 | K30: =IFERROR(__xludf.DUMMYFUNCTION("(GOOGLEFINANCE(""BVMF:"" & B30))"),41.39) -> 41.39 | L30: =O30/N30 -> 33.549067 | M30: =O30/K30 -> 0.081055974 | N30: 0.1 | O30: {=IFERROR(INDEX(DPA[], MATCH(B30, DPA[Ação], 0), MATCH(DPA[[#HEADERS],[Media_DPA_3Anos]], DPA[#HEADERS], 0)),"")} -> 3.3549068 | P30: =O30*A30 -> 335.49068
A31: 100 | B31: VALE3 | C31: =IFERROR((F31/$B$9), 0) -> 0.056231844 | D31: 10 | E31: =(D31/SUM(Ações_Nacionais[Nota]))*$D$3 -> 0.0375 | F31: =A31*K31 -> 7503 | G31: =IFERROR(__xludf.DUMMYFUNCTION("IFERROR(QUERY(IMPORTRANGE(""https://docs.google.com/spreadsheets/d/1ujByqR8S8LRZ2kRtkvuCwCRPYw31ta3JdfXYcMP7NC4/edit?usp=sharing"", ""Indicadores_Ações!A30:B""), ""SELECT Col2 WHERE Col1 = '""&B31 &""'"", 0), 0)"),66.68989552863204) -> 66.689896 | H31: 0.2 | I31: =G31*(1-H31) -> 53.351916 | J31: =1-(K31/G31) -> -0.12505799 | K31: =IFERROR(__xludf.DUMMYFUNCTION("(GOOGLEFINANCE(""BVMF:"" & B31))"),75.03) -> 75.03 | L31: =O31/N31 -> 60.299977 | M31: =O31/K31 -> 0.080367822 | N31: 0.1 | O31: {=IFERROR(INDEX(DPA[], MATCH(B31, DPA[Ação], 0), MATCH(DPA[[#HEADERS],[Media_DPA_3Anos]], DPA[#HEADERS], 0)),"")} -> 6.0299977 | P31: =O31*A31 -> 602.99977
A32: 100 | B32: WEGE3 | C32: =IFERROR((F32/$B$9), 0) -> 0.036925802 | D32: 10 | E32: =(D32/SUM(Ações_Nacionais[Nota]))*$D$3 -> 0.0375 | F32: =A32*K32 -> 4927 | G32: =IFERROR(__xludf.DUMMYFUNCTION("IFERROR(QUERY(IMPORTRANGE(""https://docs.google.com/spreadsheets/d/1ujByqR8S8LRZ2kRtkvuCwCRPYw31ta3JdfXYcMP7NC4/edit?usp=sharing"", ""Indicadores_Ações!A30:B""), ""SELECT Col2 WHERE Col1 = '""&B32 &""'"", 0), 0)"),43.463711792231344) -> 43.463712 | H32: 0.18 | I32: =G32*(1-H32) -> 35.640244 | J32: =1-(K32/G32) -> -0.13358933 | K32: =IFERROR(__xludf.DUMMYFUNCTION("(GOOGLEFINANCE(""BVMF:"" & B32))"),49.27) -> 49.27 | L32: =O32/N32 -> 38.830538 | M32: =O32/K32 -> 0.031524691 | N32: 0.04 | O32: {=IFERROR(INDEX(DPA[], MATCH(B32, DPA[Ação], 0), MATCH(DPA[[#HEADERS],[Media_DPA_3Anos]], DPA[#HEADERS], 0)),"")} -> 1.5532215 | P32: =O32*A32 -> 155.32215
A33: 100 | B33: ISAE4 | C33: =IFERROR((F33/$B$9), 0) -> 0.019500901 | D33: 10 | E33: =(D33/SUM(Ações_Nacionais[Nota]))*$D$3 -> 0.0375 | F33: =A33*K33 -> 2602 | G33: =IFERROR(__xludf.DUMMYFUNCTION("IFERROR(QUERY(IMPORTRANGE(""https://docs.google.com/spreadsheets/d/1ujByqR8S8LRZ2kRtkvuCwCRPYw31ta3JdfXYcMP7NC4/edit?usp=sharing"", ""Indicadores_Ações!A30:B""), ""SELECT Col2 WHERE Col1 = '""&B33 &""'"", 0), 0)"),22.856505078982625) -> 22.856505 | H33: 0.1 | I33: =G33*(1-H33) -> 20.570855 | J33: =1-(K33/G33) -> -0.13840676 | K33: =IFERROR(__xludf.DUMMYFUNCTION("(GOOGLEFINANCE(""BVMF:"" & B33))"),26.02) -> 26.02 | L33: =O33/N33 -> 23.334489 | M33: =O33/K33 -> 0.089679051 | N33: 0.1 | O33: {=IFERROR(INDEX(DPA[], MATCH(B33, DPA[Ação], 0), MATCH(DPA[[#HEADERS],[Media_DPA_3Anos]], DPA[#HEADERS], 0)),"")} -> 2.3334489 | P33: =O33*A33 -> 233.34489
A34: 100 | B34: TAEE11 | C34: =IFERROR((F34/$B$9), 0) -> 0.028157142 | D34: 10 | E34: =(D34/SUM(Ações_Nacionais[Nota]))*$D$3 -> 0.0375 | F34: =A34*K34 -> 3757 | G34: =IFERROR(__xludf.DUMMYFUNCTION("IFERROR(QUERY(IMPORTRANGE(""https://docs.google.com/spreadsheets/d/1ujByqR8S8LRZ2kRtkvuCwCRPYw31ta3JdfXYcMP7NC4/edit?usp=sharing"", ""Indicadores_Ações!A30:B""), ""SELECT Col2 WHERE Col1 = '""&B34 &""'"", 0), 0)"),31.145258480966675) -> 31.145258 | H34: 0.1 | I34: =G34*(1-H34) -> 28.030733 | J34: =1-(K34/G34) -> -0.20628313 | K34: =IFERROR(__xludf.DUMMYFUNCTION("(GOOGLEFINANCE(""BVMF:"" & B34))"),37.57) -> 37.57 | L34: =O34/N34 -> 37.356548 | M34: =O34/K34 -> 0.079545484 | N34: 0.08 | O34: {=IFERROR(INDEX(DPA[], MATCH(B34, DPA[Ação], 0), MATCH(DPA[[#HEADERS],[Media_DPA_3Anos]], DPA[#HEADERS], 0)),"")} -> 2.9885238 | P34: =O34*A34 -> 298.85238
A51: QTD | B51: Fii | C51: Peso | D51: Nota | E51: Peso Ideal | F51: Financeiro | G51: Preço mercado | H51: Barato | I51: VP/Cota | J51: Justo | K51: Div/12 | L51: LPC 3 anos | M51: Rend_Cota | N51: Rendimento_Total | O51: Spread | P51: IPCA | Q51: Taxa_Total | R51: P/M | S51: Financeiro_P/M
A52: 50 | B52: LVBI11 | C52: =IFERROR((F52/$B$9), 0) -> 0.036907066 | D52: 10 | E52: =(D52/SUM(Fiis[Nota]))*$D$4 -> 0.022727273 | F52: =A52*G52 -> 4924.5 | G52: =IFERROR(__xludf.DUMMYFUNCTION("GOOGLEFINANCE(B52)"),98.49) -> 98.49 | H52: =G52/I52 -> 0.81761581 | I52: =IFERROR(__xludf.DUMMYFUNCTION("IFERROR(QUERY(IMPORTRANGE(""16ctS2M9RWvjMVkO6L0BV75dNPXE73e0O2aKZF1Q8mU8"", ""Indicadores!A2:E""), ""SELECT Col2 WHERE Col1 = '""&B52 &""'"", 0), 0)"),120.46) -> 120.46 | J52: =SUM(L52/Q52) -> 92.192334 | K52: =L52/12 -> 0.75 | L52: 9 | M52: =A52*K52 -> 37.5 | N52: =IFERROR(M52*12,0) -> 450 | O52: 0.02 | P52: =$F$91 -> 0.0761 | Q52: =IFERROR((1+O52) * (1+P52)-1, 0) -> 0.097622 | R52: 104.65 | S52: =R52*A52 -> 5232.5
A53: 50 | B53: GGRC11 | C53: =IFERROR((F53/$B$9), 0) -> 0.0033950453 | D53: 10 | E53: =(D53/SUM(Fiis[Nota]))*$D$4 -> 0.022727273 | F53: =A53*G53 -> 453 | G53: =IFERROR(__xludf.DUMMYFUNCTION("GOOGLEFINANCE(B53)"),9.06) -> 9.06 | H53: =G53/I53 -> 0.82139619 | I53: =IFERROR(__xludf.DUMMYFUNCTION("IFERROR(QUERY(IMPORTRANGE(""16ctS2M9RWvjMVkO6L0BV75dNPXE73e0O2aKZF1Q8mU8"", ""Indicadores!A2:E""), ""SELECT Col2 WHERE Col1 = '""&B53 &""'"", 0), 0)"),11.03) -> 11.03 | J53: =SUM(L53/Q53) -> 10.245178 | K53: =L53/12 -> 0.096666667 | L53: {=IFERROR(INDEX(LCP_3Anos[], MATCH(B53, LCP_3Anos[Fii], 0), MATCH(LCP_3Anos[[#HEADERS],[Media_DPA_3Anos]], LCP_3Anos[#HEADERS], 0)),"")} -> 1.16 | M53: =A53*K53 -> 4.8333333 | N53: =IFERROR(M53*12,0) -> 58 | O53: 0.03 | P53: =$F$90 -> 0.0808 | Q53: =IFERROR((1+O53) * (1+P53)-1, 0) -> 0.113224 | R53: 10.01 | S53: =R53*A53 -> 500.5
A54: 50 | B54: XPLG11 | C54: =IFERROR((F54/$B$9), 0) -> 0.033725616 | D54: 10 | E54: =(D54/SUM(Fiis[Nota]))*$D$4 -> 0.022727273 | F54: =A54*G54 -> 4500 | G54: =IFERROR(__xludf.DUMMYFUNCTION("GOOGLEFINANCE(B54)"),90.0) -> 90 | H54: =G54/I54 -> 0.85510689 | I54: =IFERROR(__xludf.DUMMYFUNCTION("IFERROR(QUERY(IMPORTRANGE(""16ctS2M9RWvjMVkO6L0BV75dNPXE73e0O2aKZF1Q8mU8"", ""Indicadores!A2:E""), ""SELECT Col2 WHERE Col1 = '""&B54 &""'"", 0), 0)"),105.25) -> 105.25 | J54: =SUM(L54/Q54) -> 96.904386 | K54: =L54/12 -> 0.78833333 | L54: {=IFERROR(INDEX(LCP_3Anos[], MATCH(B54, LCP_3Anos[Fii], 0), MATCH(LCP_3Anos[[#HEADERS],[Media_DPA_3Anos]], LCP_3Anos[#HEADERS], 0)),"")} -> 9.46 | M54: =A54*K54 -> 39.416667 | N54: =IFERROR(M54*12,0) -> 473 | O54: 0.02 | P54: =$F$91 -> 0.0761 | Q54: =IFERROR((1+O54) * (1+P54)-1, 0) -> 0.097622 | R54: 93.43 | S54: =R54*A54 -> 4671.5
A55: 50 | B55: GARE11 | C55: =IFERROR((F55/$B$9), 0) -> 0.0030840202 | D55: 10 | E55: =(D55/SUM(Fiis[Nota]))*$D$4 -> 0.022727273 | F55: =A55*G55 -> 411.5 | G55: =IFERROR(__xludf.DUMMYFUNCTION("GOOGLEFINANCE(B55)"),8.23) -> 8.23 | H55: =G55/I55 -> 0.88781014 | I55: =IFERROR(__xludf.DUMMYFUNCTION("IFERROR(QUERY(IMPORTRANGE(""16ctS2M9RWvjMVkO6L0BV75dNPXE73e0O2aKZF1Q8mU8"", ""Indicadores!A2:E""), ""SELECT Col2 WHERE Col1 = '""&B55 &""'"", 0), 0)"),9.27) -> 9.27 | J55: =SUM(L55/Q55) -> 8.4787678 | K55: =L55/12 -> 0.08 | L55: {=IFERROR(INDEX(LCP_3Anos[], MATCH(B55, LCP_3Anos[Fii], 0), MATCH(LCP_3Anos[[#HEADERS],[Media_DPA_3Anos]], LCP_3Anos[#HEADERS], 0)),"")} -> 0.96 | M55: =A55*K55 -> 4 | N55: =IFERROR(M55*12,0) -> 48 | O55: 0.03 | P55: =$F$90 -> 0.0808 | Q55: =IFERROR((1+O55) * (1+P55)-1, 0) -> 0.113224 | R55: 8.54 | S55: =R55*A55 -> 427
A56: 50 | B56: PMLL11 | C56: =IFERROR((F56/$B$9), 0) -> 0.037783932 | D56: 10 | E56: =(D56/SUM(Fiis[Nota]))*$D$4 -> 0.022727273 | F56: =A56*G56 -> 5041.5 | G56: =IFERROR(__xludf.DUMMYFUNCTION("GOOGLEFINANCE(B56)"),100.83) -> 100.83 | H56: =G56/I56 -> 0.86423245 | I56: =IFERROR(__xludf.DUMMYFUNCTION("IFERROR(QUERY(IMPORTRANGE(""16ctS2M9RWvjMVkO6L0BV75dNPXE73e0O2aKZF1Q8mU8"", ""Indicadores!A2:E""), ""SELECT Col2 WHERE Col1 = '""&B56 &""'"", 0), 0)"),116.67) -> 116.67 | J56: =SUM(L56/Q56) -> 102.19691 | K56: =L56/12 -> 0.83138889 | L56: {=IFERROR(INDEX(LCP_3Anos[], MATCH(B56, LCP_3Anos[Fii], 0), MATCH(LCP_3Anos[[#HEADERS],[Media_DPA_3Anos]], LCP_3Anos[#HEADERS], 0)),"")} -> 9.9766667 | M56: =A56*K56 -> 41.569444 | N56: =IFERROR(M56*12,0) -> 498.83333 | O56: 0.02 | P56: =$F$91 -> 0.0761 | Q56: =IFERROR((1+O56) * (1+P56)-1, 0) -> 0.097622 | R56: 99.15 | S56: =R56*A56 -> 4957.5
A57: 50 | B57: BTLG11 | C57: =IFERROR((F57/$B$9), 0) -> 0.036862098 | D57: 10 | E57: =(D57/SUM(Fiis[Nota]))*$D$4 -> 0.022727273 | F57: =A57*G57 -> 4918.5 | G57: =IFERROR(__xludf.DUMMYFUNCTION("GOOGLEFINANCE(B57)"),98.37) -> 98.37 | H57: =G57/I57 -> 0.96064453 | I57: =IFERROR(__xludf.DUMMYFUNCTION("IFERROR(QUERY(IMPORTRANGE(""16ctS2M9RWvjMVkO6L0BV75dNPXE73e0O2aKZF1Q8mU8"", ""Indicadores!A2:E""), ""SELECT Col2 WHERE Col1 = '""&B57 &""'"", 0), 0)"),102.4) -> 102.4 | J57: =SUM(L57/Q57) -> 100.31638 | K57: =L57/12 -> 0.77111111 | L57: {=IFERROR(INDEX(LCP_3Anos[], MATCH(B57, LCP_3Anos[Fii], 0), MATCH(LCP_3Anos[[#HEADERS],[Media_DPA_3Anos]], LCP_3Anos[#HEADERS], 0)),"")} -> 9.2533333 | M57: =A57*K57 -> 38.555556 | N57: =IFERROR(M57*12,0) -> 462.66667 | O57: 0.015 | P57: =$F$91 -> 0.0761 | Q57: =IFERROR((1+O57) * (1+P57)-1, 0) -> 0.0922415 | R57: 97.58 | S57: =R57*A57 -> 4879
A58: 50 | B58: HGBS11 | C58: =IFERROR((F58/$B$9), 0) -> 0.0069699606 | D58: 10 | E58: =(D58/SUM(Fiis[Nota]))*$D$4 -> 0.022727273 | F58: =A58*G58 -> 930 | G58: =IFERROR(__xludf.DUMMYFUNCTION("GOOGLEFINANCE(B58)"),18.6) -> 18.6 | H58: =G58/I58 -> 0.91265947 | I58: =IFERROR(__xludf.DUMMYFUNCTION("IFERROR(QUERY(IMPORTRANGE(""16ctS2M9RWvjMVkO6L0BV75dNPXE73e0O2aKZF1Q8mU8"", ""Indicadores!A2:E""), ""SELECT Col2 WHERE Col1 = '""&B58 &""'"", 0), 0)"),20.38) -> 20.38 | J58: =SUM(L58/Q58) -> 19.053082 | K58: =L58/12 -> 0.155 | L58: {=IFERROR(INDEX(LCP_3Anos[], MATCH(B58, LCP_3Anos[Fii], 0), MATCH(LCP_3Anos[[#HEADERS],[Media_DPA_3Anos]], LCP_3Anos[#HEADERS], 0)),"")} -> 1.86 | M58: =A58*K58 -> 7.75 | N58: =IFERROR(M58*12,0) -> 93 | O58: 0.02 | P58: =$F$91 -> 0.0761 | Q58: =IFERROR((1+O58) * (1+P58)-1, 0) -> 0.097622 | R58: 18.42 | S58: =R58*A58 -> 921
A59: 50 | B59: BRCO11 | C59: =IFERROR((F59/$B$9), 0) -> 0.041909699 | D59: 10 | E59: =(D59/SUM(Fiis[Nota]))*$D$4 -> 0.022727273 | F59: =A59*G59 -> 5592 | G59: =IFERROR(__xludf.DUMMYFUNCTION("GOOGLEFINANCE(B59)"),111.84) -> 111.84 | H59: =G59/I59 -> 0.96647079 | I59: =IFERROR(__xludf.DUMMYFUNCTION("IFERROR(QUERY(IMPORTRANGE(""16ctS2M9RWvjMVkO6L0BV75dNPXE73e0O2aKZF1Q8mU8"", ""Indicadores!A2:E""), ""SELECT Col2 WHERE Col1 = '""&B59 &""'"", 0), 0)"),115.72) -> 115.72 | J59: =SUM(L59/Q59) -> 110.72384 | K59: =L59/12 -> 0.85111111 | L59: {=IFERROR(INDEX(LCP_3Anos[], MATCH(B59, LCP_3Anos[Fii], 0), MATCH(LCP_3Anos[[#HEADERS],[Media_DPA_3Anos]], LCP_3Anos[#HEADERS], 0)),"")} -> 10.213333 | M59: =A59*K59 -> 42.555556 | N59: =IFERROR(M59*12,0) -> 510.66667 | O59: 0.015 | P59: =$F$91 -> 0.0761 | Q59: =IFERROR((1+O59) * (1+P59)-1, 0) -> 0.0922415 | R59: 100.45 | S59: =R59*A59 -> 5022.5
A60: 50 | B60: HGRU11 | C60: =IFERROR((F60/$B$9), 0) -> 0.043090095 | D60: 10 | E60: =(D60/SUM(Fiis[Nota]))*$D$4 -> 0.022727273 | F60: =A60*G60 -> 5749.5 | G60: =IFERROR(__xludf.DUMMYFUNCTION("GOOGLEFINANCE(B60)"),114.99) -> 114.99 | H60: =G60/I60 -> 0.89208689 | I60: =IFERROR(__xludf.DUMMYFUNCTION("IFERROR(QUERY(IMPORTRANGE(""16ctS2M9RWvjMVkO6L0BV75dNPXE73e0O2aKZF1Q8mU8"", ""Indicadores!A2:E""), ""SELECT Col2 WHERE Col1 = '""&B60 &""'"", 0), 0)"),128.9) -> 128.9 | J60: =SUM(L60/Q60) -> 116.77696 | K60: =L60/12 -> 0.95 | L60: {=IFERROR(INDEX(LCP_3Anos[], MATCH(B60, LCP_3Anos[Fii], 0), MATCH(LCP_3Anos[[#HEADERS],[Media_DPA_3Anos]], LCP_3Anos[#HEADERS], 0)),"")} -> 11.4 | M60: =A60*K60 -> 47.5 | N60: =IFERROR(M60*12,0) -> 570 | O60: 0.02 | P60: =$F$91 -> 0.0761 | Q60: =IFERROR((1+O60) * (1+P60)-1, 0) -> 0.097622 | R60: 120 | S60: =R60*A60 -> 6000
A61: 50 | B61: MXRF11 | C61: =IFERROR((F61/$B$9), 0) -> 0.0034699912 | D61: 10 | E61: =(D61/SUM(Fiis[Nota]))*$D$4 -> 0.022727273 | F61: =A61*G61 -> 463 | G61: =IFERROR(__xludf.DUMMYFUNCTION("GOOGLEFINANCE(B61)"),9.26) -> 9.26 | H61: =G61/I61 -> 0.98826041 | I61: =IFERROR(__xludf.DUMMYFUNCTION("IFERROR(QUERY(IMPORTRANGE(""16ctS2M9RWvjMVkO6L0BV75dNPXE73e0O2aKZF1Q8mU8"", ""Indicadores!A2:E""), ""SELECT Col2 WHERE Col1 = '""&B61 &""'"", 0), 0)"),9.37) -> 9.37 | J61: =SUM(L61/Q61) -> 9.0538355 | K61: =L61/12 -> 0.0975 | L61: {=IFERROR(INDEX(LCP_3Anos[], MATCH(B61, LCP_3Anos[Fii], 0), MATCH(LCP_3Anos[[#HEADERS],[Media_DPA_3Anos]], LCP_3Anos[#HEADERS], 0)),"")} -> 1.17 | M61: =A61*K61 -> 4.875 | N61: =IFERROR(M61*12,0) -> 58.5 | O61: 0.045 | P61: =$F$89 -> 0.0806 | Q61: =IFERROR((1+O61) * (1+P61)-1, 0) -> 0.129227 | R61: 9.25 | S61: =R61*A61 -> 462.5
A62: 50 | B62: PCIP11 | C62: =IFERROR((F62/$B$9), 0) -> 0.027055439 | D62: 0 | E62: =(D62/SUM(Fiis[Nota]))*$D$4 -> 0 | F62: =A62*G62 -> 3610 | G62: =IFERROR(__xludf.DUMMYFUNCTION("GOOGLEFINANCE(B62)"),72.2) -> 72.2 | H62: =G62/I62 -> 0.77734711 | I62: =IFERROR(__xludf.DUMMYFUNCTION("IFERROR(QUERY(IMPORTRANGE(""16ctS2M9RWvjMVkO6L0BV75dNPXE73e0O2aKZF1Q8mU8"", ""Indicadores!A2:E""), ""SELECT Col2 WHERE Col1 = '""&B62 &""'"", 0), 0)"),92.88) -> 92.88 | J62: =SUM(L62/Q62) -> 74.287881 | K62: =L62/12 -> 0.8 | L62: {=IFERROR(INDEX(LCP_3Anos[], MATCH(B62, LCP_3Anos[Fii], 0), MATCH(LCP_3Anos[[#HEADERS],[Media_DPA_3Anos]], LCP_3Anos[#HEADERS], 0)),"")} -> 9.6 | M62: =A62*K62 -> 40 | N62: =IFERROR(M62*12,0) -> 480 | O62: 0.045 | P62: =$F$89 -> 0.0806 | Q62: =IFERROR((1+O62) * (1+P62)-1, 0) -> 0.129227 | R62: 0 | S62: =R62*A62 -> 0
A63: 50 | B63: HGLG11 | C63: =IFERROR((F63/$B$9), 0) -> 0.055163866 | D63: 0 | E63: =(D63/SUM(Fiis[Nota]))*$D$4 -> 0 | F63: =A63*G63 -> 7360.5 | G63: =IFERROR(__xludf.DUMMYFUNCTION("GOOGLEFINANCE(B63)"),147.21) -> 147.21 | H63: =G63/I63 -> 0.88680723 | I63: =IFERROR(__xludf.DUMMYFUNCTION("IFERROR(QUERY(IMPORTRANGE(""16ctS2M9RWvjMVkO6L0BV75dNPXE73e0O2aKZF1Q8mU8"", ""Indicadores!A2:E""), ""SELECT Col2 WHERE Col1 = '""&B63 &""'"", 0), 0)"),166.0) -> 166 | J63: =SUM(L63/Q63) -> 151.96694 | K63: =L63/12 -> 1.1 | L63: {=IFERROR(INDEX(LCP_3Anos[], MATCH(B63, LCP_3Anos[Fii], 0), MATCH(LCP_3Anos[[#HEADERS],[Media_DPA_3Anos]], LCP_3Anos[#HEADERS], 0)),"")} -> 13.2 | M63: =A63*K63 -> 55 | N63: =IFERROR(M63*12,0) -> 660 | O63: 0.01 | P63: =$F$91 -> 0.0761 | Q63: =IFERROR((1+O63) * (1+P63)-1, 0) -> 0.086861 | R63: 0 | S63: =R63*A63 -> 0
A64: 50 | B64: KNRI11 | C64: =IFERROR((F64/$B$9), 0) -> 0.058262875 | D64: 10 | E64: =(D64/SUM(Fiis[Nota]))*$D$4 -> 0.022727273 | F64: =A64*G64 -> 7774 | G64: =IFERROR(__xludf.DUMMYFUNCTION("GOOGLEFINANCE(B64)"),155.48) -> 155.48 | H64: =G64/I64 -> 0.95298805 | I64: =IFERROR(__xludf.DUMMYFUNCTION("IFERROR(QUERY(IMPORTRANGE(""16ctS2M9RWvjMVkO6L0BV75dNPXE73e0O2aKZF1Q8mU8"", ""Indicadores!A2:E""), ""SELECT Col2 WHERE Col1 = '""&B64 &""'"", 0), 0)"),163.15) -> 163.15 | J64: =SUM(L64/Q64) -> 149.79779 | K64: =L64/12 -> 1.0104167 | L64: {=IFERROR(INDEX(LCP_3Anos[], MATCH(B64, LCP_3Anos[Fii], 0), MATCH(LCP_3Anos[[#HEADERS],[Media_DPA_3Anos]], LCP_3Anos[#HEADERS], 0)),"")} -> 12.125 | M64: =A64*K64 -> 50.520833 | N64: =IFERROR(M64*12,0) -> 606.25 | O64: 0.0045 | P64: =$F$91 -> 0.0761 | Q64: =IFERROR((1+O64) * (1+P64)-1, 0) -> 0.08094245 | R64: 0 | S64: =R64*A64 -> 0
A82: Tipo | B82: qtd | C82: Financeiro | D82: % Peso | E82: CDI_Bruto | F82: CDI_Liquido | G82: Retorno(%) | H82: Data da Aplicação | I82: Hoje | J82: Dia_Corridos | K82: Redimento | L82: CDI Diário (%)
A83: CDB | B83: 20000 | C83: =SUM(B83,K83) -> 20046.399 | D83: =IFERROR(SUM(C83/$B$9),0) -> 0.15023937 | E83: 1.15 | F83: =E83 * (1 - 0.225) -> 0.89125 | G83: =F83*Indicadores!$J$3 -> 0.12388375 | H83: 46251 | I83: =TODAY() -> 46257 | J83: =NETWORKDAYS(H83, I83, FERIADOS!B:B) -> 5 | K83: =(B83 * ((1 + L83) ^ J83))-B83 -> 46.399104 | L83: =((1 + G83) ^ (1/252)) - 1 -> 0.00046356107
A84: LFTB11 | B84: 50 | C84: =SUM(B84,K84) -> 50.26504 | D84: =IFERROR(SUM(C84/$B$9),0) -> 0.00037671543 | E84: 1.09 | F84: =E84 * (1 - 0.225) -> 0.84475 | G84: =F84*Indicadores!$J$3 -> 0.11742025 | H84: 46240 | I84: =TODAY() -> 46257 | J84: =NETWORKDAYS(H84, I84, FERIADOS!B:B) -> 12 | K84: =(B84 * ((1 + L84) ^ J84))-B84 -> 0.2650397 | L84: =((1 + G84) ^ (1/252)) - 1 -> 0.00044066326
A85: Tesouro Selic | B85: 0.5 | C85: =B85*Indicadores!$E$7 -> 9824.2 | D85: =IFERROR(SUM(C85/$B$9),0) -> 0.073628266
A88: Tipo | B88: qtd | C88: preço | D88: Financeiro | E88: % Peso | F88: Rent_Bruta | G88: Rent_Liq | H88: Retorno(%)
A89: =Indicadores!A3 -> Tesouro IPCA+ 2029 | E89: =IFERROR(SUM(D89/$B$9),0) -> 0 | F89: =Indicadores!D3 -> 0.0806 | G89: =F89 * (1 - 0.15) -> 0.06851 | H89: =IFERROR((1+Indicadores!$J$4) * (1+G89)-1, 0) -> 0.11598416
A90: =Indicadores!A4 -> Tesouro IPCA+ 2032 | C90: =Indicadores!C4 -> 3007.31 | D90: =B90*C90 -> 0 | E90: =IFERROR(SUM(D90/$B$9),0) -> 0 | F90: =Indicadores!D4 -> 0.0808 | G90: =F90 * (1 - 0.15) -> 0.06868 | H90: =IFERROR((1+Indicadores!$J$4) * (1+G90)-1, 0) -> 0.11616172
A91: =Indicadores!A5 -> Tesouro IPCA+ 2040 | C91: =Indicadores!C5 -> 1737.24 | D91: =B91*C91 -> 0 | E91: =IFERROR(SUM(D91/$B$9),0) -> 0 | F91: =Indicadores!D5 -> 0.0761 | G91: =F91 * (1 - 0.15) -> 0.064685 | H91: =IFERROR((1+Indicadores!$J$4) * (1+G91)-1, 0) -> 0.11198922
A92: =Indicadores!A6 -> Tesouro Renda+ Aposentadoria Extra 2065 | B92: 10.79 | C92: =Indicadores!C6 -> 186.18 | D92: =B92*Indicadores!E6 -> 1908.4273 | E92: =IFERROR(SUM(D92/$B$9),0) -> 0.014302864 | F92: =Indicadores!D6 -> 0.0726 | G92: =F92 * (1 - 0.15) -> 0.06171 | H92: =IFERROR((1+Indicadores!$J$4) * (1+G92)-1, 0) -> 0.10888204
A96: Etf | B96: qtd | C96: Peso | D96: financeiro | E96: financeiro ($) | F96: preço | G96: Dolar/REAL
A97: DIA | B97: 1.0442029 | C97: =IFERROR(SUM(D97/$B$9),0) -> 0.021406435 | D97: =(B97*F97)*G97 -> 2856.2549 | E97: =B97*F97 -> 555.74567 | F97: =IFERROR(__xludf.DUMMYFUNCTION("GOOGLEFINANCE(A97)"),532.22) -> 532.22 | G97: =IFERROR(__xludf.DUMMYFUNCTION("GOOGLEFINANCE(""CURRENCY:USD/BRL"")"),5.1395) -> 5.1395
A98: XBOX | B98: 3.9044345 | C98: =IFERROR(SUM(D98/$B$9),0) -> 0.015144532 | D98: =(B98*F98)*G98 -> 2020.7309 | E98: =B98*F98 -> 393.17655 | F98: =IFERROR(__xludf.DUMMYFUNCTION("GOOGLEFINANCE(A98)"),100.7) -> 100.7 | G98: =IFERROR(__xludf.DUMMYFUNCTION("GOOGLEFINANCE(""CURRENCY:USD/BRL"")"),5.1395) -> 5.1395
A99: SPXB11 | B99: 50 | C99: =IFERROR(SUM(D99/$B$9),0) -> 0.0065226773 | D99: =B99*F99 -> 870.31911 | F99: =IFERROR(__xludf.DUMMYFUNCTION("GOOGLEFINANCE(""IVVB11"")* 0.039040892927697"),17.40638211181371) -> 17.406382 | G99: =IFERROR(__xludf.DUMMYFUNCTION("GOOGLEFINANCE(""CURRENCY:USD/BRL"")"),5.1395) -> 5.1395
A103: Cripto | B103: qtd | C103: Peso | D103: financeiro | E103: financeiro ($) | F103: preço | G103: USD | H103: Investido R$ | I103: % investido | J103: Preço medio | K103: Perda
A104: BTC | B104: 0.00808981 | C104: =IFERROR(SUM(D104/B9),0) -> 0.024202589 | D104: =B104*F104 -> 3229.3451 | E104: =B104*G104 -> 628.33837 | F104: =IFERROR(__xludf.DUMMYFUNCTION("GOOGLEFINANCE(""CURRENCY:BTCBRL"") "),399186.7638) -> 399186.76 | G104: =IFERROR(__xludf.DUMMYFUNCTION("GOOGLEFINANCE(""CURRENCY:BTCUSD"") "),77670.35) -> 77670.35 | H104: =B104*J104 -> 4246.4269 | I104: =IFERROR(SUM((B104*J104/B9),0),"") -> 0.031825192 | J104: 524910.59 | K104: =H104-D104 -> 1017.0819
A105: USDT | B105: 0.54351 | C105: =IFERROR(SUM(D105/B9),0) -> 2.0935136e-05 | D105: =B105*F105 -> 2.7933696 | F105: =IFERROR(__xludf.DUMMYFUNCTION("GOOGLEFINANCE(""CURRENCY:USDTBRL"") "),5.1395) -> 5.1395

Sheet Eficiencia
B2: Perfomance | C2: Y Mensal Consolidado | D2: YMC_Media | E2: Y_Anual_FIIs | F2: Y Mensal FIIs | G2: YMF_Media | H2: % Ganho Capital
B3: =IFERROR(((financeiros[Valor Bruto]-(financeiros[Valor Aplicado]-financeiros[Total Proventos]))/financeiros[Valor Bruto]),0) -> 0.0098889109 | C3: =IFERROR((G19/(HOME!B3+HOME!B4)),0) -> 0.00075026182 | D3: 0.0045 | E3: =financeiros[FIIs_Provento]/HOME!B4 -> 0.09605855 | F3: =IFERROR(SUMPRODUCT(Fiis[QTD],Fiis[Div/12])/SUMPRODUCT(Fiis[QTD],Fiis[P/M]),"") -> 0.012519695 | G3: 0.007 | H3: =IFERROR(( financeiros[Ganho Capital]/financeiros[Valor Aplicado]),0) -> 0.00010317174
B6: Total Proventos | C6: FIIs_Provento | D6: Valor Aplicado | E6: Valor Bruto | F6: Ganho Capital
B7: =SUM(B13:M13)+ SUM(B16:M16) + SUM(B19:M19) -> 1305.71 | C7: =IFERROR(SUM(Fiis[Rendimento_Total]),"") -> 4968.9167 | D7: 133415.97 | E7: =HOME!B9 -> 133429.73 | F7: =E7-D7 -> 13.764757
B11: Proventos pagos
B12: 45315 | C12: 45346 | D12: 45375 | E12: 45406 | F12: 45436 | G12: 45467 | H12: 45497 | I12: 45528 | J12: 45559 | K12: 45589 | L12: 45620 | M12: 45650
B13: 0 | C13: 12.57 | D13: 13.69 | E13: 0 | F13: 11.33 | G13: 3.58 | H13: 9.34 | I13: 15.3 | J13: 10.42 | K13: 32.53 | L13: 5.97 | M13: 5.9
B14: =IFERROR(SUM((B16/B13)-1),0) -> 0 | C14: =IFERROR(SUM((C16/C13)-1),0) -> -0.048528242 | D14: =IFERROR(SUM((D16/D13)-1),0) -> 3.3959094 | E14: =IFERROR(SUM((E16/E13)-1),0) -> 0 | F14: =IFERROR(SUM((F16/F13)-1),0) -> 3.2436011 | G14: =IFERROR(SUM((G16/G13)-1),0) -> 14.061453 | H14: =IFERROR(SUM((H16/H13)-1),0) -> 3.4421842 | I14: =IFERROR(SUM((I16/I13)-1),0) -> 4.8810458 | ... M14: =IFERROR(SUM((M16/M13)-1),0) -> 14.625424
B15: 45682 | C15: 45713 | D15: 45741 | E15: 45772 | F15: 45802 | G15: 45833 | H15: 45863 | I15: 45894 | J15: 45925 | K15: 45955 | L15: 45986 | M15: 46016
B16: 40.51 | C16: 11.96 | D16: 60.18 | E16: 28.25 | F16: 48.08 | G16: 53.92 | H16: 41.49 | I16: 89.98 | J16: 53.99 | K16: 42.11 | L16: 74.29 | M16: 92.19
B17: =IFERROR(SUM((B19/B16)-1),0) -> 0.6669958 | C17: =IFERROR(SUM((C19/C16)-1),0) -> 2.7533445 | D17: =IFERROR(SUM((D19/D16)-1),0) -> 1.1889332 | E17: =IFERROR(SUM((E19/E16)-1),0) -> 0.6300885 | F17: =IFERROR(SUM((F19/F16)-1),0) -> 0.35170549 | G17: =IFERROR(SUM((G19/G16)-1),0) -> 0.28876113 | H17: =IFERROR(SUM((H19/H16)-1),0) -> 0.12557243 | I17: =IFERROR(SUM((I19/I16)-1),0) -> -0.14703267 | ... M17: =IFERROR(SUM((M19/M16)-1),0) -> -1
B18: 46023 | C18: 46054 | D18: 46082 | E18: 46113 | F18: 46143 | G18: 46174 | H18: 46204 | I18: 46235 | J18: 46266 | K18: 46296 | L18: 46327 | M18: 46357
B19: 67.53 | C19: 44.89 | D19: 131.73 | E19: 46.05 | F19: 64.99 | G19: 69.49 | H19: 46.7 | I19: 76.75 | J19: 0 | K19: 0 | L19: 0 | M19: 0
B40: Rentabilidade Mensal da Carteira FIIs: | D40: =IFERROR(SUMPRODUCT(Fiis[QTD],Fiis[Div/12])/SUMPRODUCT(Fiis[QTD],Fiis[P/M]),"") -> 0.012519695 | J40: Feito | M40: Feito | P40: Feito | S40: Feito | V40: Feito | Y40: Feito | AB40: Feito | AE40: Atual | AH40: Não | AK40: Não | AN40: Não | AQ40: Não
B41: Rentabilidade Anualizado da Carteira FIIs: | D41: =IF(D40="","",D40*12) -> 0.15023634 | G41: Rentabilidade Acumulado da Carteira FIIs: | I41: =IFERROR((SUM(K58:AS58)+SUMPRODUCT(D43:D52,F43:F52))/SUMPRODUCT(D43:D52,E43:E52)-1,"") -> 0.28896026 | J41: Jan | M41: Fev | P41: Mar | S41: Abr | V41: Mai | Y41: Jun | AB41: Jul | AE41: Ago | AH41: Set | AK41: Out | AN41: Nov | AQ41: Dez
A42: Fundo | B42: Segmento | C42: Classificação de Risco | D42: Qtidade Cotas Atual | E42: Preço Médio | F42: Cotação Atual | G42: Yield on Cost (YoC) | H42: Valorização | I42: Rentabilidade | J42: Qtidade de Cotas no Mês | K42: Dividendos (por cota) | L42: Proventos Recebidos | M42: Qtidade de Cotas no Mês | N42: Dividendos (por cota) | O42: Proventos Recebidos | P42: Qtidade de Cotas no Mês | Q42: Dividendos (por cota) | R42: Proventos Recebidos | S42: Qtidade de Cotas no Mês | T42: Dividendos (por cota) | U42: Proventos Recebidos | V42: Qtidade de Cotas no Mês | W42: Dividendos (por cota) | X42: Proventos Recebidos | Y42: Qtidade de Cotas no Mês | Z42: Dividendos (por cota) | AA42: Proventos Recebidos | AB42: Qtidade de Cotas no Mês | AC42: Dividendos (por cota) | AD42: Proventos Recebidos | AE42: Qtidade de Cotas no Mês | AF42: Dividendos (por cota) | AG42: Proventos Recebidos | AH42: Qtidade de Cotas no Mês | AI42: Dividendos (por cota) | AJ42: Proventos Recebidos | AK42: Qtidade de Cotas no Mês | AL42: Dividendos (por cota) | AM42: Proventos Recebidos | AN42: Qtidade de Cotas no Mês | AO42: Dividendos (por cota) | AP42: Proventos Recebidos | AQ42: Qtidade de Cotas no Mês | AR42: Dividendos (por cota) | AS42: Proventos Recebidos
A43: GGRC11 | B43: Logística | C43: Oportunidade | D43: {=IFERROR(INDEX(Fiis[], MATCH(A43, Fiis[Fii], 0), MATCH(Fiis[[#HEADERS],[QTD]], Fiis[#HEADERS], 0)), "")} -> 50 | E43: {=IFERROR(INDEX(Fiis[], MATCH(A43, Fiis[Fii], 0), MATCH(Fiis[[#HEADERS],[P/M]], Fiis[#HEADERS], 0)), "")} -> 10.01 | F43: =IFERROR(__xludf.DUMMYFUNCTION("IFERROR(GOOGLEFINANCE(A43),"""")"),9.06) -> 9.06 | G43: =IFERROR(SUMPRODUCT((MOD(COLUMN(K43:AS43)-COLUMN(K43), 3) = 0) * (K43:AS43))/SUMPRODUCT((MOD(COLUMN(K43:AS43)-COLUMN(K43), 3) = 0) * (NOT(ISBLANK(K43:AS43))))/E43*12,"") -> 0.11988012 | H43: =IFERROR(F43/E43-1,"") -> -0.094905095 | I43: =IFERROR((SUMPRODUCT((MOD(COLUMN(L43:AS43)-COLUMN(L43), 3) = 0) * (L43:AS43))+D43*F43)/(D43*E43)-1,"") -> 0.014385614 | J43: 39 | K43: =IF(J43=0,"",L43/J43) -> 0.1 | L43: 3.9 | M43: 39 | N43: =IF(M43=0,"",O43/M43) -> 0.1 | O43: 3.9 | P43: 39 | Q43: =IF(P43=0,"",R43/P43) -> 0.1 | R43: 3.9 | S43: 64 | T43: =IF(S43=0,"",U43/S43) -> 0.1 | U43: 6.4 | V43: 69,00 | W43: =IF(V43=0,"",X43/V43) -> 0.1 | X43: 6.9 | Y43: 79 | Z43: =IF(Y43=0,"",AA43/Y43) -> 0.1 | AA43: 7.9 | AB43: 109 | AC43: =IF(AB43=0,"",AD43/AB43) -> 0.1 | AD43: 10.9 | AE43: 109 | AF43: =IF(AE43=0,"",AG43/AE43) -> 0.1 | AG43: 10.9 | AH43: 0 | AJ43: =IF(AH43=0,"",AI43*AH43) | AK43: 0 | AM43: =IF(AK43=0,"",AL43*AK43) | AN43: 0 | AP43: =IF(AN43=0,"",AO43*AN43) | AQ43: 0 | AS43: =IF(AQ43=0,"",AR43*AQ43)
A44: LVBI11 | B44: Logística | C44: Ancoragem | D44: {=IFERROR(INDEX(Fiis[], MATCH(A44, Fiis[Fii], 0), MATCH(Fiis[[#HEADERS],[QTD]], Fiis[#HEADERS], 0)), "")} -> 50 | E44: {=IFERROR(INDEX(Fiis[], MATCH(A44, Fiis[Fii], 0), MATCH(Fiis[[#HEADERS],[P/M]], Fiis[#HEADERS], 0)), "")} -> 104.65 | F44: =IFERROR(__xludf.DUMMYFUNCTION("IFERROR(GOOGLEFINANCE(A44),"""")"),98.49) -> 98.49 | G44: =IFERROR(SUMPRODUCT((MOD(COLUMN(K44:AS44)-COLUMN(K44), 3) = 0) * (K44:AS44))/SUMPRODUCT((MOD(COLUMN(K44:AS44)-COLUMN(K44), 3) = 0) * (NOT(ISBLANK(K44:AS44))))/E44*12,"") -> 0.086000956 | H44: =IFERROR(F44/E44-1,"") -> -0.058862876 | I44: =IFERROR((SUMPRODUCT((MOD(COLUMN(L44:AS44)-COLUMN(L44), 3) = 0) * (L44:AS44))+D44*F44)/(D44*E44)-1,"") -> -0.050262781 | J44: 4 | K44: =IF(J44=0,"",L44/J44) -> 0.75 | L44: 3 | M44: 7 | N44: =IF(M44=0,"",O44/M44) -> 0.75 | O44: 5.25 | P44: 7 | Q44: =IF(P44=0,"",R44/P44) -> 0.75 | R44: 5.25 | S44: 7 | T44: =IF(S44=0,"",U44/S44) -> 0.75 | U44: 5.25 | V44: 7 | W44: =IF(V44=0,"",X44/V44) -> 0.75 | X44: 5.25 | Y44: 7 | Z44: =IF(Y44=0,"",AA44/Y44) -> 0.75 | AA44: 5.25 | AB44: 10 | AC44: =IF(AB44=0,"",AD44/AB44) -> 0.75 | AD44: 7.5 | AE44: 11 | AF44: =IF(AE44=0,"",AG44/AE44) -> 0.75 | AG44: 8.25 | AH44: 0 | AJ44: =IF(AH44=0,"",AI44*AH44) | AK44: 0 | AM44: =IF(AK44=0,"",AL44*AK44) | AN44: 0 | AP44: =IF(AN44=0,"",AO44*AN44) | AQ44: 0 | AS44: =IF(AQ44=0,"",AR44*AQ44)
A45: GARE11 | B45: Renda Urbana | C45: Oportunidade | D45: {=IFERROR(INDEX(Fiis[], MATCH(A45, Fiis[Fii], 0), MATCH(Fiis[[#HEADERS],[QTD]], Fiis[#HEADERS], 0)), "")} -> 50 | E45: {=IFERROR(INDEX(Fiis[], MATCH(A45, Fiis[Fii], 0), MATCH(Fiis[[#HEADERS],[P/M]], Fiis[#HEADERS], 0)), "")} -> 8.54 | F45: =IFERROR(__xludf.DUMMYFUNCTION("IFERROR(GOOGLEFINANCE(A45),"""")"),8.23) -> 8.23 | G45: =IFERROR(SUMPRODUCT((MOD(COLUMN(K45:AS45)-COLUMN(K45), 3) = 0) * (K45:AS45))/SUMPRODUCT((MOD(COLUMN(K45:AS45)-COLUMN(K45), 3) = 0) * (NOT(ISBLANK(K45:AS45))))/E45*12,"") -> 0.11666722 | H45: =IFERROR(F45/E45-1,"") -> -0.036299766 | I45: =IFERROR((SUMPRODUCT((MOD(COLUMN(L45:AS45)-COLUMN(L45), 3) = 0) * (L45:AS45))+D45*F45)/(D45*E45)-1,"") -> 0.072576112 | J45: 39 | K45: =IF(J45=0,"",L45/J45) -> 0.083076923 | L45: 3.24 | M45: 39 | N45: =IF(M45=0,"",O45/M45) -> 0.083076923 | O45: 3.24 | P45: 59 | Q45: =IF(P45=0,"",R45/P45) -> 0.083050847 | R45: 4.9 | S45: 75 | T45: =IF(S45=0,"",U45/S45) -> 0.083066667 | U45: 6.23 | V45: 87 | W45: =IF(V45=0,"",X45/V45) -> 0.082988506 | X45: 7.22 | Y45: 87 | Z45: =IF(Y45=0,"",AA45/Y45) -> 0.082988506 | AA45: 7.22 | AB45: 87 | AC45: =IF(AB45=0,"",AD45/AB45) -> 0.082988506 | AD45: 7.22 | AE45: 87 | AF45: =IF(AE45=0,"",AG45/AE45) -> 0.082988506 | AG45: 7.22 | AH45: 0 | AJ45: =IF(AH45=0,"",AI45*AH45) | AK45: 0 | AM45: =IF(AK45=0,"",AL45*AK45) | AN45: 0 | AP45: =IF(AN45=0,"",AO45*AN45) | AQ45: 0 | AS45: =IF(AQ45=0,"",AR45*AQ45)
A46: XPLG11 | B46: Logística | C46: Oportunidade | D46: {=IFERROR(INDEX(Fiis[], MATCH(A46, Fiis[Fii], 0), MATCH(Fiis[[#HEADERS],[QTD]], Fiis[#HEADERS], 0)), "")} -> 50 | E46: {=IFERROR(INDEX(Fiis[], MATCH(A46, Fiis[Fii], 0), MATCH(Fiis[[#HEADERS],[P/M]], Fiis[#HEADERS], 0)), "")} -> 93.43 | F46: =IFERROR(__xludf.DUMMYFUNCTION("IFERROR(GOOGLEFINANCE(A46),"""")"),90.0) -> 90 | G46: =IFERROR(SUMPRODUCT((MOD(COLUMN(K46:AS46)-COLUMN(K46), 3) = 0) * (K46:AS46))/SUMPRODUCT((MOD(COLUMN(K46:AS46)-COLUMN(K46), 3) = 0) * (NOT(ISBLANK(K46:AS46))))/E46*12,"") -> 0.10531949 | H46: =IFERROR(F46/E46-1,"") -> -0.036711977 | I46: =IFERROR((SUMPRODUCT((MOD(COLUMN(L46:AS46)-COLUMN(L46), 3) = 0) * (L46:AS46))+D46*F46)/(D46*E46)-1,"") -> -0.030041742 | J46: 4 | K46: =IF(J46=0,"",L46/J46) -> 0.82 | L46: 3.28 | M46: 4 | N46: =IF(M46=0,"",O46/M46) -> 0.82 | O46: 3.28 | P46: 4 | Q46: =IF(P46=0,"",R46/P46) -> 0.82 | R46: 3.28 | S46: 4 | T46: =IF(S46=0,"",U46/S46) -> 0.82 | U46: 3.28 | V46: 4 | W46: =IF(V46=0,"",X46/V46) -> 0.82 | X46: 3.28 | Y46: 4 | Z46: =IF(Y46=0,"",AA46/Y46) -> 0.82 | AA46: 3.28 | AB46: 6 | AC46: =IF(AB46=0,"",AD46/AB46) -> 0.82 | AD46: 4.92 | AE46: 8 | AF46: =IF(AE46=0,"",AG46/AE46) -> 0.82 | AG46: 6.56 | AH46: 0 | AJ46: =IF(AH46=0,"",AI46*AH46) | AK46: 0 | AM46: =IF(AK46=0,"",AL46*AK46) | AN46: 0 | AP46: =IF(AN46=0,"",AO46*AN46) | AQ46: 0 | AS46: =IF(AQ46=0,"",AR46*AQ46)
A47: PMLL11 | B47: Shoppings | C47: Oportunidade | D47: {=IFERROR(INDEX(Fiis[], MATCH(A47, Fiis[Fii], 0), MATCH(Fiis[[#HEADERS],[QTD]], Fiis[#HEADERS], 0)), "")} -> 50 | E47: {=IFERROR(INDEX(Fiis[], MATCH(A47, Fiis[Fii], 0), MATCH(Fiis[[#HEADERS],[P/M]], Fiis[#HEADERS], 0)), "")} -> 99.15 | F47: =IFERROR(__xludf.DUMMYFUNCTION("IFERROR(GOOGLEFINANCE(A47),"""")"),100.83) -> 100.83 | G47: =IFERROR(SUMPRODUCT((MOD(COLUMN(K47:AS47)-COLUMN(K47), 3) = 0) * (K47:AS47))/SUMPRODUCT((MOD(COLUMN(K47:AS47)-COLUMN(K47), 3) = 0) * (NOT(ISBLANK(K47:AS47))))/E47*12,"") -> 0.12102874 | H47: =IFERROR(F47/E47-1,"") -> 0.016944024 | I47: =IFERROR((SUMPRODUCT((MOD(COLUMN(L47:AS47)-COLUMN(L47), 3) = 0) * (L47:AS47))+D47*F47)/(D47*E47)-1,"") -> 0.02380232 | J47: 4 | K47: =IF(J47=0,"",L47/J47) -> 1 | L47: 4 | M47: 4 | N47: =IF(M47=0,"",O47/M47) -> 1 | O47: 4 | P47: 4 | Q47: =IF(P47=0,"",R47/P47) -> 1 | R47: 4 | S47: 4 | T47: =IF(S47=0,"",U47/S47) -> 1 | U47: 4 | V47: 4 | W47: =IF(V47=0,"",X47/V47) -> 1 | X47: 4 | Y47: 4 | Z47: =IF(Y47=0,"",AA47/Y47) -> 1 | AA47: 4 | AB47: 4 | AC47: =IF(AB47=0,"",AD47/AB47) -> 1 | AD47: 4 | AE47: 6 | AF47: =IF(AE47=0,"",AG47/AE47) -> 1 | AG47: 6 | AH47: 0 | AJ47: =IF(AH47=0,"",AI47*AH47) | AK47: 0 | AM47: =IF(AK47=0,"",AL47*AK47) | AN47: 0 | AP47: =IF(AN47=0,"",AO47*AN47) | AQ47: 0 | AS47: =IF(AQ47=0,"",AR47*AQ47)
A48: BTLG11 | B48: Logística | C48: Ancoragem | D48: {=IFERROR(INDEX(Fiis[], MATCH(A48, Fiis[Fii], 0), MATCH(Fiis[[#HEADERS],[QTD]], Fiis[#HEADERS], 0)), "")} -> 50 | E48: {=IFERROR(INDEX(Fiis[], MATCH(A48, Fiis[Fii], 0), MATCH(Fiis[[#HEADERS],[P/M]], Fiis[#HEADERS], 0)), "")} -> 97.58 | F48: =IFERROR(__xludf.DUMMYFUNCTION("IFERROR(GOOGLEFINANCE(A48),"""")"),98.37) -> 98.37 | G48: =IFERROR(SUMPRODUCT((MOD(COLUMN(K48:AS48)-COLUMN(K48), 3) = 0) * (K48:AS48))/SUMPRODUCT((MOD(COLUMN(K48:AS48)-COLUMN(K48), 3) = 0) * (NOT(ISBLANK(K48:AS48))))/E48*12,"") -> 0.099303136 | H48: =IFERROR(F48/E48-1,"") -> 0.0080959213 | I48: =IFERROR((SUMPRODUCT((MOD(COLUMN(L48:AS48)-COLUMN(L48), 3) = 0) * (L48:AS48))+D48*F48)/(D48*E48)-1,"") -> 0.013392089 | J48: 4 | K48: =IF(J48=0,"",L48/J48) -> 0.8 | L48: 3.2 | M48: 4 | N48: =IF(M48=0,"",O48/M48) -> 0.8 | O48: 3.2 | P48: 4 | Q48: =IF(P48=0,"",R48/P48) -> 0.81 | R48: 3.24 | S48: 4 | T48: =IF(S48=0,"",U48/S48) -> 0.81 | U48: 3.24 | V48: 4 | W48: =IF(V48=0,"",X48/V48) -> 0.81 | X48: 3.24 | Y48: 4 | Z48: =IF(Y48=0,"",AA48/Y48) -> 0.81 | AA48: 3.24 | AB48: 4 | AC48: =IF(AB48=0,"",AD48/AB48) -> 0.81 | AD48: 3.24 | AE48: 4 | AF48: =IF(AE48=0,"",AG48/AE48) -> 0.81 | AG48: 3.24 | AH48: 0 | AJ48: =IF(AH48=0,"",AI48*AH48) | AK48: 0 | AM48: =IF(AK48=0,"",AL48*AK48) | AN48: 0 | AP48: =IF(AN48=0,"",AO48*AN48) | AQ48: 0 | AS48: =IF(AQ48=0,"",AR48*AQ48)
A49: HGBS11 | B49: Shoppings | C49: Oportunidade | D49: {=IFERROR(INDEX(Fiis[], MATCH(A49, Fiis[Fii], 0), MATCH(Fiis[[#HEADERS],[QTD]], Fiis[#HEADERS], 0)), "")} -> 50 | E49: {=IFERROR(INDEX(Fiis[], MATCH(A49, Fiis[Fii], 0), MATCH(Fiis[[#HEADERS],[P/M]], Fiis[#HEADERS], 0)), "")} -> 18.42 | F49: =IFERROR(__xludf.DUMMYFUNCTION("IFERROR(GOOGLEFINANCE(A49),"""")"),18.6) -> 18.6 | G49: =IFERROR(SUMPRODUCT((MOD(COLUMN(K49:AS49)-COLUMN(K49), 3) = 0) * (K49:AS49))/SUMPRODUCT((MOD(COLUMN(K49:AS49)-COLUMN(K49), 3) = 0) * (NOT(ISBLANK(K49:AS49))))/E49*12,"") -> 0.10830619 | H49: =IFERROR(F49/E49-1,"") -> 0.009771987 | I49: =IFERROR((SUMPRODUCT((MOD(COLUMN(L49:AS49)-COLUMN(L49), 3) = 0) * (L49:AS49))+D49*F49)/(D49*E49)-1,"") -> 0.038653637 | J49: 20 | K49: =IF(J49=0,"",L49/J49) -> 0.15 | L49: 3 | M49: 20 | N49: =IF(M49=0,"",O49/M49) -> 0.16 | O49: 3.2 | P49: 20 | Q49: =IF(P49=0,"",R49/P49) -> 0.17 | R49: 3.4 | S49: 20 | T49: =IF(S49=0,"",U49/S49) -> 0.17 | U49: 3.4 | V49: 20 | W49: =IF(V49=0,"",X49/V49) -> 0.17 | X49: 3.4 | Y49: 20 | Z49: =IF(Y49=0,"",AA49/Y49) -> 0.17 | AA49: 3.4 | AB49: 20 | AC49: =IF(AB49=0,"",AD49/AB49) -> 0.17 | AD49: 3.4 | AE49: 20 | AF49: =IF(AE49=0,"",AG49/AE49) -> 0.17 | AG49: 3.4 | AH49: 0 | AJ49: =IF(AH49=0,"",AI49*AH49) | AK49: 0 | AM49: =IF(AK49=0,"",AL49*AK49) | AN49: 0 | AP49: =IF(AN49=0,"",AO49*AN49) | AQ49: 0 | AS49: =IF(AQ49=0,"",AR49*AQ49)
A50: BRCO11 | B50: Logística | C50: Oportunidade | D50: {=IFERROR(INDEX(Fiis[], MATCH(A50, Fiis[Fii], 0), MATCH(Fiis[[#HEADERS],[QTD]], Fiis[#HEADERS], 0)), "")} -> 50 | E50: {=IFERROR(INDEX(Fiis[], MATCH(A50, Fiis[Fii], 0), MATCH(Fiis[[#HEADERS],[P/M]], Fiis[#HEADERS], 0)), "")} -> 100.45 | F50: =IFERROR(__xludf.DUMMYFUNCTION("IFERROR(GOOGLEFINANCE(A50),"""")"),111.84) -> 111.84 | G50: =IFERROR(SUMPRODUCT((MOD(COLUMN(K50:AS50)-COLUMN(K50), 3) = 0) * (K50:AS50))/SUMPRODUCT((MOD(COLUMN(K50:AS50)-COLUMN(K50), 3) = 0) * (NOT(ISBLANK(K50:AS50))))/E50*12,"") -> 0.11110005 | H50: =IFERROR(F50/E50-1,"") -> 0.11338975 | I50: =IFERROR((SUMPRODUCT((MOD(COLUMN(L50:AS50)-COLUMN(L50), 3) = 0) * (L50:AS50))+D50*F50)/(D50*E50)-1,"") -> 0.11783375 | J50: 3 | K50: =IF(J50=0,"",L50/J50) -> 0.87 | L50: 2.61 | M50: 3 | N50: =IF(M50=0,"",O50/M50) -> 0.87 | O50: 2.61 | P50: 3 | Q50: =IF(P50=0,"",R50/P50) -> 0.92 | R50: 2.76 | S50: 3 | T50: =IF(S50=0,"",U50/S50) -> 0.92 | U50: 2.76 | V50: 3 | W50: =IF(V50=0,"",X50/V50) -> 0.95 | X50: 2.85 | Y50: 3 | Z50: =IF(Y50=0,"",AA50/Y50) -> 0.95 | AA50: 2.85 | AB50: 3 | AC50: =IF(AB50=0,"",AD50/AB50) -> 1.05 | AD50: 3.15 | AE50: 3 | AF50: =IF(AE50=0,"",AG50/AE50) -> 0.91 | AG50: 2.73 | AH50: 0 | AJ50: =IF(AH50=0,"",AI50*AH50) | AK50: 0 | AM50: =IF(AK50=0,"",AL50*AK50) | AN50: 0 | AP50: =IF(AN50=0,"",AO50*AN50) | AQ50: 0 | AS50: =IF(AQ50=0,"",AR50*AQ50)
A51: MXRF11 | B51: CRI | C51: Ancoragem | D51: {=IFERROR(INDEX(Fiis[], MATCH(A51, Fiis[Fii], 0), MATCH(Fiis[[#HEADERS],[QTD]], Fiis[#HEADERS], 0)), "")} -> 50 | E51: {=IFERROR(INDEX(Fiis[], MATCH(A51, Fiis[Fii], 0), MATCH(Fiis[[#HEADERS],[P/M]], Fiis[#HEADERS], 0)), "")} -> 9.25 | F51: =IFERROR(__xludf.DUMMYFUNCTION("IFERROR(GOOGLEFINANCE(A51),"""")"),9.26) -> 9.26 | G51: =IFERROR(SUMPRODUCT((MOD(COLUMN(K51:AS51)-COLUMN(K51), 3) = 0) * (K51:AS51))/SUMPRODUCT((MOD(COLUMN(K51:AS51)-COLUMN(K51), 3) = 0) * (NOT(ISBLANK(K51:AS51))))/E51*12,"") -> 0.12895753 | H51: =IFERROR(F51/E51-1,"") -> 0.0010810811 | I51: =IFERROR((SUMPRODUCT((MOD(COLUMN(L51:AS51)-COLUMN(L51), 3) = 0) * (L51:AS51))+D51*F51)/(D51*E51)-1,"") -> 0.037189189 | J51: 21 | K51: =IF(J51=0,"",L51/J51) -> 0.1 | L51: 2.1 | M51: 21 | N51: =IF(M51=0,"",O51/M51) -> 0.1 | O51: 2.1 | P51: 21 | Q51: =IF(P51=0,"",R51/P51) -> 0.1 | R51: 2.1 | S51: 21 | T51: =IF(S51=0,"",U51/S51) -> 0.095238095 | U51: 2 | V51: 21 | W51: =IF(V51=0,"",X51/V51) -> 0.1 | X51: 2.1 | Y51: 21 | Z51: =IF(Y51=0,"",AA51/Y51) -> 0.1 | AA51: 2.1 | AB51: 21 | AC51: =IF(AB51=0,"",AD51/AB51) -> 0.1 | AD51: 2.1 | AE51: 21 | AF51: =IF(AE51=0,"",AG51/AE51) -> 0.1 | AG51: 2.1 | AH51: 0 | AJ51: =IF(AH51=0,"",AI51*AH51) | AK51: 0 | AM51: =IF(AK51=0,"",AL51*AK51) | AN51: 0 | AP51: =IF(AN51=0,"",AO51*AN51) | AQ51: 0 | AS51: =IF(AQ51=0,"",AR51*AQ51)
A52: HGLG11 | B52: Logística | C52: Oportunidade | D52: {=IFERROR(INDEX(Fiis[], MATCH(A52, Fiis[Fii], 0), MATCH(Fiis[[#HEADERS],[QTD]], Fiis[#HEADERS], 0)), "")} -> 50 | E52: {=IFERROR(INDEX(Fiis[], MATCH(A52, Fiis[Fii], 0), MATCH(Fiis[[#HEADERS],[P/M]], Fiis[#HEADERS], 0)), "")} -> 0 | F52: =IFERROR(__xludf.DUMMYFUNCTION("IFERROR(GOOGLEFINANCE(A52),"""")"),147.21) -> 147.21 | G52: =IFERROR(SUMPRODUCT((MOD(COLUMN(K52:AS52)-COLUMN(K52), 3) = 0) * (K52:AS52))/SUMPRODUCT((MOD(COLUMN(K52:AS52)-COLUMN(K52), 3) = 0) * (NOT(ISBLANK(K52:AS52))))/E52*12,"") | H52: =IFERROR(F52/E52-1,"") | I52: =IFERROR((SUMPRODUCT((MOD(COLUMN(L52:AS52)-COLUMN(L52), 3) = 0) * (L52:AS52))+D52*F52)/(D52*E52)-1,"") | K52: =IF(J52=0,"",L52/J52) | L52: 0 | N52: =IF(M52=0,"",O52/M52) | O52: 0 | Q52: =IF(P52=0,"",R52/P52) | R52: 0 | T52: =IF(S52=0,"",U52/S52) | U52: 0 | W52: =IF(V52=0,"",X52/V52) | X52: 0 | Z52: =IF(Y52=0,"",AA52/Y52) | AA52: 0 | AC52: =IF(AB52=0,"",AD52/AB52) | AD52: 0 | AF52: =IF(AE52=0,"",AG52/AE52) | AG52: 0 | AH52: 0 | AJ52: =IF(AH52=0,"",AI52*AH52) | AK52: 0 | AM52: =IF(AK52=0,"",AL52*AK52) | AN52: 0 | AP52: =IF(AN52=0,"",AO52*AN52) | AQ52: 0 | AS52: =IF(AQ52=0,"",AR52*AQ52)
A53: KNRI11 | B53: Log/Laje | C53: Ancoragem | D53: {=IFERROR(INDEX(Fiis[], MATCH(A53, Fiis[Fii], 0), MATCH(Fiis[[#HEADERS],[QTD]], Fiis[#HEADERS], 0)), "")} -> 50 | E53: {=IFERROR(INDEX(Fiis[], MATCH(A53, Fiis[Fii], 0), MATCH(Fiis[[#HEADERS],[P/M]], Fiis[#HEADERS], 0)), "")} -> 0 | F53: =IFERROR(__xludf.DUMMYFUNCTION("IFERROR(GOOGLEFINANCE(A53),"""")"),155.48) -> 155.48 | G53: =IFERROR(SUMPRODUCT((MOD(COLUMN(K53:AS53)-COLUMN(K53), 3) = 0) * (K53:AS53))/SUMPRODUCT((MOD(COLUMN(K53:AS53)-COLUMN(K53), 3) = 0) * (NOT(ISBLANK(K53:AS53))))/E53*12,"") | H53: =IFERROR(F53/E53-1,"") | I53: =IFERROR((SUMPRODUCT((MOD(COLUMN(L53:AS53)-COLUMN(L53), 3) = 0) * (L53:AS53))+D53*F53)/(D53*E53)-1,"") | AH53: 0 | AJ53: =IF(AH53=0,"",AI53*AH53) | AK53: 0 | AM53: =IF(AK53=0,"",AL53*AK53) | AN53: 0 | AP53: =IF(AN53=0,"",AO53*AN53) | AQ53: 0 | AS53: =IF(AQ53=0,"",AR53*AQ53)
A54: HGRU11 | B54: Renda Urbana | C54: Ancoragem | D54: {=IFERROR(INDEX(Fiis[], MATCH(A54, Fiis[Fii], 0), MATCH(Fiis[[#HEADERS],[QTD]], Fiis[#HEADERS], 0)), "")} -> 50 | E54: {=IFERROR(INDEX(Fiis[], MATCH(A54, Fiis[Fii], 0), MATCH(Fiis[[#HEADERS],[P/M]], Fiis[#HEADERS], 0)), "")} -> 120 | F54: =IFERROR(__xludf.DUMMYFUNCTION("IFERROR(GOOGLEFINANCE(A54),"""")"),114.99) -> 114.99 | G54: =IFERROR(SUMPRODUCT((MOD(COLUMN(K54:AS54)-COLUMN(K54), 3) = 0) * (K54:AS54))/SUMPRODUCT((MOD(COLUMN(K54:AS54)-COLUMN(K54), 3) = 0) * (NOT(ISBLANK(K54:AS54))))/E54*12,"") | H54: =IFERROR(F54/E54-1,"") -> -0.04175 | I54: =IFERROR((SUMPRODUCT((MOD(COLUMN(L54:AS54)-COLUMN(L54), 3) = 0) * (L54:AS54))+D54*F54)/(D54*E54)-1,"") -> -0.04175 | AH54: 0 | AJ54: =IF(AH54=0,"",AI54*AH54) | AK54: 0 | AM54: =IF(AK54=0,"",AL54*AK54) | AN54: 0 | AP54: =IF(AN54=0,"",AO54*AN54) | AQ54: 0 | AS54: =IF(AQ54=0,"",AR54*AQ54)
A55: PCIP11 | B55: CRI | C55: Oportunidade | D55: {=IFERROR(INDEX(Fiis[], MATCH(A55, Fiis[Fii], 0), MATCH(Fiis[[#HEADERS],[QTD]], Fiis[#HEADERS], 0)), "")} -> 50 | E55: {=IFERROR(INDEX(Fiis[], MATCH(A55, Fiis[Fii], 0), MATCH(Fiis[[#HEADERS],[P/M]], Fiis[#HEADERS], 0)), "")} -> 0 | F55: =IFERROR(__xludf.DUMMYFUNCTION("IFERROR(GOOGLEFINANCE(A55),"""")"),72.2) -> 72.2 | G55: =IFERROR(SUMPRODUCT((MOD(COLUMN(K55:AS55)-COLUMN(K55), 3) = 0) * (K55:AS55))/SUMPRODUCT((MOD(COLUMN(K55:AS55)-COLUMN(K55), 3) = 0) * (NOT(ISBLANK(K55:AS55))))/E55*12,"") | H55: =IFERROR(F55/E55-1,"") | I55: =IFERROR((SUMPRODUCT((MOD(COLUMN(L55:AS55)-COLUMN(L55), 3) = 0) * (L55:AS55))+D55*F55)/(D55*E55)-1,"") | AH55: 0 | AJ55: =IF(AH55=0,"",AI55*AH55) | AK55: 0 | AM55: =IF(AK55=0,"",AL55*AK55) | AN55: 0 | AP55: =IF(AN55=0,"",AO55*AN55) | AQ55: 0 | AS55: =IF(AQ55=0,"",AR55*AQ55)
G56: =IFERROR(SUMPRODUCT((MOD(COLUMN(K56:AS56)-COLUMN(K56), 3) = 0) * (K56:AS56))/SUMPRODUCT((MOD(COLUMN(K56:AS56)-COLUMN(K56), 3) = 0) * (NOT(ISBLANK(K56:AS56))))/E56*12,"") | H56: =IFERROR(F56/E56-1,"") | I56: =IFERROR((SUMPRODUCT((MOD(COLUMN(L56:AS56)-COLUMN(L56), 3) = 0) * (L56:AS56))+D56*F56)/(D56*E56)-1,"")
I58: Proventos: | K58: =SUMPRODUCT(J42:J57,K42:K57) -> 28.33 | N58: =SUMPRODUCT(M42:M57,N42:N57) -> 30.78 | Q58: =SUMPRODUCT(P42:P57,Q42:Q57) -> 32.83 | T58: =SUMPRODUCT(S42:S57,T42:T57) -> 36.56 | W58: =SUMPRODUCT(V42:V57,W42:W57) -> 38.24 | Z58: =SUMPRODUCT(Y42:Y57,Z42:Z57) -> 39.24 | AC58: =SUMPRODUCT(AB42:AB57,AC42:AC57) -> 46.43 | AF58: =SUMPRODUCT(AE42:AE57,AF42:AF57) -> 50.4 | AI58: =SUMPRODUCT(AH42:AH57,AI42:AI57) -> 0 | AL58: =SUMPRODUCT(AK42:AK57,AL42:AL57) -> 0 | AO58: =SUMPRODUCT(AN42:AN57,AO42:AO57) -> 0 | AR58: =SUMPRODUCT(AQ42:AQ57,AR42:AR57) -> 0
I59: YoC Mensal: | K59: =IFERROR(K58/SUMPRODUCT(J42:J57,$E42:$E57),"") -> 0.0089462499 | N59: =IFERROR(N58/SUMPRODUCT(M42:M57,$E42:$E57),"") -> 0.0088432013 | Q59: =IFERROR(Q58/SUMPRODUCT(P42:P57,$E42:$E57),"") -> 0.0089909734 | T59: =IFERROR(T58/SUMPRODUCT(S42:S57,$E42:$E57),"") -> 0.0090532473 | W59: =IFERROR(W58/SUMPRODUCT(V42:V57,$E42:$E57),"") -> 0.0091246188 | Z59: =IFERROR(Z58/SUMPRODUCT(Y42:Y57,$E42:$E57),"") -> 0.0091448068 | AC59: =IFERROR(AC58/SUMPRODUCT(AB42:AB57,$E42:$E57),"") -> 0.0091180993 | AF59: =IFERROR(AF58/SUMPRODUCT(AE42:AE57,$E42:$E57),"") -> 0.009029216 | AI59: =IFERROR(AI58/SUMPRODUCT(AH42:AH57,$E42:$E57),"") | AL59: =IFERROR(AL58/SUMPRODUCT(AK42:AK57,$E42:$E57),"") | AO59: =IFERROR(AO58/SUMPRODUCT(AN42:AN57,$E42:$E57),"") | AR59: =IFERROR(AR58/SUMPRODUCT(AQ42:AQ57,$E42:$E57),"")
I60: YoC Anualizado: | K60: =IF(K59="","",K59*12) -> 0.107355 | N60: =IF(N59="","",N59*12) -> 0.10611841 | Q60: =IF(Q59="","",Q59*12) -> 0.10789168 | T60: =IF(T59="","",T59*12) -> 0.10863897 | W60: =IF(W59="","",W59*12) -> 0.10949543 | Z60: =IF(Z59="","",Z59*12) -> 0.10973768 | AC60: =IF(AC59="","",AC59*12) -> 0.10941719 | AF60: =IF(AF59="","",AF59*12) -> 0.10835059 | AI60: =IF(AI59="","",AI59*12) | AL60: =IF(AL59="","",AL59*12) | AO60: =IF(AO59="","",AO59*12) | AR60: =IF(AR59="","",AR59*12)

Sheet Decio_Bazin
A2: Ação | B2: Media_DPA_3Anos | C2: Anos_Media | E2: Fii | F2: Media_DPA_3Anos | G2: Anos_Media | I2: Ano | J2: LPC | L2: Ano | M2: LPC | O2: Ano | P2: LPC | R2: Ano | S2: LPC
A3: BBSE3 | B3: =C22/C3 -> 3.4236045 | C3: 2 | E3: KNRI11 | F3: =IFERROR(J6/G3,0) -> 12.125 | G3: 2 | I3: Ano_1 | L3: Ano_1 | M3: 9.18 | O3: Ano_1 | R3: Ano_1
A4: BBAS3 | B4: =C29/C4 -> 1.0152495 | C4: 1 | E4: PMLL11 | F4: =IFERROR(J13/G4,0) -> 9.9766667 | G4: 3 | I4: Ano_2 | J4: 12 | L4: Ano_2 | M4: 9.36 | O4: Ano_2 | R4: Ano_2 | S4: 1.09
A5: ITUB3 | B5: =C36/C5 -> 3.3549068 | C5: 2 | E5: XPLG11 | F5: =IFERROR(M6/G5,0) -> 9.46 | G5: 3 | I5: Ano_3 | J5: 12.25 | L5: Ano_3 | M5: 9.84 | O5: Ano_3 | P5: 1.86 | R5: Ano_3 | S5: 1.13
A6: BRBI11 | B6: =C43/C6 -> 1.86 | C6: 1 | E6: BTLG11 | F6: =IFERROR(M13/G6,0) -> 9.2533333 | G6: 3 | I6: Total | J6: =SUM(J4:J5) -> 24.25 | L6: Total | M6: =SUM(M3:M5) -> 28.38 | O6: Total | P6: =SUM(P3:P5) -> 1.86 | R6: Total | S6: =SUM(S3:S5) -> 2.22
A7: TAEE11 | B7: =G22/C7 -> 2.9885238 | C7: 1 | E7: HGBS11 | F7: =IFERROR(P6/G7,0) -> 1.86 | G7: 1
A8: CMIG4 | B8: =G36/C8 -> 1.3200653 | C8: 3 | E8: GGRC11 | F8: =IFERROR(P13/G8,0) -> 1.16 | G8: 2
A9: ISAE4 | B9: =G29/C9 -> 2.3334489 | C9: 2 | E9: PORD11 | F9: =IFERROR(S6/G9,0) -> 1.11 | G9: 2 | I9: Ano | J9: LPC | L9: Ano | M9: LPC | O9: Ano | P9: LPC | R9: Ano | S9: LPC
A10: VALE3 | B10: =K29/C10 -> 6.0299977 | C10: 2 | E10: BRCO11 | F10: =IFERROR(S13/G10,0) -> 10.213333 | G10: 3 | I10: Ano_1 | J10: 9.65 | L10: Ano_1 | M10: 9 | O10: Ano_1 | R10: Ano_1 | S10: 9.58
A11: PETR4 | B11: =K36/1 -> 2.9760672 | C11: 1 | E11: GARE11 | F11: =IFERROR(N20/G11,0) -> 0.96 | G11: 1 | I11: Ano_2 | J11: 10.03 | L11: Ano_2 | M11: 9.27 | O11: Ano_2 | P11: 1.11 | R11: Ano_2 | S11: 10.44
A12: SAPR4 | B12: =G43/C12 -> 0.29011989 | C12: 3 | E12: MXRF11 | F12: =IFERROR(Q20/G12,0) -> 1.17 | G12: 1 | I12: Ano_3 | J12: 10.25 | L12: Ano_3 | M12: 9.49 | O12: Ano_3 | P12: 1.21 | R12: Ano_3 | S12: 10.62
A13: WEGE3 | B13: =K22/C13 -> 1.5532215 | C13: 2 | E13: HGLG11 | F13: =IFERROR(N27/G13,0) -> 13.2 | G13: 1 | I13: Total | J13: =SUM(J10:J12) -> 29.93 | L13: Total | M13: =SUM(M10:M12) -> 27.76 | O13: Total | P13: =SUM(P10:P12) -> 2.32 | R13: Total | S13: =SUM(S10:S12) -> 30.64
A14: ITSA4 | B14: =K43/C14 -> 1.0454975 | C14: 2 | E14: HGRU11 | F14: =IFERROR(Q27/G14,0) -> 11.4 | G14: 1
E15: PCIP11 | F15: =IFERROR(N34/G15,0) -> 9.6 | G15: 1
M16: Ano | N16: LPC | P16: Ano | Q16: LPC
M17: Ano_1 | P17: Ano_1
A18: Tipo | B18: Bruto | C18: Liquido | E18: Tipo | F18: Bruto | G18: Liquido | I18: Tipo | J18: Bruto | K18: Liquido | M18: Ano_2 | P18: Ano_2
A19: JCP | B19: =SUMIF(BBSE3_2[Tipo], "JSCP", BBSE3_2[Valor]) -> 0 | C19: =SUM(B19*(1-0.15)) -> 0 | E19: JCP | F19: =SUMIF(TAEE11_2[Tipo], "JSCP", TAEE11_2[Valor]) -> 1.604909 | G19: =SUM(F19*(1-0.15)) -> 1.3641727 | I19: JCP | J19: =SUMIF(WEGE3_2[Tipo], "JSCP", WEGE3_2[Valor]) -> 0.66664613 | K19: =SUM(J19*(1-0.15)) -> 0.56664921 | M19: Ano_3 | N19: 0.96 | P19: Ano_3 | Q19: 1.17
A20: Dividendos | B20: =SUMIF(BBSE3_2[Tipo], "Dividendos", BBSE3_2[Valor]) -> 6.8472089 | C20: =SUM(B20) -> 6.8472089 | E20: Dividendos | F20: =SUMIF(TAEE11_2[Tipo], "Dividendos", TAEE11_2[Valor]) -> 1.6243512 | G20: =SUM(F20) -> 1.6243512 | I20: Dividendos | J20: =SUMIF(WEGE3_2[Tipo], "Dividendos", WEGE3_2[Valor]) -> 2.5397939 | K20: =SUM(J20) -> 2.5397939 | M20: Total | N20: =SUM(N17:N19) -> 0.96 | P20: Total | Q20: =SUM(Q17:Q19) -> 1.17
E21: Rend. Trib. | F21: =SUMIF(TAEE11_2[Tipo], "Rend. Trib.", TAEE11_2[Valor]) -> 0 | G21: =SUM(F21*(1-0.2)) -> 0 | I21: Rend. Trib. | J21: =SUMIF(WEGE3_2[Tipo], "Rend. Trib.", WEGE3_2[Valor]) -> 0 | K21: =SUM(J21*(1-0.2)) -> 0
A22: Total | B22: =SUM(B19:B21) -> 6.8472089 | C22: =SUM(C19:C21) -> 6.8472089 | E22: Total | F22: =SUM(F19:F21) -> 3.2292602 | G22: =SUM(G19:G21) -> 2.9885238 | I22: Total | J22: =SUM(J19:J21) -> 3.20644 | K22: =SUM(K19:K21) -> 3.1064431
M23: Ano | N23: LPC | P23: Ano | Q23: LPC
M24: Ano_1 | P24: Ano_1
A25: Tipo | B25: Bruto | C25: Liquido | E25: Tipo | F25: Bruto | G25: Liquido | I25: Tipo | J25: Bruto | K25: Liquido | M25: Ano_2 | P25: Ano_2
A26: JCP | B26: =SUMIF(BBAS3_2[Tipo], "JSCP", BBAS3_2[Valor]) -> 1.034409 | C26: =SUM(B26*(1-0.15)) -> 0.87924765 | E26: JCP | F26: =SUMIF(ISAE4_2[Tipo], "JSCP", ISAE4_2[Valor]) -> 5.490468 | G26: =SUM(F26*(1-0.15)) -> 4.6668978 | I26: JCP | J26: =SUMIF(VALE3_2[Tipo], "JSCP", VALE3_2[Valor]) -> 6.0792511 | K26: =SUM(J26*(1-0.15)) -> 5.1673635 | M26: Ano_3 | N26: 13.2 | P26: Ano_3 | Q26: 11.4
A27: Dividendos | B27: =SUMIF(BBAS3_2[Tipo], "Dividendos", BBAS3_2[Valor]) -> 0.13600181 | C27: =SUM(B27) -> 0.13600181 | E27: Dividendos | F27: =SUMIF(ISAE4_2[Tipo], "Dividendos", ISAE4_2[Valor]) -> 0 | G27: =SUM(F27) -> 0 | I27: Dividendos | J27: =SUMIF(VALE3_2[Tipo], "Dividendos", VALE3_2[Valor]) -> 6.8926318 | K27: =SUM(J27) -> 6.8926318 | M27: Total | N27: =SUM(N24:N26) -> 13.2 | P27: Total | Q27: =SUM(Q24:Q26) -> 11.4
E28: Rend. Trib. | F28: =SUMIF(ISAE4_2[Tipo], "Rend. Trib.", ISAE4_2[Valor]) -> 0 | G28: =SUM(F28*(1-0.2)) -> 0
A29: Total | B29: =SUM(B26:B28) -> 1.1704108 | C29: =SUM(C26:C28) -> 1.0152495 | E29: Total | F29: =SUM(F26:F28) -> 5.490468 | G29: =SUM(G26:G28) -> 4.6668978 | I29: Total | J29: =SUM(J26:J28) -> 12.971883 | K29: =SUM(K26:K28) -> 12.059995
M30: Ano | N30: LPC
M31: Ano_1 | N31: 0
A32: Tipo | B32: Bruto | C32: Liquido | E32: Tipo | F32: Bruto | G32: Liquido | I32: Tipo | J32: Bruto | K32: Liquido | M32: Ano_2 | N32: 0
A33: JCP | B33: =SUMIF(ITUB3_2[Tipo], "JSCP", ITUB3_2[Valor]) -> 2.90063 | C33: =SUM(B33*(1-0.15)) -> 2.4655355 | E33: JCP | F33: =SUMIF(CMIG4_2[Tipo], "JSCP", CMIG4_2[Valor]) -> 2.7103664 | G33: =SUM(F33*(1-0.15)) -> 2.3038114 | I33: JCP | J33: =SUMIF(PETR4_2[Tipo], "JSCP", PETR4_2[Valor]) -> 1.7185074 | K33: =SUM(J33*(1-0.15)) -> 1.4607313 | M33: Ano_3 | N33: 9.6
A34: Dividendos | B34: =SUMIF(ITUB3_2[Tipo], "Dividendos", ITUB3_2[Valor]) -> 4.244278 | C34: =SUM(B34) -> 4.244278 | E34: Dividendos | F34: =SUMIF(CMIG4_2[Tipo], "Dividendos", CMIG4_2[Valor]) -> 1.6563846 | G34: =SUM(F34) -> 1.6563846 | I34: Dividendos | J34: =SUMIF(PETR4_2[Tipo], "Dividendos", PETR4_2[Valor]) -> 1.5153359 | K34: =SUM(J34) -> 1.5153359 | M34: Total | N34: =SUM(N31:N33) -> 9.6
A35: Rend. Trib. | B35: =SUMIF(ITUB3_2[Tipo], "Rend. Trib.", ITUB3_2[Valor]) -> 0 | C35: =SUM(B35*(1-0.2)) -> 0 | E35: Rend. Trib. | F35: =SUMIF(CMIG4_2[Tipo], "Rend. Trib.", CMIG4_2[Valor]) -> 0 | G35: =SUM(F35*(1-0.2)) -> 0
A36: Total | B36: =SUM(B33:B35) -> 7.144908 | C36: =SUM(C33:C35) -> 6.7098135 | E36: Total | F36: =SUM(F33:F35) -> 4.3667509 | G36: =SUM(G33:G35) -> 3.960196 | I36: Total | J36: =SUM(J33:J35) -> 3.2338433 | K36: =SUM(K33:K35) -> 2.9760672
A39: Tipo | B39: Bruto | C39: Liquido | E39: Tipo | F39: Bruto | G39: Liquido | I39: Tipo | J39: Bruto | K39: Liquido
A40: JCP | B40: =SUMIF(BRBI11_2[Tipo], "JSCP", BRBI11_2[Valor]) -> 0 | C40: =SUM(B40*(1-0.15)) -> 0 | E40: JCP | F40: =SUMIF(SAPR4_2[Tipo], "JSCP", SAPR4_2[Valor]) -> 1.0239526 | G40: =SUM(F40*(1-0.15)) -> 0.87035968 | I40: JCP | J40: =SUMIF(ITUB3_2[Tipo], "JSCP", ITSA4_2[Valor]) -> 2.4046305 | K40: =SUM(J40*(1-0.15)) -> 2.0439359
A41: Dividendos | B41: =SUMIF(BRBI11_2[Tipo], "Dividendos", BRBI11_2[Valor]) -> 1.86 | C41: =SUM(B41) -> 1.86 | E41: Dividendos | F41: =SUMIF(SAPR4_2[Tipo], "Dividendos", SAPR4_2[Valor]) -> 0 | G41: =SUM(F41) -> 0 | I41: Dividendos | J41: =SUMIF(ITUB3_2[Tipo], "Dividendos", ITSA4_2[Valor]) -> 0.047059 | K41: =SUM(J41) -> 0.047059
A42: Rend. Trib. | B42: =SUMIF(BRBI11_2[Tipo], "Rend. Trib.", BRBI11_2[Valor]) -> 0 | C42: =SUM(B42*(1-0.2)) -> 0 | E42: Rend. Trib. | F42: =SUMIF(SAPR4_2[Tipo], "Rend. Trib.", SAPR4_2[Valor]) -> 0 | G42: =SUM(F42*(1-0.2)) -> 0 | I42: Rend. Trib. | J42: =SUMIF(ITUB3_2[Tipo], "Rend. Trib.", ITSA4_2[Valor]) -> 0 | K42: =SUM(J42*(1-0.2)) -> 0
A43: Total | B43: =SUM(B40:B42) -> 1.86 | C43: =SUM(C40:C42) -> 1.86 | E43: Total | F43: =SUM(F40:F42) -> 1.0239526 | G43: =SUM(G40:G42) -> 0.87035968 | I43: Total | J43: =SUM(J40:J42) -> 2.4516895 | K43: =SUM(K40:K42) -> 2.0909949
A47: Tipo | B47: Data COM | C47: Pagamento | D47: Valor | F47: Tipo | G47: Data COM | H47: Pagamento | I47: Valor | K47: Tipo | L47: Data COM | M47: Pagamento | N47: Valor
A48: Dividendos | B48: 45883 | C48: 45895 | D48: 1.9420952 | F48: Dividendos | G48: 45975 | H48: 46050 | I48: 0.51895321 | K48: Dividendos | L48: 46010 | M48: 46981 | N48: 0.412832
F49: JSCP | G49: 45975 | H49: 46050 | I49: 0.41940723 | K49: Dividendos | L49: 46010 | M49: 46610 | N49: 0.412832
A50: Dividendos | B50: 45708 | C50: 45722 | D50: 2.2723292 | F50: Dividendos | G50: 45887 | H50: 45988 | I50: 0.23019206 | K50: Dividendos | L50: 46010 | M50: 46246 | N50: 0.412832
A51: Dividendos | B51: 45520 | C51: 45534 | D51: 1.390909 | F51: JSCP | G51: 45887 | H51: 45988 | I51: 0.63897936 | K51: JSCP | L51: 45994 | M51: 46003 | N51: 0.11129412
F52: JSCP | G52: 45789 | H52: 45896 | I52: 0.54652245 | K52: Dividendos | L52: 45994 | M52: 46003 | N52: 0.3417
A53: Dividendos | B53: 45330 | C53: 45344 | D53: 1.2418756 | F53: Dividendos | G53: 45776 | H53: 45805 | I53: 0.5533013 | K53: JSCP | L53: 45926 | M53: 46003 | N53: 0.110235
F54: Dividendos | G54: 45776 | H54: 45988 | I54: 0.32190459 | K54: Dividendos | L54: 45863 | M54: 45882 | N54: 0.17145038
K55: JSCP | L55: 45828 | M55: 45882 | N55: 0.094058
K56: JSCP | L56: 45737 | M56: 45882 | N56: 0.08070588
K57: Dividendos | L57: 45716 | M57: 45728 | N57: 0.30265269
K58: JSCP | L58: 45646 | M58: 45728 | N58: 0.07976471
A59: Tipo | B59: Data COM | C59: Pagamento | D59: Valor | F59: Tipo | G59: Data COM | H59: Pagamento | I59: Valor | K59: JSCP | L59: 45562 | M59: 45728 | N59: 0.070059
A60: JSCP | B60: 45993 | C60: 46003 | D60: 0.04583263 | F60: JSCP | G60: 46014 | I60: 0.11840132 | K60: Dividendos | L60: 45506 | M60: 45518 | N60: 0.187552
A61: JSCP | B61: 45992 | C61: 46002 | D61: 0.07192713 | F61: JSCP | G61: 46014 | I61: 0.11840132 | K61: JSCP | L61: 45471 | M61: 45518 | N61: 0.06276471
A62: JSCP | B62: 45810 | C62: 45820 | D62: 0.09044687 | F62: Dividendos | G62: 46013 | H62: 46021 | I62: 0.145875 | K62: JSCP | L62: 45373 | M62: 45518 | N62: 0.05776471
A63: JSCP | B63: 45810 | C63: 45820 | D63: 0.3342584 | F63: JSCP | G63: 45929 | I63: 0.1057 | K63: Dividendos | L63: 45345 | M63: 45364 | N63: 0.29794279
A64: Dividendos | B64: 45727 | C64: 45736 | D64: 0.13600181 | F64: JSCP | G64: 45929 | I64: 0.1057
A65: JSCP | B65: 45727 | C65: 45736 | D65: 0.34259249 | F65: JSCP | G65: 45831 | I65: 0.104303
A66: JSCP | B66: 45727 | C66: 45737 | D66: 0.14935148 | F66: JSCP | G66: 45831 | I66: 0.104303 | K66: Tipo | L66: Data COM | M66: Pagamento | N66: Valor
A67: Rend. Trib. | B67: 45727 | C67: 45736 | D67: 0.00354526 | F67: Dividendos | G67: 45777 | H67: 46021 | I67: 0.3294059 | K67: JSCP | L67: 46020 | M67: 46050 | N67: 0.250553
A68: Rend. Trib. | B68: 45727 | C68: 45736 | D68: 0.00893062 | F68: Dividendos | G68: 45777 | H68: 45838 | I68: 0.3294059 | K68: JSCP | L68: 46008 | M68: 46021 | N68: 0.224999
F69: JSCP | G69: 45741 | I69: 0.094559 | K69: JSCP | L69: 45985 | M69: 46003 | N69: 0.224999
F70: JSCP | G70: 45741 | H70: 46386 | I70: 0.09455892 | K70: JSCP | L70: 45960 | M70: 45989 | N70: 0.224999
F71: JSCP | G71: 45649 | H71: 46021 | I71: 0.09790376 | K71: JSCP | L71: 45727 | M71: 45737 | N71: 0.786945
F72: JSCP | G72: 45649 | H72: 45838 | I72: 0.097904 | K72: JSCP | L72: 45699 | M72: 45709 | N72: 0.786945
F73: JSCP | G73: 45558 | H73: 46021 | I73: 0.082601 | K73: JSCP | L73: 45666 | M73: 45678 | N73: 0.786945
F74: JSCP | G74: 45558 | H74: 45838 | I74: 0.08260111 | K74: JSCP | L74: 45273 | M74: 45392 | N74: 1.961247
F75: Dividendos | G75: 45527 | H75: 45534 | I75: 0.49635976 | K75: JSCP | L75: 45273 | M75: 45306 | N75: 0.242836
A76: Tipo | B76: Data COM | C76: Pagamento | D76: Valor | F76: JSCP | G76: 45464 | H76: 46021 | I76: 0.07510604
A77: JSCP | B77: 46021 | C77: 46055 | D77: 0.01765 | F77: JSCP | G77: 45464 | H77: 45838 | I77: 0.07510604
A78: Bonificação | B78: 46014 | C78: 46021 | D78: 0.03 | F78: Dividendos | G78: 45411 | H78: 45653 | I78: 0.121134 | K78: Tipo | L78: Data COM | M78: Pagamento | N78: Valor
A79: JSCP | B79: 46000 | C79: 46142 | D79: 0.36975 | F79: Dividendos | G79: 45411 | H79: 45471 | I79: 0.121134 | K79: Dividendos | L79: 46002 | M79: 46085 | N79: 0.768134
A80: Dividendos | B80: 46000 | C80: 46010 | D80: 1.868223 | F80: Bonificação | G80: 45411 | H80: 45415 | I80: 0.3 | K80: Dividendos | L80: 46002 | M80: 46029 | N80: 1.244102
A81: JSCP | B81: 45989 | C81: 46024 | D81: 0.01765 | F81: JSCP | G81: 45377 | H81: 46021 | I81: 0.08778293 | K81: JSCP | L81: 46002 | M81: 46085 | N81: 1.569535
A82: JSCP | B82: 45961 | C82: 45992 | D82: 0.01765 | F82: JSCP | G82: 45377 | H82: 45838 | I82: 0.08778293 | K82: JSCP | L82: 45881 | M82: 45903 | N82: 1.895387
A83: JSCP | B83: 45930 | C83: 45964 | D83: 0.01765 | F83: JSCP | G83: 45281 | H83: 45653 | I83: 0.30051 | K83: Dividendos | L83: 45723 | M83: 45730 | N83: 2.1418475
A84: JSCP | B84: 45898 | C84: 45931 | D84: 0.01765 | F84: JSCP | G84: 45281 | H84: 45471 | I84: 0.30051 | K84: JSCP | L84: 45637 | M84: 45730 | N84: 0.520531
A85: JSCP | B85: 45887 | C85: 45898 | D85: 0.3634 | F85: JSCP | G85: 45194 | H85: 45653 | I85: 0.094971 | K85: JSCP | L85: 45506 | M85: 45539 | N85: 2.0937981
A86: JSCP | B86: 45869 | C86: 45901 | D86: 0.01765 | F86: JSCP | G86: 45194 | H86: 45471 | I86: 0.094971 | K86: Dividendos | L86: 45362 | M86: 45370 | N86: 2.7385484
A87: JSCP | B87: 45838 | C87: 45870 | D87: 0.01765 | F87: JSCP | G87: 45100 | H87: 45653 | I87: 0.096953
A88: JSCP | B88: 45817 | C88: 45898 | D88: 0.3341 | F88: JSCP | G88: 45100 | H88: 45471 | I88: 0.096953
A89: JSCP | B89: 45807 | C89: 45839 | D89: 0.01765 | F89: Dividendos | G89: 45043 | H89: 45288 | I89: 0.056535 | K89: Tipo | L89: Data COM | M89: Pagamento | N89: Valor
A90: JSCP | B90: 45777 | C90: 45810 | D90: 0.01765 | F90: Dividendos | G90: 45043 | H90: 45107 | I90: 0.056535 | K90: Dividendos | L90: 45763 | M90: 45828 | N90: 0.35477261
A91: JSCP | B91: 45747 | C91: 45779 | D91: 0.01765 | F91: JSCP | G91: 45012 | H91: 45653 | I91: 0.096392 | K91: Dividendos | L91: 45763 | M91: 45797 | N91: 0.35477261
A92: Bonificação | B92: 45733 | C92: 45736 | D92: 0.1 | F92: JSCP | G92: 45012 | H92: 45471 | I92: 0.096392 | K92: Dividendos | L92: 46013 | M92: 46101 | N92: 0.29642144
A93: JSCP | B93: 45716 | C93: 45748 | D93: 0.01765 | K93: JSCP | L93: 46013 | M93: 46073 | N93: 0.471604
A94: Dividendos | B94: 45705 | C94: 45723 | D94: 1.25093 | K94: JSCP | L94: 46013 | M94: 46101 | N94: 0.17518233
A95: JSCP | B95: 45705 | C95: 45723 | D95: 0.33344 | F95: Tipo | G95: Data COM | H95: Pagamento | I95: Valor | K95: JSCP | L95: 45890 | M95: 45982 | N95: 0.33596205
A96: JSCP | B96: 45688 | C96: 45722 | D96: 0.01765 | F96: Dividendos | G96: 45978 | H96: 45987 | I96: 1.02 | K96: JSCP | L96: 45890 | M96: 46013 | N96: 0.13504029
A97: JSCP | B97: 45656 | C97: 45691 | D97: 0.01765 | F97: Dividendos | G97: 45881 | H97: 45890 | I97: 0.36 | K97: Dividendos | L97: 45890 | M97: 46013 | N97: 0.20092175
A98: JSCP | B98: 45635 | C98: 45723 | D98: 0.31056 | F98: Dividendos | G98: 45790 | H98: 45800 | I98: 0.3 | K98: Dividendos | L98: 45810 | M98: 45922 | N98: 0.30844749
A99: JSCP | B99: 45625 | C99: 45659 | D99: 0.01765 | F99: Dividendos | G99: 45743 | H99: 45751 | I99: 0.18 | K99: JSCP | L99: 45810 | M99: 45922 | N99: 0.1461356
A100: JSCP | B100: 45596 | C100: 45628 | D100: 0.01765 | K100: JSCP | L100: 45810 | M100: 45889 | N100: 0.4545831
A101: JSCP | B101: 45565 | C101: 45597 | D101: 0.01765 | K101: Rend. Trib. | L101: 45763 | M101: 45797 | N101: 0.02152467
A102: JSCP | B102: 45554 | C102: 45723 | D102: 0.27298
A103: JSCP | B103: 45534 | C103: 45566 | D103: 0.01765 | F103: Tipo | G103: Data COM | H103: Pagamento | I103: Valor
A104: JSCP | B104: 45504 | C104: 45537 | D104: 0.01765 | F104: JSCP | G104: 46021 | I104: 0.11252854
A105: JSCP | B105: 45471 | C105: 45505 | D105: 0.01765 | F105: JSCP | G105: 45838 | I105: 0.28686103
A106: JSCP | B106: 45463 | C106: 45534 | D106: 0.251 | F106: JSCP | G106: 45656 | H106: 45834 | I106: 0.162991
...

Sheet Indicadores
A2: Título | B2: Taxa de Compra | C2: Preço_Uni | D2: Taxa de Resgate | E2: Preço Unitário de Resgate | F2: Data/Hora da Atualização | G2: Data do Vencimento | I2: Renda | J2: valor
A3: Tesouro IPCA+ 2029 | B3: #NUM! | C3: 0 | D3: 0.0806 | E3: 3846.52 | F3: 46255.827 | G3: 47253 | I3: Selic | J3: 0.139
A4: Tesouro IPCA+ 2032 | B4: 0.0796 | C4: 3007.31 | D4: 0.0808 | E4: 2987.53 | F4: 46255.827 | G4: 48441 | I4: IPCA | J4: 0.044430246
A5: Tesouro IPCA+ 2040 | B5: 0.0749 | C5: 1737.24 | D5: 0.0761 | E5: 1710.51 | F5: 46255.827 | G5: 51363 | I5: Juros_Real | J5: =(1+J3)/(1+(J4+0.0025))-1 -> 0.087942587
A6: Tesouro Renda+ Aposentadoria Extra 2065 | B6: 0.0714 | C6: 186.18 | D6: 0.0726 | E6: 176.87 | F6: 46255.827 | G6: 67556
A7: Tesouro Selic 2031 | B7: #NUM! | C7: 19657.2 | D7: #NUM! | E7: 19648.4 | F7: 46255.827 | G7: 47908

Sheet Aporte
L2: Ticker | M2: QTD | N2: Valor
A3: Ticker | B3: Está barato? | C3: % atual | D3: % ideal | E3: Diferença | F3: Nota | G3: Peso do aporte | H3: R$ Aportar | I3: QTD_Compra | J3: Valor_Total | K3: % Somada | L3: =IFERROR(__xludf.DUMMYFUNCTION("IFERROR( FILTER({ ARRAYFORMULA( Aporte_Mensal[Ticker] & ""("" & Aporte_Mensal[QTD_Compra] & "" "" & TEXT(Aporte_Mensal[% Somada], ""##0.00%"") & "")"" ), Aporte_Mensal[QTD_Compra], Aporte_Mensal[Valor_Total] }, Ap"&"orte_Mensal[QTD_Compra]>0), {""📉 Sem aportes (0x 0.00%)"",0,1} ) "),"📉 Sem aportes (0x 0.00%)") -> 📉 Sem aportes (0x 0.00%) | M3: =IFERROR(__xludf.DUMMYFUNCTION("""COMPUTED_VALUE"""),0.0) -> 0 | N3: =IFERROR(__xludf.DUMMYFUNCTION("""COMPUTED_VALUE"""),1.0) -> 1
A4: BBAS3 | B4: {=IFERROR(IF(AND( INDEX(Ações_Nacionais[], MATCH(A4, Ações_Nacionais[Ação], 0), MATCH(Ações_Nacionais[[#HEADERS],[Preço mercado]], Ações_Nacionais[#HEADERS], 0)) < INDEX(Ações_Nacionais[], MATCH(A4, Ações_Nacionais[Ação], 0), MATCH(Ações_Nacionais[[#HEADERS],[Bazin]], Ações_Nacionais[#HEADERS], 0)), ), "SIM", "NÃO"), "")} -> NÃO | C4: {=IFERROR(INDEX(Ações_Nacionais[], MATCH(A4, Ações_Nacionais[Ação], 0), MATCH(Ações_Nacionais[[#HEADERS],[Peso]], Ações_Nacionais[#HEADERS], 0)), "")} -> 0.013812513 | D4: {=IFERROR(INDEX(Ações_Nacionais[], MATCH(A4, Ações_Nacionais[Ação], 0), MATCH(Ações_Nacionais[[#HEADERS],[Peso Ideal]], Ações_Nacionais[#HEADERS], 0)), "")} -> 0.0375 | E4: =IF(AND(B4="SIM", C4<D4), D4-C4, 0) -> 0 | F4: {=IFERROR(INDEX(Ações_Nacionais[], MATCH(A4, Ações_Nacionais[Ação], 0), 4), "")} -> 10 | G4: =IF(AND(B4="SIM", E4>0), (E4 * F4) / SUMPRODUCT((Aporte_Mensal[Está barato?]="SIM") * (Aporte_Mensal[Diferença]) * (Aporte_Mensal[Nota])), 0) -> 0 | H4: =G4*HOME!$S$8 -> 0 | I4: {=INT(H4 / INDEX(Ações_Nacionais[], MATCH(A4, Ações_Nacionais[Ação], 0), MATCH(Ações_Nacionais[[#HEADERS],[Preço mercado]], Ações_Nacionais[#HEADERS], 0)))} -> 0 | J4: {=I4 * INDEX(Ações_Nacionais[], MATCH(A4, Ações_Nacionais[Ação], 0), MATCH(Ações_Nacionais[[#HEADERS],[Preço mercado]], Ações_Nacionais[#HEADERS], 0))} -> 0 | K4: =((J4/HOME!$B$9)+C4) -> 0.013812513
A5: BBSE3 | B5: {=IFERROR(IF(AND( INDEX(Ações_Nacionais[], MATCH(A5, Ações_Nacionais[Ação], 0), MATCH(Ações_Nacionais[[#HEADERS],[Preço mercado]], Ações_Nacionais[#HEADERS], 0)) < INDEX(Ações_Nacionais[], MATCH(A5, Ações_Nacionais[Ação], 0), MATCH(Ações_Nacionais[[#HEADERS],[Bazin]], Ações_Nacionais[#HEADERS], 0)), ), "SIM", "NÃO"), "")} -> NÃO | C5: {=IFERROR(INDEX(Ações_Nacionais[], MATCH(A5, Ações_Nacionais[Ação], 0), MATCH(Ações_Nacionais[[#HEADERS],[Peso]], Ações_Nacionais[#HEADERS], 0)), "")} -> 0.027872348 | D5: {=IFERROR(INDEX(Ações_Nacionais[], MATCH(A5, Ações_Nacionais[Ação], 0), MATCH(Ações_Nacionais[[#HEADERS],[Peso Ideal]], Ações_Nacionais[#HEADERS], 0)), "")} -> 0.0375 | E5: =IF(AND(B5="SIM", C5<D5), D5-C5, 0) -> 0 | F5: {=IFERROR(INDEX(Ações_Nacionais[], MATCH(A5, Ações_Nacionais[Ação], 0), 4), "")} -> 10 | G5: =IF(AND(B5="SIM", E5>0), (E5 * F5) / SUMPRODUCT((Aporte_Mensal[Está barato?]="SIM") * (Aporte_Mensal[Diferença]) * (Aporte_Mensal[Nota])), 0) -> 0 | H5: =G5*HOME!$S$8 -> 0 | I5: {=INT(H5 / INDEX(Ações_Nacionais[], MATCH(A5, Ações_Nacionais[Ação], 0), MATCH(Ações_Nacionais[[#HEADERS],[Preço mercado]], Ações_Nacionais[#HEADERS], 0)))} -> 0 | J5: {=I5 * INDEX(Ações_Nacionais[], MATCH(A5, Ações_Nacionais[Ação], 0), MATCH(Ações_Nacionais[[#HEADERS],[Preço mercado]], Ações_Nacionais[#HEADERS], 0))} -> 0 | K5: =((J5/HOME!$B$9)+C5) -> 0.027872348
A6: VALE3 | B6: {=IFERROR(IF(AND( INDEX(Ações_Nacionais[], MATCH(A6, Ações_Nacionais[Ação], 0), MATCH(Ações_Nacionais[[#HEADERS],[Preço mercado]], Ações_Nacionais[#HEADERS], 0)) < INDEX(Ações_Nacionais[], MATCH(A6, Ações_Nacionais[Ação], 0), MATCH(Ações_Nacionais[[#HEADERS],[Bazin]], Ações_Nacionais[#HEADERS], 0)), ), "SIM", "NÃO"), "")} -> NÃO | C6: {=IFERROR(INDEX(Ações_Nacionais[], MATCH(A6, Ações_Nacionais[Ação], 0), MATCH(Ações_Nacionais[[#HEADERS],[Peso]], Ações_Nacionais[#HEADERS], 0)), "")} -> 0.056231844 | D6: {=IFERROR(INDEX(Ações_Nacionais[], MATCH(A6, Ações_Nacionais[Ação], 0), MATCH(Ações_Nacionais[[#HEADERS],[Peso Ideal]], Ações_Nacionais[#HEADERS], 0)), "")} -> 0.0375 | E6: =IF(AND(B6="SIM", C6<D6), D6-C6, 0) -> 0 | F6: {=IFERROR(INDEX(Ações_Nacionais[], MATCH(A6, Ações_Nacionais[Ação], 0), 4), "")} -> 10 | G6: =IF(AND(B6="SIM", E6>0), (E6 * F6) / SUMPRODUCT((Aporte_Mensal[Está barato?]="SIM") * (Aporte_Mensal[Diferença]) * (Aporte_Mensal[Nota])), 0) -> 0 | H6: =G6*HOME!$S$8 -> 0 | I6: {=INT(H6 / INDEX(Ações_Nacionais[], MATCH(A6, Ações_Nacionais[Ação], 0), MATCH(Ações_Nacionais[[#HEADERS],[Preço mercado]], Ações_Nacionais[#HEADERS], 0)))} -> 0 | J6: {=I6 * INDEX(Ações_Nacionais[], MATCH(A6, Ações_Nacionais[Ação], 0), MATCH(Ações_Nacionais[[#HEADERS],[Preço mercado]], Ações_Nacionais[#HEADERS], 0))} -> 0 | K6: =((J6/HOME!$B$9)+C6) -> 0.056231844
A7: TAEE11 | B7: {=IFERROR(IF(AND( INDEX(Ações_Nacionais[], MATCH(A7, Ações_Nacionais[Ação], 0), MATCH(Ações_Nacionais[[#HEADERS],[Preço mercado]], Ações_Nacionais[#HEADERS], 0)) < INDEX(Ações_Nacionais[], MATCH(A7, Ações_Nacionais[Ação], 0), MATCH(Ações_Nacionais[[#HEADERS],[Bazin]], Ações_Nacionais[#HEADERS], 0)), ), "SIM", "NÃO"), "")} -> NÃO | C7: {=IFERROR(INDEX(Ações_Nacionais[], MATCH(A7, Ações_Nacionais[Ação], 0), MATCH(Ações_Nacionais[[#HEADERS],[Peso]], Ações_Nacionais[#HEADERS], 0)), "")} -> 0.028157142 | D7: {=IFERROR(INDEX(Ações_Nacionais[], MATCH(A7, Ações_Nacionais[Ação], 0), MATCH(Ações_Nacionais[[#HEADERS],[Peso Ideal]], Ações_Nacionais[#HEADERS], 0)), "")} -> 0.0375 | E7: =IF(AND(B7="SIM", C7<D7), D7-C7, 0) -> 0 | F7: {=IFERROR(INDEX(Ações_Nacionais[], MATCH(A7, Ações_Nacionais[Ação], 0), 4), "")} -> 10 | G7: =IF(AND(B7="SIM", E7>0), (E7 * F7) / SUMPRODUCT((Aporte_Mensal[Está barato?]="SIM") * (Aporte_Mensal[Diferença]) * (Aporte_Mensal[Nota])), 0) -> 0 | H7: =G7*HOME!$S$8 -> 0 | I7: {=INT(H7 / INDEX(Ações_Nacionais[], MATCH(A7, Ações_Nacionais[Ação], 0), MATCH(Ações_Nacionais[[#HEADERS],[Preço mercado]], Ações_Nacionais[#HEADERS], 0)))} -> 0 | J7: {=I7 * INDEX(Ações_Nacionais[], MATCH(A7, Ações_Nacionais[Ação], 0), MATCH(Ações_Nacionais[[#HEADERS],[Preço mercado]], Ações_Nacionais[#HEADERS], 0))} -> 0 | K7: =((J7/HOME!$B$9)+C7) -> 0.028157142
A8: ITUB3 | B8: {=IFERROR(IF(AND( INDEX(Ações_Nacionais[], MATCH(A8, Ações_Nacionais[Ação], 0), MATCH(Ações_Nacionais[[#HEADERS],[Preço mercado]], Ações_Nacionais[#HEADERS], 0)) < INDEX(Ações_Nacionais[], MATCH(A8, Ações_Nacionais[Ação], 0), MATCH(Ações_Nacionais[[#HEADERS],[Bazin]], Ações_Nacionais[#HEADERS], 0)), ), "SIM", "NÃO"), "")} -> NÃO | C8: {=IFERROR(INDEX(Ações_Nacionais[], MATCH(A8, Ações_Nacionais[Ação], 0), MATCH(Ações_Nacionais[[#HEADERS],[Peso]], Ações_Nacionais[#HEADERS], 0)), "")} -> 0.031020072 | D8: {=IFERROR(INDEX(Ações_Nacionais[], MATCH(A8, Ações_Nacionais[Ação], 0), MATCH(Ações_Nacionais[[#HEADERS],[Peso Ideal]], Ações_Nacionais[#HEADERS], 0)), "")} -> 0.0375 | E8: =IF(AND(B8="SIM", C8<D8), D8-C8, 0) -> 0 | F8: {=IFERROR(INDEX(Ações_Nacionais[], MATCH(A8, Ações_Nacionais[Ação], 0), 4), "")} -> 10 | G8: =IF(AND(B8="SIM", E8>0), (E8 * F8) / SUMPRODUCT((Aporte_Mensal[Está barato?]="SIM") * (Aporte_Mensal[Diferença]) * (Aporte_Mensal[Nota])), 0) -> 0 | H8: =G8*HOME!$S$8 -> 0 | I8: {=INT(H8 / INDEX(Ações_Nacionais[], MATCH(A8, Ações_Nacionais[Ação], 0), MATCH(Ações_Nacionais[[#HEADERS],[Preço mercado]], Ações_Nacionais[#HEADERS], 0)))} -> 0 | J8: {=I8 * INDEX(Ações_Nacionais[], MATCH(A8, Ações_Nacionais[Ação], 0), MATCH(Ações_Nacionais[[#HEADERS],[Preço mercado]], Ações_Nacionais[#HEADERS], 0))} -> 0 | K8: =((J8/HOME!$B$9)+C8) -> 0.031020072
A9: PETR4 | B9: {=IFERROR(IF(AND( INDEX(Ações_Nacionais[], MATCH(A9, Ações_Nacionais[Ação], 0), MATCH(Ações_Nacionais[[#HEADERS],[Preço mercado]], Ações_Nacionais[#HEADERS], 0)) < INDEX(Ações_Nacionais[], MATCH(A9, Ações_Nacionais[Ação], 0), MATCH(Ações_Nacionais[[#HEADERS],[Bazin]], Ações_Nacionais[#HEADERS], 0)), ), "SIM", "NÃO"), "")} -> NÃO | C9: {=IFERROR(INDEX(Ações_Nacionais[], MATCH(A9, Ações_Nacionais[Ação], 0), MATCH(Ações_Nacionais[[#HEADERS],[Peso]], Ações_Nacionais[#HEADERS], 0)), "")} -> 0.033200995 | D9: {=IFERROR(INDEX(Ações_Nacionais[], MATCH(A9, Ações_Nacionais[Ação], 0), MATCH(Ações_Nacionais[[#HEADERS],[Peso Ideal]], Ações_Nacionais[#HEADERS], 0)), "")} -> 0.0375 | E9: =IF(AND(B9="SIM", C9<D9), D9-C9, 0) -> 0 | F9: {=IFERROR(INDEX(Ações_Nacionais[], MATCH(A9, Ações_Nacionais[Ação], 0), 4), "")} -> 10 | G9: =IF(AND(B9="SIM", E9>0), (E9 * F9) / SUMPRODUCT((Aporte_Mensal[Está barato?]="SIM") * (Aporte_Mensal[Diferença]) * (Aporte_Mensal[Nota])), 0) -> 0 | H9: =G9*HOME!$S$8 -> 0 | I9: {=INT(H9 / INDEX(Ações_Nacionais[], MATCH(A9, Ações_Nacionais[Ação], 0), MATCH(Ações_Nacionais[[#HEADERS],[Preço mercado]], Ações_Nacionais[#HEADERS], 0)))} -> 0 | J9: {=I9 * INDEX(Ações_Nacionais[], MATCH(A9, Ações_Nacionais[Ação], 0), MATCH(Ações_Nacionais[[#HEADERS],[Preço mercado]], Ações_Nacionais[#HEADERS], 0))} -> 0 | K9: =((J9/HOME!$B$9)+C9) -> 0.033200995
A10: WEGE3 | B10: {=IFERROR(IF(AND( INDEX(Ações_Nacionais[], MATCH(A10, Ações_Nacionais[Ação], 0), MATCH(Ações_Nacionais[[#HEADERS],[Preço mercado]], Ações_Nacionais[#HEADERS], 0)) < INDEX(Ações_Nacionais[], MATCH(A10, Ações_Nacionais[Ação], 0), MATCH(Ações_Nacionais[[#HEADERS],[Bazin]], Ações_Nacionais[#HEADERS], 0)), ), "SIM", "NÃO"), "")} -> NÃO | C10: {=IFERROR(INDEX(Ações_Nacionais[], MATCH(A10, Ações_Nacionais[Ação], 0), MATCH(Ações_Nacionais[[#HEADERS],[Peso]], Ações_Nacionais[#HEADERS], 0)), "")} -> 0.036925802 | D10: {=IFERROR(INDEX(Ações_Nacionais[], MATCH(A10, Ações_Nacionais[Ação], 0), MATCH(Ações_Nacionais[[#HEADERS],[Peso Ideal]], Ações_Nacionais[#HEADERS], 0)), "")} -> 0.0375 | E10: =IF(AND(B10="SIM", C10<D10), D10-C10, 0) -> 0 | F10: {=IFERROR(INDEX(Ações_Nacionais[], MATCH(A10, Ações_Nacionais[Ação], 0), 4), "")} -> 10 | G10: =IF(AND(B10="SIM", E10>0), (E10 * F10) / SUMPRODUCT((Aporte_Mensal[Está barato?]="SIM") * (Aporte_Mensal[Diferença]) * (Aporte_Mensal[Nota])), 0) -> 0 | H10: =G10*HOME!$S$8 -> 0 | I10: {=INT(H10 / INDEX(Ações_Nacionais[], MATCH(A10, Ações_Nacionais[Ação], 0), MATCH(Ações_Nacionais[[#HEADERS],[Preço mercado]], Ações_Nacionais[#HEADERS], 0)))} -> 0 | J10: {=I10 * INDEX(Ações_Nacionais[], MATCH(A10, Ações_Nacionais[Ação], 0), MATCH(Ações_Nacionais[[#HEADERS],[Preço mercado]], Ações_Nacionais[#HEADERS], 0))} -> 0 | K10: =((J10/HOME!$B$9)+C10) -> 0.036925802
A11: BRBI11 | B11: {=IFERROR(IF(AND( INDEX(Ações_Nacionais[], MATCH(A11, Ações_Nacionais[Ação], 0), MATCH(Ações_Nacionais[[#HEADERS],[Preço mercado]], Ações_Nacionais[#HEADERS], 0)) < INDEX(Ações_Nacionais[], MATCH(A11, Ações_Nacionais[Ação], 0), MATCH(Ações_Nacionais[[#HEADERS],[Bazin]], Ações_Nacionais[#HEADERS], 0)), ), "SIM", "NÃO"), "")} -> SIM | C11: {=IFERROR(INDEX(Ações_Nacionais[], MATCH(A11, Ações_Nacionais[Ação], 0), MATCH(Ações_Nacionais[[#HEADERS],[Peso]], Ações_Nacionais[#HEADERS], 0)), "")} -> 0.0091059163 | D11: {=IFERROR(INDEX(Ações_Nacionais[], MATCH(A11, Ações_Nacionais[Ação], 0), MATCH(Ações_Nacionais[[#HEADERS],[Peso Ideal]], Ações_Nacionais[#HEADERS], 0)), "")} -> 0 | E11: =IF(AND(B11="SIM", C11<D11), D11-C11, 0) -> 0 | F11: {=IFERROR(INDEX(Ações_Nacionais[], MATCH(A11, Ações_Nacionais[Ação], 0), 4), "")} -> 0 | G11: =IF(AND(B11="SIM", E11>0), (E11 * F11) / SUMPRODUCT((Aporte_Mensal[Está barato?]="SIM") * (Aporte_Mensal[Diferença]) * (Aporte_Mensal[Nota])), 0) -> 0 | H11: =G11*HOME!$S$8 -> 0 | I11: {=INT(H11 / INDEX(Ações_Nacionais[], MATCH(A11, Ações_Nacionais[Ação], 0), MATCH(Ações_Nacionais[[#HEADERS],[Preço mercado]], Ações_Nacionais[#HEADERS], 0)))} -> 0 | J11: {=I11 * INDEX(Ações_Nacionais[], MATCH(A11, Ações_Nacionais[Ação], 0), MATCH(Ações_Nacionais[[#HEADERS],[Preço mercado]], Ações_Nacionais[#HEADERS], 0))} -> 0 | K11: =((J11/HOME!$B$9)+C11) -> 0.0091059163
A12: CMIG4 | B12: {=IFERROR(IF(AND( INDEX(Ações_Nacionais[], MATCH(A12, Ações_Nacionais[Ação], 0), MATCH(Ações_Nacionais[[#HEADERS],[Preço mercado]], Ações_Nacionais[#HEADERS], 0)) < INDEX(Ações_Nacionais[], MATCH(A12, Ações_Nacionais[Ação], 0), MATCH(Ações_Nacionais[[#HEADERS],[Bazin]], Ações_Nacionais[#HEADERS], 0)), ), "SIM", "NÃO"), "")} -> SIM | C12: {=IFERROR(INDEX(Ações_Nacionais[], MATCH(A12, Ações_Nacionais[Ação], 0), MATCH(Ações_Nacionais[[#HEADERS],[Peso]], Ações_Nacionais[#HEADERS], 0)), "")} -> 0.0075245597 | D12: {=IFERROR(INDEX(Ações_Nacionais[], MATCH(A12, Ações_Nacionais[Ação], 0), MATCH(Ações_Nacionais[[#HEADERS],[Peso Ideal]], Ações_Nacionais[#HEADERS], 0)), "")} -> 0.0375 | E12: =IF(AND(B12="SIM", C12<D12), D12-C12, 0) -> 0.02997544 | F12: {=IFERROR(INDEX(Ações_Nacionais[], MATCH(A12, Ações_Nacionais[Ação], 0), 4), "")} -> 10 | G12: =IF(AND(B12="SIM", E12>0), (E12 * F12) / SUMPRODUCT((Aporte_Mensal[Está barato?]="SIM") * (Aporte_Mensal[Diferença]) * (Aporte_Mensal[Nota])), 0) -> 0.47846692 | H12: =G12*HOME!$S$8 -> 0 | I12: {=INT(H12 / INDEX(Ações_Nacionais[], MATCH(A12, Ações_Nacionais[Ação], 0), MATCH(Ações_Nacionais[[#HEADERS],[Preço mercado]], Ações_Nacionais[#HEADERS], 0)))} -> 0 | J12: {=I12 * INDEX(Ações_Nacionais[], MATCH(A12, Ações_Nacionais[Ação], 0), MATCH(Ações_Nacionais[[#HEADERS],[Preço mercado]], Ações_Nacionais[#HEADERS], 0))} -> 0 | K12: =((J12/HOME!$B$9)+C12) -> 0.0075245597 | L12: =IF(HOME!$U$8 = 0, "Ações : 💸 Sem aporte", "Ações K: " & IF(HOME!$Q$8 - SUM(Aporte_Mensal[Valor_Total]) - SUM(Fiis_Aporte[Valor_Total]) < 0, "🔻", "🟢") & TEXT(HOME!$V$8, " R$ #,##0.00") & " V:💰 " & TEXT(HOME!$U$8, " R$ #,##0.00") ) -> Ações : 💸 Sem aporte
A13: ISAE4 | B13: {=IFERROR(IF(AND( INDEX(Ações_Nacionais[], MATCH(A13, Ações_Nacionais[Ação], 0), MATCH(Ações_Nacionais[[#HEADERS],[Preço mercado]], Ações_Nacionais[#HEADERS], 0)) < INDEX(Ações_Nacionais[], MATCH(A13, Ações_Nacionais[Ação], 0), MATCH(Ações_Nacionais[[#HEADERS],[Bazin]], Ações_Nacionais[#HEADERS], 0)), ), "SIM", "NÃO"), "")} -> NÃO | C13: {=IFERROR(INDEX(Ações_Nacionais[], MATCH(A13, Ações_Nacionais[Ação], 0), MATCH(Ações_Nacionais[[#HEADERS],[Peso]], Ações_Nacionais[#HEADERS], 0)), "")} -> 0.019500901 | D13: {=IFERROR(INDEX(Ações_Nacionais[], MATCH(A13, Ações_Nacionais[Ação], 0), MATCH(Ações_Nacionais[[#HEADERS],[Peso Ideal]], Ações_Nacionais[#HEADERS], 0)), "")} -> 0.0375 | E13: =IF(AND(B13="SIM", C13<D13), D13-C13, 0) -> 0 | F13: {=IFERROR(INDEX(Ações_Nacionais[], MATCH(A13, Ações_Nacionais[Ação], 0), 4), "")} -> 10 | G13: =IF(AND(B13="SIM", E13>0), (E13 * F13) / SUMPRODUCT((Aporte_Mensal[Está barato?]="SIM") * (Aporte_Mensal[Diferença]) * (Aporte_Mensal[Nota])), 0) -> 0 | H13: =G13*HOME!$S$8 -> 0 | I13: {=INT(H13 / INDEX(Ações_Nacionais[], MATCH(A13, Ações_Nacionais[Ação], 0), MATCH(Ações_Nacionais[[#HEADERS],[Preço mercado]], Ações_Nacionais[#HEADERS], 0)))} -> 0 | J13: {=I13 * INDEX(Ações_Nacionais[], MATCH(A13, Ações_Nacionais[Ação], 0), MATCH(Ações_Nacionais[[#HEADERS],[Preço mercado]], Ações_Nacionais[#HEADERS], 0))} -> 0 | K13: =((J13/HOME!$B$9)+C13) -> 0.019500901 | L13: =IF(HOME!$U$8 = 0, "FIIs : 💸 Sem aporte", "FIIs K: " & IF(HOME!$Q$8 - SUM(Aporte_Mensal[Valor_Total]) - SUM(Fiis_Aporte[Valor_Total]) < 0, "🔻", "🟢") & TEXT(HOME!$V$8, " R$ #,##0.00") & " V:💰 " & TEXT(HOME!$U$8, " R$ #,##0.00") ) -> FIIs : 💸 Sem aporte
A14: SAPR4 | B14: {=IFERROR(IF(AND( INDEX(Ações_Nacionais[], MATCH(A14, Ações_Nacionais[Ação], 0), MATCH(Ações_Nacionais[[#HEADERS],[Preço mercado]], Ações_Nacionais[#HEADERS], 0)) < INDEX(Ações_Nacionais[], MATCH(A14, Ações_Nacionais[Ação], 0), MATCH(Ações_Nacionais[[#HEADERS],[Bazin]], Ações_Nacionais[#HEADERS], 0)), ), "SIM", "NÃO"), "")} -> SIM | C14: {=IFERROR(INDEX(Ações_Nacionais[], MATCH(A14, Ações_Nacionais[Ação], 0), MATCH(Ações_Nacionais[[#HEADERS],[Peso]], Ações_Nacionais[#HEADERS], 0)), "")} -> 0.0048265104 | D14: {=IFERROR(INDEX(Ações_Nacionais[], MATCH(A14, Ações_Nacionais[Ação], 0), MATCH(Ações_Nacionais[[#HEADERS],[Peso Ideal]], Ações_Nacionais[#HEADERS], 0)), "")} -> 0.0375 | E14: =IF(AND(B14="SIM", C14<D14), D14-C14, 0) -> 0.03267349 | F14: {=IFERROR(INDEX(Ações_Nacionais[], MATCH(A14, Ações_Nacionais[Ação], 0), 4), "")} -> 10 | G14: =IF(AND(B14="SIM", E14>0), (E14 * F14) / SUMPRODUCT((Aporte_Mensal[Está barato?]="SIM") * (Aporte_Mensal[Diferença]) * (Aporte_Mensal[Nota])), 0) -> 0.52153308 | H14: =G14*HOME!$S$8 -> 0 | I14: {=INT(H14 / INDEX(Ações_Nacionais[], MATCH(A14, Ações_Nacionais[Ação], 0), MATCH(Ações_Nacionais[[#HEADERS],[Preço mercado]], Ações_Nacionais[#HEADERS], 0)))} -> 0 | J14: {=I14 * INDEX(Ações_Nacionais[], MATCH(A14, Ações_Nacionais[Ação], 0), MATCH(Ações_Nacionais[[#HEADERS],[Preço mercado]], Ações_Nacionais[#HEADERS], 0))} -> 0 | K14: =((J14/HOME!$B$9)+C14) -> 0.0048265104
L17: Ticker | M17: QTD | N17: Valor
A18: Ticker | B18: Está barato? | C18: % atual | D18: % ideal | E18: Diferença | F18: Nota | G18: Peso do aporte | H18: R$ Aportar | I18: QTD_Compra | J18: Valor_Total | K18: % Somada | L18: =IFERROR(__xludf.DUMMYFUNCTION("IFERROR( FILTER({ ARRAYFORMULA( Fiis_Aporte[Ticker] & ""("" & Fiis_Aporte[QTD_Compra] & "" "" & TEXT(Fiis_Aporte[% Somada], ""##0.00%"") & "")"" ), Fiis_Aporte[QTD_Compra], Fiis_Aporte[Valor_Total] }, Fiis_Aporte["&"QTD_Compra]>0), {""📉 Sem aportes (0x 0.00%)"",0,1} ) "),"📉 Sem aportes (0x 0.00%)") -> 📉 Sem aportes (0x 0.00%) | M18: =IFERROR(__xludf.DUMMYFUNCTION("""COMPUTED_VALUE"""),0.0) -> 0 | N18: =IFERROR(__xludf.DUMMYFUNCTION("""COMPUTED_VALUE"""),1.0) -> 1
A19: XPLG11 | B19: {=IFERROR(IF(AND( INDEX(Fiis[], MATCH(A19, Fiis[Fii], 0), MATCH(Fiis[[#HEADERS],[Preço mercado]], Fiis[#HEADERS], 0)) < INDEX(Fiis[], MATCH(A19, Fiis[Fii], 0), MATCH(Fiis[[#HEADERS],[Barato]], Fiis[#HEADERS], 0)), INDEX(Fiis[], MATCH(A19, Fiis[Fii], 0), MATCH(Fiis[[#HEADERS],[Preço mercado]], Fiis[#HEADERS], 0)) < INDEX(Fiis[], MATCH(A19, Fiis[Fii], 0), MATCH(Fiis[[#HEADERS],[Justo]], Fiis[#HEADERS], 0)), INDEX(Fiis[], MATCH(A19, Fiis[Fii], 0), MATCH(Fiis[[#HEADERS],[Preço mercado]], Fiis[#HEADERS], 0)) < INDEX(Fiis[], MATCH(A19, Fiis[Fii], 0), MATCH(Fiis[[#HEADERS],[VP/Cota]], Fiis[#HEADERS], 0)) ), "SIM", "NÃO"), "")} -> NÃO | C19: {=IFERROR(INDEX(Fiis[], MATCH(A19, Fiis[Fii], 0), MATCH(Fiis[[#HEADERS],[Peso]], Fiis[#HEADERS], 0)), "")} -> 0.033725616 | D19: {=IFERROR(INDEX(Fiis[], MATCH(A19, Fiis[Fii], 0), MATCH(Fiis[[#HEADERS],[Peso Ideal]], Fiis[#HEADERS], 0)), "")} -> 0.022727273 | E19: =IF(AND(B19="SIM", C19<D19), D19-C19, 0) -> 0 | F19: {=IFERROR(INDEX(Fiis[], MATCH(A19, Fiis[Fii], 0), MATCH(Fiis[[#HEADERS],[Nota]], Fiis[#HEADERS], 0)), "")} -> 10 | G19: =IF(AND(B19="SIM", E19>0), (E19 * F19) / SUMPRODUCT((Fiis_Aporte[Está barato?]="SIM") * (Fiis_Aporte[Diferença]) * (Fiis_Aporte[Nota])), 0) -> 0 | H19: =G19*HOME!$T$8 -> 0 | I19: {=INT(H19 / INDEX(Fiis[], MATCH(A19, Fiis[Fii], 0), MATCH(Fiis[[#HEADERS],[Preço mercado]], Fiis[#HEADERS], 0)))} -> 0 | J19: {=I19 * INDEX(Fiis[], MATCH(A19, Fiis[Fii], 0), MATCH(Fiis[[#HEADERS],[Preço mercado]], Fiis[#HEADERS], 0))} -> 0 | K19: =((J19/HOME!$B$9)+C19) -> 0.033725616
A20: PMLL11 | B20: {=IFERROR(IF(AND( INDEX(Fiis[], MATCH(A20, Fiis[Fii], 0), MATCH(Fiis[[#HEADERS],[Preço mercado]], Fiis[#HEADERS], 0)) < INDEX(Fiis[], MATCH(A20, Fiis[Fii], 0), MATCH(Fiis[[#HEADERS],[Barato]], Fiis[#HEADERS], 0)), INDEX(Fiis[], MATCH(A20, Fiis[Fii], 0), MATCH(Fiis[[#HEADERS],[Preço mercado]], Fiis[#HEADERS], 0)) < INDEX(Fiis[], MATCH(A20, Fiis[Fii], 0), MATCH(Fiis[[#HEADERS],[Justo]], Fiis[#HEADERS], 0)), INDEX(Fiis[], MATCH(A20, Fiis[Fii], 0), MATCH(Fiis[[#HEADERS],[Preço mercado]], Fiis[#HEADERS], 0)) < INDEX(Fiis[], MATCH(A20, Fiis[Fii], 0), MATCH(Fiis[[#HEADERS],[VP/Cota]], Fiis[#HEADERS], 0)) ), "SIM", "NÃO"), "")} -> NÃO | C20: {=IFERROR(INDEX(Fiis[], MATCH(A20, Fiis[Fii], 0), MATCH(Fiis[[#HEADERS],[Peso]], Fiis[#HEADERS], 0)), "")} -> 0.037783932 | D20: {=IFERROR(INDEX(Fiis[], MATCH(A20, Fiis[Fii], 0), MATCH(Fiis[[#HEADERS],[Peso Ideal]], Fiis[#HEADERS], 0)), "")} -> 0.022727273 | E20: =IF(AND(B20="SIM", C20<D20), D20-C20, 0) -> 0 | F20: {=IFERROR(INDEX(Fiis[], MATCH(A20, Fiis[Fii], 0), MATCH(Fiis[[#HEADERS],[Nota]], Fiis[#HEADERS], 0)), "")} -> 10 | G20: =IF(AND(B20="SIM", E20>0), (E20 * F20) / SUMPRODUCT((Fiis_Aporte[Está barato?]="SIM") * (Fiis_Aporte[Diferença]) * (Fiis_Aporte[Nota])), 0) -> 0 | H20: =G20*HOME!$T$8 -> 0 | I20: {=INT(H20 / INDEX(Fiis[], MATCH(A20, Fiis[Fii], 0), MATCH(Fiis[[#HEADERS],[Preço mercado]], Fiis[#HEADERS], 0)))} -> 0 | J20: {=I20 * INDEX(Fiis[], MATCH(A20, Fiis[Fii], 0), MATCH(Fiis[[#HEADERS],[Preço mercado]], Fiis[#HEADERS], 0))} -> 0 | K20: =((J20/HOME!$B$9)+C20) -> 0.037783932
A21: MXRF11 | B21: {=IFERROR(IF(AND( INDEX(Fiis[], MATCH(A21, Fiis[Fii], 0), MATCH(Fiis[[#HEADERS],[Preço mercado]], Fiis[#HEADERS], 0)) < INDEX(Fiis[], MATCH(A21, Fiis[Fii], 0), MATCH(Fiis[[#HEADERS],[Barato]], Fiis[#HEADERS], 0)), INDEX(Fiis[], MATCH(A21, Fiis[Fii], 0), MATCH(Fiis[[#HEADERS],[Preço mercado]], Fiis[#HEADERS], 0)) < INDEX(Fiis[], MATCH(A21, Fiis[Fii], 0), MATCH(Fiis[[#HEADERS],[Justo]], Fiis[#HEADERS], 0)), INDEX(Fiis[], MATCH(A21, Fiis[Fii], 0), MATCH(Fiis[[#HEADERS],[Preço mercado]], Fiis[#HEADERS], 0)) < INDEX(Fiis[], MATCH(A21, Fiis[Fii], 0), MATCH(Fiis[[#HEADERS],[VP/Cota]], Fiis[#HEADERS], 0)) ), "SIM", "NÃO"), "")} -> NÃO | C21: {=IFERROR(INDEX(Fiis[], MATCH(A21, Fiis[Fii], 0), MATCH(Fiis[[#HEADERS],[Peso]], Fiis[#HEADERS], 0)), "")} -> 0.0034699912 | D21: {=IFERROR(INDEX(Fiis[], MATCH(A21, Fiis[Fii], 0), MATCH(Fiis[[#HEADERS],[Peso Ideal]], Fiis[#HEADERS], 0)), "")} -> 0.022727273 | E21: =IF(AND(B21="SIM", C21<D21), D21-C21, 0) -> 0 | F21: {=IFERROR(INDEX(Fiis[], MATCH(A21, Fiis[Fii], 0), MATCH(Fiis[[#HEADERS],[Nota]], Fiis[#HEADERS], 0)), "")} -> 10 | G21: =IF(AND(B21="SIM", E21>0), (E21 * F21) / SUMPRODUCT((Fiis_Aporte[Está barato?]="SIM") * (Fiis_Aporte[Diferença]) * (Fiis_Aporte[Nota])), 0) -> 0 | H21: =G21*HOME!$T$8 -> 0 | I21: {=INT(H21 / INDEX(Fiis[], MATCH(A21, Fiis[Fii], 0), MATCH(Fiis[[#HEADERS],[Preço mercado]], Fiis[#HEADERS], 0)))} -> 0 | J21: {=I21 * INDEX(Fiis[], MATCH(A21, Fiis[Fii], 0), MATCH(Fiis[[#HEADERS],[Preço mercado]], Fiis[#HEADERS], 0))} -> 0 | K21: =((J21/HOME!$B$9)+C21) -> 0.0034699912
A22: LVBI11 | B22: {=IFERROR(IF(AND( INDEX(Fiis[], MATCH(A22, Fiis[Fii], 0), MATCH(Fiis[[#HEADERS],[Preço mercado]], Fiis[#HEADERS], 0)) < INDEX(Fiis[], MATCH(A22, Fiis[Fii], 0), MATCH(Fiis[[#HEADERS],[Barato]], Fiis[#HEADERS], 0)), INDEX(Fiis[], MATCH(A22, Fiis[Fii], 0), MATCH(Fiis[[#HEADERS],[Preço mercado]], Fiis[#HEADERS], 0)) < INDEX(Fiis[], MATCH(A22, Fiis[Fii], 0), MATCH(Fiis[[#HEADERS],[Justo]], Fiis[#HEADERS], 0)), INDEX(Fiis[], MATCH(A22, Fiis[Fii], 0), MATCH(Fiis[[#HEADERS],[Preço mercado]], Fiis[#HEADERS], 0)) < INDEX(Fiis[], MATCH(A22, Fiis[Fii], 0), MATCH(Fiis[[#HEADERS],[VP/Cota]], Fiis[#HEADERS], 0)) ), "SIM", "NÃO"), "")} -> NÃO | C22: {=IFERROR(INDEX(Fiis[], MATCH(A22, Fiis[Fii], 0), MATCH(Fiis[[#HEADERS],[Peso]], Fiis[#HEADERS], 0)), "")} -> 0.036907066 | D22: {=IFERROR(INDEX(Fiis[], MATCH(A22, Fiis[Fii], 0), MATCH(Fiis[[#HEADERS],[Peso Ideal]], Fiis[#HEADERS], 0)), "")} -> 0.022727273 | E22: =IF(AND(B22="SIM", C22<D22), D22-C22, 0) -> 0 | F22: {=IFERROR(INDEX(Fiis[], MATCH(A22, Fiis[Fii], 0), MATCH(Fiis[[#HEADERS],[Nota]], Fiis[#HEADERS], 0)), "")} -> 10 | G22: =IF(AND(B22="SIM", E22>0), (E22 * F22) / SUMPRODUCT((Fiis_Aporte[Está barato?]="SIM") * (Fiis_Aporte[Diferença]) * (Fiis_Aporte[Nota])), 0) -> 0 | H22: =G22*HOME!$T$8 -> 0 | I22: {=INT(H22 / INDEX(Fiis[], MATCH(A22, Fiis[Fii], 0), MATCH(Fiis[[#HEADERS],[Preço mercado]], Fiis[#HEADERS], 0)))} -> 0 | J22: {=I22 * INDEX(Fiis[], MATCH(A22, Fiis[Fii], 0), MATCH(Fiis[[#HEADERS],[Preço mercado]], Fiis[#HEADERS], 0))} -> 0 | K22: =((J22/HOME!$B$9)+C22) -> 0.036907066
A23: HGLG11 | B23: {=IFERROR(IF(AND( INDEX(Fiis[], MATCH(A23, Fiis[Fii], 0), MATCH(Fiis[[#HEADERS],[Preço mercado]], Fiis[#HEADERS], 0)) < INDEX(Fiis[], MATCH(A23, Fiis[Fii], 0), MATCH(Fiis[[#HEADERS],[Barato]], Fiis[#HEADERS], 0)), INDEX(Fiis[], MATCH(A23, Fiis[Fii], 0), MATCH(Fiis[[#HEADERS],[Preço mercado]], Fiis[#HEADERS], 0)) < INDEX(Fiis[], MATCH(A23, Fiis[Fii], 0), MATCH(Fiis[[#HEADERS],[Justo]], Fiis[#HEADERS], 0)), INDEX(Fiis[], MATCH(A23, Fiis[Fii], 0), MATCH(Fiis[[#HEADERS],[Preço mercado]], Fiis[#HEADERS], 0)) < INDEX(Fiis[], MATCH(A23, Fiis[Fii], 0), MATCH(Fiis[[#HEADERS],[VP/Cota]], Fiis[#HEADERS], 0)) ), "SIM", "NÃO"), "")} -> NÃO | C23: {=IFERROR(INDEX(Fiis[], MATCH(A23, Fiis[Fii], 0), MATCH(Fiis[[#HEADERS],[Peso]], Fiis[#HEADERS], 0)), "")} -> 0.055163866 | D23: {=IFERROR(INDEX(Fiis[], MATCH(A23, Fiis[Fii], 0), MATCH(Fiis[[#HEADERS],[Peso Ideal]], Fiis[#HEADERS], 0)), "")} -> 0 | E23: =IF(AND(B23="SIM", C23<D23), D23-C23, 0) -> 0 | F23: {=IFERROR(INDEX(Fiis[], MATCH(A23, Fiis[Fii], 0), MATCH(Fiis[[#HEADERS],[Nota]], Fiis[#HEADERS], 0)), "")} -> 0 | G23: =IF(AND(B23="SIM", E23>0), (E23 * F23) / SUMPRODUCT((Fiis_Aporte[Está barato?]="SIM") * (Fiis_Aporte[Diferença]) * (Fiis_Aporte[Nota])), 0) -> 0 | H23: =G23*HOME!$T$8 -> 0 | I23: {=INT(H23 / INDEX(Fiis[], MATCH(A23, Fiis[Fii], 0), MATCH(Fiis[[#HEADERS],[Preço mercado]], Fiis[#HEADERS], 0)))} -> 0 | J23: {=I23 * INDEX(Fiis[], MATCH(A23, Fiis[Fii], 0), MATCH(Fiis[[#HEADERS],[Preço mercado]], Fiis[#HEADERS], 0))} -> 0 | K23: =((J23/HOME!$B$9)+C23) -> 0.055163866
A24: HGBS11 | B24: {=IFERROR(IF(AND( INDEX(Fiis[], MATCH(A24, Fiis[Fii], 0), MATCH(Fiis[[#HEADERS],[Preço mercado]], Fiis[#HEADERS], 0)) < INDEX(Fiis[], MATCH(A24, Fiis[Fii], 0), MATCH(Fiis[[#HEADERS],[Barato]], Fiis[#HEADERS], 0)), INDEX(Fiis[], MATCH(A24, Fiis[Fii], 0), MATCH(Fiis[[#HEADERS],[Preço mercado]], Fiis[#HEADERS], 0)) < INDEX(Fiis[], MATCH(A24, Fiis[Fii], 0), MATCH(Fiis[[#HEADERS],[Justo]], Fiis[#HEADERS], 0)), INDEX(Fiis[], MATCH(A24, Fiis[Fii], 0), MATCH(Fiis[[#HEADERS],[Preço mercado]], Fiis[#HEADERS], 0)) < INDEX(Fiis[], MATCH(A24, Fiis[Fii], 0), MATCH(Fiis[[#HEADERS],[VP/Cota]], Fiis[#HEADERS], 0)) ), "SIM", "NÃO"), "")} -> NÃO | C24: {=IFERROR(INDEX(Fiis[], MATCH(A24, Fiis[Fii], 0), MATCH(Fiis[[#HEADERS],[Peso]], Fiis[#HEADERS], 0)), "")} -> 0.0069699606 | D24: {=IFERROR(INDEX(Fiis[], MATCH(A24, Fiis[Fii], 0), MATCH(Fiis[[#HEADERS],[Peso Ideal]], Fiis[#HEADERS], 0)), "")} -> 0.022727273 | E24: =IF(AND(B24="SIM", C24<D24), D24-C24, 0) -> 0 | F24: {=IFERROR(INDEX(Fiis[], MATCH(A24, Fiis[Fii], 0), MATCH(Fiis[[#HEADERS],[Nota]], Fiis[#HEADERS], 0)), "")} -> 10 | G24: =IF(AND(B24="SIM", E24>0), (E24 * F24) / SUMPRODUCT((Fiis_Aporte[Está barato?]="SIM") * (Fiis_Aporte[Diferença]) * (Fiis_Aporte[Nota])), 0) -> 0 | H24: =G24*HOME!$T$8 -> 0 | I24: {=INT(H24 / INDEX(Fiis[], MATCH(A24, Fiis[Fii], 0), MATCH(Fiis[[#HEADERS],[Preço mercado]], Fiis[#HEADERS], 0)))} -> 0 | J24: {=I24 * INDEX(Fiis[], MATCH(A24, Fiis[Fii], 0), MATCH(Fiis[[#HEADERS],[Preço mercado]], Fiis[#HEADERS], 0))} -> 0 | K24: =((J24/HOME!$B$9)+C24) -> 0.0069699606
A25: GGRC11 | B25: {=IFERROR(IF(AND( INDEX(Fiis[], MATCH(A25, Fiis[Fii], 0), MATCH(Fiis[[#HEADERS],[Preço mercado]], Fiis[#HEADERS], 0)) < INDEX(Fiis[], MATCH(A25, Fiis[Fii], 0), MATCH(Fiis[[#HEADERS],[Barato]], Fiis[#HEADERS], 0)), INDEX(Fiis[], MATCH(A25, Fiis[Fii], 0), MATCH(Fiis[[#HEADERS],[Preço mercado]], Fiis[#HEADERS], 0)) < INDEX(Fiis[], MATCH(A25, Fiis[Fii], 0), MATCH(Fiis[[#HEADERS],[Justo]], Fiis[#HEADERS], 0)), INDEX(Fiis[], MATCH(A25, Fiis[Fii], 0), MATCH(Fiis[[#HEADERS],[Preço mercado]], Fiis[#HEADERS], 0)) < INDEX(Fiis[], MATCH(A25, Fiis[Fii], 0), MATCH(Fiis[[#HEADERS],[VP/Cota]], Fiis[#HEADERS], 0)) ), "SIM", "NÃO"), "")} -> NÃO | C25: {=IFERROR(INDEX(Fiis[], MATCH(A25, Fiis[Fii], 0), MATCH(Fiis[[#HEADERS],[Peso]], Fiis[#HEADERS], 0)), "")} -> 0.0033950453 | D25: {=IFERROR(INDEX(Fiis[], MATCH(A25, Fiis[Fii], 0), MATCH(Fiis[[#HEADERS],[Peso Ideal]], Fiis[#HEADERS], 0)), "")} -> 0.022727273 | E25: =IF(AND(B25="SIM", C25<D25), D25-C25, 0) -> 0 | F25: {=IFERROR(INDEX(Fiis[], MATCH(A25, Fiis[Fii], 0), MATCH(Fiis[[#HEADERS],[Nota]], Fiis[#HEADERS], 0)), "")} -> 10 | G25: =IF(AND(B25="SIM", E25>0), (E25 * F25) / SUMPRODUCT((Fiis_Aporte[Está barato?]="SIM") * (Fiis_Aporte[Diferença]) * (Fiis_Aporte[Nota])), 0) -> 0 | H25: =G25*HOME!$T$8 -> 0 | I25: {=INT(H25 / INDEX(Fiis[], MATCH(A25, Fiis[Fii], 0), MATCH(Fiis[[#HEADERS],[Preço mercado]], Fiis[#HEADERS], 0)))} -> 0 | J25: {=I25 * INDEX(Fiis[], MATCH(A25, Fiis[Fii], 0), MATCH(Fiis[[#HEADERS],[Preço mercado]], Fiis[#HEADERS], 0))} -> 0 | K25: =((J25/HOME!$B$9)+C25) -> 0.0033950453
A26: GARE11 | B26: {=IFERROR(IF(AND( INDEX(Fiis[], MATCH(A26, Fiis[Fii], 0), MATCH(Fiis[[#HEADERS],[Preço mercado]], Fiis[#HEADERS], 0)) < INDEX(Fiis[], MATCH(A26, Fiis[Fii], 0), MATCH(Fiis[[#HEADERS],[Barato]], Fiis[#HEADERS], 0)), INDEX(Fiis[], MATCH(A26, Fiis[Fii], 0), MATCH(Fiis[[#HEADERS],[Preço mercado]], Fiis[#HEADERS], 0)) < INDEX(Fiis[], MATCH(A26, Fiis[Fii], 0), MATCH(Fiis[[#HEADERS],[Justo]], Fiis[#HEADERS], 0)), INDEX(Fiis[], MATCH(A26, Fiis[Fii], 0), MATCH(Fiis[[#HEADERS],[Preço mercado]], Fiis[#HEADERS], 0)) < INDEX(Fiis[], MATCH(A26, Fiis[Fii], 0), MATCH(Fiis[[#HEADERS],[VP/Cota]], Fiis[#HEADERS], 0)) ), "SIM", "NÃO"), "")} -> NÃO | C26: {=IFERROR(INDEX(Fiis[], MATCH(A26, Fiis[Fii], 0), MATCH(Fiis[[#HEADERS],[Peso]], Fiis[#HEADERS], 0)), "")} -> 0.0030840202 | D26: {=IFERROR(INDEX(Fiis[], MATCH(A26, Fiis[Fii], 0), MATCH(Fiis[[#HEADERS],[Peso Ideal]], Fiis[#HEADERS], 0)), "")} -> 0.022727273 | E26: =IF(AND(B26="SIM", C26<D26), D26-C26, 0) -> 0 | F26: {=IFERROR(INDEX(Fiis[], MATCH(A26, Fiis[Fii], 0), MATCH(Fiis[[#HEADERS],[Nota]], Fiis[#HEADERS], 0)), "")} -> 10 | G26: =IF(AND(B26="SIM", E26>0), (E26 * F26) / SUMPRODUCT((Fiis_Aporte[Está barato?]="SIM") * (Fiis_Aporte[Diferença]) * (Fiis_Aporte[Nota])), 0) -> 0 | H26: =G26*HOME!$T$8 -> 0 | I26: {=INT(H26 / INDEX(Fiis[], MATCH(A26, Fiis[Fii], 0), MATCH(Fiis[[#HEADERS],[Preço mercado]], Fiis[#HEADERS], 0)))} -> 0 | J26: {=I26 * INDEX(Fiis[], MATCH(A26, Fiis[Fii], 0), MATCH(Fiis[[#HEADERS],[Preço mercado]], Fiis[#HEADERS], 0))} -> 0 | K26: =((J26/HOME!$B$9)+C26) -> 0.0030840202
A27: BTLG11 | B27: {=IFERROR(IF(AND( INDEX(Fiis[], MATCH(A27, Fiis[Fii], 0), MATCH(Fiis[[#HEADERS],[Preço mercado]], Fiis[#HEADERS], 0)) < INDEX(Fiis[], MATCH(A27, Fiis[Fii], 0), MATCH(Fiis[[#HEADERS],[Barato]], Fiis[#HEADERS], 0)), INDEX(Fiis[], MATCH(A27, Fiis[Fii], 0), MATCH(Fiis[[#HEADERS],[Preço mercado]], Fiis[#HEADERS], 0)) < INDEX(Fiis[], MATCH(A27, Fiis[Fii], 0), MATCH(Fiis[[#HEADERS],[Justo]], Fiis[#HEADERS], 0)), INDEX(Fiis[], MATCH(A27, Fiis[Fii], 0), MATCH(Fiis[[#HEADERS],[Preço mercado]], Fiis[#HEADERS], 0)) < INDEX(Fiis[], MATCH(A27, Fiis[Fii], 0), MATCH(Fiis[[#HEADERS],[VP/Cota]], Fiis[#HEADERS], 0)) ), "SIM", "NÃO"), "")} -> NÃO | C27: {=IFERROR(INDEX(Fiis[], MATCH(A27, Fiis[Fii], 0), MATCH(Fiis[[#HEADERS],[Peso]], Fiis[#HEADERS], 0)), "")} -> 0.036862098 | D27: {=IFERROR(INDEX(Fiis[], MATCH(A27, Fiis[Fii], 0), MATCH(Fiis[[#HEADERS],[Peso Ideal]], Fiis[#HEADERS], 0)), "")} -> 0.022727273 | E27: =IF(AND(B27="SIM", C27<D27), D27-C27, 0) -> 0 | F27: {=IFERROR(INDEX(Fiis[], MATCH(A27, Fiis[Fii], 0), MATCH(Fiis[[#HEADERS],[Nota]], Fiis[#HEADERS], 0)), "")} -> 10 | G27: =IF(AND(B27="SIM", E27>0), (E27 * F27) / SUMPRODUCT((Fiis_Aporte[Está barato?]="SIM") * (Fiis_Aporte[Diferença]) * (Fiis_Aporte[Nota])), 0) -> 0 | H27: =G27*HOME!$T$8 -> 0 | I27: {=INT(H27 / INDEX(Fiis[], MATCH(A27, Fiis[Fii], 0), MATCH(Fiis[[#HEADERS],[Preço mercado]], Fiis[#HEADERS], 0)))} -> 0 | J27: {=I27 * INDEX(Fiis[], MATCH(A27, Fiis[Fii], 0), MATCH(Fiis[[#HEADERS],[Preço mercado]], Fiis[#HEADERS], 0))} -> 0 | K27: =((J27/HOME!$B$9)+C27) -> 0.036862098
A28: BRCO11 | B28: {=IFERROR(IF(AND( INDEX(Fiis[], MATCH(A28, Fiis[Fii], 0), MATCH(Fiis[[#HEADERS],[Preço mercado]], Fiis[#HEADERS], 0)) < INDEX(Fiis[], MATCH(A28, Fiis[Fii], 0), MATCH(Fiis[[#HEADERS],[Barato]], Fiis[#HEADERS], 0)), INDEX(Fiis[], MATCH(A28, Fiis[Fii], 0), MATCH(Fiis[[#HEADERS],[Preço mercado]], Fiis[#HEADERS], 0)) < INDEX(Fiis[], MATCH(A28, Fiis[Fii], 0), MATCH(Fiis[[#HEADERS],[Justo]], Fiis[#HEADERS], 0)), INDEX(Fiis[], MATCH(A28, Fiis[Fii], 0), MATCH(Fiis[[#HEADERS],[Preço mercado]], Fiis[#HEADERS], 0)) < INDEX(Fiis[], MATCH(A28, Fiis[Fii], 0), MATCH(Fiis[[#HEADERS],[VP/Cota]], Fiis[#HEADERS], 0)) ), "SIM", "NÃO"), "")} -> NÃO | C28: {=IFERROR(INDEX(Fiis[], MATCH(A28, Fiis[Fii], 0), MATCH(Fiis[[#HEADERS],[Peso]], Fiis[#HEADERS], 0)), "")} -> 0.041909699 | D28: {=IFERROR(INDEX(Fiis[], MATCH(A28, Fiis[Fii], 0), MATCH(Fiis[[#HEADERS],[Peso Ideal]], Fiis[#HEADERS], 0)), "")} -> 0.022727273 | E28: =IF(AND(B28="SIM", C28<D28), D28-C28, 0) -> 0 | F28: {=IFERROR(INDEX(Fiis[], MATCH(A28, Fiis[Fii], 0), MATCH(Fiis[[#HEADERS],[Nota]], Fiis[#HEADERS], 0)), "")} -> 10 | G28: =IF(AND(B28="SIM", E28>0), (E28 * F28) / SUMPRODUCT((Fiis_Aporte[Está barato?]="SIM") * (Fiis_Aporte[Diferença]) * (Fiis_Aporte[Nota])), 0) -> 0 | H28: =G28*HOME!$T$8 -> 0 | I28: {=INT(H28 / INDEX(Fiis[], MATCH(A28, Fiis[Fii], 0), MATCH(Fiis[[#HEADERS],[Preço mercado]], Fiis[#HEADERS], 0)))} -> 0 | J28: {=I28 * INDEX(Fiis[], MATCH(A28, Fiis[Fii], 0), MATCH(Fiis[[#HEADERS],[Preço mercado]], Fiis[#HEADERS], 0))} -> 0 | K28: =((J28/HOME!$B$9)+C28) -> 0.041909699
E31: Ticker | F31: Valor
A32: Ticker | B32: Está barato? | C32: Valor | E32: =IFERROR(__xludf.DUMMYFUNCTION("IFERROR( FILTER({Baratos[Ticker],Baratos[Valor]}, Baratos[Está barato?]=""SIM""), {""🛑 Nenhum ativo barato"",0} ) "),"BBAS3") -> BBAS3 | F32: =IFERROR(__xludf.DUMMYFUNCTION("""COMPUTED_VALUE"""),18.43) -> 18.43
A33: BBAS3 | B33: {=IFERROR(IF(AND( INDEX(Ações_Nacionais[], MATCH(A33, Ações_Nacionais[Ação], 0), MATCH(Ações_Nacionais[[#HEADERS],[Preço mercado]], Ações_Nacionais[#HEADERS], 0)) < INDEX(Ações_Nacionais[], MATCH(A33, Ações_Nacionais[Ação], 0), MATCH(Ações_Nacionais[[#HEADERS],[Barato]], Ações_Nacionais[#HEADERS], 0)), ), "SIM", "NÃO"), "")} -> SIM | C33: {=IFERROR(INDEX(Ações_Nacionais[], MATCH(A33, Ações_Nacionais[Ação], 0), MATCH(Ações_Nacionais[[#HEADERS],[Preço mercado]], Ações_Nacionais[#HEADERS], 0)), "")} -> 18.43 | E33: =IFERROR(__xludf.DUMMYFUNCTION("""COMPUTED_VALUE"""),"SAPR4") -> SAPR4 | F33: =IFERROR(__xludf.DUMMYFUNCTION("""COMPUTED_VALUE"""),6.44) -> 6.44
A34: BBSE3 | B34: {=IFERROR(IF(AND( INDEX(Ações_Nacionais[], MATCH(A34, Ações_Nacionais[Ação], 0), MATCH(Ações_Nacionais[[#HEADERS],[Preço mercado]], Ações_Nacionais[#HEADERS], 0)) < INDEX(Ações_Nacionais[], MATCH(A34, Ações_Nacionais[Ação], 0), MATCH(Ações_Nacionais[[#HEADERS],[Barato]], Ações_Nacionais[#HEADERS], 0)), ), "SIM", "NÃO"), "")} -> NÃO | C34: {=IFERROR(INDEX(Ações_Nacionais[], MATCH(A34, Ações_Nacionais[Ação], 0), MATCH(Ações_Nacionais[[#HEADERS],[Preço mercado]], Ações_Nacionais[#HEADERS], 0)), "")} -> 37.19 | E34: =IFERROR(__xludf.DUMMYFUNCTION("""COMPUTED_VALUE"""),"XPLG11") -> XPLG11 | F34: =IFERROR(__xludf.DUMMYFUNCTION("""COMPUTED_VALUE"""),90.0) -> 90
A35: VALE3 | B35: {=IFERROR(IF(AND( INDEX(Ações_Nacionais[], MATCH(A35, Ações_Nacionais[Ação], 0), MATCH(Ações_Nacionais[[#HEADERS],[Preço mercado]], Ações_Nacionais[#HEADERS], 0)) < INDEX(Ações_Nacionais[], MATCH(A35, Ações_Nacionais[Ação], 0), MATCH(Ações_Nacionais[[#HEADERS],[Barato]], Ações_Nacionais[#HEADERS], 0)), ), "SIM", "NÃO"), "")} -> NÃO | C35: {=IFERROR(INDEX(Ações_Nacionais[], MATCH(A35, Ações_Nacionais[Ação], 0), MATCH(Ações_Nacionais[[#HEADERS],[Preço mercado]], Ações_Nacionais[#HEADERS], 0)), "")} -> 75.03 | E35: =IFERROR(__xludf.DUMMYFUNCTION("""COMPUTED_VALUE"""),"HGBS11") -> HGBS11 | F35: =IFERROR(__xludf.DUMMYFUNCTION("""COMPUTED_VALUE"""),18.6) -> 18.6
A36: TAEE11 | B36: {=IFERROR(IF(AND( INDEX(Ações_Nacionais[], MATCH(A36, Ações_Nacionais[Ação], 0), MATCH(Ações_Nacionais[[#HEADERS],[Preço mercado]], Ações_Nacionais[#HEADERS], 0)) < INDEX(Ações_Nacionais[], MATCH(A36, Ações_Nacionais[Ação], 0), MATCH(Ações_Nacionais[[#HEADERS],[Barato]], Ações_Nacionais[#HEADERS], 0)), ), "SIM", "NÃO"), "")} -> NÃO | C36: {=IFERROR(INDEX(Ações_Nacionais[], MATCH(A36, Ações_Nacionais[Ação], 0), MATCH(Ações_Nacionais[[#HEADERS],[Preço mercado]], Ações_Nacionais[#HEADERS], 0)), "")} -> 37.57 | E36: =IFERROR(__xludf.DUMMYFUNCTION("""COMPUTED_VALUE"""),"HGLG11") -> HGLG11 | F36: =IFERROR(__xludf.DUMMYFUNCTION("""COMPUTED_VALUE"""),147.21) -> 147.21
A37: ITUB3 | B37: {=IFERROR(IF(AND( INDEX(Ações_Nacionais[], MATCH(A37, Ações_Nacionais[Ação], 0), MATCH(Ações_Nacionais[[#HEADERS],[Preço mercado]], Ações_Nacionais[#HEADERS], 0)) < INDEX(Ações_Nacionais[], MATCH(A37, Ações_Nacionais[Ação], 0), MATCH(Ações_Nacionais[[#HEADERS],[Barato]], Ações_Nacionais[#HEADERS], 0)), ), "SIM", "NÃO"), "")} -> NÃO | C37: {=IFERROR(INDEX(Ações_Nacionais[], MATCH(A37, Ações_Nacionais[Ação], 0), MATCH(Ações_Nacionais[[#HEADERS],[Preço mercado]], Ações_Nacionais[#HEADERS], 0)), "")} -> 41.39 | E37: =IFERROR(__xludf.DUMMYFUNCTION("""COMPUTED_VALUE"""),"BTLG11") -> BTLG11 | F37: =IFERROR(__xludf.DUMMYFUNCTION("""COMPUTED_VALUE"""),98.37) -> 98.37
A38: PETR4 | B38: {=IFERROR(IF(AND( INDEX(Ações_Nacionais[], MATCH(A38, Ações_Nacionais[Ação], 0), MATCH(Ações_Nacionais[[#HEADERS],[Preço mercado]], Ações_Nacionais[#HEADERS], 0)) < INDEX(Ações_Nacionais[], MATCH(A38, Ações_Nacionais[Ação], 0), MATCH(Ações_Nacionais[[#HEADERS],[Barato]], Ações_Nacionais[#HEADERS], 0)), ), "SIM", "NÃO"), "")} -> NÃO | C38: {=IFERROR(INDEX(Ações_Nacionais[], MATCH(A38, Ações_Nacionais[Ação], 0), MATCH(Ações_Nacionais[[#HEADERS],[Preço mercado]], Ações_Nacionais[#HEADERS], 0)), "")} -> 44.3 | E38: =IFERROR(__xludf.DUMMYFUNCTION("""COMPUTED_VALUE"""),"GGRC11") -> GGRC11 | F38: =IFERROR(__xludf.DUMMYFUNCTION("""COMPUTED_VALUE"""),9.06) -> 9.06
A39: WEGE3 | B39: {=IFERROR(IF(AND( INDEX(Ações_Nacionais[], MATCH(A39, Ações_Nacionais[Ação], 0), MATCH(Ações_Nacionais[[#HEADERS],[Preço mercado]], Ações_Nacionais[#HEADERS], 0)) < INDEX(Ações_Nacionais[], MATCH(A39, Ações_Nacionais[Ação], 0), MATCH(Ações_Nacionais[[#HEADERS],[Barato]], Ações_Nacionais[#HEADERS], 0)), ), "SIM", "NÃO"), "")} -> NÃO | C39: {=IFERROR(INDEX(Ações_Nacionais[], MATCH(A39, Ações_Nacionais[Ação], 0), MATCH(Ações_Nacionais[[#HEADERS],[Preço mercado]], Ações_Nacionais[#HEADERS], 0)), "")} -> 49.27 | E39: =IFERROR(__xludf.DUMMYFUNCTION("""COMPUTED_VALUE"""),"GARE11") -> GARE11 | F39: =IFERROR(__xludf.DUMMYFUNCTION("""COMPUTED_VALUE"""),8.23) -> 8.23
A40: BRBI11 | B40: {=IFERROR(IF(AND( INDEX(Ações_Nacionais[], MATCH(A40, Ações_Nacionais[Ação], 0), MATCH(Ações_Nacionais[[#HEADERS],[Preço mercado]], Ações_Nacionais[#HEADERS], 0)) < INDEX(Ações_Nacionais[], MATCH(A40, Ações_Nacionais[Ação], 0), MATCH(Ações_Nacionais[[#HEADERS],[Barato]], Ações_Nacionais[#HEADERS], 0)), ), "SIM", "NÃO"), "")} -> NÃO | C40: {=IFERROR(INDEX(Ações_Nacionais[], MATCH(A40, Ações_Nacionais[Ação], 0), MATCH(Ações_Nacionais[[#HEADERS],[Preço mercado]], Ações_Nacionais[#HEADERS], 0)), "")} -> 12.15 | E40: =IFERROR(__xludf.DUMMYFUNCTION("""COMPUTED_VALUE"""),"PMLL11") -> PMLL11 | F40: =IFERROR(__xludf.DUMMYFUNCTION("""COMPUTED_VALUE"""),100.83) -> 100.83
A41: CMIG4 | B41: {=IFERROR(IF(AND( INDEX(Ações_Nacionais[], MATCH(A41, Ações_Nacionais[Ação], 0), MATCH(Ações_Nacionais[[#HEADERS],[Preço mercado]], Ações_Nacionais[#HEADERS], 0)) < INDEX(Ações_Nacionais[], MATCH(A41, Ações_Nacionais[Ação], 0), MATCH(Ações_Nacionais[[#HEADERS],[Barato]], Ações_Nacionais[#HEADERS], 0)), ), "SIM", "NÃO"), "")} -> NÃO | C41: {=IFERROR(INDEX(Ações_Nacionais[], MATCH(A41, Ações_Nacionais[Ação], 0), MATCH(Ações_Nacionais[[#HEADERS],[Preço mercado]], Ações_Nacionais[#HEADERS], 0)), "")} -> 10.04 | E41: =IFERROR(__xludf.DUMMYFUNCTION("""COMPUTED_VALUE"""),"HGRU11") -> HGRU11 | F41: =IFERROR(__xludf.DUMMYFUNCTION("""COMPUTED_VALUE"""),114.99) -> 114.99
A42: ISAE4 | B42: {=IFERROR(IF(AND( INDEX(Ações_Nacionais[], MATCH(A42, Ações_Nacionais[Ação], 0), MATCH(Ações_Nacionais[[#HEADERS],[Preço mercado]], Ações_Nacionais[#HEADERS], 0)) < INDEX(Ações_Nacionais[], MATCH(A42, Ações_Nacionais[Ação], 0), MATCH(Ações_Nacionais[[#HEADERS],[Barato]], Ações_Nacionais[#HEADERS], 0)), ), "SIM", "NÃO"), "")} -> NÃO | C42: {=IFERROR(INDEX(Ações_Nacionais[], MATCH(A42, Ações_Nacionais[Ação], 0), MATCH(Ações_Nacionais[[#HEADERS],[Preço mercado]], Ações_Nacionais[#HEADERS], 0)), "")} -> 26.02 | E42: =IFERROR(__xludf.DUMMYFUNCTION("""COMPUTED_VALUE"""),"PCIP11") -> PCIP11 | F42: =IFERROR(__xludf.DUMMYFUNCTION("""COMPUTED_VALUE"""),72.2) -> 72.2
A43: SAPR4 | B43: {=IFERROR(IF(AND( INDEX(Ações_Nacionais[], MATCH(A43, Ações_Nacionais[Ação], 0), MATCH(Ações_Nacionais[[#HEADERS],[Preço mercado]], Ações_Nacionais[#HEADERS], 0)) < INDEX(Ações_Nacionais[], MATCH(A43, Ações_Nacionais[Ação], 0), MATCH(Ações_Nacionais[[#HEADERS],[Barato]], Ações_Nacionais[#HEADERS], 0)), ), "SIM", "NÃO"), "")} -> SIM | C43: {=IFERROR(INDEX(Ações_Nacionais[], MATCH(A43, Ações_Nacionais[Ação], 0), MATCH(Ações_Nacionais[[#HEADERS],[Preço mercado]], Ações_Nacionais[#HEADERS], 0)), "")} -> 6.44
A44: XPLG11 | B44: {=IFERROR(IF(AND( INDEX(Fiis[], MATCH(A44, Fiis[Fii], 0), MATCH(Fiis[[#HEADERS],[Preço mercado]], Fiis[#HEADERS], 0)) < INDEX(Fiis[], MATCH(A44, Fiis[Fii], 0), MATCH(Fiis[[#HEADERS],[Justo]], Fiis[#HEADERS], 0)), INDEX(Fiis[], MATCH(A44, Fiis[Fii], 0), MATCH(Fiis[[#HEADERS],[Preço mercado]], Fiis[#HEADERS], 0)) < INDEX(Fiis[], MATCH(A44, Fiis[Fii], 0), MATCH(Fiis[[#HEADERS],[VP/Cota]], Fiis[#HEADERS], 0)) ), "SIM", "NÃO"), "")} -> SIM | C44: =IFERROR(__xludf.DUMMYFUNCTION("IFERROR(GOOGLEFINANCE(""BVMF:"" & A44),0)"),90.0) -> 90
A45: HGBS11 | B45: {=IFERROR(IF(AND( INDEX(Fiis[], MATCH(A45, Fiis[Fii], 0), MATCH(Fiis[[#HEADERS],[Preço mercado]], Fiis[#HEADERS], 0)) < INDEX(Fiis[], MATCH(A45, Fiis[Fii], 0), MATCH(Fiis[[#HEADERS],[Justo]], Fiis[#HEADERS], 0)), INDEX(Fiis[], MATCH(A45, Fiis[Fii], 0), MATCH(Fiis[[#HEADERS],[Preço mercado]], Fiis[#HEADERS], 0)) < INDEX(Fiis[], MATCH(A45, Fiis[Fii], 0), MATCH(Fiis[[#HEADERS],[VP/Cota]], Fiis[#HEADERS], 0)) ), "SIM", "NÃO"), "")} -> SIM | C45: =IFERROR(__xludf.DUMMYFUNCTION("IFERROR(GOOGLEFINANCE(""BVMF:"" & A45),0)"),18.6) -> 18.6
A46: BRCO11 | B46: {=IFERROR(IF(AND( INDEX(Fiis[], MATCH(A46, Fiis[Fii], 0), MATCH(Fiis[[#HEADERS],[Preço mercado]], Fiis[#HEADERS], 0)) < INDEX(Fiis[], MATCH(A46, Fiis[Fii], 0), MATCH(Fiis[[#HEADERS],[Justo]], Fiis[#HEADERS], 0)), INDEX(Fiis[], MATCH(A46, Fiis[Fii], 0), MATCH(Fiis[[#HEADERS],[Preço mercado]], Fiis[#HEADERS], 0)) < INDEX(Fiis[], MATCH(A46, Fiis[Fii], 0), MATCH(Fiis[[#HEADERS],[VP/Cota]], Fiis[#HEADERS], 0)) ), "SIM", "NÃO"), "")} -> NÃO | C46: =IFERROR(__xludf.DUMMYFUNCTION("IFERROR(GOOGLEFINANCE(""BVMF:"" & A46),0)"),111.84) -> 111.84
A47: HGLG11 | B47: {=IFERROR(IF(AND( INDEX(Fiis[], MATCH(A47, Fiis[Fii], 0), MATCH(Fiis[[#HEADERS],[Preço mercado]], Fiis[#HEADERS], 0)) < INDEX(Fiis[], MATCH(A47, Fiis[Fii], 0), MATCH(Fiis[[#HEADERS],[Justo]], Fiis[#HEADERS], 0)), INDEX(Fiis[], MATCH(A47, Fiis[Fii], 0), MATCH(Fiis[[#HEADERS],[Preço mercado]], Fiis[#HEADERS], 0)) < INDEX(Fiis[], MATCH(A47, Fiis[Fii], 0), MATCH(Fiis[[#HEADERS],[VP/Cota]], Fiis[#HEADERS], 0)) ), "SIM", "NÃO"), "")} -> SIM | C47: =IFERROR(__xludf.DUMMYFUNCTION("IFERROR(GOOGLEFINANCE(""BVMF:"" & A47),0)"),147.21) -> 147.21
A48: LVBI11 | B48: {=IFERROR(IF(AND( INDEX(Fiis[], MATCH(A48, Fiis[Fii], 0), MATCH(Fiis[[#HEADERS],[Preço mercado]], Fiis[#HEADERS], 0)) < INDEX(Fiis[], MATCH(A48, Fiis[Fii], 0), MATCH(Fiis[[#HEADERS],[Justo]], Fiis[#HEADERS], 0)), INDEX(Fiis[], MATCH(A48, Fiis[Fii], 0), MATCH(Fiis[[#HEADERS],[Preço mercado]], Fiis[#HEADERS], 0)) < INDEX(Fiis[], MATCH(A48, Fiis[Fii], 0), MATCH(Fiis[[#HEADERS],[VP/Cota]], Fiis[#HEADERS], 0)) ), "SIM", "NÃO"), "")} -> NÃO | C48: =IFERROR(__xludf.DUMMYFUNCTION("IFERROR(GOOGLEFINANCE(""BVMF:"" & A48),0)"),98.49) -> 98.49
A49: BTLG11 | B49: {=IFERROR(IF(AND( INDEX(Fiis[], MATCH(A49, Fiis[Fii], 0), MATCH(Fiis[[#HEADERS],[Preço mercado]], Fiis[#HEADERS], 0)) < INDEX(Fiis[], MATCH(A49, Fiis[Fii], 0), MATCH(Fiis[[#HEADERS],[Justo]], Fiis[#HEADERS], 0)), INDEX(Fiis[], MATCH(A49, Fiis[Fii], 0), MATCH(Fiis[[#HEADERS],[Preço mercado]], Fiis[#HEADERS], 0)) < INDEX(Fiis[], MATCH(A49, Fiis[Fii], 0), MATCH(Fiis[[#HEADERS],[VP/Cota]], Fiis[#HEADERS], 0)) ), "SIM", "NÃO"), "")} -> SIM | C49: =IFERROR(__xludf.DUMMYFUNCTION("IFERROR(GOOGLEFINANCE(""BVMF:"" & A49),0)"),98.37) -> 98.37
A50: GGRC11 | B50: {=IFERROR(IF(AND( INDEX(Fiis[], MATCH(A50, Fiis[Fii], 0), MATCH(Fiis[[#HEADERS],[Preço mercado]], Fiis[#HEADERS], 0)) < INDEX(Fiis[], MATCH(A50, Fiis[Fii], 0), MATCH(Fiis[[#HEADERS],[Justo]], Fiis[#HEADERS], 0)), INDEX(Fiis[], MATCH(A50, Fiis[Fii], 0), MATCH(Fiis[[#HEADERS],[Preço mercado]], Fiis[#HEADERS], 0)) < INDEX(Fiis[], MATCH(A50, Fiis[Fii], 0), MATCH(Fiis[[#HEADERS],[VP/Cota]], Fiis[#HEADERS], 0)) ), "SIM", "NÃO"), "")} -> SIM | C50: =IFERROR(__xludf.DUMMYFUNCTION("IFERROR(GOOGLEFINANCE(""BVMF:"" & A50),0)"),9.06) -> 9.06
A51: GARE11 | B51: {=IFERROR(IF(AND( INDEX(Fiis[], MATCH(A51, Fiis[Fii], 0), MATCH(Fiis[[#HEADERS],[Preço mercado]], Fiis[#HEADERS], 0)) < INDEX(Fiis[], MATCH(A51, Fiis[Fii], 0), MATCH(Fiis[[#HEADERS],[Justo]], Fiis[#HEADERS], 0)), INDEX(Fiis[], MATCH(A51, Fiis[Fii], 0), MATCH(Fiis[[#HEADERS],[Preço mercado]], Fiis[#HEADERS], 0)) < INDEX(Fiis[], MATCH(A51, Fiis[Fii], 0), MATCH(Fiis[[#HEADERS],[VP/Cota]], Fiis[#HEADERS], 0)) ), "SIM", "NÃO"), "")} -> SIM | C51: =IFERROR(__xludf.DUMMYFUNCTION("IFERROR(GOOGLEFINANCE(""BVMF:"" & A51),0)"),8.23) -> 8.23
A52: PMLL11 | B52: {=IFERROR(IF(AND( INDEX(Fiis[], MATCH(A52, Fiis[Fii], 0), MATCH(Fiis[[#HEADERS],[Preço mercado]], Fiis[#HEADERS], 0)) < INDEX(Fiis[], MATCH(A52, Fiis[Fii], 0), MATCH(Fiis[[#HEADERS],[Justo]], Fiis[#HEADERS], 0)), INDEX(Fiis[], MATCH(A52, Fiis[Fii], 0), MATCH(Fiis[[#HEADERS],[Preço mercado]], Fiis[#HEADERS], 0)) < INDEX(Fiis[], MATCH(A52, Fiis[Fii], 0), MATCH(Fiis[[#HEADERS],[VP/Cota]], Fiis[#HEADERS], 0)) ), "SIM", "NÃO"), "")} -> SIM | C52: =IFERROR(__xludf.DUMMYFUNCTION("IFERROR(GOOGLEFINANCE(""BVMF:"" & A52),0)"),100.83) -> 100.83
A53: KNRI11 | B53: {=IFERROR(IF(AND( INDEX(Fiis[], MATCH(A53, Fiis[Fii], 0), MATCH(Fiis[[#HEADERS],[Preço mercado]], Fiis[#HEADERS], 0)) < INDEX(Fiis[], MATCH(A53, Fiis[Fii], 0), MATCH(Fiis[[#HEADERS],[Justo]], Fiis[#HEADERS], 0)), INDEX(Fiis[], MATCH(A53, Fiis[Fii], 0), MATCH(Fiis[[#HEADERS],[Preço mercado]], Fiis[#HEADERS], 0)) < INDEX(Fiis[], MATCH(A53, Fiis[Fii], 0), MATCH(Fiis[[#HEADERS],[VP/Cota]], Fiis[#HEADERS], 0)) ), "SIM", "NÃO"), "")} -> NÃO | C53: =IFERROR(__xludf.DUMMYFUNCTION("IFERROR(GOOGLEFINANCE(""BVMF:"" & A53),0)"),155.48) -> 155.48
A54: MXRF11 | B54: {=IFERROR(IF(AND( INDEX(Fiis[], MATCH(A54, Fiis[Fii], 0), MATCH(Fiis[[#HEADERS],[Preço mercado]], Fiis[#HEADERS], 0)) < INDEX(Fiis[], MATCH(A54, Fiis[Fii], 0), MATCH(Fiis[[#HEADERS],[Justo]], Fiis[#HEADERS], 0)), INDEX(Fiis[], MATCH(A54, Fiis[Fii], 0), MATCH(Fiis[[#HEADERS],[Preço mercado]], Fiis[#HEADERS], 0)) < INDEX(Fiis[], MATCH(A54, Fiis[Fii], 0), MATCH(Fiis[[#HEADERS],[VP/Cota]], Fiis[#HEADERS], 0)) ), "SIM", "NÃO"), "")} -> NÃO | C54: =IFERROR(__xludf.DUMMYFUNCTION("IFERROR(GOOGLEFINANCE(""BVMF:"" & A54),0)"),9.26) -> 9.26
A55: HGRU11 | B55: {=IFERROR(IF(AND( INDEX(Fiis[], MATCH(A55, Fiis[Fii], 0), MATCH(Fiis[[#HEADERS],[Preço mercado]], Fiis[#HEADERS], 0)) < INDEX(Fiis[], MATCH(A55, Fiis[Fii], 0), MATCH(Fiis[[#HEADERS],[Justo]], Fiis[#HEADERS], 0)), INDEX(Fiis[], MATCH(A55, Fiis[Fii], 0), MATCH(Fiis[[#HEADERS],[Preço mercado]], Fiis[#HEADERS], 0)) < INDEX(Fiis[], MATCH(A55, Fiis[Fii], 0), MATCH(Fiis[[#HEADERS],[VP/Cota]], Fiis[#HEADERS], 0)) ), "SIM", "NÃO"), "")} -> SIM | C55: =IFERROR(__xludf.DUMMYFUNCTION("IFERROR(GOOGLEFINANCE(""BVMF:"" & A55),0)"),114.99) -> 114.99
A56: PCIP11 | B56: {=IFERROR(IF(AND( INDEX(Fiis[], MATCH(A56, Fiis[Fii], 0), MATCH(Fiis[[#HEADERS],[Preço mercado]], Fiis[#HEADERS], 0)) < INDEX(Fiis[], MATCH(A56, Fiis[Fii], 0), MATCH(Fiis[[#HEADERS],[Justo]], Fiis[#HEADERS], 0)), INDEX(Fiis[], MATCH(A56, Fiis[Fii], 0), MATCH(Fiis[[#HEADERS],[Preço mercado]], Fiis[#HEADERS], 0)) < INDEX(Fiis[], MATCH(A56, Fiis[Fii], 0), MATCH(Fiis[[#HEADERS],[VP/Cota]], Fiis[#HEADERS], 0)) ), "SIM", "NÃO"), "")} -> SIM | C56: =IFERROR(__xludf.DUMMYFUNCTION("IFERROR(GOOGLEFINANCE(""BVMF:"" & A56),0)"),72.2) -> 72.2
A82: Calculo de Emissao | C82: Preço depois da Emissão | E82: =SUM(C85+(C86*C87))/(1+C86) -> 18.745776
C83: P/VP depois da Emissão | E83: =(C88 + (C87 * C86/100)) / (1 + C86/100) -> 0.017021355
A84: Nome_FIIs | C84: HGBS11
A85: Preço Fechamento | C85: =IFERROR(__xludf.DUMMYFUNCTION("GOOGLEFINANCE(C84)"),18.6) -> 18.6
A86: Percentual de Emissão | C86: 0.0831
A87: Preço da Sub | C87: 20.5
A88: P/VP | C88: {=IFERROR(INDEX(#REF!, MATCH(C91, #REF!, 0), MATCH(#REF!, #REF!, 0)), "")}
A90: Calculadora de Arbitragem | G90: Manual
A91: Nome_Fiis | C91: =C84 -> HGBS11 | G91: Calculadora de Flipagem Para novo P/VP
A92: Qtd_Cota | C92: {=IFERROR(INDEX(Fiis[], MATCH(C91, Fiis[Fii], 0), MATCH(Fiis[[#HEADERS],[QTD]], Fiis[#HEADERS], 0)), "")} -> 50 | G92: Nome_Fiis | I92: =C84 -> HGBS11
A93: %_De_Cota_Emissão | C93: =C86 -> 0.0831 | G93: Qtd_Cota | I93: =C92 -> 50
A94: Direito_QTD_Cota | C94: =ROUNDDOWN(C92*C93,0) -> 4 | G94: %_De_Cota_Emissão | I94: =C86 -> 0.0831
A95: Valor_Mercado | C95: =IFERROR(__xludf.DUMMYFUNCTION("GOOGLEFINANCE(C91)"),18.6) -> 18.6 | G95: Direito_QTD_Cota | I95: =C94 -> 4
A96: Valor_Da_Emissão | C96: =C87 -> 20.5 | G96: Valor_Mercado | I96: =IFERROR(__xludf.DUMMYFUNCTION("GOOGLEFINANCE(I92)"),18.6) -> 18.6
A97: IR | C97: 0.2 | G97: P/VP depois da Emissão | I97: =E83 -> 0.017021355
A98: Valor_IR | C98: =C99*C97 -> -1.52 | G98: P/VP depois da Emissão | I98: 1
A99: Lucro_Bruto | C99: =(C94*C95)-(C94*C96) -> -7.6 | G99: P/VP Desejavel | I99: 0.98
A100: Lucro_Liquido | C100: =C99-C98 -> -6.08 | G100: P/VP Desejavel | I100: =E83*0.98 -> 0.016680928
G101: IR | I101: 0.2
A102: Calculo se Compensa Arbitragem | G102: Valor_IR | I102: =I103*I101 -> 14.866655
A103: Rendimento | B103: {=IFERROR(INDEX(Fiis[], MATCH(C84, Fiis[Fii], 0), MATCH(Fiis[[#HEADERS],[Div/12]], Fiis[#HEADERS], 0)), "")} -> 0.155 | G103: Lucro_Bruto | I103: =(I95*I96)-(I95*I100) -> 74.333276
A104: Rendimento_2M | B104: =(B103*C94)*2 -> 1.24 | G104: Lucro_Liquido | I104: =I103-I102 -> 59.466621
A105: Lucro | B105: =C100-B104 -> -7.32
A106: Lucro_em_M | B106: =IFERROR(C100/B104,0) -> -4.9032258 | G106: Calculo se Compensa Flipagem
G107: Rendimento | H107: {=IFERROR(INDEX(Fiis[], MATCH(C84, Fiis[Fii], 0), MATCH(Fiis[[#HEADERS],[Div/12]], Fiis[#HEADERS], 0)), "")} -> 0.155
G108: Rendimento_2M | H108: =(H107*I95)*2 -> 1.24
A109: Calculadora Venda de Direito | G109: Lucro | H109: =I104-H108 -> 58.226621
A110: Preço_Direito | B110: 0.2 | G110: Lucro_em_M | H110: =IFERROR(ROUNDDOWN(I104/H108,0),0) -> 47
A111: Qtd_Direito | B111: =C94 -> 4
A112: IR | B112: 0.15
A113: Valor_IR | B113: =B114*B112 -> 0.12
A114: Lucro_Bruto | B114: =B110*B111 -> 0.8
A115: Lucro_Liquido | B115: =B114-B113 -> 0.68
A117: Oque compensa -------------------> | C117: =IF(B115 < B105 , "Arbitragem compensa" , "Venda de Direitos compensa") -> Venda de Direitos compensa

Sheet grafico
A3: ticker | B3: setor | C3: peso | D3: financeiro | F3: Setor | G3: % do total | H3: Total Investido | J3: ticker | K3: setor | L3: peso | M3: financeiro | O3: Setor | P3: % do total | Q3: Total Investido | T3: ticker | U3: setor | V3: peso | W3: financeiro | Y3: Setor | Z3: % do total | AA3: Total Investido
A4: BBAS3 | B4: Banco | C4: =IFERROR((D4/$B$24), 0) -> 0.045068838 | D4: {=IFERROR(INDEX(Ações_Nacionais[], MATCH(A4, Ações_Nacionais[Ação], 0), MATCH(Ações_Nacionais[[#HEADERS],[Financeiro]], Ações_Nacionais[#HEADERS], 0)), "")} -> 1843 | F4: Banco | G4: =SUMIF(Setores_Ações[setor], "Banco", Setores_Ações[peso]) -> 0.27124447 | H4: =SUMIF(Setores_Ações[setor], "Banco", Setores_Ações[financeiro]) -> 11092 | J4: BBAS3 | K4: Banco | L4: =IFERROR((M4/$B$24), 0) -> 0.12235872 | M4: {=IFERROR( INDEX(Ações_Nacionais[], MATCH(J4, Ações_Nacionais[Ação], 0), MATCH(Ações_Nacionais[[#HEADERS],[Peso Ideal]], Ações_Nacionais[#HEADERS], 0)) * $B$26, "")} -> 5003.6151 | O4: Banco | P4: =SUMIF(Peso_Ideal_Ações[setor], "Banco", Peso_Ideal_Ações[peso]) -> 0.36707615 | Q4: =SUMIF(Peso_Ideal_Ações[setor], "Banco", Peso_Ideal_Ações[financeiro]) -> 15010.845 | T4: BBAS3 | U4: Financeiro | V4: =IFERROR((W4/$B$24), 0) -> 0.12235872 | W4: {=IFERROR( INDEX(Ações_Nacionais[], MATCH(T4, Ações_Nacionais[Ação], 0), MATCH(Ações_Nacionais[[#HEADERS],[Peso Ideal]], Ações_Nacionais[#HEADERS], 0)) * $B$26, "")} -> 5003.6151 | Y4: Financeiro | Z4: =SUMIF(Peso_Setores_Ideal[setor], "Financeiro", Peso_Setores_Ideal[peso]) -> 0.48943487 | AA4: =SUMIF(Peso_Setores_Ideal[setor], "Financeiro", Peso_Setores_Ideal[financeiro]) -> 20014.46
A5: BBSE3 | B5: Seguradora | C5: =IFERROR((D5/$B$24), 0) -> 0.09094466 | D5: {=IFERROR(INDEX(Ações_Nacionais[], MATCH(A5, Ações_Nacionais[Ação], 0), MATCH(Ações_Nacionais[[#HEADERS],[Financeiro]], Ações_Nacionais[#HEADERS], 0)), "")} -> 3719 | F5: Energia | G5: =SUMIF(Setores_Ações[setor], "Energia", Setores_Ações[peso]) -> 0.18005527 | H5: =SUMIF(Setores_Ações[setor], "Energia", Setores_Ações[financeiro]) -> 7363 | J5: BBSE3 | K5: Seguradora | L5: =IFERROR((M5/$B$24), 0) -> 0.12235872 | M5: {=IFERROR( INDEX(Ações_Nacionais[], MATCH(J5, Ações_Nacionais[Ação], 0), MATCH(Ações_Nacionais[[#HEADERS],[Peso Ideal]], Ações_Nacionais[#HEADERS], 0)) * $B$26, "")} -> 5003.6151 | O5: Energia | P5: =SUMIF(Peso_Ideal_Ações[setor], "Energia", Peso_Ideal_Ações[peso]) -> 0.36707615 | Q5: =SUMIF(Peso_Ideal_Ações[setor], "Energia", Peso_Ideal_Ações[financeiro]) -> 15010.845 | T5: BBSE3 | U5: Financeiro | V5: =IFERROR((W5/$B$24), 0) -> 0.12235872 | W5: {=IFERROR( INDEX(Ações_Nacionais[], MATCH(T5, Ações_Nacionais[Ação], 0), MATCH(Ações_Nacionais[[#HEADERS],[Peso Ideal]], Ações_Nacionais[#HEADERS], 0)) * $B$26, "")} -> 5003.6151 | Y5: Energia | Z5: =SUMIF(Peso_Setores_Ideal[setor], "Energia", Peso_Setores_Ideal[peso]) -> 0.36707615 | AA5: =SUMIF(Peso_Setores_Ideal[setor], "Energia", Peso_Setores_Ideal[financeiro]) -> 15010.845
A6: VALE3 | B6: Commodities | C6: =IFERROR((D6/$B$24), 0) -> 0.18347884 | D6: {=IFERROR(INDEX(Ações_Nacionais[], MATCH(A6, Ações_Nacionais[Ação], 0), MATCH(Ações_Nacionais[[#HEADERS],[Financeiro]], Ações_Nacionais[#HEADERS], 0)), "")} -> 7503 | F6: Cresc. | G6: =SUMIF(Setores_Ações[setor], "Cresc.", Setores_Ações[peso]) -> 0.15019686 | H6: =SUMIF(Setores_Ações[setor], "Cresc.", Setores_Ações[financeiro]) -> 6142 | J6: VALE3 | K6: Commodities | L6: =IFERROR((M6/$B$24), 0) -> 0.12235872 | M6: {=IFERROR( INDEX(Ações_Nacionais[], MATCH(J6, Ações_Nacionais[Ação], 0), MATCH(Ações_Nacionais[[#HEADERS],[Peso Ideal]], Ações_Nacionais[#HEADERS], 0)) * $B$26, "")} -> 5003.6151 | O6: Cresc. | P6: =SUMIF(Peso_Ideal_Ações[setor], "Cresc.", Peso_Ideal_Ações[peso]) -> 0.12235872 | Q6: =SUMIF(Peso_Ideal_Ações[setor], "Cresc.", Peso_Ideal_Ações[financeiro]) -> 5003.6151 | T6: VALE3 | U6: Commodities | V6: =IFERROR((W6/$B$24), 0) -> 0.12235872 | W6: {=IFERROR( INDEX(Ações_Nacionais[], MATCH(T6, Ações_Nacionais[Ação], 0), MATCH(Ações_Nacionais[[#HEADERS],[Peso Ideal]], Ações_Nacionais[#HEADERS], 0)) * $B$26, "")} -> 5003.6151 | Y6: Commodities | Z6: =SUMIF(Peso_Setores_Ideal[setor], "Commodities", Peso_Setores_Ideal[peso]) -> 0.24471744 | AA6: =SUMIF(Peso_Setores_Ideal[setor], "Commodities", Peso_Setores_Ideal[financeiro]) -> 10007.23
A7: TAEE11 | B7: Energia | C7: =IFERROR((D7/$B$24), 0) -> 0.091873915 | D7: {=IFERROR(INDEX(Ações_Nacionais[], MATCH(A7, Ações_Nacionais[Ação], 0), MATCH(Ações_Nacionais[[#HEADERS],[Financeiro]], Ações_Nacionais[#HEADERS], 0)), "")} -> 3757 | F7: Seguradora | G7: =SUMIF(Setores_Ações[setor], "Seguradora", Setores_Ações[peso]) -> 0.09094466 | H7: =SUMIF(Setores_Ações[setor], "Seguradora", Setores_Ações[financeiro]) -> 3719 | J7: TAEE11 | K7: Energia | L7: =IFERROR((M7/$B$24), 0) -> 0.12235872 | M7: {=IFERROR( INDEX(Ações_Nacionais[], MATCH(J7, Ações_Nacionais[Ação], 0), MATCH(Ações_Nacionais[[#HEADERS],[Peso Ideal]], Ações_Nacionais[#HEADERS], 0)) * $B$26, "")} -> 5003.6151 | O7: Seguradora | P7: =SUMIF(Peso_Ideal_Ações[setor], "Seguradora", Peso_Ideal_Ações[peso]) -> 0.12235872 | Q7: =SUMIF(Peso_Ideal_Ações[setor], "Seguradora", Peso_Ideal_Ações[financeiro]) -> 5003.6151 | T7: TAEE11 | U7: Energia | V7: =IFERROR((W7/$B$24), 0) -> 0.12235872 | W7: {=IFERROR( INDEX(Ações_Nacionais[], MATCH(T7, Ações_Nacionais[Ação], 0), MATCH(Ações_Nacionais[[#HEADERS],[Peso Ideal]], Ações_Nacionais[#HEADERS], 0)) * $B$26, "")} -> 5003.6151 | Y7: Saneamento | Z7: =SUMIF(Peso_Setores_Ideal[setor], "Saneamento", Peso_Setores_Ideal[peso]) -> 0.12235872 | AA7: =SUMIF(Peso_Setores_Ideal[setor], "Saneamento", Peso_Setores_Ideal[financeiro]) -> 5003.6151
A8: ITUB3 | B8: Banco | C8: =IFERROR((D8/$B$24), 0) -> 0.19560805 | D8: {=IFERROR(INDEX(Ações_Nacionais[], MATCH(A8, Ações_Nacionais[Ação], 0), MATCH(Ações_Nacionais[[#HEADERS],[Financeiro]], Ações_Nacionais[#HEADERS], 0)) + INDEX(Ações_Nacionais[], MATCH("ITUB4", Ações_Nacionais[Ação], 0), MATCH(Ações_Nacionais[[#HEADERS],[Financeiro]], Ações_Nacionais[#HEADERS], 0)), "")} -> 7999 | F8: Saneamento | G8: =SUMIF(Setores_Ações[setor], "Saneamento", Setores_Ações[peso]) -> 0.015748417 | H8: =SUMIF(Setores_Ações[setor], "Saneamento", Setores_Ações[financeiro]) -> 644 | J8: ITUB3 | K8: Banco | L8: =IFERROR((M8/$B$24), 0) -> 0.12235872 | M8: {=IFERROR( INDEX(Ações_Nacionais[], MATCH(J8, Ações_Nacionais[Ação], 0), MATCH(Ações_Nacionais[[#HEADERS],[Peso Ideal]], Ações_Nacionais[#HEADERS], 0)) * $B$26, "")} -> 5003.6151 | O8: Saneamento | P8: =SUMIF(Peso_Ideal_Ações[setor], "Saneamento", Peso_Ideal_Ações[peso]) -> 0.12235872 | Q8: =SUMIF(Peso_Ideal_Ações[setor], "Saneamento", Peso_Ideal_Ações[financeiro]) -> 5003.6151 | T8: ITUB3 | U8: Financeiro | V8: =IFERROR((W8/$B$24), 0) -> 0.12235872 | W8: {=IFERROR( INDEX(Ações_Nacionais[], MATCH(T8, Ações_Nacionais[Ação], 0), MATCH(Ações_Nacionais[[#HEADERS],[Peso Ideal]], Ações_Nacionais[#HEADERS], 0)) * $B$26, "")} -> 5003.6151 | Y8: Industria | Z8: =SUMIF(Peso_Setores_Ideal[setor], "Industria", Peso_Setores_Ideal[peso]) -> 0.12235872 | AA8: =SUMIF(Peso_Setores_Ideal[setor], "Industria", Peso_Setores_Ideal[financeiro]) -> 5003.6151
A9: PETR4 | B9: Commodities | C9: =IFERROR((D9/$B$24), 0) -> 0.1083315 | D9: {=IFERROR(INDEX(Ações_Nacionais[], MATCH(A9, Ações_Nacionais[Ação], 0), MATCH(Ações_Nacionais[[#HEADERS],[Financeiro]], Ações_Nacionais[#HEADERS], 0)), "")} -> 4430 | F9: Commodities | G9: =SUMIF(Setores_Ações[setor], "Commodities", Setores_Ações[peso]) -> 0.29181033 | H9: =SUMIF(Setores_Ações[setor], "Commodities", Setores_Ações[financeiro]) -> 11933 | J9: PETR4 | K9: Commodities | L9: =IFERROR((M9/$B$24), 0) -> 0.12235872 | M9: {=IFERROR( INDEX(Ações_Nacionais[], MATCH(J9, Ações_Nacionais[Ação], 0), MATCH(Ações_Nacionais[[#HEADERS],[Peso Ideal]], Ações_Nacionais[#HEADERS], 0)) * $B$26, "")} -> 5003.6151 | O9: Commodities | P9: =SUMIF(Peso_Ideal_Ações[setor], "Commodities", Peso_Ideal_Ações[peso]) -> 0.24471744 | Q9: =SUMIF(Peso_Ideal_Ações[setor], "Commodities", Peso_Ideal_Ações[financeiro]) -> 10007.23 | T9: PETR4 | U9: Commodities | V9: =IFERROR((W9/$B$24), 0) -> 0.12235872 | W9: {=IFERROR( INDEX(Ações_Nacionais[], MATCH(T9, Ações_Nacionais[Ação], 0), MATCH(Ações_Nacionais[[#HEADERS],[Peso Ideal]], Ações_Nacionais[#HEADERS], 0)) * $B$26, "")} -> 5003.6151
A10: WEGE3 | B10: Cresc. | C10: =IFERROR((D10/$B$24), 0) -> 0.12048517 | D10: {=IFERROR(INDEX(Ações_Nacionais[], MATCH(A10, Ações_Nacionais[Ação], 0), MATCH(Ações_Nacionais[[#HEADERS],[Financeiro]], Ações_Nacionais[#HEADERS], 0)), "")} -> 4927 | J10: WEGE3 | K10: Cresc. | L10: =IFERROR((M10/$B$24), 0) -> 0.12235872 | M10: {=IFERROR( INDEX(Ações_Nacionais[], MATCH(J10, Ações_Nacionais[Ação], 0), MATCH(Ações_Nacionais[[#HEADERS],[Peso Ideal]], Ações_Nacionais[#HEADERS], 0)) * $B$26, "")} -> 5003.6151 | T10: WEGE3 | U10: Industria | V10: =IFERROR((W10/$B$24), 0) -> 0.12235872 | W10: {=IFERROR( INDEX(Ações_Nacionais[], MATCH(T10, Ações_Nacionais[Ação], 0), MATCH(Ações_Nacionais[[#HEADERS],[Peso Ideal]], Ações_Nacionais[#HEADERS], 0)) * $B$26, "")} -> 5003.6151
A11: BRBI11 | B11: Cresc. | C11: =IFERROR((D11/$B$24), 0) -> 0.029711687 | D11: {=IFERROR(INDEX(Ações_Nacionais[], MATCH(A11, Ações_Nacionais[Ação], 0), MATCH(Ações_Nacionais[[#HEADERS],[Financeiro]], Ações_Nacionais[#HEADERS], 0)), "")} -> 1215 | J11: BRBI11 | K11: Cresc. | L11: =IFERROR((M11/$B$24), 0) -> 0 | M11: {=IFERROR( INDEX(Ações_Nacionais[], MATCH(J11, Ações_Nacionais[Ação], 0), MATCH(Ações_Nacionais[[#HEADERS],[Peso Ideal]], Ações_Nacionais[#HEADERS], 0)) * $B$26, "")} -> 0 | T11: BRBI11 | U11: Financeiro | V11: =IFERROR((W11/$B$24), 0) -> 0 | W11: {=IFERROR( INDEX(Ações_Nacionais[], MATCH(T11, Ações_Nacionais[Ação], 0), MATCH(Ações_Nacionais[[#HEADERS],[Peso Ideal]], Ações_Nacionais[#HEADERS], 0)) * $B$26, "")} -> 0
A12: CMIG4 | B12: Energia | C12: =IFERROR((D12/$B$24), 0) -> 0.024551879 | D12: {=IFERROR(INDEX(Ações_Nacionais[], MATCH(A12, Ações_Nacionais[Ação], 0), MATCH(Ações_Nacionais[[#HEADERS],[Financeiro]], Ações_Nacionais[#HEADERS], 0)), "")} -> 1004 | J12: CMIG4 | K12: Energia | L12: =IFERROR((M12/$B$24), 0) -> 0.12235872 | M12: {=IFERROR( INDEX(Ações_Nacionais[], MATCH(J12, Ações_Nacionais[Ação], 0), MATCH(Ações_Nacionais[[#HEADERS],[Peso Ideal]], Ações_Nacionais[#HEADERS], 0)) * $B$26, "")} -> 5003.6151 | T12: CMIG4 | U12: Energia | V12: =IFERROR((W12/$B$24), 0) -> 0.12235872 | W12: {=IFERROR( INDEX(Ações_Nacionais[], MATCH(T12, Ações_Nacionais[Ação], 0), MATCH(Ações_Nacionais[[#HEADERS],[Peso Ideal]], Ações_Nacionais[#HEADERS], 0)) * $B$26, "")} -> 5003.6151
A13: ISAE4 | B13: Energia | C13: =IFERROR((D13/$B$24), 0) -> 0.063629472 | D13: {=IFERROR(INDEX(Ações_Nacionais[], MATCH(A13, Ações_Nacionais[Ação], 0), MATCH(Ações_Nacionais[[#HEADERS],[Financeiro]], Ações_Nacionais[#HEADERS], 0)), "")} -> 2602 | J13: ISAE4 | K13: Energia | L13: =IFERROR((M13/$B$24), 0) -> 0.12235872 | M13: {=IFERROR( INDEX(Ações_Nacionais[], MATCH(J13, Ações_Nacionais[Ação], 0), MATCH(Ações_Nacionais[[#HEADERS],[Peso Ideal]], Ações_Nacionais[#HEADERS], 0)) * $B$26, "")} -> 5003.6151 | T13: ISAE4 | U13: Energia | V13: =IFERROR((W13/$B$24), 0) -> 0.12235872 | W13: {=IFERROR( INDEX(Ações_Nacionais[], MATCH(T13, Ações_Nacionais[Ação], 0), MATCH(Ações_Nacionais[[#HEADERS],[Peso Ideal]], Ações_Nacionais[#HEADERS], 0)) * $B$26, "")} -> 5003.6151
A14: SAPR4 | B14: Saneamento | C14: =IFERROR((D14/$B$24), 0) -> 0.015748417 | D14: {=IFERROR(INDEX(Ações_Nacionais[], MATCH(A14, Ações_Nacionais[Ação], 0), MATCH(Ações_Nacionais[[#HEADERS],[Financeiro]], Ações_Nacionais[#HEADERS], 0)), "")} -> 644 | J14: SAPR4 | K14: Saneamento | L14: =IFERROR((M14/$B$24), 0) -> 0.12235872 | M14: {=IFERROR( INDEX(Ações_Nacionais[], MATCH(J14, Ações_Nacionais[Ação], 0), MATCH(Ações_Nacionais[[#HEADERS],[Peso Ideal]], Ações_Nacionais[#HEADERS], 0)) * $B$26, "")} -> 5003.6151 | T14: SAPR4 | U14: Saneamento | V14: =IFERROR((W14/$B$24), 0) -> 0.12235872 | W14: {=IFERROR( INDEX(Ações_Nacionais[], MATCH(T14, Ações_Nacionais[Ação], 0), MATCH(Ações_Nacionais[[#HEADERS],[Peso Ideal]], Ações_Nacionais[#HEADERS], 0)) * $B$26, "")} -> 5003.6151
A15: ITSA4 | B15: Banco | C15: =IFERROR((D15/$B$24), 0) -> 0.030567579 | D15: {=IFERROR(INDEX(Ações_Nacionais[], MATCH(A15, Ações_Nacionais[Ação], 0), MATCH(Ações_Nacionais[[#HEADERS],[Financeiro]], Ações_Nacionais[#HEADERS], 0)), "")} -> 1250 | J15: ITSA4 | K15: Banco | L15: =IFERROR((M15/$B$24), 0) -> 0.12235872 | M15: {=IFERROR( INDEX(Ações_Nacionais[], MATCH(J15, Ações_Nacionais[Ação], 0), MATCH(Ações_Nacionais[[#HEADERS],[Peso Ideal]], Ações_Nacionais[#HEADERS], 0)) * $B$26, "")} -> 5003.6151 | T15: ITSA4 | U15: Financeiro | V15: =IFERROR((W15/$B$24), 0) -> 0.12235872 | W15: {=IFERROR( INDEX(Ações_Nacionais[], MATCH(T15, Ações_Nacionais[Ação], 0), MATCH(Ações_Nacionais[[#HEADERS],[Peso Ideal]], Ações_Nacionais[#HEADERS], 0)) * $B$26, "")} -> 5003.6151
A24: Total Ações | B24: =SUM(HOME!B3) -> 40893
A25: Total FIIs | B25: =HOME!B4 -> 51728
A26: Total investido | B26: =HOME!B9 -> 133429.73
F29: Sub_Setor | G29: % do Total | H29: Total Investido
A30: ticker | B30: setor | C30: peso | D30: financeiro | F30: Log | G30: =SUMIF(Grafico_Total[setor], F30, Grafico_Total[peso]) -> 0.20456834 | H30: =SUMIF(Grafico_Total[setor], F30, Grafico_Total[financeiro]) -> 27295.5
A31: BBAS3 | B31: Financeiro | C31: =IFERROR((D31/$B$26), 0) -> 0.013812513 | D31: {=IFERROR(INDEX(Ações_Nacionais[], MATCH(A31, Ações_Nacionais[Ação], 0), MATCH(Ações_Nacionais[[#HEADERS],[Financeiro]], Ações_Nacionais[#HEADERS], 0)), "")} -> 1843 | F31: Shopp | G31: =SUMIF(Grafico_Total[setor], F31, Grafico_Total[peso]) -> 0.044753892 | H31: =SUMIF(Grafico_Total[setor], F31, Grafico_Total[financeiro]) -> 5971.5
A32: BBSE3 | B32: Financeiro | C32: =IFERROR((D32/$B$26), 0) -> 0.027872348 | D32: {=IFERROR(INDEX(Ações_Nacionais[], MATCH(A32, Ações_Nacionais[Ação], 0), MATCH(Ações_Nacionais[[#HEADERS],[Financeiro]], Ações_Nacionais[#HEADERS], 0)), "")} -> 3719 | F32: NTNB | G32: =SUMIF(Grafico_Total[setor], F32, Grafico_Total[peso]) -> 0.014302864 | H32: =SUMIF(Grafico_Total[setor], F32, Grafico_Total[financeiro]) -> 1908.4273
A33: VALE3 | B33: Commodities | C33: =IFERROR((D33/$B$26), 0) -> 0.056231844 | D33: {=IFERROR(INDEX(Ações_Nacionais[], MATCH(A33, Ações_Nacionais[Ação], 0), MATCH(Ações_Nacionais[[#HEADERS],[Financeiro]], Ações_Nacionais[#HEADERS], 0)), "")} -> 7503 | F33: Renda_Urbana | G33: =SUMIF(Grafico_Total[setor], F33, Grafico_Total[peso]) -> 0.0064790656 | H33: =SUMIF(Grafico_Total[setor], F33, Grafico_Total[financeiro]) -> 864.5
A34: TAEE11 | B34: Energia | C34: =IFERROR((D34/$B$26), 0) -> 0.028157142 | D34: {=IFERROR(INDEX(Ações_Nacionais[], MATCH(A34, Ações_Nacionais[Ação], 0), MATCH(Ações_Nacionais[[#HEADERS],[Financeiro]], Ações_Nacionais[#HEADERS], 0)), "")} -> 3757 | F34: Papel | G34: =SUMIF(Grafico_Total[setor], F34, Grafico_Total[peso]) -> 0.0034699912 | H34: =SUMIF(Grafico_Total[setor], F34, Grafico_Total[financeiro]) -> 463
A35: ITUB3 | B35: Financeiro | C35: =IFERROR((D35/$B$26), 0) -> 0.031020072 | D35: {=IFERROR(INDEX(Ações_Nacionais[], MATCH(A35, Ações_Nacionais[Ação], 0), MATCH(Ações_Nacionais[[#HEADERS],[Financeiro]], Ações_Nacionais[#HEADERS], 0)), "")} -> 4139 | F35: Financeiro | G35: =SUMIF(Grafico_Total[setor], F35, Grafico_Total[peso]) -> 0.08181085 | H35: =SUMIF(Grafico_Total[setor], F35, Grafico_Total[financeiro]) -> 10916
A36: PETR4 | B36: Commodities | C36: =IFERROR((D36/$B$26), 0) -> 0.033200995 | D36: {=IFERROR(INDEX(Ações_Nacionais[], MATCH(A36, Ações_Nacionais[Ação], 0), MATCH(Ações_Nacionais[[#HEADERS],[Financeiro]], Ações_Nacionais[#HEADERS], 0)), "")} -> 4430 | F36: Energia | G36: =SUMIF(Grafico_Total[setor], F36, Grafico_Total[peso]) -> 0.055182602 | H36: =SUMIF(Grafico_Total[setor], F36, Grafico_Total[financeiro]) -> 7363
A37: WEGE3 | B37: Industria | C37: =IFERROR((D37/$B$26), 0) -> 0.036925802 | D37: {=IFERROR(INDEX(Ações_Nacionais[], MATCH(A37, Ações_Nacionais[Ação], 0), MATCH(Ações_Nacionais[[#HEADERS],[Financeiro]], Ações_Nacionais[#HEADERS], 0)), "")} -> 4927 | F37: Commodities | G37: =SUMIF(Grafico_Total[setor], F37, Grafico_Total[peso]) -> 0.089432839 | H37: =SUMIF(Grafico_Total[setor], F37, Grafico_Total[financeiro]) -> 11933
A38: BRBI11 | B38: Financeiro | C38: =IFERROR((D38/$B$26), 0) -> 0.0091059163 | D38: {=IFERROR(INDEX(Ações_Nacionais[], MATCH(A38, Ações_Nacionais[Ação], 0), MATCH(Ações_Nacionais[[#HEADERS],[Financeiro]], Ações_Nacionais[#HEADERS], 0)), "")} -> 1215 | F38: Saneamento | G38: =SUMIF(Grafico_Total[setor], F38, Grafico_Total[peso]) -> 0.0048265104 | H38: =SUMIF(Grafico_Total[setor], F38, Grafico_Total[financeiro]) -> 644
A39: CMIG4 | B39: Energia | C39: =IFERROR((D39/$B$26), 0) -> 0.0075245597 | D39: {=IFERROR(INDEX(Ações_Nacionais[], MATCH(A39, Ações_Nacionais[Ação], 0), MATCH(Ações_Nacionais[[#HEADERS],[Financeiro]], Ações_Nacionais[#HEADERS], 0)), "")} -> 1004 | F39: Industria | G39: =SUMIF(Grafico_Total[setor], F39, Grafico_Total[peso]) -> 0.036925802 | H39: =SUMIF(Grafico_Total[setor], F39, Grafico_Total[financeiro]) -> 4927
A40: ISAE4 | B40: Energia | C40: =IFERROR((D40/$B$26), 0) -> 0.019500901 | D40: {=IFERROR(INDEX(Ações_Nacionais[], MATCH(A40, Ações_Nacionais[Ação], 0), MATCH(Ações_Nacionais[[#HEADERS],[Financeiro]], Ações_Nacionais[#HEADERS], 0)), "")} -> 2602 | F40: Renda_Fixa | G40: =SUMIF(Grafico_Total[setor], F40, Grafico_Total[peso]) -> 0.22424435 | H40: =SUMIF(Grafico_Total[setor], F40, Grafico_Total[financeiro]) -> 29920.864
A41: SAPR4 | B41: Saneamento | C41: =IFERROR((D41/$B$26), 0) -> 0.0048265104 | D41: {=IFERROR(INDEX(Ações_Nacionais[], MATCH(A41, Ações_Nacionais[Ação], 0), MATCH(Ações_Nacionais[[#HEADERS],[Financeiro]], Ações_Nacionais[#HEADERS], 0)), "")} -> 644 | F41: Internacional | G41: =SUMIF(Grafico_Total[setor], F41, Grafico_Total[peso]) -> 0.043073644 | H41: =SUMIF(Grafico_Total[setor], F41, Grafico_Total[financeiro]) -> 5747.3049
A42: XPLG11 | B42: Log | C42: =IFERROR((D42/$B$26), 0) -> 0.033725616 | D42: {=IFERROR(INDEX(Fiis[], MATCH(A42, Fiis[Fii], 0), MATCH(Fiis[[#HEADERS],[Financeiro]], Fiis[#HEADERS], 0)), "")} -> 4500 | F42: Cripto | G42: =SUMIF(Grafico_Total[setor], F42, Grafico_Total[peso]) -> 0.024223524 | H42: =SUMIF(Grafico_Total[setor], F42, Grafico_Total[financeiro]) -> 3232.1384
A43: HGBS11 | B43: Shopp | C43: =IFERROR((D43/$B$26), 0) -> 0.0069699606 | D43: {=IFERROR(INDEX(Fiis[], MATCH(A43, Fiis[Fii], 0), MATCH(Fiis[[#HEADERS],[Financeiro]], Fiis[#HEADERS], 0)), "")} -> 930
A44: Tesouro Renda | B44: NTNB | C44: =IFERROR((D44/$B$26), 0) -> 0.014302864 | D44: {=IFERROR(INDEX(Carteira[], MATCH(A44, Carteira[Tipo], 0), MATCH(Carteira[[#HEADERS],[Capital]], Carteira[#HEADERS], 0)), "")} -> 1908.4273
A45: BRCO11 | B45: Log | C45: =IFERROR((D45/$B$26), 0) -> 0.041909699 | D45: {=IFERROR(INDEX(Fiis[], MATCH(A45, Fiis[Fii], 0), MATCH(Fiis[[#HEADERS],[Financeiro]], Fiis[#HEADERS], 0)), "")} -> 5592
A46: HGLG11 | B46: Log | C46: =IFERROR((D46/$B$26), 0) -> 0.055163866 | D46: {=IFERROR(INDEX(Fiis[], MATCH(A46, Fiis[Fii], 0), MATCH(Fiis[[#HEADERS],[Financeiro]], Fiis[#HEADERS], 0)), "")} -> 7360.5
A47: LVBI11 | B47: Log | C47: =IFERROR((D47/$B$26), 0) -> 0.036907066 | D47: {=IFERROR(INDEX(Fiis[], MATCH(A47, Fiis[Fii], 0), MATCH(Fiis[[#HEADERS],[Financeiro]], Fiis[#HEADERS], 0)), "")} -> 4924.5
A48: BTLG11 | B48: Log | C48: =IFERROR((D48/$B$26), 0) -> 0.036862098 | D48: {=IFERROR(INDEX(Fiis[], MATCH(A48, Fiis[Fii], 0), MATCH(Fiis[[#HEADERS],[Financeiro]], Fiis[#HEADERS], 0)), "")} -> 4918.5
A49: GGRC11 | B49: Renda_Urbana | C49: =IFERROR((D49/$B$26), 0) -> 0.0033950453 | D49: {=IFERROR(INDEX(Fiis[], MATCH(A49, Fiis[Fii], 0), MATCH(Fiis[[#HEADERS],[Financeiro]], Fiis[#HEADERS], 0)), "")} -> 453
A50: GARE11 | B50: Renda_Urbana | C50: =IFERROR((D50/$B$26), 0) -> 0.0030840202 | D50: {=IFERROR(INDEX(Fiis[], MATCH(A50, Fiis[Fii], 0), MATCH(Fiis[[#HEADERS],[Financeiro]], Fiis[#HEADERS], 0)), "")} -> 411.5
A51: PMLL11 | B51: Shopp | C51: =IFERROR((D51/$B$26), 0) -> 0.037783932 | D51: {=IFERROR(INDEX(Fiis[], MATCH(A51, Fiis[Fii], 0), MATCH(Fiis[[#HEADERS],[Financeiro]], Fiis[#HEADERS], 0)), "")} -> 5041.5
C52: =IFERROR((D52/$B$26), 0) -> 0
A53: MXRF11 | B53: Papel | C53: =IFERROR((D53/$B$26), 0) -> 0.0034699912 | D53: {=IFERROR(INDEX(Fiis[], MATCH(A53, Fiis[Fii], 0), MATCH(Fiis[[#HEADERS],[Financeiro]], Fiis[#HEADERS], 0)), "")} -> 463
A54: Renda_Fixa | B54: Renda_Fixa | C54: =IFERROR((D54/$B$26), 0) -> 0.22424435 | D54: {=IFERROR(INDEX(Carteira[], MATCH(A54, Carteira[Tipo], 0), MATCH(Carteira[[#HEADERS],[Capital]], Carteira[#HEADERS], 0)), "")} -> 29920.864
A55: Etfs | B55: Internacional | C55: =IFERROR((D55/$B$26), 0) -> 0.043073644 | D55: {=IFERROR(INDEX(Carteira[], MATCH(A55, Carteira[Tipo], 0), MATCH(Carteira[[#HEADERS],[Capital]], Carteira[#HEADERS], 0)), "")} -> 5747.3049
A56: Cripto | B56: Cripto | C56: =IFERROR((D56/$B$26), 0) -> 0.024223524 | D56: {=IFERROR(INDEX(Carteira[], MATCH(A56, Carteira[Tipo], 0), MATCH(Carteira[[#HEADERS],[Capital]], Carteira[#HEADERS], 0)), "")} -> 3232.1384
A60: Fundo | B60: Segmento | C60: Classificação de Risco | D60: Qtidade Cotas Atual | E60: Cotação Atual | F60: Saldo Atual | G60: Posição
A61: GGRC11 | B61: Logística | C61: Oportunidade | D61: {=IFERROR(INDEX(Fiis[], MATCH(A61, Fiis[Fii], 0), MATCH(Fiis[[#HEADERS],[QTD]], Fiis[#HEADERS], 0)), "")} -> 50 | E61: =IFERROR(__xludf.DUMMYFUNCTION("GOOGLEFINANCE(A61)"),9.06) -> 9.06 | F61: =D61*E61 -> 453 | G61: =IFERROR((F61/grafico!$B$25), 0) -> 0.0087573461
A62: LVBI11 | B62: Logística | C62: Ancoragem | D62: {=IFERROR(INDEX(Fiis[], MATCH(A62, Fiis[Fii], 0), MATCH(Fiis[[#HEADERS],[QTD]], Fiis[#HEADERS], 0)), "")} -> 50 | E62: =IFERROR(__xludf.DUMMYFUNCTION("GOOGLEFINANCE(A62)"),98.49) -> 98.49 | F62: =D62*E62 -> 4924.5 | G62: =IFERROR((F62/grafico!$B$25), 0) -> 0.095199892
A63: GARE11 | B63: Renda Urb/Log | C63: Oportunidade | D63: {=IFERROR(INDEX(Fiis[], MATCH(A63, Fiis[Fii], 0), MATCH(Fiis[[#HEADERS],[QTD]], Fiis[#HEADERS], 0)), "")} -> 50 | E63: =IFERROR(__xludf.DUMMYFUNCTION("GOOGLEFINANCE(A63)"),8.23) -> 8.23 | F63: =D63*E63 -> 411.5 | G63: =IFERROR((F63/grafico!$B$25), 0) -> 0.0079550727
A64: XPLG11 | B64: Logística | C64: Oportunidade | D64: {=IFERROR(INDEX(Fiis[], MATCH(A64, Fiis[Fii], 0), MATCH(Fiis[[#HEADERS],[QTD]], Fiis[#HEADERS], 0)), "")} -> 50 | E64: =IFERROR(__xludf.DUMMYFUNCTION("GOOGLEFINANCE(A64)"),90.0) -> 90 | F64: =D64*E64 -> 4500 | G64: =IFERROR((F64/grafico!$B$25), 0) -> 0.086993504
A65: PMLL11 | B65: Shoppings | C65: Oportunidade | D65: {=IFERROR(INDEX(Fiis[], MATCH(A65, Fiis[Fii], 0), MATCH(Fiis[[#HEADERS],[QTD]], Fiis[#HEADERS], 0)), "")} -> 50 | E65: =IFERROR(__xludf.DUMMYFUNCTION("GOOGLEFINANCE(A65)"),100.83) -> 100.83 | F65: =D65*E65 -> 5041.5 | G65: =IFERROR((F65/grafico!$B$25), 0) -> 0.097461723
A66: BTLG11 | B66: Logística | C66: Ancoragem | D66: {=IFERROR(INDEX(Fiis[], MATCH(A66, Fiis[Fii], 0), MATCH(Fiis[[#HEADERS],[QTD]], Fiis[#HEADERS], 0)), "")} -> 50 | E66: =IFERROR(__xludf.DUMMYFUNCTION("GOOGLEFINANCE(A66)"),98.37) -> 98.37 | F66: =D66*E66 -> 4918.5 | G66: =IFERROR((F66/grafico!$B$25), 0) -> 0.0950839
A67: HGBS11 | B67: Shoppings | C67: Oportunidade | D67: {=IFERROR(INDEX(Fiis[], MATCH(A67, Fiis[Fii], 0), MATCH(Fiis[[#HEADERS],[QTD]], Fiis[#HEADERS], 0)), "")} -> 50 | E67: =IFERROR(__xludf.DUMMYFUNCTION("GOOGLEFINANCE(A67)"),18.6) -> 18.6 | F67: =D67*E67 -> 930 | G67: =IFERROR((F67/grafico!$B$25), 0) -> 0.017978658
A68: BRCO11 | B68: Logística | C68: Oportunidade | D68: {=IFERROR(INDEX(Fiis[], MATCH(A68, Fiis[Fii], 0), MATCH(Fiis[[#HEADERS],[QTD]], Fiis[#HEADERS], 0)), "")} -> 50 | E68: =IFERROR(__xludf.DUMMYFUNCTION("GOOGLEFINANCE(A68)"),111.84) -> 111.84 | F68: =D68*E68 -> 5592 | G68: =IFERROR((F68/grafico!$B$25), 0) -> 0.10810393
A69: MXRF11 | B69: CRI | C69: Ancoragem | D69: {=IFERROR(INDEX(Fiis[], MATCH(A69, Fiis[Fii], 0), MATCH(Fiis[[#HEADERS],[QTD]], Fiis[#HEADERS], 0)), "")} -> 50 | E69: =IFERROR(__xludf.DUMMYFUNCTION("GOOGLEFINANCE(A69)"),9.26) -> 9.26 | F69: =D69*E69 -> 463 | G69: =IFERROR((F69/grafico!$B$25), 0) -> 0.008950665
A70: HGLG11 | B70: Logística | C70: Oportunidade | D70: {=IFERROR(INDEX(Fiis[], MATCH(A70, Fiis[Fii], 0), MATCH(Fiis[[#HEADERS],[QTD]], Fiis[#HEADERS], 0)), "")} -> 50 | E70: =IFERROR(__xludf.DUMMYFUNCTION("GOOGLEFINANCE(A70)"),147.21) -> 147.21 | F70: =D70*E70 -> 7360.5 | G70: =IFERROR((F70/grafico!$B$25), 0) -> 0.14229238
A71: KNRI11 | B71: Lajes/Log | C71: Ancoragem | D71: {=IFERROR(INDEX(Fiis[], MATCH(A71, Fiis[Fii], 0), MATCH(Fiis[[#HEADERS],[QTD]], Fiis[#HEADERS], 0)), "")} -> 50 | E71: =IFERROR(__xludf.DUMMYFUNCTION("GOOGLEFINANCE(A71)"),155.48) -> 155.48 | F71: =D71*E71 -> 7774 | G71: =IFERROR((F71/grafico!$B$25), 0) -> 0.15028611
A72: HGRU11 | B72: Renda Urbana | C72: Ancoragem | D72: {=IFERROR(INDEX(Fiis[], MATCH(A72, Fiis[Fii], 0), MATCH(Fiis[[#HEADERS],[QTD]], Fiis[#HEADERS], 0)), "")} -> 50 | E72: =IFERROR(__xludf.DUMMYFUNCTION("GOOGLEFINANCE(A72)"),114.99) -> 114.99 | F72: =D72*E72 -> 5749.5 | G72: =IFERROR((F72/grafico!$B$25), 0) -> 0.1111487
A73: PCIP11 | B73: CRI | C73: Oportunidade | D73: {=IFERROR(INDEX(Fiis[], MATCH(A73, Fiis[Fii], 0), MATCH(Fiis[[#HEADERS],[QTD]], Fiis[#HEADERS], 0)), "")} -> 50 | E73: =IFERROR(__xludf.DUMMYFUNCTION("GOOGLEFINANCE(A73)"),72.2) -> 72.2 | F73: =D73*E73 -> 3610 | G73: =IFERROR((F73/grafico!$B$25), 0) -> 0.069788122

Sheet FERIADOS
A1: 46023
A2: 46070
A3: 46115
A4: 46117
A5: 46133
A6: 46143
A7: 46177
A8: 46272
A9: 46307
A10: 46328
A11: 46341
A12: 46346
A13: 46381

Sheet Status_Script
A1: Nome | B1: Status | C1: Data/Hora
A4: Selic_IPCA | B4: OK ✅ | C4: 46251.449
A5: Titulos_IPCA | B5: OK ✅ | C5: 46257.595
A6: Feriados | B6: OK ✅ | C6: 46209.391
