Workbook

Sheet HOME
A2: Tipo | B2: Capital | C2: Peso(%) | D2: Peso Ideal | F2: Selic
A3: Ações Nacionais | B3: =SUM(Ações_Nacionais[Financeiro]) -> 6264.32 | C3: =IFERROR((B3/$B$9), 0) -> 0.38165049 | D3: 0.45 | F3: =Indicadores!J3 -> 0.139 | J3: TICKER | K3: FCFE_KE | L3: Excess_Return | M3: TIR
A4: FIIs | B4: =SUM(Fiis[Financeiro]) -> 5656.11 | C4: =IFERROR((B4/$B$9), 0) -> 0.3445956 | D4: 0.25 | F4: IPCA | J4: BBAS3 | K4: =IFERROR(__xludf.DUMMYFUNCTION("IFERROR(QUERY(IMPORTRANGE(""https://docs.google.com/spreadsheets/d/13BtipUqnMqTLuIjTLHxotLh69yonOifaQ-H3QjUvBGk/edit?usp=sharing"", ""Indicadores_Ações!A30:C""), ""SELECT Col2 WHERE Col1 = '""&J4 &""'"", 0), 0)"),24.582325592518224) -> 24.582326 | L4: =IFERROR(__xludf.DUMMYFUNCTION("IFERROR(QUERY(IMPORTRANGE(""https://docs.google.com/spreadsheets/d/13BtipUqnMqTLuIjTLHxotLh69yonOifaQ-H3QjUvBGk/edit?usp=sharing"", ""Indicadores_Ações!A30:D""), ""SELECT Col3 WHERE Col1 = '""&J4 &""'"", 0), 0)"),22.05252712910461) -> 22.052527 | M4: =IFERROR(__xludf.DUMMYFUNCTION("IFERROR(QUERY(IMPORTRANGE(""https://docs.google.com/spreadsheets/d/13BtipUqnMqTLuIjTLHxotLh69yonOifaQ-H3QjUvBGk/edit?usp=sharing"", ""Indicadores_Ações!A30:W""), ""SELECT Col4 WHERE Col1 = '""&J4 &""'"", 0), 0)"),0.20153510282095904) -> 0.2015351
A5: Renda_Fixa | B5: =SUM(Renda_Fixa[Financeiro]) -> 1428.8859 | C5: =IFERROR((B5/$B$9), 0) -> 0.08705414 | D5: 0.12 | F5: =Indicadores!J4 -> 0.044430246 | J5: BBSE3 | K5: =IFERROR(__xludf.DUMMYFUNCTION("IFERROR(QUERY(IMPORTRANGE(""https://docs.google.com/spreadsheets/d/13BtipUqnMqTLuIjTLHxotLh69yonOifaQ-H3QjUvBGk/edit?usp=sharing"", ""Indicadores_Ações!A30:C""), ""SELECT Col2 WHERE Col1 = '""&J5 &""'"", 0), 0)"),41.278339110948615) -> 41.278339 | L5: =IFERROR(__xludf.DUMMYFUNCTION("IFERROR(QUERY(IMPORTRANGE(""https://docs.google.com/spreadsheets/d/13BtipUqnMqTLuIjTLHxotLh69yonOifaQ-H3QjUvBGk/edit?usp=sharing"", ""Indicadores_Ações!A30:D""), ""SELECT Col3 WHERE Col1 = '""&J5 &""'"", 0), 0)"),35.54874689479061) -> 35.548747 | M5: =IFERROR(__xludf.DUMMYFUNCTION("IFERROR(QUERY(IMPORTRANGE(""https://docs.google.com/spreadsheets/d/13BtipUqnMqTLuIjTLHxotLh69yonOifaQ-H3QjUvBGk/edit?usp=sharing"", ""Indicadores_Ações!A30:W""), ""SELECT Col4 WHERE Col1 = '""&J5 &""'"", 0), 0)"),0.16419505043441035) -> 0.16419505
A6: Etfs | B6: =SUM(Etfs[financeiro]) -> 2323.0474 | C6: =IFERROR((B6/$B$9), 0) -> 0.14153047 | D6: 0.14 | J6: ITUB3 | K6: =IFERROR(__xludf.DUMMYFUNCTION("IFERROR(QUERY(IMPORTRANGE(""https://docs.google.com/spreadsheets/d/13BtipUqnMqTLuIjTLHxotLh69yonOifaQ-H3QjUvBGk/edit?usp=sharing"", ""Indicadores_Ações!A30:C""), ""SELECT Col2 WHERE Col1 = '""&J6 &""'"", 0), 0)"),42.94063084013628) -> 42.940631 | L6: =IFERROR(__xludf.DUMMYFUNCTION("IFERROR(QUERY(IMPORTRANGE(""https://docs.google.com/spreadsheets/d/13BtipUqnMqTLuIjTLHxotLh69yonOifaQ-H3QjUvBGk/edit?usp=sharing"", ""Indicadores_Ações!A30:D""), ""SELECT Col3 WHERE Col1 = '""&J6 &""'"", 0), 0)"),36.14885822843896) -> 36.148858 | M6: =IFERROR(__xludf.DUMMYFUNCTION("IFERROR(QUERY(IMPORTRANGE(""https://docs.google.com/spreadsheets/d/13BtipUqnMqTLuIjTLHxotLh69yonOifaQ-H3QjUvBGk/edit?usp=sharing"", ""Indicadores_Ações!A30:W""), ""SELECT Col4 WHERE Col1 = '""&J6 &""'"", 0), 0)"),0.15140007110151935) -> 0.15140007
A7: Tesouro Renda | B7: =SUM(Tesouro[Financeiro]) -> 307.7726 | C7: =IFERROR((B7/$B$9), 0) -> 0.018750888 | D7: 0.02 | J7: ITSA4 | K7: =IFERROR(__xludf.DUMMYFUNCTION("IFERROR(QUERY(IMPORTRANGE(""https://docs.google.com/spreadsheets/d/13BtipUqnMqTLuIjTLHxotLh69yonOifaQ-H3QjUvBGk/edit?usp=sharing"", ""Indicadores_Ações!A30:C""), ""SELECT Col2 WHERE Col1 = '""&J7 &""'"", 0), 0)"),14.820468978710906) -> 14.820469 | L7: =IFERROR(__xludf.DUMMYFUNCTION("IFERROR(QUERY(IMPORTRANGE(""https://docs.google.com/spreadsheets/d/13BtipUqnMqTLuIjTLHxotLh69yonOifaQ-H3QjUvBGk/edit?usp=sharing"", ""Indicadores_Ações!A30:D""), ""SELECT Col3 WHERE Col1 = '""&J7 &""'"", 0), 0)"),12.519149674593985) -> 12.51915 | M7: =IFERROR(__xludf.DUMMYFUNCTION("IFERROR(QUERY(IMPORTRANGE(""https://docs.google.com/spreadsheets/d/13BtipUqnMqTLuIjTLHxotLh69yonOifaQ-H3QjUvBGk/edit?usp=sharing"", ""Indicadores_Ações!A30:W""), ""SELECT Col4 WHERE Col1 = '""&J7 &""'"", 0), 0)"),0.254539876482554) -> 0.25453988
A8: Cripto | B8: =SUM(Cripto[financeiro]) -> 433.62544 | C8: =IFERROR((B8/$B$9), 0) -> 0.026418408 | D8: 0.02 | J8: CMIG4 | K8: =IFERROR(__xludf.DUMMYFUNCTION("IFERROR(QUERY(IMPORTRANGE(""https://docs.google.com/spreadsheets/d/13BtipUqnMqTLuIjTLHxotLh69yonOifaQ-H3QjUvBGk/edit?usp=sharing"", ""Indicadores_Ações!A30:C""), ""SELECT Col2 WHERE Col1 = '""&J8 &""'"", 0), 0)"),11.72733300564568) -> 11.727333 | L8: =IFERROR(__xludf.DUMMYFUNCTION("IFERROR(QUERY(IMPORTRANGE(""https://docs.google.com/spreadsheets/d/13BtipUqnMqTLuIjTLHxotLh69yonOifaQ-H3QjUvBGk/edit?usp=sharing"", ""Indicadores_Ações!A30:D""), ""SELECT Col3 WHERE Col1 = '""&J8 &""'"", 0), 0)"),"") | M8: =IFERROR(__xludf.DUMMYFUNCTION("IFERROR(QUERY(IMPORTRANGE(""https://docs.google.com/spreadsheets/d/13BtipUqnMqTLuIjTLHxotLh69yonOifaQ-H3QjUvBGk/edit?usp=sharing"", ""Indicadores_Ações!A30:W""), ""SELECT Col4 WHERE Col1 = '""&J8 &""'"", 0), 0)"),0.07521528348136512) -> 0.075215283
A9: Capital | B9: =SUM(B3:B8) -> 16413.761 | C9: =SUM(C3:C8) -> 1 | D9: =SUM(D3:D8) -> 1 | J9: TAEE11 | K9: =IFERROR(__xludf.DUMMYFUNCTION("IFERROR(QUERY(IMPORTRANGE(""https://docs.google.com/spreadsheets/d/13BtipUqnMqTLuIjTLHxotLh69yonOifaQ-H3QjUvBGk/edit?usp=sharing"", ""Indicadores_Ações!A30:C""), ""SELECT Col2 WHERE Col1 = '""&J9 &""'"", 0), 0)"),32.73144074168751) -> 32.731441 | L9: =IFERROR(__xludf.DUMMYFUNCTION("IFERROR(QUERY(IMPORTRANGE(""https://docs.google.com/spreadsheets/d/13BtipUqnMqTLuIjTLHxotLh69yonOifaQ-H3QjUvBGk/edit?usp=sharing"", ""Indicadores_Ações!A30:D""), ""SELECT Col3 WHERE Col1 = '""&J9 &""'"", 0), 0)"),"") | M9: =IFERROR(__xludf.DUMMYFUNCTION("IFERROR(QUERY(IMPORTRANGE(""https://docs.google.com/spreadsheets/d/13BtipUqnMqTLuIjTLHxotLh69yonOifaQ-H3QjUvBGk/edit?usp=sharing"", ""Indicadores_Ações!A30:W""), ""SELECT Col4 WHERE Col1 = '""&J9 &""'"", 0), 0)"),-0.0017091351308990512) -> -0.0017091351
J10: ISAE4 | K10: =IFERROR(__xludf.DUMMYFUNCTION("IFERROR(QUERY(IMPORTRANGE(""https://docs.google.com/spreadsheets/d/13BtipUqnMqTLuIjTLHxotLh69yonOifaQ-H3QjUvBGk/edit?usp=sharing"", ""Indicadores_Ações!A30:C""), ""SELECT Col2 WHERE Col1 = '""&J10 &""'"", 0), 0)"),24.700599016406418) -> 24.700599 | L10: =IFERROR(__xludf.DUMMYFUNCTION("IFERROR(QUERY(IMPORTRANGE(""https://docs.google.com/spreadsheets/d/13BtipUqnMqTLuIjTLHxotLh69yonOifaQ-H3QjUvBGk/edit?usp=sharing"", ""Indicadores_Ações!A30:D""), ""SELECT Col3 WHERE Col1 = '""&J10 &""'"", 0), 0)"),"") | M10: =IFERROR(__xludf.DUMMYFUNCTION("IFERROR(QUERY(IMPORTRANGE(""https://docs.google.com/spreadsheets/d/13BtipUqnMqTLuIjTLHxotLh69yonOifaQ-H3QjUvBGk/edit?usp=sharing"", ""Indicadores_Ações!A30:W""), ""SELECT Col4 WHERE Col1 = '""&J10 &""'"", 0), 0)"),0.017886036232895787) -> 0.017886036
J11: WEGE3 | K11: =IFERROR(__xludf.DUMMYFUNCTION("IFERROR(QUERY(IMPORTRANGE(""https://docs.google.com/spreadsheets/d/13BtipUqnMqTLuIjTLHxotLh69yonOifaQ-H3QjUvBGk/edit?usp=sharing"", ""Indicadores_Ações!A30:C""), ""SELECT Col2 WHERE Col1 = '""&J11 &""'"", 0), 0)"),42.56865445908471) -> 42.568654 | L11: =IFERROR(__xludf.DUMMYFUNCTION("IFERROR(QUERY(IMPORTRANGE(""https://docs.google.com/spreadsheets/d/13BtipUqnMqTLuIjTLHxotLh69yonOifaQ-H3QjUvBGk/edit?usp=sharing"", ""Indicadores_Ações!A30:D""), ""SELECT Col3 WHERE Col1 = '""&J11 &""'"", 0), 0)"),"") | M11: =IFERROR(__xludf.DUMMYFUNCTION("IFERROR(QUERY(IMPORTRANGE(""https://docs.google.com/spreadsheets/d/13BtipUqnMqTLuIjTLHxotLh69yonOifaQ-H3QjUvBGk/edit?usp=sharing"", ""Indicadores_Ações!A30:W""), ""SELECT Col4 WHERE Col1 = '""&J11 &""'"", 0), 0)"),0.12833071325893916) -> 0.12833071
J12: VALE3 | K12: =IFERROR(__xludf.DUMMYFUNCTION("IFERROR(QUERY(IMPORTRANGE(""https://docs.google.com/spreadsheets/d/13BtipUqnMqTLuIjTLHxotLh69yonOifaQ-H3QjUvBGk/edit?usp=sharing"", ""Indicadores_Ações!A30:C""), ""SELECT Col2 WHERE Col1 = '""&J12 &""'"", 0), 0)"),67.54718003647454) -> 67.54718 | L12: =IFERROR(__xludf.DUMMYFUNCTION("IFERROR(QUERY(IMPORTRANGE(""https://docs.google.com/spreadsheets/d/13BtipUqnMqTLuIjTLHxotLh69yonOifaQ-H3QjUvBGk/edit?usp=sharing"", ""Indicadores_Ações!A30:D""), ""SELECT Col3 WHERE Col1 = '""&J12 &""'"", 0), 0)"),"") | M12: =IFERROR(__xludf.DUMMYFUNCTION("IFERROR(QUERY(IMPORTRANGE(""https://docs.google.com/spreadsheets/d/13BtipUqnMqTLuIjTLHxotLh69yonOifaQ-H3QjUvBGk/edit?usp=sharing"", ""Indicadores_Ações!A30:W""), ""SELECT Col4 WHERE Col1 = '""&J12 &""'"", 0), 0)"),0.09310251941736486) -> 0.093102519
J13: PETR4 | K13: =IFERROR(__xludf.DUMMYFUNCTION("IFERROR(QUERY(IMPORTRANGE(""https://docs.google.com/spreadsheets/d/13BtipUqnMqTLuIjTLHxotLh69yonOifaQ-H3QjUvBGk/edit?usp=sharing"", ""Indicadores_Ações!A30:C""), ""SELECT Col2 WHERE Col1 = '""&J13 &""'"", 0), 0)"),45.58782647565251) -> 45.587826 | L13: =IFERROR(__xludf.DUMMYFUNCTION("IFERROR(QUERY(IMPORTRANGE(""https://docs.google.com/spreadsheets/d/13BtipUqnMqTLuIjTLHxotLh69yonOifaQ-H3QjUvBGk/edit?usp=sharing"", ""Indicadores_Ações!A30:D""), ""SELECT Col3 WHERE Col1 = '""&J13 &""'"", 0), 0)"),"") | M13: =IFERROR(__xludf.DUMMYFUNCTION("IFERROR(QUERY(IMPORTRANGE(""https://docs.google.com/spreadsheets/d/13BtipUqnMqTLuIjTLHxotLh69yonOifaQ-H3QjUvBGk/edit?usp=sharing"", ""Indicadores_Ações!A30:W""), ""SELECT Col4 WHERE Col1 = '""&J13 &""'"", 0), 0)"),0.12034904732443337) -> 0.12034905
J14: SAPR4 | K14: =IFERROR(__xludf.DUMMYFUNCTION("IFERROR(QUERY(IMPORTRANGE(""https://docs.google.com/spreadsheets/d/13BtipUqnMqTLuIjTLHxotLh69yonOifaQ-H3QjUvBGk/edit?usp=sharing"", ""Indicadores_Ações!A30:C""), ""SELECT Col2 WHERE Col1 = '""&J14 &""'"", 0), 0)"),7.255943037069481) -> 7.255943 | L14: =IFERROR(__xludf.DUMMYFUNCTION("IFERROR(QUERY(IMPORTRANGE(""https://docs.google.com/spreadsheets/d/13BtipUqnMqTLuIjTLHxotLh69yonOifaQ-H3QjUvBGk/edit?usp=sharing"", ""Indicadores_Ações!A30:D""), ""SELECT Col3 WHERE Col1 = '""&J14 &""'"", 0), 0)"),"") | M14: =IFERROR(__xludf.DUMMYFUNCTION("IFERROR(QUERY(IMPORTRANGE(""https://docs.google.com/spreadsheets/d/13BtipUqnMqTLuIjTLHxotLh69yonOifaQ-H3QjUvBGk/edit?usp=sharing"", ""Indicadores_Ações!A30:W""), ""SELECT Col4 WHERE Col1 = '""&J14 &""'"", 0), 0)"),0.13281138489251504) -> 0.13281138
A21: QTD | B21: Ação | C21: Peso | D21: Nota | E21: Peso Ideal | F21: Financeiro | G21: FCFE_KE | H21: MG_FCFE | I21: P/Teto | J21: Margen | K21: Preço mercado | L21: TIR
A22: 28 | B22: BBAS3 | C22: =IFERROR((F22/$B$9), 0) -> 0.038416545 | D22: 10 | E22: =(D22/SUM(Ações_Nacionais[Nota]))*$D$3 -> 0.040909091 | F22: =A22*K22 -> 630.56 | G22: {=IFERROR(INDEX(FCD[], MATCH(B22, FCD[TICKER], 0), MATCH(FCD[[#HEADERS],[FCFE_KE]], FCD[#HEADERS], 0)),"")} -> 24.582326 | H22: 0.2 | I22: =G22*(1-H22) -> 19.66586 | J22: =IFERROR(1-(K22/G22),"") -> 0.08389465 | K22: =IFERROR(__xludf.DUMMYFUNCTION("(GOOGLEFINANCE(""BVMF:"" & B22))"),22.52) -> 22.52 | L22: {=IFERROR(INDEX(FCD[], MATCH(B22, FCD[TICKER], 0), MATCH(FCD[[#HEADERS],[TIR]], FCD[#HEADERS], 0)),"")} -> 0.2015351
A23: 20 | B23: ITSA4 | C23: =IFERROR((F23/$B$9), 0) -> 0.017095411 | D23: 10 | E23: =(D23/SUM(Ações_Nacionais[Nota]))*$D$3 -> 0.040909091 | F23: =A23*K23 -> 280.6 | G23: {=IFERROR(INDEX(FCD[], MATCH(B23, FCD[TICKER], 0), MATCH(FCD[[#HEADERS],[FCFE_KE]], FCD[#HEADERS], 0)),"")} -> 14.820469 | H23: 0.16 | I23: =G23*(1-H23) -> 12.449194 | J23: =IFERROR(1-(K23/G23),"") -> 0.0533363 | K23: =IFERROR(__xludf.DUMMYFUNCTION("(GOOGLEFINANCE(""BVMF:"" & B23))"),14.03) -> 14.03 | L23: {=IFERROR(INDEX(FCD[], MATCH(B23, FCD[TICKER], 0), MATCH(FCD[[#HEADERS],[TIR]], FCD[#HEADERS], 0)),"")} -> 0.25453988
A24: 59 | B24: SAPR4 | C24: =IFERROR((F24/$B$9), 0) -> 0.024586686 | D24: 10 | E24: =(D24/SUM(Ações_Nacionais[Nota]))*$D$3 -> 0.040909091 | F24: =A24*K24 -> 403.56 | G24: {=IFERROR(INDEX(FCD[], MATCH(B24, FCD[TICKER], 0), MATCH(FCD[[#HEADERS],[FCFE_KE]], FCD[#HEADERS], 0)),"")} -> 7.255943 | H24: 0.1 | I24: =G24*(1-H24) -> 6.5303487 | J24: =IFERROR(1-(K24/G24),"") -> 0.057324463 | K24: =IFERROR(__xludf.DUMMYFUNCTION("(GOOGLEFINANCE(""BVMF:"" & B24))"),6.84) -> 6.84 | L24: {=IFERROR(INDEX(FCD[], MATCH(B24, FCD[TICKER], 0), MATCH(FCD[[#HEADERS],[TIR]], FCD[#HEADERS], 0)),"")} -> 0.13281138
A25: 46 | B25: CMIG4 | C25: =IFERROR((F25/$B$9), 0) -> 0.031668549 | D25: 10 | E25: =(D25/SUM(Ações_Nacionais[Nota]))*$D$3 -> 0.040909091 | F25: =A25*K25 -> 519.8 | G25: {=IFERROR(INDEX(FCD[], MATCH(B25, FCD[TICKER], 0), MATCH(FCD[[#HEADERS],[FCFE_KE]], FCD[#HEADERS], 0)),"")} -> 11.727333 | H25: 0.13 | I25: =G25*(1-H25) -> 10.20278 | J25: =IFERROR(1-(K25/G25),"") -> 0.036439061 | K25: =IFERROR(__xludf.DUMMYFUNCTION("(GOOGLEFINANCE(""BVMF:"" & B25))"),11.3) -> 11.3 | L25: {=IFERROR(INDEX(FCD[], MATCH(B25, FCD[TICKER], 0), MATCH(FCD[[#HEADERS],[TIR]], FCD[#HEADERS], 0)),"")} -> 0.075215283
A26: 17 | B26: ITUB4 | C26: =IFERROR((F26/$B$9), 0) -> 0.043272227 | D26: 10 | E26: =(D26/SUM(Ações_Nacionais[Nota]))*$D$3 -> 0.040909091 | F26: =A26*K26 -> 710.26 | G26: {=IFERROR(INDEX(FCD[], MATCH("ITUB3", FCD[TICKER], 0), MATCH(FCD[[#HEADERS],[FCFE_KE]], FCD[#HEADERS], 0)),"")} -> 42.940631 | H26: 0.15 | I26: =G26*(1-H26) -> 36.499536 | J26: =IFERROR(1-(K26/G26),"") -> 0.027028733 | K26: =IFERROR(__xludf.DUMMYFUNCTION("(GOOGLEFINANCE(""BVMF:"" & B26))"),41.78) -> 41.78 | L26: {=IFERROR(INDEX(FCD[], MATCH("ITUB3", FCD[TICKER], 0), MATCH(FCD[[#HEADERS],[TIR]], FCD[#HEADERS], 0)),"")} -> 0.15140007
A27: 35 | B27: BBSE3 | C27: =IFERROR((F27/$B$9), 0) -> 0.087277375 | D27: 10 | E27: =(D27/SUM(Ações_Nacionais[Nota]))*$D$3 -> 0.040909091 | F27: =A27*K27 -> 1432.55 | G27: {=IFERROR(INDEX(FCD[], MATCH(B27, FCD[TICKER], 0), MATCH(FCD[[#HEADERS],[FCFE_KE]], FCD[#HEADERS], 0)),"")} -> 41.278339 | H27: 0.15 | I27: =G27*(1-H27) -> 35.086588 | J27: =IFERROR(1-(K27/G27),"") -> 0.008438787 | K27: =IFERROR(__xludf.DUMMYFUNCTION("(GOOGLEFINANCE(""BVMF:"" & B27))"),40.93) -> 40.93 | L27: {=IFERROR(INDEX(FCD[], MATCH(B27, FCD[TICKER], 0), MATCH(FCD[[#HEADERS],[TIR]], FCD[#HEADERS], 0)),"")} -> 0.16419505
A28: 13 | B28: PETR4 | C28: =IFERROR((F28/$B$9), 0) -> 0.038705936 | D28: 10 | E28: =(D28/SUM(Ações_Nacionais[Nota]))*$D$3 -> 0.040909091 | F28: =A28*K28 -> 635.31 | G28: {=IFERROR(INDEX(FCD[], MATCH(B28, FCD[TICKER], 0), MATCH(FCD[[#HEADERS],[FCFE_KE]], FCD[#HEADERS], 0)),"")} -> 45.587826 | H28: 0.2 | I28: =G28*(1-H28) -> 36.470261 | J28: =IFERROR(1-(K28/G28),"") -> -0.07199671 | K28: =IFERROR(__xludf.DUMMYFUNCTION("(GOOGLEFINANCE(""BVMF:"" & B28))"),48.87) -> 48.87 | L28: {=IFERROR(INDEX(FCD[], MATCH(B28, FCD[TICKER], 0), MATCH(FCD[[#HEADERS],[TIR]], FCD[#HEADERS], 0)),"")} -> 0.12034905
A29: 1 | B29: ITUB3 | C29: =IFERROR((F29/$B$9), 0) -> 0.0028006987 | D29: 10 | E29: =(D29/SUM(Ações_Nacionais[Nota]))*$D$3 -> 0.040909091 | F29: =A29*K29 -> 45.97 | G29: {=IFERROR(INDEX(FCD[], MATCH(B29, FCD[TICKER], 0), MATCH(FCD[[#HEADERS],[FCFE_KE]], FCD[#HEADERS], 0)),"")} -> 42.940631 | H29: 0.15 | I29: =G29*(1-H29) -> 36.499536 | J29: =IFERROR(1-(K29/G29),"") -> -0.070547849 | K29: =IFERROR(__xludf.DUMMYFUNCTION("(GOOGLEFINANCE(""BVMF:"" & B29))"),45.97) -> 45.97 | L29: {=IFERROR(INDEX(FCD[], MATCH(B29, FCD[TICKER], 0), MATCH(FCD[[#HEADERS],[TIR]], FCD[#HEADERS], 0)),"")} -> 0.15140007
A30: 1 | B30: ISAE4 | C30: =IFERROR((F30/$B$9), 0) -> 0.0016888268 | D30: 0 | E30: =(D30/SUM(Ações_Nacionais[Nota]))*$D$3 -> 0 | F30: =A30*K30 -> 27.72 | G30: {=IFERROR(INDEX(FCD[], MATCH(B30, FCD[TICKER], 0), MATCH(FCD[[#HEADERS],[FCFE_KE]], FCD[#HEADERS], 0)),"")} -> 24.700599 | H30: 0.1 | I30: =G30*(1-H30) -> 22.230539 | J30: =IFERROR(1-(K30/G30),"") -> -0.12223999 | K30: =IFERROR(__xludf.DUMMYFUNCTION("(GOOGLEFINANCE(""BVMF:"" & B30))"),27.72) -> 27.72 | L30: {=IFERROR(INDEX(FCD[], MATCH(B30, FCD[TICKER], 0), MATCH(FCD[[#HEADERS],[TIR]], FCD[#HEADERS], 0)),"")} -> 0.017886036
A31: 1 | B31: WEGE3 | C31: =IFERROR((F31/$B$9), 0) -> 0.0031577162 | D31: 10 | E31: =(D31/SUM(Ações_Nacionais[Nota]))*$D$3 -> 0.040909091 | F31: =A31*K31 -> 51.83 | G31: {=IFERROR(INDEX(FCD[], MATCH(B31, FCD[TICKER], 0), MATCH(FCD[[#HEADERS],[FCFE_KE]], FCD[#HEADERS], 0)),"")} -> 42.568654 | H31: 0.15 | I31: =G31*(1-H31) -> 36.183356 | J31: =IFERROR(1-(K31/G31),"") -> -0.21756256 | K31: =IFERROR(__xludf.DUMMYFUNCTION("(GOOGLEFINANCE(""BVMF:"" & B31))"),51.83) -> 51.83 | L31: {=IFERROR(INDEX(FCD[], MATCH(B31, FCD[TICKER], 0), MATCH(FCD[[#HEADERS],[TIR]], FCD[#HEADERS], 0)),"")} -> 0.12833071
A32: 18 | B32: TAEE11 | C32: =IFERROR((F32/$B$9), 0) -> 0.044995171 | D32: 10 | E32: =(D32/SUM(Ações_Nacionais[Nota]))*$D$3 -> 0.040909091 | F32: =A32*K32 -> 738.54 | G32: {=IFERROR(INDEX(FCD[], MATCH(B32, FCD[TICKER], 0), MATCH(FCD[[#HEADERS],[FCFE_KE]], FCD[#HEADERS], 0)),"")} -> 32.731441 | H32: 0.1 | I32: =G32*(1-H32) -> 29.458297 | J32: =IFERROR(1-(K32/G32),"") -> -0.2535348 | K32: =IFERROR(__xludf.DUMMYFUNCTION("(GOOGLEFINANCE(""BVMF:"" & B32))"),41.03) -> 41.03 | L32: {=IFERROR(INDEX(FCD[], MATCH(B32, FCD[TICKER], 0), MATCH(FCD[[#HEADERS],[TIR]], FCD[#HEADERS], 0)),"")} -> -0.0017091351
A33: 17 | B33: BRBI11 | C33: =IFERROR((F33/$B$9), 0) -> 0.014758957 | D33: 0 | E33: =(D33/SUM(Ações_Nacionais[Nota]))*$D$3 -> 0 | F33: =A33*K33 -> 242.25 | G33: {=IFERROR(INDEX(FCD[], MATCH(B33, FCD[TICKER], 0), MATCH(FCD[[#HEADERS],[FCFE_KE]], FCD[#HEADERS], 0)),"")} | H33: 0.2 | I33: =G33*(1-H33) -> 0 | K33: =IFERROR(__xludf.DUMMYFUNCTION("(GOOGLEFINANCE(""BVMF:"" & B33))"),14.25) -> 14.25 | L33: {=IFERROR(INDEX(FCD[], MATCH(B33, FCD[TICKER], 0), MATCH(FCD[[#HEADERS],[TIR]], FCD[#HEADERS], 0)),"")}
A34: 7 | B34: VALE3 | C34: =IFERROR((F34/$B$9), 0) -> 0.033226388 | D34: 10 | E34: =(D34/SUM(Ações_Nacionais[Nota]))*$D$3 -> 0.040909091 | F34: =A34*K34 -> 545.37 | G34: {=IFERROR(INDEX(FCD[], MATCH(B34, FCD[TICKER], 0), MATCH(FCD[[#HEADERS],[FCFE_KE]], FCD[#HEADERS], 0)),"")} -> 67.54718 | H34: 0.15 | I34: =G34*(1-H34) -> 57.415103 | K34: =IFERROR(__xludf.DUMMYFUNCTION("(GOOGLEFINANCE(""BVMF:"" & B34))"),77.91) -> 77.91 | L34: {=IFERROR(INDEX(FCD[], MATCH(B34, FCD[TICKER], 0), MATCH(FCD[[#HEADERS],[TIR]], FCD[#HEADERS], 0)),"")} -> 0.093102519
A51: QTD | B51: Fii | C51: Peso | D51: Nota | E51: Peso Ideal | F51: Financeiro | G51: Preço mercado | H51: P/VP | I51: VP/Cota | J51: Justo | K51: Div/12 | L51: LPC 3 anos | M51: Rend_Cota | N51: Rendimento_Total | O51: Spread | P51: IPCA | Q51: Taxa_Total | R51: P/M | S51: Financeiro_P/M
A52: 11 | B52: LVBI11 | C52: =IFERROR((F52/$B$9), 0) -> 0.065147164 | D52: 10 | E52: =(D52/SUM(Fiis[Nota]))*$D$4 -> 0.022727273 | F52: =A52*G52 -> 1069.31 | G52: =IFERROR(__xludf.DUMMYFUNCTION("GOOGLEFINANCE(B52)"),97.21) -> 97.21 | H52: =IFERROR(G52/I52,"") -> 0.80698987 | I52: =IFERROR(__xludf.DUMMYFUNCTION("IFERROR(QUERY(IMPORTRANGE(""https://docs.google.com/spreadsheets/d/1YexoNxj_9I75NcLB5j4bqKMWUJQZyOsjhfYiXJYkJNI/edit?usp=sharing"", ""Indicadores!A2:E""), ""SELECT Col2 WHERE Col1 = '""&B52 &""'"", 0), 0)"),120.46) -> 120.46 | J52: =SUM(L52/Q52) -> 93.362933 | K52: =L52/12 -> 0.75 | L52: 9 | M52: =A52*K52 -> 8.25 | N52: =IFERROR(M52*12,0) -> 99 | O52: 0.02 | P52: =$F$91 -> 0.0749 | Q52: =IFERROR((1+O52) * (1+P52)-1, 0) -> 0.096398 | R52: 104.65 | S52: =R52*A52 -> 1151.15
A53: 109 | B53: GGRC11 | C53: =IFERROR((F53/$B$9), 0) -> 0.059766922 | D53: 10 | E53: =(D53/SUM(Fiis[Nota]))*$D$4 -> 0.022727273 | F53: =A53*G53 -> 981 | G53: =IFERROR(__xludf.DUMMYFUNCTION("GOOGLEFINANCE(B53)"),9.0) -> 9 | H53: =IFERROR(G53/I53,"") -> 0.81595648 | I53: =IFERROR(__xludf.DUMMYFUNCTION("IFERROR(QUERY(IMPORTRANGE(""https://docs.google.com/spreadsheets/d/1YexoNxj_9I75NcLB5j4bqKMWUJQZyOsjhfYiXJYkJNI/edit?usp=sharing"", ""Indicadores!A2:E""), ""SELECT Col2 WHERE Col1 = '""&B53 &""'"", 0), 0)"),11.03) -> 11.03 | J53: =SUM(L53/Q53) -> 10.406107 | K53: =L53/12 -> 0.096666667 | L53: {=IFERROR(INDEX(LCP_3Anos[], MATCH(B53, LCP_3Anos[Fii], 0), MATCH(LCP_3Anos[[#HEADERS],[Media_DPA_3Anos]], LCP_3Anos[#HEADERS], 0)),"")} -> 1.16 | M53: =A53*K53 -> 10.536667 | N53: =IFERROR(M53*12,0) -> 126.44 | O53: 0.03 | P53: =$F$90 -> 0.0791 | Q53: =IFERROR((1+O53) * (1+P53)-1, 0) -> 0.111473 | R53: 10.01 | S53: =R53*A53 -> 1091.09
A54: 8 | B54: XPLG11 | C54: =IFERROR((F54/$B$9), 0) -> 0.044640591 | D54: 10 | E54: =(D54/SUM(Fiis[Nota]))*$D$4 -> 0.022727273 | F54: =A54*G54 -> 732.72 | G54: =IFERROR(__xludf.DUMMYFUNCTION("GOOGLEFINANCE(B54)"),91.59) -> 91.59 | H54: =IFERROR(G54/I54,"") -> 0.87021378 | I54: =IFERROR(__xludf.DUMMYFUNCTION("IFERROR(QUERY(IMPORTRANGE(""https://docs.google.com/spreadsheets/d/1YexoNxj_9I75NcLB5j4bqKMWUJQZyOsjhfYiXJYkJNI/edit?usp=sharing"", ""Indicadores!A2:E""), ""SELECT Col2 WHERE Col1 = '""&B54 &""'"", 0), 0)"),105.25) -> 105.25 | J54: =SUM(L54/Q54) -> 98.134816 | K54: =L54/12 -> 0.78833333 | L54: {=IFERROR(INDEX(LCP_3Anos[], MATCH(B54, LCP_3Anos[Fii], 0), MATCH(LCP_3Anos[[#HEADERS],[Media_DPA_3Anos]], LCP_3Anos[#HEADERS], 0)),"")} -> 9.46 | M54: =A54*K54 -> 6.3066667 | N54: =IFERROR(M54*12,0) -> 75.68 | O54: 0.02 | P54: =$F$91 -> 0.0749 | Q54: =IFERROR((1+O54) * (1+P54)-1, 0) -> 0.096398 | R54: 93.43 | S54: =R54*A54 -> 747.44
A55: 87 | B55: GARE11 | C55: =IFERROR((F55/$B$9), 0) -> 0.044523616 | D55: 10 | E55: =(D55/SUM(Fiis[Nota]))*$D$4 -> 0.022727273 | F55: =A55*G55 -> 730.8 | G55: =IFERROR(__xludf.DUMMYFUNCTION("GOOGLEFINANCE(B55)"),8.4) -> 8.4 | H55: =IFERROR(G55/I55,"") -> 0.90614887 | I55: =IFERROR(__xludf.DUMMYFUNCTION("IFERROR(QUERY(IMPORTRANGE(""https://docs.google.com/spreadsheets/d/1YexoNxj_9I75NcLB5j4bqKMWUJQZyOsjhfYiXJYkJNI/edit?usp=sharing"", ""Indicadores!A2:E""), ""SELECT Col2 WHERE Col1 = '""&B55 &""'"", 0), 0)"),9.27) -> 9.27 | J55: =SUM(L55/Q55) -> 8.6119509 | K55: =L55/12 -> 0.08 | L55: {=IFERROR(INDEX(LCP_3Anos[], MATCH(B55, LCP_3Anos[Fii], 0), MATCH(LCP_3Anos[[#HEADERS],[Media_DPA_3Anos]], LCP_3Anos[#HEADERS], 0)),"")} -> 0.96 | M55: =A55*K55 -> 6.96 | N55: =IFERROR(M55*12,0) -> 83.52 | O55: 0.03 | P55: =$F$90 -> 0.0791 | Q55: =IFERROR((1+O55) * (1+P55)-1, 0) -> 0.111473 | R55: 8.54 | S55: =R55*A55 -> 742.98
A56: 6 | B56: PMLL11 | C56: =IFERROR((F56/$B$9), 0) -> 0.037534358 | D56: 10 | E56: =(D56/SUM(Fiis[Nota]))*$D$4 -> 0.022727273 | F56: =A56*G56 -> 616.08 | G56: =IFERROR(__xludf.DUMMYFUNCTION("GOOGLEFINANCE(B56)"),102.68) -> 102.68 | H56: =IFERROR(G56/I56,"") -> 0.88008914 | I56: =IFERROR(__xludf.DUMMYFUNCTION("IFERROR(QUERY(IMPORTRANGE(""https://docs.google.com/spreadsheets/d/1YexoNxj_9I75NcLB5j4bqKMWUJQZyOsjhfYiXJYkJNI/edit?usp=sharing"", ""Indicadores!A2:E""), ""SELECT Col2 WHERE Col1 = '""&B56 &""'"", 0), 0)"),116.67) -> 116.67 | J56: =SUM(L56/Q56) -> 103.49454 | K56: =L56/12 -> 0.83138889 | L56: {=IFERROR(INDEX(LCP_3Anos[], MATCH(B56, LCP_3Anos[Fii], 0), MATCH(LCP_3Anos[[#HEADERS],[Media_DPA_3Anos]], LCP_3Anos[#HEADERS], 0)),"")} -> 9.9766667 | M56: =A56*K56 -> 4.9883333 | N56: =IFERROR(M56*12,0) -> 59.86 | O56: 0.02 | P56: =$F$91 -> 0.0749 | Q56: =IFERROR((1+O56) * (1+P56)-1, 0) -> 0.096398 | R56: 99.15 | S56: =R56*A56 -> 594.9
A57: 4 | B57: BTLG11 | C57: =IFERROR((F57/$B$9), 0) -> 0.024425846 | D57: 10 | E57: =(D57/SUM(Fiis[Nota]))*$D$4 -> 0.022727273 | F57: =A57*G57 -> 400.92 | G57: =IFERROR(__xludf.DUMMYFUNCTION("GOOGLEFINANCE(B57)"),100.23) -> 100.23 | H57: =IFERROR(G57/I57,"") -> 0.97880859 | I57: =IFERROR(__xludf.DUMMYFUNCTION("IFERROR(QUERY(IMPORTRANGE(""https://docs.google.com/spreadsheets/d/1YexoNxj_9I75NcLB5j4bqKMWUJQZyOsjhfYiXJYkJNI/edit?usp=sharing"", ""Indicadores!A2:E""), ""SELECT Col2 WHERE Col1 = '""&B57 &""'"", 0), 0)"),102.4) -> 102.4 | J57: =SUM(L57/Q57) -> 101.65873 | K57: =L57/12 -> 0.77111111 | L57: {=IFERROR(INDEX(LCP_3Anos[], MATCH(B57, LCP_3Anos[Fii], 0), MATCH(LCP_3Anos[[#HEADERS],[Media_DPA_3Anos]], LCP_3Anos[#HEADERS], 0)),"")} -> 9.2533333 | M57: =A57*K57 -> 3.0844444 | N57: =IFERROR(M57*12,0) -> 37.013333 | O57: 0.015 | P57: =$F$91 -> 0.0749 | Q57: =IFERROR((1+O57) * (1+P57)-1, 0) -> 0.0910235 | R57: 97.58 | S57: =R57*A57 -> 390.32
A58: 20 | B58: HGBS11 | C58: =IFERROR((F58/$B$9), 0) -> 0.022761389 | D58: 10 | E58: =(D58/SUM(Fiis[Nota]))*$D$4 -> 0.022727273 | F58: =A58*G58 -> 373.6 | G58: =IFERROR(__xludf.DUMMYFUNCTION("GOOGLEFINANCE(B58)"),18.68) -> 18.68 | H58: =IFERROR(G58/I58,"") -> 0.91658489 | I58: =IFERROR(__xludf.DUMMYFUNCTION("IFERROR(QUERY(IMPORTRANGE(""https://docs.google.com/spreadsheets/d/1YexoNxj_9I75NcLB5j4bqKMWUJQZyOsjhfYiXJYkJNI/edit?usp=sharing"", ""Indicadores!A2:E""), ""SELECT Col2 WHERE Col1 = '""&B58 &""'"", 0), 0)"),20.38) -> 20.38 | J58: =SUM(L58/Q58) -> 19.295006 | K58: =L58/12 -> 0.155 | L58: {=IFERROR(INDEX(LCP_3Anos[], MATCH(B58, LCP_3Anos[Fii], 0), MATCH(LCP_3Anos[[#HEADERS],[Media_DPA_3Anos]], LCP_3Anos[#HEADERS], 0)),"")} -> 1.86 | M58: =A58*K58 -> 3.1 | N58: =IFERROR(M58*12,0) -> 37.2 | O58: 0.02 | P58: =$F$91 -> 0.0749 | Q58: =IFERROR((1+O58) * (1+P58)-1, 0) -> 0.096398 | R58: 18.42 | S58: =R58*A58 -> 368.4
A59: 3 | B59: BRCO11 | C59: =IFERROR((F59/$B$9), 0) -> 0.020132497 | D59: 10 | E59: =(D59/SUM(Fiis[Nota]))*$D$4 -> 0.022727273 | F59: =A59*G59 -> 330.45 | G59: =IFERROR(__xludf.DUMMYFUNCTION("GOOGLEFINANCE(B59)"),110.15) -> 110.15 | H59: =IFERROR(G59/I59,"") -> 0.95186657 | I59: =IFERROR(__xludf.DUMMYFUNCTION("IFERROR(QUERY(IMPORTRANGE(""https://docs.google.com/spreadsheets/d/1YexoNxj_9I75NcLB5j4bqKMWUJQZyOsjhfYiXJYkJNI/edit?usp=sharing"", ""Indicadores!A2:E""), ""SELECT Col2 WHERE Col1 = '""&B59 &""'"", 0), 0)"),115.72) -> 115.72 | J59: =SUM(L59/Q59) -> 112.20546 | K59: =L59/12 -> 0.85111111 | L59: {=IFERROR(INDEX(LCP_3Anos[], MATCH(B59, LCP_3Anos[Fii], 0), MATCH(LCP_3Anos[[#HEADERS],[Media_DPA_3Anos]], LCP_3Anos[#HEADERS], 0)),"")} -> 10.213333 | M59: =A59*K59 -> 2.5533333 | N59: =IFERROR(M59*12,0) -> 30.64 | O59: 0.015 | P59: =$F$91 -> 0.0749 | Q59: =IFERROR((1+O59) * (1+P59)-1, 0) -> 0.0910235 | R59: 100.45 | S59: =R59*A59 -> 301.35
A60: 2 | B60: HGRU11 | C60: =IFERROR((F60/$B$9), 0) -> 0.013930993 | D60: 10 | E60: =(D60/SUM(Fiis[Nota]))*$D$4 -> 0.022727273 | F60: =A60*G60 -> 228.66 | G60: =IFERROR(__xludf.DUMMYFUNCTION("GOOGLEFINANCE(B60)"),114.33) -> 114.33 | H60: =IFERROR(G60/I60,"") -> 0.88696664 | I60: =IFERROR(__xludf.DUMMYFUNCTION("IFERROR(QUERY(IMPORTRANGE(""https://docs.google.com/spreadsheets/d/1YexoNxj_9I75NcLB5j4bqKMWUJQZyOsjhfYiXJYkJNI/edit?usp=sharing"", ""Indicadores!A2:E""), ""SELECT Col2 WHERE Col1 = '""&B60 &""'"", 0), 0)"),128.9) -> 128.9 | J60: =SUM(L60/Q60) -> 118.25971 | K60: =L60/12 -> 0.95 | L60: {=IFERROR(INDEX(LCP_3Anos[], MATCH(B60, LCP_3Anos[Fii], 0), MATCH(LCP_3Anos[[#HEADERS],[Media_DPA_3Anos]], LCP_3Anos[#HEADERS], 0)),"")} -> 11.4 | M60: =A60*K60 -> 1.9 | N60: =IFERROR(M60*12,0) -> 22.8 | O60: 0.02 | P60: =$F$91 -> 0.0749 | Q60: =IFERROR((1+O60) * (1+P60)-1, 0) -> 0.096398 | R60: 120 | S60: =R60*A60 -> 240
A61: 21 | B61: MXRF11 | C61: =IFERROR((F61/$B$9), 0) -> 0.011732229 | D61: 10 | E61: =(D61/SUM(Fiis[Nota]))*$D$4 -> 0.022727273 | F61: =A61*G61 -> 192.57 | G61: =IFERROR(__xludf.DUMMYFUNCTION("GOOGLEFINANCE(B61)"),9.17) -> 9.17 | H61: =IFERROR(G61/I61,"") -> 0.97865528 | I61: =IFERROR(__xludf.DUMMYFUNCTION("IFERROR(QUERY(IMPORTRANGE(""https://docs.google.com/spreadsheets/d/1YexoNxj_9I75NcLB5j4bqKMWUJQZyOsjhfYiXJYkJNI/edit?usp=sharing"", ""Indicadores!A2:E""), ""SELECT Col2 WHERE Col1 = '""&B61 &""'"", 0), 0)"),9.37) -> 9.37 | J61: =SUM(L61/Q61) -> 9.2330274 | K61: =L61/12 -> 0.0975 | L61: {=IFERROR(INDEX(LCP_3Anos[], MATCH(B61, LCP_3Anos[Fii], 0), MATCH(LCP_3Anos[[#HEADERS],[Media_DPA_3Anos]], LCP_3Anos[#HEADERS], 0)),"")} -> 1.17 | M61: =A61*K61 -> 2.0475 | N61: =IFERROR(M61*12,0) -> 24.57 | O61: 0.045 | P61: =$F$89 -> 0.0782 | Q61: =IFERROR((1+O61) * (1+P61)-1, 0) -> 0.126719 | R61: 9.25 | S61: =R61*A61 -> 194.25
A62: 0 | B62: PCIP11 | C62: =IFERROR((F62/$B$9), 0) -> 0 | D62: 0 | E62: =(D62/SUM(Fiis[Nota]))*$D$4 -> 0 | F62: =A62*G62 -> 0 | G62: =IFERROR(__xludf.DUMMYFUNCTION("GOOGLEFINANCE(B62)"),73.79) -> 73.79 | H62: =IFERROR(G62/I62,"") -> 0.79446598 | I62: =IFERROR(__xludf.DUMMYFUNCTION("IFERROR(QUERY(IMPORTRANGE(""https://docs.google.com/spreadsheets/d/1YexoNxj_9I75NcLB5j4bqKMWUJQZyOsjhfYiXJYkJNI/edit?usp=sharing"", ""Indicadores!A2:E""), ""SELECT Col2 WHERE Col1 = '""&B62 &""'"", 0), 0)"),92.88) -> 92.88 | J62: =SUM(L62/Q62) -> 75.758174 | K62: =L62/12 -> 0.8 | L62: {=IFERROR(INDEX(LCP_3Anos[], MATCH(B62, LCP_3Anos[Fii], 0), MATCH(LCP_3Anos[[#HEADERS],[Media_DPA_3Anos]], LCP_3Anos[#HEADERS], 0)),"")} -> 9.6 | M62: =A62*K62 -> 0 | N62: =IFERROR(M62*12,0) -> 0 | O62: 0.045 | P62: =$F$89 -> 0.0782 | Q62: =IFERROR((1+O62) * (1+P62)-1, 0) -> 0.126719 | R62: 0 | S62: =R62*A62 -> 0
A63: 0 | B63: HGLG11 | C63: =IFERROR((F63/$B$9), 0) -> 0 | D63: 0 | E63: =(D63/SUM(Fiis[Nota]))*$D$4 -> 0 | F63: =A63*G63 -> 0 | G63: =IFERROR(__xludf.DUMMYFUNCTION("GOOGLEFINANCE(B63)"),146.45) -> 146.45 | H63: =IFERROR(G63/I63,"") -> 0.88222892 | I63: =IFERROR(__xludf.DUMMYFUNCTION("IFERROR(QUERY(IMPORTRANGE(""https://docs.google.com/spreadsheets/d/1YexoNxj_9I75NcLB5j4bqKMWUJQZyOsjhfYiXJYkJNI/edit?usp=sharing"", ""Indicadores!A2:E""), ""SELECT Col2 WHERE Col1 = '""&B63 &""'"", 0), 0)"),166.0) -> 166 | J63: =SUM(L63/Q63) -> 154.11739 | K63: =L63/12 -> 1.1 | L63: {=IFERROR(INDEX(LCP_3Anos[], MATCH(B63, LCP_3Anos[Fii], 0), MATCH(LCP_3Anos[[#HEADERS],[Media_DPA_3Anos]], LCP_3Anos[#HEADERS], 0)),"")} -> 13.2 | M63: =A63*K63 -> 0 | N63: =IFERROR(M63*12,0) -> 0 | O63: 0.01 | P63: =$F$91 -> 0.0749 | Q63: =IFERROR((1+O63) * (1+P63)-1, 0) -> 0.085649 | R63: 0 | S63: =R63*A63 -> 0
A64: 0 | B64: KNRI11 | C64: =IFERROR((F64/$B$9), 0) -> 0 | D64: 10 | E64: =(D64/SUM(Fiis[Nota]))*$D$4 -> 0.022727273 | F64: =A64*G64 -> 0 | G64: =IFERROR(__xludf.DUMMYFUNCTION("GOOGLEFINANCE(B64)"),157.0) -> 157 | H64: =IFERROR(G64/I64,"") -> 0.96230463 | I64: =IFERROR(__xludf.DUMMYFUNCTION("IFERROR(QUERY(IMPORTRANGE(""https://docs.google.com/spreadsheets/d/1YexoNxj_9I75NcLB5j4bqKMWUJQZyOsjhfYiXJYkJNI/edit?usp=sharing"", ""Indicadores!A2:E""), ""SELECT Col2 WHERE Col1 = '""&B64 &""'"", 0), 0)"),163.15) -> 163.15 | J64: =SUM(L64/Q64) -> 152.06231 | K64: =L64/12 -> 1.0104167 | L64: {=IFERROR(INDEX(LCP_3Anos[], MATCH(B64, LCP_3Anos[Fii], 0), MATCH(LCP_3Anos[[#HEADERS],[Media_DPA_3Anos]], LCP_3Anos[#HEADERS], 0)),"")} -> 12.125 | M64: =A64*K64 -> 0 | N64: =IFERROR(M64*12,0) -> 0 | O64: 0.0045 | P64: =$F$91 -> 0.0749 | Q64: =IFERROR((1+O64) * (1+P64)-1, 0) -> 0.07973705 | R64: 0 | S64: =R64*A64 -> 0
A82: Tipo | B82: qtd | C82: Financeiro | D82: % Peso | E82: CDI_Bruto | F82: CDI_Liquido | G82: Retorno(%) | H82: Data da Aplicação | I82: Hoje | J82: Dia_Corridos | K82: Redimento | L82: CDI Diário (%)
A83: CDB | B83: 1032.02 | C83: =SUM(B83,K83) -> 1033.4559 | D83: =IFERROR(SUM(C83/$B$9),0) -> 0.06296277 | E83: 1.15 | F83: =E83 * (1 - 0.225) -> 0.89125 | G83: =F83*Indicadores!$J$3 -> 0.12388375 | H83: 46273 | I83: =TODAY() -> 46275 | J83: =NETWORKDAYS(H83, I83, FERIADOS!A:A) -> 3 | K83: =(B83 * ((1 + L83) ^ J83))-B83 -> 1.4358783 | L83: =((1 + G83) ^ (1/252)) - 1 -> 0.00046356107
A84: LFTB11 | B84: 0 | C84: =SUM(B84,K84) -> 0 | D84: =IFERROR(SUM(C84/$B$9),0) -> 0 | E84: 1.09 | F84: =E84 * (1 - 0.225) -> 0.84475 | G84: =F84*Indicadores!$J$3 -> 0.11742025 | H84: 46267 | I84: =TODAY() -> 46275 | J84: =NETWORKDAYS(H84, I84, FERIADOS!A:A) -> 6 | K84: =(B84 * ((1 + L84) ^ J84))-B84 -> 0 | L84: =((1 + G84) ^ (1/252)) - 1 -> 0.00044066326
A85: Tesouro Selic | B85: 0.02 | C85: =B85*Indicadores!$E$7 -> 395.43 | D85: =IFERROR(SUM(C85/$B$9),0) -> 0.02409137 | J85: =NETWORKDAYS(H85, I85, FERIADOS!A:A) -> 0
A88: Tipo | B88: qtd | C88: preço | D88: Financeiro | E88: % Peso | F88: Rent_Bruta | G88: Rent_Liq | H88: Retorno(%)
A89: =Indicadores!A3 -> Tesouro IPCA+ 2029 | E89: =IFERROR(SUM(D89/$B$9),0) -> 0 | F89: =Indicadores!D3 -> 0.0782 | G89: =F89 * (1 - 0.15) -> 0.06647 | H89: =IFERROR((1+Indicadores!$J$4) * (1+G89)-1, 0) -> 0.11385352
A90: =Indicadores!A4 -> Tesouro IPCA+ 2032 | C90: =Indicadores!C4 -> 3041.71 | D90: =B90*C90 -> 0 | E90: =IFERROR(SUM(D90/$B$9),0) -> 0 | F90: =Indicadores!D4 -> 0.0791 | G90: =F90 * (1 - 0.15) -> 0.067235 | H90: =IFERROR((1+Indicadores!$J$4) * (1+G90)-1, 0) -> 0.11465251
A91: =Indicadores!A5 -> Tesouro IPCA+ 2040 | C91: =Indicadores!C5 -> 1767.6 | D91: =B91*C91 -> 0 | E91: =IFERROR(SUM(D91/$B$9),0) -> 0 | F91: =Indicadores!D5 -> 0.0749 | G91: =F91 * (1 - 0.15) -> 0.063665 | H91: =IFERROR((1+Indicadores!$J$4) * (1+G91)-1, 0) -> 0.1109239
A92: =Indicadores!A6 -> Tesouro Renda+ Aposentadoria Extra 2065 | B92: 1.79 | C92: =Indicadores!C6 -> 181 | D92: =B92*Indicadores!E6 -> 307.7726 | E92: =IFERROR(SUM(D92/$B$9),0) -> 0.018750888 | F92: =Indicadores!D6 -> 0.0733 | G92: =F92 * (1 - 0.15) -> 0.062305 | H92: =IFERROR((1+Indicadores!$J$4) * (1+G92)-1, 0) -> 0.10950347
A96: Etf | B96: qtd | C96: Peso | D96: financeiro | E96: financeiro ($) | F96: preço | G96: Dolar/REAL
A97: DIA | B97: 0.04420291 | C97: =IFERROR(SUM(D97/$B$9),0) -> 0.0071923557 | D97: =(B97*F97)*G97 -> 118.05361 | E97: =B97*F97 -> 23.069057 | F97: =IFERROR(__xludf.DUMMYFUNCTION("GOOGLEFINANCE(A97)"),521.89) -> 521.89 | G97: =IFERROR(__xludf.DUMMYFUNCTION("GOOGLEFINANCE(""CURRENCY:USD/BRL"")"),5.11740085) -> 5.1174009
A98: XBOX | B98: 3.9044345 | C98: =IFERROR(SUM(D98/$B$9),0) -> 0.12281392 | D98: =(B98*F98)*G98 -> 2015.8383 | E98: =B98*F98 -> 393.91839 | F98: =IFERROR(__xludf.DUMMYFUNCTION("GOOGLEFINANCE(A98)"),100.89) -> 100.89 | G98: =IFERROR(__xludf.DUMMYFUNCTION("GOOGLEFINANCE(""CURRENCY:USD/BRL"")"),5.11740085) -> 5.1174009
A99: SPXB11 | B99: 11 | C99: =IFERROR(SUM(D99/$B$9),0) -> 0.0115242 | D99: =B99*F99 -> 189.15547 | F99: =IFERROR(__xludf.DUMMYFUNCTION("GOOGLEFINANCE(""IVVB11"")* 0.039040892927697"),17.19595169893342) -> 17.195952 | G99: =IFERROR(__xludf.DUMMYFUNCTION("GOOGLEFINANCE(""CURRENCY:USD/BRL"")"),5.11740085) -> 5.1174009
A103: Cripto | B103: qtd | C103: Peso | D103: financeiro | E103: financeiro ($) | F103: preço | G103: USD | H103: Investido R$ | I103: % investido | J103: Preço medio | K103: Perda
A104: BTC | B104: 0.00108981 | C104: =IFERROR(SUM(D104/B9),0) -> 0.026248955 | D104: =B104*F104 -> 430.84408 | E104: =B104*G104 -> 84.191975 | F104: =IFERROR(__xludf.DUMMYFUNCTION("GOOGLEFINANCE(""CURRENCY:BTCBRL"") "),395338.71290000004) -> 395338.71 | G104: =IFERROR(__xludf.DUMMYFUNCTION("GOOGLEFINANCE(""CURRENCY:BTCUSD"") "),77253.81) -> 77253.81 | H104: =B104*J104 -> 572.05281 | I104: =IFERROR(SUM((B104*J104/B9),0),"") -> 0.034852024 | J104: 524910.59 | K104: =H104-D104 -> 141.20873
A105: USDT | B105: 0.54351 | C105: =IFERROR(SUM(D105/B9),0) -> 0.00016945284 | D105: =B105*F105 -> 2.7813585 | F105: =IFERROR(__xludf.DUMMYFUNCTION("GOOGLEFINANCE(""CURRENCY:USDTBRL"") "),5.11740085) -> 5.1174009

Sheet Eficiencia
B2: Perfomance | C2: Y Mensal Consolidado | D2: YMC_Media | E2: Y_Anual_FIIs | F2: Y Mensal FIIs | G2: YMF_Media | H2: % Ganho Capital
B3: =IFERROR(((financeiros[Valor Bruto]-(financeiros[Valor Aplicado]-financeiros[Total Proventos]))/financeiros[Valor Bruto]),0) -> 0.11724073 | C3: =IFERROR((J19/(HOME!B3+HOME!B4)),0) -> 0.011623742 | D3: 0.0045 | E3: =financeiros[FIIs_Provento]/HOME!B4 -> 0.10550066 | F3: =IFERROR(SUMPRODUCT(Fiis[QTD],Fiis[Div/12])/SUMPRODUCT(Fiis[QTD],Fiis[P/M]),"") -> 0.0085413895 | G3: 0.007 | H3: =IFERROR(( financeiros[Ganho Capital]/financeiros[Valor Aplicado]),0) -> 0.030129971
B6: Total Proventos | C6: FIIs_Provento | D6: Valor Aplicado | E6: Valor Bruto | F6: Ganho Capital
B7: =SUM(B13:M13)+ SUM(B16:M16) + SUM(B19:M19) -> 1444.28 | C7: =IFERROR(SUM(Fiis[Rendimento_Total]),"") -> 596.72333 | D7: 15933.68 | E7: =HOME!B9 -> 16413.761 | F7: =E7-D7 -> 480.08132
B11: Proventos pagos
B12: 45315 | C12: 45346 | D12: 45375 | E12: 45406 | F12: 45436 | G12: 45467 | H12: 45497 | I12: 45528 | J12: 45559 | K12: 45589 | L12: 45620 | M12: 45650
B13: 0 | C13: 12.57 | D13: 13.69 | E13: 0 | F13: 11.33 | G13: 3.58 | H13: 9.34 | I13: 15.3 | J13: 10.42 | K13: 32.53 | L13: 5.97 | M13: 5.9
B14: =IFERROR(SUM((B16/B13)-1),0) -> 0 | C14: =IFERROR(SUM((C16/C13)-1),0) -> -0.048528242 | D14: =IFERROR(SUM((D16/D13)-1),0) -> 3.3959094 | E14: =IFERROR(SUM((E16/E13)-1),0) -> 0 | F14: =IFERROR(SUM((F16/F13)-1),0) -> 3.2436011 | G14: =IFERROR(SUM((G16/G13)-1),0) -> 14.061453 | H14: =IFERROR(SUM((H16/H13)-1),0) -> 3.4421842 | I14: =IFERROR(SUM((I16/I13)-1),0) -> 4.8810458 | ... M14: =IFERROR(SUM((M16/M13)-1),0) -> 14.625424
B15: 45682 | C15: 45713 | D15: 45741 | E15: 45772 | F15: 45802 | G15: 45833 | H15: 45863 | I15: 45894 | J15: 45925 | K15: 45955 | L15: 45986 | M15: 46016
B16: 40.51 | C16: 11.96 | D16: 60.18 | E16: 28.25 | F16: 48.08 | G16: 53.92 | H16: 41.49 | I16: 89.98 | J16: 53.99 | K16: 42.11 | L16: 74.29 | M16: 92.19
B17: =IFERROR(SUM((B19/B16)-1),0) -> 0.6669958 | C17: =IFERROR(SUM((C19/C16)-1),0) -> 2.7533445 | D17: =IFERROR(SUM((D19/D16)-1),0) -> 1.1889332 | E17: =IFERROR(SUM((E19/E16)-1),0) -> 0.6300885 | F17: =IFERROR(SUM((F19/F16)-1),0) -> 0.35170549 | G17: =IFERROR(SUM((G19/G16)-1),0) -> 0.28876113 | H17: =IFERROR(SUM((H19/H16)-1),0) -> 0.12557243 | I17: =IFERROR(SUM((I19/I16)-1),0) -> -0.14692154 | ... M17: =IFERROR(SUM((M19/M16)-1),0) -> -1
B18: 46023 | C18: 46054 | D18: 46082 | E18: 46113 | F18: 46143 | G18: 46174 | H18: 46204 | I18: 46235 | J18: 46266 | K18: 46296 | L18: 46327 | M18: 46357
B19: 67.53 | C19: 44.89 | D19: 131.73 | E19: 46.05 | F19: 64.99 | G19: 69.49 | H19: 46.7 | I19: 76.76 | J19: 138.56 | K19: 0 | L19: 0 | M19: 0
B40: Rentabilidade Mensal da Carteira FIIs: | D40: =IFERROR(SUMPRODUCT(Fiis[QTD],Fiis[Div/12])/SUMPRODUCT(Fiis[QTD],Fiis[P/M]),"") -> 0.0085413895 | J40: Feito | M40: Feito | P40: Feito | S40: Feito | V40: Feito | Y40: Feito | AB40: Feito | AE40: Feito | AH40: Atual | AK40: Não | AN40: Não | AQ40: Não
B41: Rentabilidade Anualizado da Carteira FIIs: | D41: =IF(D40="","",D40*12) -> 0.10249667 | G41: Rentabilidade Acumulado da Carteira FIIs: | I41: =IFERROR((SUM(K58:AS58)+SUMPRODUCT(D43:D52,F43:F52))/SUMPRODUCT(D43:D52,E43:E52)-1,"") -> 0.035423549 | J41: Jan | M41: Fev | P41: Mar | S41: Abr | V41: Mai | Y41: Jun | AB41: Jul | AE41: Ago | AH41: Set | AK41: Out | AN41: Nov | AQ41: Dez
A42: Fundo | B42: Segmento | C42: Classificação de Risco | D42: Qtidade Cotas Atual | E42: Preço Médio | F42: Cotação Atual | G42: Yield on Cost (YoC) | H42: Valorização | I42: Rentabilidade | J42: Qtidade de Cotas no Mês | K42: Dividendos (por cota) | L42: Proventos Recebidos | M42: Qtidade de Cotas no Mês | N42: Dividendos (por cota) | O42: Proventos Recebidos | P42: Qtidade de Cotas no Mês | Q42: Dividendos (por cota) | R42: Proventos Recebidos | S42: Qtidade de Cotas no Mês | T42: Dividendos (por cota) | U42: Proventos Recebidos | V42: Qtidade de Cotas no Mês | W42: Dividendos (por cota) | X42: Proventos Recebidos | Y42: Qtidade de Cotas no Mês | Z42: Dividendos (por cota) | AA42: Proventos Recebidos | AB42: Qtidade de Cotas no Mês | AC42: Dividendos (por cota) | AD42: Proventos Recebidos | AE42: Qtidade de Cotas no Mês | AF42: Dividendos (por cota) | AG42: Proventos Recebidos | AH42: Qtidade de Cotas no Mês | AI42: Dividendos (por cota) | AJ42: Proventos Recebidos | AK42: Qtidade de Cotas no Mês | AL42: Dividendos (por cota) | AM42: Proventos Recebidos | AN42: Qtidade de Cotas no Mês | AO42: Dividendos (por cota) | AP42: Proventos Recebidos | AQ42: Qtidade de Cotas no Mês | AR42: Dividendos (por cota) | AS42: Proventos Recebidos
A43: GGRC11 | B43: Logística | C43: Oportunidade | D43: {=IFERROR(INDEX(Fiis[], MATCH(A43, Fiis[Fii], 0), MATCH(Fiis[[#HEADERS],[QTD]], Fiis[#HEADERS], 0)), "")} -> 109 | E43: {=IFERROR(INDEX(Fiis[], MATCH(A43, Fiis[Fii], 0), MATCH(Fiis[[#HEADERS],[P/M]], Fiis[#HEADERS], 0)), "")} -> 10.01 | F43: =IFERROR(__xludf.DUMMYFUNCTION("IFERROR(GOOGLEFINANCE(A43),"""")"),9.0) -> 9 | G43: =IFERROR(SUMPRODUCT((MOD(COLUMN(K43:AS43)-COLUMN(K43), 3) = 0) * (K43:AS43))/SUMPRODUCT((MOD(COLUMN(K43:AS43)-COLUMN(K43), 3) = 0) * (NOT(ISBLANK(K43:AS43))))/E43*12,"") -> 0.11988012 | H43: =IFERROR(F43/E43-1,"") -> -0.1008991 | I43: =IFERROR((SUMPRODUCT((MOD(COLUMN(L43:AS43)-COLUMN(L43), 3) = 0) * (L43:AS43))+D43*F43)/(D43*E43)-1,"") -> -0.040775738 | J43: 39 | K43: =IF(J43=0,"",L43/J43) -> 0.1 | L43: 3.9 | M43: 39 | N43: =IF(M43=0,"",O43/M43) -> 0.1 | O43: 3.9 | P43: 39 | Q43: =IF(P43=0,"",R43/P43) -> 0.1 | R43: 3.9 | S43: 64 | T43: =IF(S43=0,"",U43/S43) -> 0.1 | U43: 6.4 | V43: 69,00 | W43: =IF(V43=0,"",X43/V43) -> 0.1 | X43: 6.9 | Y43: 79 | Z43: =IF(Y43=0,"",AA43/Y43) -> 0.1 | AA43: 7.9 | AB43: 109 | AC43: =IF(AB43=0,"",AD43/AB43) -> 0.1 | AD43: 10.9 | AE43: 109 | AF43: =IF(AE43=0,"",AG43/AE43) -> 0.1 | AG43: 10.9 | AH43: 109 | AI43: 0.1 | AJ43: =IF(AH43=0,"",AI43*AH43) -> 10.9 | AK43: 0 | AM43: =IF(AK43=0,"",AL43*AK43) | AN43: 0 | AP43: =IF(AN43=0,"",AO43*AN43) | AQ43: 0 | AS43: =IF(AQ43=0,"",AR43*AQ43)
A44: LVBI11 | B44: Logística | C44: Ancoragem | D44: {=IFERROR(INDEX(Fiis[], MATCH(A44, Fiis[Fii], 0), MATCH(Fiis[[#HEADERS],[QTD]], Fiis[#HEADERS], 0)), "")} -> 11 | E44: {=IFERROR(INDEX(Fiis[], MATCH(A44, Fiis[Fii], 0), MATCH(Fiis[[#HEADERS],[P/M]], Fiis[#HEADERS], 0)), "")} -> 104.65 | F44: =IFERROR(__xludf.DUMMYFUNCTION("IFERROR(GOOGLEFINANCE(A44),"""")"),97.21) -> 97.21 | G44: =IFERROR(SUMPRODUCT((MOD(COLUMN(K44:AS44)-COLUMN(K44), 3) = 0) * (K44:AS44))/SUMPRODUCT((MOD(COLUMN(K44:AS44)-COLUMN(K44), 3) = 0) * (NOT(ISBLANK(K44:AS44))))/E44*12,"") -> 0.086638 | H44: =IFERROR(F44/E44-1,"") -> -0.071094123 | I44: =IFERROR((SUMPRODUCT((MOD(COLUMN(L44:AS44)-COLUMN(L44), 3) = 0) * (L44:AS44))+D44*F44)/(D44*E44)-1,"") -> -0.02435825 | J44: 4 | K44: =IF(J44=0,"",L44/J44) -> 0.75 | L44: 3 | M44: 7 | N44: =IF(M44=0,"",O44/M44) -> 0.75 | O44: 5.25 | P44: 7 | Q44: =IF(P44=0,"",R44/P44) -> 0.75 | R44: 5.25 | S44: 7 | T44: =IF(S44=0,"",U44/S44) -> 0.75 | U44: 5.25 | V44: 7 | W44: =IF(V44=0,"",X44/V44) -> 0.75 | X44: 5.25 | Y44: 7 | Z44: =IF(Y44=0,"",AA44/Y44) -> 0.75 | AA44: 5.25 | AB44: 10 | AC44: =IF(AB44=0,"",AD44/AB44) -> 0.75 | AD44: 7.5 | AE44: 11 | AF44: =IF(AE44=0,"",AG44/AE44) -> 0.75 | AG44: 8.25 | AH44: 11 | AI44: 0.8 | AJ44: =IF(AH44=0,"",AI44*AH44) -> 8.8 | AK44: 0 | AM44: =IF(AK44=0,"",AL44*AK44) | AN44: 0 | AP44: =IF(AN44=0,"",AO44*AN44) | AQ44: 0 | AS44: =IF(AQ44=0,"",AR44*AQ44)
A45: GARE11 | B45: Renda Urbana | C45: Oportunidade | D45: {=IFERROR(INDEX(Fiis[], MATCH(A45, Fiis[Fii], 0), MATCH(Fiis[[#HEADERS],[QTD]], Fiis[#HEADERS], 0)), "")} -> 87 | E45: {=IFERROR(INDEX(Fiis[], MATCH(A45, Fiis[Fii], 0), MATCH(Fiis[[#HEADERS],[P/M]], Fiis[#HEADERS], 0)), "")} -> 8.54 | F45: =IFERROR(__xludf.DUMMYFUNCTION("IFERROR(GOOGLEFINANCE(A45),"""")"),8.4) -> 8.4 | G45: =IFERROR(SUMPRODUCT((MOD(COLUMN(K45:AS45)-COLUMN(K45), 3) = 0) * (K45:AS45))/SUMPRODUCT((MOD(COLUMN(K45:AS45)-COLUMN(K45), 3) = 0) * (NOT(ISBLANK(K45:AS45))))/E45*12,"") -> 0.11619444 | H45: =IFERROR(F45/E45-1,"") -> -0.016393443 | I45: =IFERROR((SUMPRODUCT((MOD(COLUMN(L45:AS45)-COLUMN(L45), 3) = 0) * (L45:AS45))+D45*F45)/(D45*E45)-1,"") -> 0.055546583 | J45: 39 | K45: =IF(J45=0,"",L45/J45) -> 0.083076923 | L45: 3.24 | M45: 39 | N45: =IF(M45=0,"",O45/M45) -> 0.083076923 | O45: 3.24 | P45: 59 | Q45: =IF(P45=0,"",R45/P45) -> 0.083050847 | R45: 4.9 | S45: 75 | T45: =IF(S45=0,"",U45/S45) -> 0.083066667 | U45: 6.23 | V45: 87 | W45: =IF(V45=0,"",X45/V45) -> 0.082988506 | X45: 7.22 | Y45: 87 | Z45: =IF(Y45=0,"",AA45/Y45) -> 0.082988506 | AA45: 7.22 | AB45: 87 | AC45: =IF(AB45=0,"",AD45/AB45) -> 0.082988506 | AD45: 7.22 | AE45: 87 | AF45: =IF(AE45=0,"",AG45/AE45) -> 0.082988506 | AG45: 7.22 | AH45: 87 | AI45: 0.08 | AJ45: =IF(AH45=0,"",AI45*AH45) -> 6.96 | AK45: 0 | AM45: =IF(AK45=0,"",AL45*AK45) | AN45: 0 | AP45: =IF(AN45=0,"",AO45*AN45) | AQ45: 0 | AS45: =IF(AQ45=0,"",AR45*AQ45)
A46: XPLG11 | B46: Logística | C46: Oportunidade | D46: {=IFERROR(INDEX(Fiis[], MATCH(A46, Fiis[Fii], 0), MATCH(Fiis[[#HEADERS],[QTD]], Fiis[#HEADERS], 0)), "")} -> 8 | E46: {=IFERROR(INDEX(Fiis[], MATCH(A46, Fiis[Fii], 0), MATCH(Fiis[[#HEADERS],[P/M]], Fiis[#HEADERS], 0)), "")} -> 93.43 | F46: =IFERROR(__xludf.DUMMYFUNCTION("IFERROR(GOOGLEFINANCE(A46),"""")"),91.59) -> 91.59 | G46: =IFERROR(SUMPRODUCT((MOD(COLUMN(K46:AS46)-COLUMN(K46), 3) = 0) * (K46:AS46))/SUMPRODUCT((MOD(COLUMN(K46:AS46)-COLUMN(K46), 3) = 0) * (NOT(ISBLANK(K46:AS46))))/E46*12,"") -> 0.10531949 | H46: =IFERROR(F46/E46-1,"") -> -0.019693888 | I46: =IFERROR((SUMPRODUCT((MOD(COLUMN(L46:AS46)-COLUMN(L46), 3) = 0) * (L46:AS46))+D46*F46)/(D46*E46)-1,"") -> 0.030771701 | J46: 4 | K46: =IF(J46=0,"",L46/J46) -> 0.82 | L46: 3.28 | M46: 4 | N46: =IF(M46=0,"",O46/M46) -> 0.82 | O46: 3.28 | P46: 4 | Q46: =IF(P46=0,"",R46/P46) -> 0.82 | R46: 3.28 | S46: 4 | T46: =IF(S46=0,"",U46/S46) -> 0.82 | U46: 3.28 | V46: 4 | W46: =IF(V46=0,"",X46/V46) -> 0.82 | X46: 3.28 | Y46: 4 | Z46: =IF(Y46=0,"",AA46/Y46) -> 0.82 | AA46: 3.28 | AB46: 6 | AC46: =IF(AB46=0,"",AD46/AB46) -> 0.82 | AD46: 4.92 | AE46: 8 | AF46: =IF(AE46=0,"",AG46/AE46) -> 0.82 | AG46: 6.56 | AH46: 8 | AI46: 0.82 | AJ46: =IF(AH46=0,"",AI46*AH46) -> 6.56 | AK46: 0 | AM46: =IF(AK46=0,"",AL46*AK46) | AN46: 0 | AP46: =IF(AN46=0,"",AO46*AN46) | AQ46: 0 | AS46: =IF(AQ46=0,"",AR46*AQ46)
A47: PMLL11 | B47: Shoppings | C47: Oportunidade | D47: {=IFERROR(INDEX(Fiis[], MATCH(A47, Fiis[Fii], 0), MATCH(Fiis[[#HEADERS],[QTD]], Fiis[#HEADERS], 0)), "")} -> 6 | E47: {=IFERROR(INDEX(Fiis[], MATCH(A47, Fiis[Fii], 0), MATCH(Fiis[[#HEADERS],[P/M]], Fiis[#HEADERS], 0)), "")} -> 99.15 | F47: =IFERROR(__xludf.DUMMYFUNCTION("IFERROR(GOOGLEFINANCE(A47),"""")"),102.68) -> 102.68 | G47: =IFERROR(SUMPRODUCT((MOD(COLUMN(K47:AS47)-COLUMN(K47), 3) = 0) * (K47:AS47))/SUMPRODUCT((MOD(COLUMN(K47:AS47)-COLUMN(K47), 3) = 0) * (NOT(ISBLANK(K47:AS47))))/E47*12,"") -> 0.12102874 | H47: =IFERROR(F47/E47-1,"") -> 0.035602622 | I47: =IFERROR((SUMPRODUCT((MOD(COLUMN(L47:AS47)-COLUMN(L47), 3) = 0) * (L47:AS47))+D47*F47)/(D47*E47)-1,"") -> 0.10284081 | J47: 4 | K47: =IF(J47=0,"",L47/J47) -> 1 | L47: 4 | M47: 4 | N47: =IF(M47=0,"",O47/M47) -> 1 | O47: 4 | P47: 4 | Q47: =IF(P47=0,"",R47/P47) -> 1 | R47: 4 | S47: 4 | T47: =IF(S47=0,"",U47/S47) -> 1 | U47: 4 | V47: 4 | W47: =IF(V47=0,"",X47/V47) -> 1 | X47: 4 | Y47: 4 | Z47: =IF(Y47=0,"",AA47/Y47) -> 1 | AA47: 4 | AB47: 4 | AC47: =IF(AB47=0,"",AD47/AB47) -> 1 | AD47: 4 | AE47: 6 | AF47: =IF(AE47=0,"",AG47/AE47) -> 1 | AG47: 6 | AH47: 6 | AI47: 1 | AJ47: =IF(AH47=0,"",AI47*AH47) -> 6 | AK47: 0 | AM47: =IF(AK47=0,"",AL47*AK47) | AN47: 0 | AP47: =IF(AN47=0,"",AO47*AN47) | AQ47: 0 | AS47: =IF(AQ47=0,"",AR47*AQ47)
A48: BTLG11 | B48: Logística | C48: Ancoragem | D48: {=IFERROR(INDEX(Fiis[], MATCH(A48, Fiis[Fii], 0), MATCH(Fiis[[#HEADERS],[QTD]], Fiis[#HEADERS], 0)), "")} -> 4 | E48: {=IFERROR(INDEX(Fiis[], MATCH(A48, Fiis[Fii], 0), MATCH(Fiis[[#HEADERS],[P/M]], Fiis[#HEADERS], 0)), "")} -> 97.58 | F48: =IFERROR(__xludf.DUMMYFUNCTION("IFERROR(GOOGLEFINANCE(A48),"""")"),100.23) -> 100.23 | G48: =IFERROR(SUMPRODUCT((MOD(COLUMN(K48:AS48)-COLUMN(K48), 3) = 0) * (K48:AS48))/SUMPRODUCT((MOD(COLUMN(K48:AS48)-COLUMN(K48), 3) = 0) * (NOT(ISBLANK(K48:AS48))))/E48*12,"") -> 0.099303136 | H48: =IFERROR(F48/E48-1,"") -> 0.027157204 | I48: =IFERROR((SUMPRODUCT((MOD(COLUMN(L48:AS48)-COLUMN(L48), 3) = 0) * (L48:AS48))+D48*F48)/(D48*E48)-1,"") -> 0.093359295 | J48: 4 | K48: =IF(J48=0,"",L48/J48) -> 0.8 | L48: 3.2 | M48: 4 | N48: =IF(M48=0,"",O48/M48) -> 0.8 | O48: 3.2 | P48: 4 | Q48: =IF(P48=0,"",R48/P48) -> 0.81 | R48: 3.24 | S48: 4 | T48: =IF(S48=0,"",U48/S48) -> 0.81 | U48: 3.24 | V48: 4 | W48: =IF(V48=0,"",X48/V48) -> 0.81 | X48: 3.24 | Y48: 4 | Z48: =IF(Y48=0,"",AA48/Y48) -> 0.81 | AA48: 3.24 | AB48: 4 | AC48: =IF(AB48=0,"",AD48/AB48) -> 0.81 | AD48: 3.24 | AE48: 4 | AF48: =IF(AE48=0,"",AG48/AE48) -> 0.81 | AG48: 3.24 | AH48: 0 | AJ48: =IF(AH48=0,"",AI48*AH48) | AK48: 0 | AM48: =IF(AK48=0,"",AL48*AK48) | AN48: 0 | AP48: =IF(AN48=0,"",AO48*AN48) | AQ48: 0 | AS48: =IF(AQ48=0,"",AR48*AQ48)
A49: HGBS11 | B49: Shoppings | C49: Oportunidade | D49: {=IFERROR(INDEX(Fiis[], MATCH(A49, Fiis[Fii], 0), MATCH(Fiis[[#HEADERS],[QTD]], Fiis[#HEADERS], 0)), "")} -> 20 | E49: {=IFERROR(INDEX(Fiis[], MATCH(A49, Fiis[Fii], 0), MATCH(Fiis[[#HEADERS],[P/M]], Fiis[#HEADERS], 0)), "")} -> 18.42 | F49: =IFERROR(__xludf.DUMMYFUNCTION("IFERROR(GOOGLEFINANCE(A49),"""")"),18.68) -> 18.68 | G49: =IFERROR(SUMPRODUCT((MOD(COLUMN(K49:AS49)-COLUMN(K49), 3) = 0) * (K49:AS49))/SUMPRODUCT((MOD(COLUMN(K49:AS49)-COLUMN(K49), 3) = 0) * (NOT(ISBLANK(K49:AS49))))/E49*12,"") -> 0.10857763 | H49: =IFERROR(F49/E49-1,"") -> 0.014115092 | I49: =IFERROR((SUMPRODUCT((MOD(COLUMN(L49:AS49)-COLUMN(L49), 3) = 0) * (L49:AS49))+D49*F49)/(D49*E49)-1,"") -> 0.095548317 | J49: 20 | K49: =IF(J49=0,"",L49/J49) -> 0.15 | L49: 3 | M49: 20 | N49: =IF(M49=0,"",O49/M49) -> 0.16 | O49: 3.2 | P49: 20 | Q49: =IF(P49=0,"",R49/P49) -> 0.17 | R49: 3.4 | S49: 20 | T49: =IF(S49=0,"",U49/S49) -> 0.17 | U49: 3.4 | V49: 20 | W49: =IF(V49=0,"",X49/V49) -> 0.17 | X49: 3.4 | Y49: 20 | Z49: =IF(Y49=0,"",AA49/Y49) -> 0.17 | AA49: 3.4 | AB49: 20 | AC49: =IF(AB49=0,"",AD49/AB49) -> 0.17 | AD49: 3.4 | AE49: 20 | AF49: =IF(AE49=0,"",AG49/AE49) -> 0.17 | AG49: 3.4 | AH49: 20 | AI49: 0.17 | AJ49: =IF(AH49=0,"",AI49*AH49) -> 3.4 | AK49: 0 | AM49: =IF(AK49=0,"",AL49*AK49) | AN49: 0 | AP49: =IF(AN49=0,"",AO49*AN49) | AQ49: 0 | AS49: =IF(AQ49=0,"",AR49*AQ49)
A50: BRCO11 | B50: Logística | C50: Oportunidade | D50: {=IFERROR(INDEX(Fiis[], MATCH(A50, Fiis[Fii], 0), MATCH(Fiis[[#HEADERS],[QTD]], Fiis[#HEADERS], 0)), "")} -> 3 | E50: {=IFERROR(INDEX(Fiis[], MATCH(A50, Fiis[Fii], 0), MATCH(Fiis[[#HEADERS],[P/M]], Fiis[#HEADERS], 0)), "")} -> 100.45 | F50: =IFERROR(__xludf.DUMMYFUNCTION("IFERROR(GOOGLEFINANCE(A50),"""")"),110.15) -> 110.15 | G50: =IFERROR(SUMPRODUCT((MOD(COLUMN(K50:AS50)-COLUMN(K50), 3) = 0) * (K50:AS50))/SUMPRODUCT((MOD(COLUMN(K50:AS50)-COLUMN(K50), 3) = 0) * (NOT(ISBLANK(K50:AS50))))/E50*12,"") -> 0.11083458 | H50: =IFERROR(F50/E50-1,"") -> 0.096565455 | I50: =IFERROR((SUMPRODUCT((MOD(COLUMN(L50:AS50)-COLUMN(L50), 3) = 0) * (L50:AS50))+D50*F50)/(D50*E50)-1,"") -> 0.17969139 | J50: 3 | K50: =IF(J50=0,"",L50/J50) -> 0.87 | L50: 2.61 | M50: 3 | N50: =IF(M50=0,"",O50/M50) -> 0.87 | O50: 2.61 | P50: 3 | Q50: =IF(P50=0,"",R50/P50) -> 0.92 | R50: 2.76 | S50: 3 | T50: =IF(S50=0,"",U50/S50) -> 0.92 | U50: 2.76 | V50: 3 | W50: =IF(V50=0,"",X50/V50) -> 0.95 | X50: 2.85 | Y50: 3 | Z50: =IF(Y50=0,"",AA50/Y50) -> 0.95 | AA50: 2.85 | AB50: 3 | AC50: =IF(AB50=0,"",AD50/AB50) -> 1.05 | AD50: 3.15 | AE50: 3 | AF50: =IF(AE50=0,"",AG50/AE50) -> 0.91 | AG50: 2.73 | AH50: 3 | AI50: 0.91 | AJ50: =IF(AH50=0,"",AI50*AH50) -> 2.73 | AK50: 0 | AM50: =IF(AK50=0,"",AL50*AK50) | AN50: 0 | AP50: =IF(AN50=0,"",AO50*AN50) | AQ50: 0 | AS50: =IF(AQ50=0,"",AR50*AQ50)
A51: MXRF11 | B51: CRI | C51: Ancoragem | D51: {=IFERROR(INDEX(Fiis[], MATCH(A51, Fiis[Fii], 0), MATCH(Fiis[[#HEADERS],[QTD]], Fiis[#HEADERS], 0)), "")} -> 21 | E51: {=IFERROR(INDEX(Fiis[], MATCH(A51, Fiis[Fii], 0), MATCH(Fiis[[#HEADERS],[P/M]], Fiis[#HEADERS], 0)), "")} -> 9.25 | F51: =IFERROR(__xludf.DUMMYFUNCTION("IFERROR(GOOGLEFINANCE(A51),"""")"),9.17) -> 9.17 | G51: =IFERROR(SUMPRODUCT((MOD(COLUMN(K51:AS51)-COLUMN(K51), 3) = 0) * (K51:AS51))/SUMPRODUCT((MOD(COLUMN(K51:AS51)-COLUMN(K51), 3) = 0) * (NOT(ISBLANK(K51:AS51))))/E51*12,"") -> 0.12904333 | H51: =IFERROR(F51/E51-1,"") -> -0.0086486486 | I51: =IFERROR((SUMPRODUCT((MOD(COLUMN(L51:AS51)-COLUMN(L51), 3) = 0) * (L51:AS51))+D51*F51)/(D51*E51)-1,"") -> 0.088133848 | J51: 21 | K51: =IF(J51=0,"",L51/J51) -> 0.1 | L51: 2.1 | M51: 21 | N51: =IF(M51=0,"",O51/M51) -> 0.1 | O51: 2.1 | P51: 21 | Q51: =IF(P51=0,"",R51/P51) -> 0.1 | R51: 2.1 | S51: 21 | T51: =IF(S51=0,"",U51/S51) -> 0.095238095 | U51: 2 | V51: 21 | W51: =IF(V51=0,"",X51/V51) -> 0.1 | X51: 2.1 | Y51: 21 | Z51: =IF(Y51=0,"",AA51/Y51) -> 0.1 | AA51: 2.1 | AB51: 21 | AC51: =IF(AB51=0,"",AD51/AB51) -> 0.1 | AD51: 2.1 | AE51: 21 | AF51: =IF(AE51=0,"",AG51/AE51) -> 0.1 | AG51: 2.1 | AH51: 21 | AI51: 0.1 | AJ51: =IF(AH51=0,"",AI51*AH51) -> 2.1 | AK51: 0 | AM51: =IF(AK51=0,"",AL51*AK51) | AN51: 0 | AP51: =IF(AN51=0,"",AO51*AN51) | AQ51: 0 | AS51: =IF(AQ51=0,"",AR51*AQ51)
A52: HGLG11 | B52: Logística | C52: Oportunidade | D52: {=IFERROR(INDEX(Fiis[], MATCH(A52, Fiis[Fii], 0), MATCH(Fiis[[#HEADERS],[QTD]], Fiis[#HEADERS], 0)), "")} -> 0 | E52: {=IFERROR(INDEX(Fiis[], MATCH(A52, Fiis[Fii], 0), MATCH(Fiis[[#HEADERS],[P/M]], Fiis[#HEADERS], 0)), "")} -> 0 | F52: =IFERROR(__xludf.DUMMYFUNCTION("IFERROR(GOOGLEFINANCE(A52),"""")"),146.45) -> 146.45 | G52: =IFERROR(SUMPRODUCT((MOD(COLUMN(K52:AS52)-COLUMN(K52), 3) = 0) * (K52:AS52))/SUMPRODUCT((MOD(COLUMN(K52:AS52)-COLUMN(K52), 3) = 0) * (NOT(ISBLANK(K52:AS52))))/E52*12,"") | H52: =IFERROR(F52/E52-1,"") | I52: =IFERROR((SUMPRODUCT((MOD(COLUMN(L52:AS52)-COLUMN(L52), 3) = 0) * (L52:AS52))+D52*F52)/(D52*E52)-1,"") | K52: =IF(J52=0,"",L52/J52) | L52: 0 | N52: =IF(M52=0,"",O52/M52) | O52: 0 | Q52: =IF(P52=0,"",R52/P52) | R52: 0 | T52: =IF(S52=0,"",U52/S52) | U52: 0 | W52: =IF(V52=0,"",X52/V52) | X52: 0 | Z52: =IF(Y52=0,"",AA52/Y52) | AA52: 0 | AC52: =IF(AB52=0,"",AD52/AB52) | AD52: 0 | AF52: =IF(AE52=0,"",AG52/AE52) | AG52: 0 | AH52: 0 | AJ52: =IF(AH52=0,"",AI52*AH52) | AK52: 0 | AM52: =IF(AK52=0,"",AL52*AK52) | AN52: 0 | AP52: =IF(AN52=0,"",AO52*AN52) | AQ52: 0 | AS52: =IF(AQ52=0,"",AR52*AQ52)
A53: KNRI11 | B53: Log/Laje | C53: Ancoragem | D53: {=IFERROR(INDEX(Fiis[], MATCH(A53, Fiis[Fii], 0), MATCH(Fiis[[#HEADERS],[QTD]], Fiis[#HEADERS], 0)), "")} -> 0 | E53: {=IFERROR(INDEX(Fiis[], MATCH(A53, Fiis[Fii], 0), MATCH(Fiis[[#HEADERS],[P/M]], Fiis[#HEADERS], 0)), "")} -> 0 | F53: =IFERROR(__xludf.DUMMYFUNCTION("IFERROR(GOOGLEFINANCE(A53),"""")"),157.0) -> 157 | G53: =IFERROR(SUMPRODUCT((MOD(COLUMN(K53:AS53)-COLUMN(K53), 3) = 0) * (K53:AS53))/SUMPRODUCT((MOD(COLUMN(K53:AS53)-COLUMN(K53), 3) = 0) * (NOT(ISBLANK(K53:AS53))))/E53*12,"") | H53: =IFERROR(F53/E53-1,"") | I53: =IFERROR((SUMPRODUCT((MOD(COLUMN(L53:AS53)-COLUMN(L53), 3) = 0) * (L53:AS53))+D53*F53)/(D53*E53)-1,"") | AH53: 0 | AJ53: =IF(AH53=0,"",AI53*AH53) | AK53: 0 | AM53: =IF(AK53=0,"",AL53*AK53) | AN53: 0 | AP53: =IF(AN53=0,"",AO53*AN53) | AQ53: 0 | AS53: =IF(AQ53=0,"",AR53*AQ53)
A54: HGRU11 | B54: Renda Urbana | C54: Ancoragem | D54: {=IFERROR(INDEX(Fiis[], MATCH(A54, Fiis[Fii], 0), MATCH(Fiis[[#HEADERS],[QTD]], Fiis[#HEADERS], 0)), "")} -> 2 | E54: {=IFERROR(INDEX(Fiis[], MATCH(A54, Fiis[Fii], 0), MATCH(Fiis[[#HEADERS],[P/M]], Fiis[#HEADERS], 0)), "")} -> 120 | F54: =IFERROR(__xludf.DUMMYFUNCTION("IFERROR(GOOGLEFINANCE(A54),"""")"),114.33) -> 114.33 | G54: =IFERROR(SUMPRODUCT((MOD(COLUMN(K54:AS54)-COLUMN(K54), 3) = 0) * (K54:AS54))/SUMPRODUCT((MOD(COLUMN(K54:AS54)-COLUMN(K54), 3) = 0) * (NOT(ISBLANK(K54:AS54))))/E54*12,"") -> 0.095 | H54: =IFERROR(F54/E54-1,"") -> -0.04725 | I54: =IFERROR((SUMPRODUCT((MOD(COLUMN(L54:AS54)-COLUMN(L54), 3) = 0) * (L54:AS54))+D54*F54)/(D54*E54)-1,"") -> -0.039333333 | AH54: 2 | AI54: 0.95 | AJ54: =IF(AH54=0,"",AI54*AH54) -> 1.9 | AK54: 0 | AM54: =IF(AK54=0,"",AL54*AK54) | AN54: 0 | AP54: =IF(AN54=0,"",AO54*AN54) | AQ54: 0 | AS54: =IF(AQ54=0,"",AR54*AQ54)
A55: PCIP11 | B55: CRI | C55: Oportunidade | D55: {=IFERROR(INDEX(Fiis[], MATCH(A55, Fiis[Fii], 0), MATCH(Fiis[[#HEADERS],[QTD]], Fiis[#HEADERS], 0)), "")} -> 0 | E55: {=IFERROR(INDEX(Fiis[], MATCH(A55, Fiis[Fii], 0), MATCH(Fiis[[#HEADERS],[P/M]], Fiis[#HEADERS], 0)), "")} -> 0 | F55: =IFERROR(__xludf.DUMMYFUNCTION("IFERROR(GOOGLEFINANCE(A55),"""")"),73.79) -> 73.79 | G55: =IFERROR(SUMPRODUCT((MOD(COLUMN(K55:AS55)-COLUMN(K55), 3) = 0) * (K55:AS55))/SUMPRODUCT((MOD(COLUMN(K55:AS55)-COLUMN(K55), 3) = 0) * (NOT(ISBLANK(K55:AS55))))/E55*12,"") | H55: =IFERROR(F55/E55-1,"") | I55: =IFERROR((SUMPRODUCT((MOD(COLUMN(L55:AS55)-COLUMN(L55), 3) = 0) * (L55:AS55))+D55*F55)/(D55*E55)-1,"") | AH55: 0 | AJ55: =IF(AH55=0,"",AI55*AH55) | AK55: 0 | AM55: =IF(AK55=0,"",AL55*AK55) | AN55: 0 | AP55: =IF(AN55=0,"",AO55*AN55) | AQ55: 0 | AS55: =IF(AQ55=0,"",AR55*AQ55)
G56: =IFERROR(SUMPRODUCT((MOD(COLUMN(K56:AS56)-COLUMN(K56), 3) = 0) * (K56:AS56))/SUMPRODUCT((MOD(COLUMN(K56:AS56)-COLUMN(K56), 3) = 0) * (NOT(ISBLANK(K56:AS56))))/E56*12,"") | H56: =IFERROR(F56/E56-1,"") | I56: =IFERROR((SUMPRODUCT((MOD(COLUMN(L56:AS56)-COLUMN(L56), 3) = 0) * (L56:AS56))+D56*F56)/(D56*E56)-1,"")
I58: Proventos: | K58: =SUMPRODUCT(J42:J57,K42:K57) -> 28.33 | N58: =SUMPRODUCT(M42:M57,N42:N57) -> 30.78 | Q58: =SUMPRODUCT(P42:P57,Q42:Q57) -> 32.83 | T58: =SUMPRODUCT(S42:S57,T42:T57) -> 36.56 | W58: =SUMPRODUCT(V42:V57,W42:W57) -> 38.24 | Z58: =SUMPRODUCT(Y42:Y57,Z42:Z57) -> 39.24 | AC58: =SUMPRODUCT(AB42:AB57,AC42:AC57) -> 46.43 | AF58: =SUMPRODUCT(AE42:AE57,AF42:AF57) -> 50.4 | AI58: =SUMPRODUCT(AH42:AH57,AI42:AI57) -> 49.35 | AL58: =SUMPRODUCT(AK42:AK57,AL42:AL57) -> 0 | AO58: =SUMPRODUCT(AN42:AN57,AO42:AO57) -> 0 | AR58: =SUMPRODUCT(AQ42:AQ57,AR42:AR57) -> 0
I59: YoC Mensal: | K59: =IFERROR(K58/SUMPRODUCT(J42:J57,$E42:$E57),"") -> 0.0089462499 | N59: =IFERROR(N58/SUMPRODUCT(M42:M57,$E42:$E57),"") -> 0.0088432013 | Q59: =IFERROR(Q58/SUMPRODUCT(P42:P57,$E42:$E57),"") -> 0.0089909734 | T59: =IFERROR(T58/SUMPRODUCT(S42:S57,$E42:$E57),"") -> 0.0090532473 | W59: =IFERROR(W58/SUMPRODUCT(V42:V57,$E42:$E57),"") -> 0.0091246188 | Z59: =IFERROR(Z58/SUMPRODUCT(Y42:Y57,$E42:$E57),"") -> 0.0091448068 | AC59: =IFERROR(AC58/SUMPRODUCT(AB42:AB57,$E42:$E57),"") -> 0.0091180993 | AF59: =IFERROR(AF58/SUMPRODUCT(AE42:AE57,$E42:$E57),"") -> 0.009029216 | AI59: =IFERROR(AI58/SUMPRODUCT(AH42:AH57,$E42:$E57),"") -> 0.0090857875 | AL59: =IFERROR(AL58/SUMPRODUCT(AK42:AK57,$E42:$E57),"") | AO59: =IFERROR(AO58/SUMPRODUCT(AN42:AN57,$E42:$E57),"") | AR59: =IFERROR(AR58/SUMPRODUCT(AQ42:AQ57,$E42:$E57),"")
I60: YoC Anualizado: | K60: =IF(K59="","",K59*12) -> 0.107355 | N60: =IF(N59="","",N59*12) -> 0.10611841 | Q60: =IF(Q59="","",Q59*12) -> 0.10789168 | T60: =IF(T59="","",T59*12) -> 0.10863897 | W60: =IF(W59="","",W59*12) -> 0.10949543 | Z60: =IF(Z59="","",Z59*12) -> 0.10973768 | AC60: =IF(AC59="","",AC59*12) -> 0.10941719 | AF60: =IF(AF59="","",AF59*12) -> 0.10835059 | AI60: =IF(AI59="","",AI59*12) -> 0.10902945 | AL60: =IF(AL59="","",AL59*12) | AO60: =IF(AO59="","",AO59*12) | AR60: =IF(AR59="","",AR59*12)

Sheet Decio_Bazin
B2: Fii | C2: Media_DPA_3Anos | D2: Anos_Media | F2: Ano | G2: LPC | I2: Ano | J2: LPC | L2: Ano | M2: LPC | O2: Ano | P2: LPC
B3: KNRI11 | C3: =IFERROR(G6/D3,0) -> 12.125 | D3: 2 | F3: Ano_1 | I3: Ano_1 | J3: 9.18 | L3: Ano_1 | O3: Ano_1
B4: PMLL11 | C4: =IFERROR(G13/D4,0) -> 9.9766667 | D4: 3 | F4: Ano_2 | G4: 12 | I4: Ano_2 | J4: 9.36 | L4: Ano_2 | O4: Ano_2 | P4: 1.09
B5: XPLG11 | C5: =IFERROR(J6/D5,0) -> 9.46 | D5: 3 | F5: Ano_3 | G5: 12.25 | I5: Ano_3 | J5: 9.84 | L5: Ano_3 | M5: 1.86 | O5: Ano_3 | P5: 1.13
B6: BTLG11 | C6: =IFERROR(J13/D6,0) -> 9.2533333 | D6: 3 | F6: Total | G6: =SUM(G4:G5) -> 24.25 | I6: Total | J6: =SUM(J3:J5) -> 28.38 | L6: Total | M6: =SUM(M3:M5) -> 1.86 | O6: Total | P6: =SUM(P3:P5) -> 2.22
B7: HGBS11 | C7: =IFERROR(M6/D7,0) -> 1.86 | D7: 1
B8: GGRC11 | C8: =IFERROR(M13/D8,0) -> 1.16 | D8: 2
B9: PORD11 | C9: =IFERROR(P6/D9,0) -> 1.11 | D9: 2 | F9: Ano | G9: LPC | I9: Ano | J9: LPC | L9: Ano | M9: LPC | O9: Ano | P9: LPC
B10: BRCO11 | C10: =IFERROR(P13/D10,0) -> 10.213333 | D10: 3 | F10: Ano_1 | G10: 9.65 | I10: Ano_1 | J10: 9 | L10: Ano_1 | O10: Ano_1 | P10: 9.58
B11: GARE11 | C11: =IFERROR(B23/D11,0) -> 0.96 | D11: 1 | F11: Ano_2 | G11: 10.03 | I11: Ano_2 | J11: 9.27 | L11: Ano_2 | M11: 1.11 | O11: Ano_2 | P11: 10.44
B12: MXRF11 | C12: =IFERROR(E23/D12,0) -> 1.17 | D12: 1 | F12: Ano_3 | G12: 10.25 | I12: Ano_3 | J12: 9.49 | L12: Ano_3 | M12: 1.21 | O12: Ano_3 | P12: 10.62
B13: HGLG11 | C13: =IFERROR(B30/D13,0) -> 13.2 | D13: 1 | F13: Total | G13: =SUM(G10:G12) -> 29.93 | I13: Total | J13: =SUM(J10:J12) -> 27.76 | L13: Total | M13: =SUM(M10:M12) -> 2.32 | O13: Total | P13: =SUM(P10:P12) -> 30.64
B14: HGRU11 | C14: =IFERROR(E30/D14,0) -> 11.4 | D14: 1
B15: PCIP11 | C15: =IFERROR(H22/D15,0) -> 9.6 | D15: 1
G18: Ano | H18: LPC
A19: Ano | B19: LPC | D19: Ano | E19: LPC | G19: Ano_1 | H19: 0
A20: Ano_1 | D20: Ano_1 | G20: Ano_2 | H20: 0
A21: Ano_2 | D21: Ano_2 | G21: Ano_3 | H21: 9.6
A22: Ano_3 | B22: 0.96 | D22: Ano_3 | E22: 1.17 | G22: Total | H22: =SUM(H19:H21) -> 9.6
A23: Total | B23: =SUM(B20:B22) -> 0.96 | D23: Total | E23: =SUM(E20:E22) -> 1.17
A26: Ano | B26: LPC | D26: Ano | E26: LPC
A27: Ano_1 | D27: Ano_1
A28: Ano_2 | D28: Ano_2
A29: Ano_3 | B29: 13.2 | D29: Ano_3 | E29: 11.4
A30: Total | B30: =SUM(B27:B29) -> 13.2 | D30: Total | E30: =SUM(E27:E29) -> 11.4

Sheet Indicadores
A2: Título | B2: Taxa de Compra | C2: Preço_Uni | D2: Taxa de Resgate | E2: Preço Unitário de Resgate | F2: Data/Hora da Atualização | G2: Data do Vencimento | I2: Renda | J2: valor
A3: Tesouro IPCA+ 2029 | B3: 0 | C3: 0 | D3: 0.0782 | E3: 3876.66 | F3: 46275.456 | G3: 47119 | I3: Selic | J3: 0.139
A4: Tesouro IPCA+ 2032 | B4: 0.0779 | C4: 3041.71 | D4: 0.0791 | E4: 3021.2 | F4: 46275.456 | G4: 48441 | I4: IPCA | J4: 0.044430246
A5: Tesouro IPCA+ 2040 | B5: 0.0737 | C5: 1767.6 | D5: 0.0749 | E5: 1740.14 | F5: 46275.456 | G5: 51363 | I5: Juros_Real | J5: =(1+J3)/(1+(J4+0.0025))-1 -> 0.087942587
A6: Tesouro Renda+ Aposentadoria Extra 2065 | B6: 0.0721 | C6: 181 | D6: 0.0733 | E6: 171.94 | F6: 46275.456 | G6: 67556
A7: Tesouro Selic 2031 | B7: 0.00073 | C7: 19790.6 | D7: 0.00083 | E7: 19771.5 | F7: 46275.456 | G7: 47908

Sheet Aporte
E2: Ticker | F2: Valor
A3: Ticker | B3: Está barato? | C3: Valor | E3: =IFERROR(__xludf.DUMMYFUNCTION("IFERROR( FILTER({Baratos[Ticker],Baratos[Valor]}, Baratos[Está barato?]=""SIM""), {""🛑 Nenhum ativo barato"",0} ) "),"XPLG11") -> XPLG11 | F3: =IFERROR(__xludf.DUMMYFUNCTION("""COMPUTED_VALUE"""),91.59) -> 91.59
A4: BBAS3 | B4: {=IFERROR(IF(AND( INDEX(Ações_Nacionais[], MATCH(A4, Ações_Nacionais[Ação], 0), MATCH(Ações_Nacionais[[#HEADERS],[Preço mercado]], Ações_Nacionais[#HEADERS], 0)) < INDEX(Ações_Nacionais[], MATCH(A4, Ações_Nacionais[Ação], 0), MATCH(Ações_Nacionais[[#HEADERS],[P/Teto]], Ações_Nacionais[#HEADERS], 0)), ), "SIM", "NÃO"), "")} -> NÃO | C4: {=IFERROR(INDEX(Ações_Nacionais[], MATCH(A4, Ações_Nacionais[Ação], 0), MATCH(Ações_Nacionais[[#HEADERS],[Preço mercado]], Ações_Nacionais[#HEADERS], 0)), "")} -> 22.52 | E4: =IFERROR(__xludf.DUMMYFUNCTION("""COMPUTED_VALUE"""),"HGBS11") -> HGBS11 | F4: =IFERROR(__xludf.DUMMYFUNCTION("""COMPUTED_VALUE"""),18.68) -> 18.68
A5: BBSE3 | B5: {=IFERROR(IF(AND( INDEX(Ações_Nacionais[], MATCH(A5, Ações_Nacionais[Ação], 0), MATCH(Ações_Nacionais[[#HEADERS],[Preço mercado]], Ações_Nacionais[#HEADERS], 0)) < INDEX(Ações_Nacionais[], MATCH(A5, Ações_Nacionais[Ação], 0), MATCH(Ações_Nacionais[[#HEADERS],[P/Teto]], Ações_Nacionais[#HEADERS], 0)), ), "SIM", "NÃO"), "")} -> NÃO | C5: {=IFERROR(INDEX(Ações_Nacionais[], MATCH(A5, Ações_Nacionais[Ação], 0), MATCH(Ações_Nacionais[[#HEADERS],[Preço mercado]], Ações_Nacionais[#HEADERS], 0)), "")} -> 40.93 | E5: =IFERROR(__xludf.DUMMYFUNCTION("""COMPUTED_VALUE"""),"BRCO11") -> BRCO11 | F5: =IFERROR(__xludf.DUMMYFUNCTION("""COMPUTED_VALUE"""),110.15) -> 110.15
A6: VALE3 | B6: {=IFERROR(IF(AND( INDEX(Ações_Nacionais[], MATCH(A6, Ações_Nacionais[Ação], 0), MATCH(Ações_Nacionais[[#HEADERS],[Preço mercado]], Ações_Nacionais[#HEADERS], 0)) < INDEX(Ações_Nacionais[], MATCH(A6, Ações_Nacionais[Ação], 0), MATCH(Ações_Nacionais[[#HEADERS],[P/Teto]], Ações_Nacionais[#HEADERS], 0)), ), "SIM", "NÃO"), "")} -> NÃO | C6: {=IFERROR(INDEX(Ações_Nacionais[], MATCH(A6, Ações_Nacionais[Ação], 0), MATCH(Ações_Nacionais[[#HEADERS],[Preço mercado]], Ações_Nacionais[#HEADERS], 0)), "")} -> 77.91 | E6: =IFERROR(__xludf.DUMMYFUNCTION("""COMPUTED_VALUE"""),"HGLG11") -> HGLG11 | F6: =IFERROR(__xludf.DUMMYFUNCTION("""COMPUTED_VALUE"""),146.45) -> 146.45
A7: TAEE11 | B7: {=IFERROR(IF(AND( INDEX(Ações_Nacionais[], MATCH(A7, Ações_Nacionais[Ação], 0), MATCH(Ações_Nacionais[[#HEADERS],[Preço mercado]], Ações_Nacionais[#HEADERS], 0)) < INDEX(Ações_Nacionais[], MATCH(A7, Ações_Nacionais[Ação], 0), MATCH(Ações_Nacionais[[#HEADERS],[P/Teto]], Ações_Nacionais[#HEADERS], 0)), ), "SIM", "NÃO"), "")} -> NÃO | C7: {=IFERROR(INDEX(Ações_Nacionais[], MATCH(A7, Ações_Nacionais[Ação], 0), MATCH(Ações_Nacionais[[#HEADERS],[Preço mercado]], Ações_Nacionais[#HEADERS], 0)), "")} -> 41.03 | E7: =IFERROR(__xludf.DUMMYFUNCTION("""COMPUTED_VALUE"""),"BTLG11") -> BTLG11 | F7: =IFERROR(__xludf.DUMMYFUNCTION("""COMPUTED_VALUE"""),100.23) -> 100.23
A8: ITUB3 | B8: {=IFERROR(IF(AND( INDEX(Ações_Nacionais[], MATCH(A8, Ações_Nacionais[Ação], 0), MATCH(Ações_Nacionais[[#HEADERS],[Preço mercado]], Ações_Nacionais[#HEADERS], 0)) < INDEX(Ações_Nacionais[], MATCH(A8, Ações_Nacionais[Ação], 0), MATCH(Ações_Nacionais[[#HEADERS],[P/Teto]], Ações_Nacionais[#HEADERS], 0)), ), "SIM", "NÃO"), "")} -> NÃO | C8: {=IFERROR(INDEX(Ações_Nacionais[], MATCH(A8, Ações_Nacionais[Ação], 0), MATCH(Ações_Nacionais[[#HEADERS],[Preço mercado]], Ações_Nacionais[#HEADERS], 0)), "")} -> 45.97 | E8: =IFERROR(__xludf.DUMMYFUNCTION("""COMPUTED_VALUE"""),"GGRC11") -> GGRC11 | F8: =IFERROR(__xludf.DUMMYFUNCTION("""COMPUTED_VALUE"""),9.0) -> 9
A9: PETR4 | B9: {=IFERROR(IF(AND( INDEX(Ações_Nacionais[], MATCH(A9, Ações_Nacionais[Ação], 0), MATCH(Ações_Nacionais[[#HEADERS],[Preço mercado]], Ações_Nacionais[#HEADERS], 0)) < INDEX(Ações_Nacionais[], MATCH(A9, Ações_Nacionais[Ação], 0), MATCH(Ações_Nacionais[[#HEADERS],[P/Teto]], Ações_Nacionais[#HEADERS], 0)), ), "SIM", "NÃO"), "")} -> NÃO | C9: {=IFERROR(INDEX(Ações_Nacionais[], MATCH(A9, Ações_Nacionais[Ação], 0), MATCH(Ações_Nacionais[[#HEADERS],[Preço mercado]], Ações_Nacionais[#HEADERS], 0)), "")} -> 48.87 | E9: =IFERROR(__xludf.DUMMYFUNCTION("""COMPUTED_VALUE"""),"GARE11") -> GARE11 | F9: =IFERROR(__xludf.DUMMYFUNCTION("""COMPUTED_VALUE"""),8.4) -> 8.4
A10: WEGE3 | B10: {=IFERROR(IF(AND( INDEX(Ações_Nacionais[], MATCH(A10, Ações_Nacionais[Ação], 0), MATCH(Ações_Nacionais[[#HEADERS],[Preço mercado]], Ações_Nacionais[#HEADERS], 0)) < INDEX(Ações_Nacionais[], MATCH(A10, Ações_Nacionais[Ação], 0), MATCH(Ações_Nacionais[[#HEADERS],[P/Teto]], Ações_Nacionais[#HEADERS], 0)), ), "SIM", "NÃO"), "")} -> NÃO | C10: {=IFERROR(INDEX(Ações_Nacionais[], MATCH(A10, Ações_Nacionais[Ação], 0), MATCH(Ações_Nacionais[[#HEADERS],[Preço mercado]], Ações_Nacionais[#HEADERS], 0)), "")} -> 51.83 | E10: =IFERROR(__xludf.DUMMYFUNCTION("""COMPUTED_VALUE"""),"PMLL11") -> PMLL11 | F10: =IFERROR(__xludf.DUMMYFUNCTION("""COMPUTED_VALUE"""),102.68) -> 102.68
A11: BRBI11 | B11: {=IFERROR(IF(AND( INDEX(Ações_Nacionais[], MATCH(A11, Ações_Nacionais[Ação], 0), MATCH(Ações_Nacionais[[#HEADERS],[Preço mercado]], Ações_Nacionais[#HEADERS], 0)) < INDEX(Ações_Nacionais[], MATCH(A11, Ações_Nacionais[Ação], 0), MATCH(Ações_Nacionais[[#HEADERS],[P/Teto]], Ações_Nacionais[#HEADERS], 0)), ), "SIM", "NÃO"), "")} -> NÃO | C11: {=IFERROR(INDEX(Ações_Nacionais[], MATCH(A11, Ações_Nacionais[Ação], 0), MATCH(Ações_Nacionais[[#HEADERS],[Preço mercado]], Ações_Nacionais[#HEADERS], 0)), "")} -> 14.25 | E11: =IFERROR(__xludf.DUMMYFUNCTION("""COMPUTED_VALUE"""),"MXRF11") -> MXRF11 | F11: =IFERROR(__xludf.DUMMYFUNCTION("""COMPUTED_VALUE"""),9.17) -> 9.17
A12: CMIG4 | B12: {=IFERROR(IF(AND( INDEX(Ações_Nacionais[], MATCH(A12, Ações_Nacionais[Ação], 0), MATCH(Ações_Nacionais[[#HEADERS],[Preço mercado]], Ações_Nacionais[#HEADERS], 0)) < INDEX(Ações_Nacionais[], MATCH(A12, Ações_Nacionais[Ação], 0), MATCH(Ações_Nacionais[[#HEADERS],[P/Teto]], Ações_Nacionais[#HEADERS], 0)), ), "SIM", "NÃO"), "")} -> NÃO | C12: {=IFERROR(INDEX(Ações_Nacionais[], MATCH(A12, Ações_Nacionais[Ação], 0), MATCH(Ações_Nacionais[[#HEADERS],[Preço mercado]], Ações_Nacionais[#HEADERS], 0)), "")} -> 11.3 | E12: =IFERROR(__xludf.DUMMYFUNCTION("""COMPUTED_VALUE"""),"HGRU11") -> HGRU11 | F12: =IFERROR(__xludf.DUMMYFUNCTION("""COMPUTED_VALUE"""),114.33) -> 114.33
A13: ISAE4 | B13: {=IFERROR(IF(AND( INDEX(Ações_Nacionais[], MATCH(A13, Ações_Nacionais[Ação], 0), MATCH(Ações_Nacionais[[#HEADERS],[Preço mercado]], Ações_Nacionais[#HEADERS], 0)) < INDEX(Ações_Nacionais[], MATCH(A13, Ações_Nacionais[Ação], 0), MATCH(Ações_Nacionais[[#HEADERS],[P/Teto]], Ações_Nacionais[#HEADERS], 0)), ), "SIM", "NÃO"), "")} -> NÃO | C13: {=IFERROR(INDEX(Ações_Nacionais[], MATCH(A13, Ações_Nacionais[Ação], 0), MATCH(Ações_Nacionais[[#HEADERS],[Preço mercado]], Ações_Nacionais[#HEADERS], 0)), "")} -> 27.72 | E13: =IFERROR(__xludf.DUMMYFUNCTION("""COMPUTED_VALUE"""),"PCIP11") -> PCIP11 | F13: =IFERROR(__xludf.DUMMYFUNCTION("""COMPUTED_VALUE"""),73.79) -> 73.79
A14: SAPR4 | B14: {=IFERROR(IF(AND( INDEX(Ações_Nacionais[], MATCH(A14, Ações_Nacionais[Ação], 0), MATCH(Ações_Nacionais[[#HEADERS],[Preço mercado]], Ações_Nacionais[#HEADERS], 0)) < INDEX(Ações_Nacionais[], MATCH(A14, Ações_Nacionais[Ação], 0), MATCH(Ações_Nacionais[[#HEADERS],[P/Teto]], Ações_Nacionais[#HEADERS], 0)), ), "SIM", "NÃO"), "")} -> NÃO | C14: {=IFERROR(INDEX(Ações_Nacionais[], MATCH(A14, Ações_Nacionais[Ação], 0), MATCH(Ações_Nacionais[[#HEADERS],[Preço mercado]], Ações_Nacionais[#HEADERS], 0)), "")} -> 6.84
A15: XPLG11 | B15: {=IFERROR(IF(AND( INDEX(Fiis[], MATCH(A15, Fiis[Fii], 0), MATCH(Fiis[[#HEADERS],[Preço mercado]], Fiis[#HEADERS], 0)) < INDEX(Fiis[], MATCH(A15, Fiis[Fii], 0), MATCH(Fiis[[#HEADERS],[Justo]], Fiis[#HEADERS], 0)), INDEX(Fiis[], MATCH(A15, Fiis[Fii], 0), MATCH(Fiis[[#HEADERS],[Preço mercado]], Fiis[#HEADERS], 0)) < INDEX(Fiis[], MATCH(A15, Fiis[Fii], 0), MATCH(Fiis[[#HEADERS],[VP/Cota]], Fiis[#HEADERS], 0)) ), "SIM", "NÃO"), "")} -> SIM | C15: =IFERROR(__xludf.DUMMYFUNCTION("IFERROR(GOOGLEFINANCE(""BVMF:"" & A15),0)"),91.59) -> 91.59
A16: HGBS11 | B16: {=IFERROR(IF(AND( INDEX(Fiis[], MATCH(A16, Fiis[Fii], 0), MATCH(Fiis[[#HEADERS],[Preço mercado]], Fiis[#HEADERS], 0)) < INDEX(Fiis[], MATCH(A16, Fiis[Fii], 0), MATCH(Fiis[[#HEADERS],[Justo]], Fiis[#HEADERS], 0)), INDEX(Fiis[], MATCH(A16, Fiis[Fii], 0), MATCH(Fiis[[#HEADERS],[Preço mercado]], Fiis[#HEADERS], 0)) < INDEX(Fiis[], MATCH(A16, Fiis[Fii], 0), MATCH(Fiis[[#HEADERS],[VP/Cota]], Fiis[#HEADERS], 0)) ), "SIM", "NÃO"), "")} -> SIM | C16: =IFERROR(__xludf.DUMMYFUNCTION("IFERROR(GOOGLEFINANCE(""BVMF:"" & A16),0)"),18.68) -> 18.68
A17: BRCO11 | B17: {=IFERROR(IF(AND( INDEX(Fiis[], MATCH(A17, Fiis[Fii], 0), MATCH(Fiis[[#HEADERS],[Preço mercado]], Fiis[#HEADERS], 0)) < INDEX(Fiis[], MATCH(A17, Fiis[Fii], 0), MATCH(Fiis[[#HEADERS],[Justo]], Fiis[#HEADERS], 0)), INDEX(Fiis[], MATCH(A17, Fiis[Fii], 0), MATCH(Fiis[[#HEADERS],[Preço mercado]], Fiis[#HEADERS], 0)) < INDEX(Fiis[], MATCH(A17, Fiis[Fii], 0), MATCH(Fiis[[#HEADERS],[VP/Cota]], Fiis[#HEADERS], 0)) ), "SIM", "NÃO"), "")} -> SIM | C17: =IFERROR(__xludf.DUMMYFUNCTION("IFERROR(GOOGLEFINANCE(""BVMF:"" & A17),0)"),110.15) -> 110.15
A18: HGLG11 | B18: {=IFERROR(IF(AND( INDEX(Fiis[], MATCH(A18, Fiis[Fii], 0), MATCH(Fiis[[#HEADERS],[Preço mercado]], Fiis[#HEADERS], 0)) < INDEX(Fiis[], MATCH(A18, Fiis[Fii], 0), MATCH(Fiis[[#HEADERS],[Justo]], Fiis[#HEADERS], 0)), INDEX(Fiis[], MATCH(A18, Fiis[Fii], 0), MATCH(Fiis[[#HEADERS],[Preço mercado]], Fiis[#HEADERS], 0)) < INDEX(Fiis[], MATCH(A18, Fiis[Fii], 0), MATCH(Fiis[[#HEADERS],[VP/Cota]], Fiis[#HEADERS], 0)) ), "SIM", "NÃO"), "")} -> SIM | C18: =IFERROR(__xludf.DUMMYFUNCTION("IFERROR(GOOGLEFINANCE(""BVMF:"" & A18),0)"),146.45) -> 146.45
A19: LVBI11 | B19: {=IFERROR(IF(AND( INDEX(Fiis[], MATCH(A19, Fiis[Fii], 0), MATCH(Fiis[[#HEADERS],[Preço mercado]], Fiis[#HEADERS], 0)) < INDEX(Fiis[], MATCH(A19, Fiis[Fii], 0), MATCH(Fiis[[#HEADERS],[Justo]], Fiis[#HEADERS], 0)), INDEX(Fiis[], MATCH(A19, Fiis[Fii], 0), MATCH(Fiis[[#HEADERS],[Preço mercado]], Fiis[#HEADERS], 0)) < INDEX(Fiis[], MATCH(A19, Fiis[Fii], 0), MATCH(Fiis[[#HEADERS],[VP/Cota]], Fiis[#HEADERS], 0)) ), "SIM", "NÃO"), "")} -> NÃO | C19: =IFERROR(__xludf.DUMMYFUNCTION("IFERROR(GOOGLEFINANCE(""BVMF:"" & A19),0)"),97.21) -> 97.21
A20: BTLG11 | B20: {=IFERROR(IF(AND( INDEX(Fiis[], MATCH(A20, Fiis[Fii], 0), MATCH(Fiis[[#HEADERS],[Preço mercado]], Fiis[#HEADERS], 0)) < INDEX(Fiis[], MATCH(A20, Fiis[Fii], 0), MATCH(Fiis[[#HEADERS],[Justo]], Fiis[#HEADERS], 0)), INDEX(Fiis[], MATCH(A20, Fiis[Fii], 0), MATCH(Fiis[[#HEADERS],[Preço mercado]], Fiis[#HEADERS], 0)) < INDEX(Fiis[], MATCH(A20, Fiis[Fii], 0), MATCH(Fiis[[#HEADERS],[VP/Cota]], Fiis[#HEADERS], 0)) ), "SIM", "NÃO"), "")} -> SIM | C20: =IFERROR(__xludf.DUMMYFUNCTION("IFERROR(GOOGLEFINANCE(""BVMF:"" & A20),0)"),100.23) -> 100.23
A21: GGRC11 | B21: {=IFERROR(IF(AND( INDEX(Fiis[], MATCH(A21, Fiis[Fii], 0), MATCH(Fiis[[#HEADERS],[Preço mercado]], Fiis[#HEADERS], 0)) < INDEX(Fiis[], MATCH(A21, Fiis[Fii], 0), MATCH(Fiis[[#HEADERS],[Justo]], Fiis[#HEADERS], 0)), INDEX(Fiis[], MATCH(A21, Fiis[Fii], 0), MATCH(Fiis[[#HEADERS],[Preço mercado]], Fiis[#HEADERS], 0)) < INDEX(Fiis[], MATCH(A21, Fiis[Fii], 0), MATCH(Fiis[[#HEADERS],[VP/Cota]], Fiis[#HEADERS], 0)) ), "SIM", "NÃO"), "")} -> SIM | C21: =IFERROR(__xludf.DUMMYFUNCTION("IFERROR(GOOGLEFINANCE(""BVMF:"" & A21),0)"),9.0) -> 9
A22: GARE11 | B22: {=IFERROR(IF(AND( INDEX(Fiis[], MATCH(A22, Fiis[Fii], 0), MATCH(Fiis[[#HEADERS],[Preço mercado]], Fiis[#HEADERS], 0)) < INDEX(Fiis[], MATCH(A22, Fiis[Fii], 0), MATCH(Fiis[[#HEADERS],[Justo]], Fiis[#HEADERS], 0)), INDEX(Fiis[], MATCH(A22, Fiis[Fii], 0), MATCH(Fiis[[#HEADERS],[Preço mercado]], Fiis[#HEADERS], 0)) < INDEX(Fiis[], MATCH(A22, Fiis[Fii], 0), MATCH(Fiis[[#HEADERS],[VP/Cota]], Fiis[#HEADERS], 0)) ), "SIM", "NÃO"), "")} -> SIM | C22: =IFERROR(__xludf.DUMMYFUNCTION("IFERROR(GOOGLEFINANCE(""BVMF:"" & A22),0)"),8.4) -> 8.4
A23: PMLL11 | B23: {=IFERROR(IF(AND( INDEX(Fiis[], MATCH(A23, Fiis[Fii], 0), MATCH(Fiis[[#HEADERS],[Preço mercado]], Fiis[#HEADERS], 0)) < INDEX(Fiis[], MATCH(A23, Fiis[Fii], 0), MATCH(Fiis[[#HEADERS],[Justo]], Fiis[#HEADERS], 0)), INDEX(Fiis[], MATCH(A23, Fiis[Fii], 0), MATCH(Fiis[[#HEADERS],[Preço mercado]], Fiis[#HEADERS], 0)) < INDEX(Fiis[], MATCH(A23, Fiis[Fii], 0), MATCH(Fiis[[#HEADERS],[VP/Cota]], Fiis[#HEADERS], 0)) ), "SIM", "NÃO"), "")} -> SIM | C23: =IFERROR(__xludf.DUMMYFUNCTION("IFERROR(GOOGLEFINANCE(""BVMF:"" & A23),0)"),102.68) -> 102.68
A24: KNRI11 | B24: {=IFERROR(IF(AND( INDEX(Fiis[], MATCH(A24, Fiis[Fii], 0), MATCH(Fiis[[#HEADERS],[Preço mercado]], Fiis[#HEADERS], 0)) < INDEX(Fiis[], MATCH(A24, Fiis[Fii], 0), MATCH(Fiis[[#HEADERS],[Justo]], Fiis[#HEADERS], 0)), INDEX(Fiis[], MATCH(A24, Fiis[Fii], 0), MATCH(Fiis[[#HEADERS],[Preço mercado]], Fiis[#HEADERS], 0)) < INDEX(Fiis[], MATCH(A24, Fiis[Fii], 0), MATCH(Fiis[[#HEADERS],[VP/Cota]], Fiis[#HEADERS], 0)) ), "SIM", "NÃO"), "")} -> NÃO | C24: =IFERROR(__xludf.DUMMYFUNCTION("IFERROR(GOOGLEFINANCE(""BVMF:"" & A24),0)"),157.0) -> 157
A25: MXRF11 | B25: {=IFERROR(IF(AND( INDEX(Fiis[], MATCH(A25, Fiis[Fii], 0), MATCH(Fiis[[#HEADERS],[Preço mercado]], Fiis[#HEADERS], 0)) < INDEX(Fiis[], MATCH(A25, Fiis[Fii], 0), MATCH(Fiis[[#HEADERS],[Justo]], Fiis[#HEADERS], 0)), INDEX(Fiis[], MATCH(A25, Fiis[Fii], 0), MATCH(Fiis[[#HEADERS],[Preço mercado]], Fiis[#HEADERS], 0)) < INDEX(Fiis[], MATCH(A25, Fiis[Fii], 0), MATCH(Fiis[[#HEADERS],[VP/Cota]], Fiis[#HEADERS], 0)) ), "SIM", "NÃO"), "")} -> SIM | C25: =IFERROR(__xludf.DUMMYFUNCTION("IFERROR(GOOGLEFINANCE(""BVMF:"" & A25),0)"),9.17) -> 9.17
A26: HGRU11 | B26: {=IFERROR(IF(AND( INDEX(Fiis[], MATCH(A26, Fiis[Fii], 0), MATCH(Fiis[[#HEADERS],[Preço mercado]], Fiis[#HEADERS], 0)) < INDEX(Fiis[], MATCH(A26, Fiis[Fii], 0), MATCH(Fiis[[#HEADERS],[Justo]], Fiis[#HEADERS], 0)), INDEX(Fiis[], MATCH(A26, Fiis[Fii], 0), MATCH(Fiis[[#HEADERS],[Preço mercado]], Fiis[#HEADERS], 0)) < INDEX(Fiis[], MATCH(A26, Fiis[Fii], 0), MATCH(Fiis[[#HEADERS],[VP/Cota]], Fiis[#HEADERS], 0)) ), "SIM", "NÃO"), "")} -> SIM | C26: =IFERROR(__xludf.DUMMYFUNCTION("IFERROR(GOOGLEFINANCE(""BVMF:"" & A26),0)"),114.33) -> 114.33
A27: PCIP11 | B27: {=IFERROR(IF(AND( INDEX(Fiis[], MATCH(A27, Fiis[Fii], 0), MATCH(Fiis[[#HEADERS],[Preço mercado]], Fiis[#HEADERS], 0)) < INDEX(Fiis[], MATCH(A27, Fiis[Fii], 0), MATCH(Fiis[[#HEADERS],[Justo]], Fiis[#HEADERS], 0)), INDEX(Fiis[], MATCH(A27, Fiis[Fii], 0), MATCH(Fiis[[#HEADERS],[Preço mercado]], Fiis[#HEADERS], 0)) < INDEX(Fiis[], MATCH(A27, Fiis[Fii], 0), MATCH(Fiis[[#HEADERS],[VP/Cota]], Fiis[#HEADERS], 0)) ), "SIM", "NÃO"), "")} -> SIM | C27: =IFERROR(__xludf.DUMMYFUNCTION("IFERROR(GOOGLEFINANCE(""BVMF:"" & A27),0)"),73.79) -> 73.79
A33: Calculo de Emissao | C33: Preço depois da Emissão | E33: =SUM(C36+(C37*C38))/(1+C37) -> 18.819638
C34: P/VP depois da Emissão | E34: =(C39 + (C38 * C37/100)) / (1 + C37/100) -> 0.017021355
A35: Nome_FIIs | C35: HGBS11
A36: Preço Fechamento | C36: =IFERROR(__xludf.DUMMYFUNCTION("GOOGLEFINANCE(C35)"),18.68) -> 18.68
A37: Percentual de Emissão | C37: 0.0831
A38: Preço da Sub | C38: 20.5
A39: P/VP | C39: {=IFERROR(INDEX(#REF!, MATCH(C42, #REF!, 0), MATCH(#REF!, #REF!, 0)), "")}
A41: Calculadora de Arbitragem | G41: Manual
A42: Nome_Fiis | C42: =C35 -> HGBS11 | G42: Calculadora de Flipagem Para novo P/VP
A43: Qtd_Cota | C43: {=IFERROR(INDEX(Fiis[], MATCH(C42, Fiis[Fii], 0), MATCH(Fiis[[#HEADERS],[QTD]], Fiis[#HEADERS], 0)), "")} -> 20 | G43: Nome_Fiis | I43: =C35 -> HGBS11
A44: %_De_Cota_Emissão | C44: =C37 -> 0.0831 | G44: Qtd_Cota | I44: =C43 -> 20
A45: Direito_QTD_Cota | C45: =ROUNDDOWN(C43*C44,0) -> 1 | G45: %_De_Cota_Emissão | I45: =C37 -> 0.0831
A46: Valor_Mercado | C46: =IFERROR(__xludf.DUMMYFUNCTION("GOOGLEFINANCE(C42)"),18.68) -> 18.68 | G46: Direito_QTD_Cota | I46: =C45 -> 1
A47: Valor_Da_Emissão | C47: =C38 -> 20.5 | G47: Valor_Mercado | I47: =IFERROR(__xludf.DUMMYFUNCTION("GOOGLEFINANCE(I43)"),18.68) -> 18.68
A48: IR | C48: 0.2 | G48: P/VP depois da Emissão | I48: =E34 -> 0.017021355
A49: Valor_IR | C49: =C50*C48 -> -0.364 | G49: P/VP depois da Emissão | I49: 1
A50: Lucro_Bruto | C50: =(C45*C46)-(C45*C47) -> -1.82 | G50: P/VP Desejavel | I50: 0.98
A51: Lucro_Liquido | C51: =C50-C49 -> -1.456 | G51: P/VP Desejavel | I51: =E34*0.98 -> 0.016680928
G52: IR | I52: 0.2
A53: Calculo se Compensa Arbitragem | G53: Valor_IR | I53: =I54*I52 -> 3.7326638
A54: Rendimento | B54: {=IFERROR(INDEX(Fiis[], MATCH(C35, Fiis[Fii], 0), MATCH(Fiis[[#HEADERS],[Div/12]], Fiis[#HEADERS], 0)), "")} -> 0.155 | G54: Lucro_Bruto | I54: =(I46*I47)-(I46*I51) -> 18.663319
A55: Rendimento_2M | B55: =(B54*C45)*2 -> 0.31 | G55: Lucro_Liquido | I55: =I54-I53 -> 14.930655
A56: Lucro | B56: =C51-B55 -> -1.766
A57: Lucro_em_M | B57: =IFERROR(C51/B55,0) -> -4.6967742 | G57: Calculo se Compensa Flipagem
G58: Rendimento | H58: {=IFERROR(INDEX(Fiis[], MATCH(C35, Fiis[Fii], 0), MATCH(Fiis[[#HEADERS],[Div/12]], Fiis[#HEADERS], 0)), "")} -> 0.155
G59: Rendimento_2M | H59: =(H58*I46)*2 -> 0.31
A60: Calculadora Venda de Direito | G60: Lucro | H60: =I55-H59 -> 14.620655
A61: Preço_Direito | B61: 0.2 | G61: Lucro_em_M | H61: =IFERROR(ROUNDDOWN(I55/H59,0),0) -> 48
A62: Qtd_Direito | B62: =C45 -> 1
A63: IR | B63: 0.15
A64: Valor_IR | B64: =B65*B63 -> 0.03
A65: Lucro_Bruto | B65: =B61*B62 -> 0.2
A66: Lucro_Liquido | B66: =B65-B64 -> 0.17
A68: Oque compensa -------------------> | C68: =IF(B66 < B56 , "Arbitragem compensa" , "Venda de Direitos compensa") -> Venda de Direitos compensa

Sheet grafico
A3: ticker | B3: setor | C3: peso | D3: financeiro | F3: Setor | G3: % do total | H3: Total Investido | J3: ticker | K3: setor | L3: peso | M3: financeiro | O3: Setor | P3: % do total | Q3: Total Investido | T3: ticker | U3: setor | V3: peso | W3: financeiro | Y3: Setor | Z3: % do total | AA3: Total Investido
A4: BBAS3 | B4: Banco | C4: =IFERROR((D4/$B$24), 0) -> 0.10065897 | D4: {=IFERROR(INDEX(Ações_Nacionais[], MATCH(A4, Ações_Nacionais[Ação], 0), MATCH(Ações_Nacionais[[#HEADERS],[Financeiro]], Ações_Nacionais[#HEADERS], 0)), "")} -> 630.56 | F4: Banco | G4: =SUMIF(Setores_Ações[setor], "Banco", Setores_Ações[peso]) -> 0.26617255 | H4: =SUMIF(Setores_Ações[setor], "Banco", Setores_Ações[financeiro]) -> 1667.39 | J4: BBAS3 | K4: Banco | L4: =IFERROR((M4/$B$24), 0) -> 0.10718994 | M4: {=IFERROR( INDEX(Ações_Nacionais[], MATCH(J4, Ações_Nacionais[Ação], 0), MATCH(Ações_Nacionais[[#HEADERS],[Peso Ideal]], Ações_Nacionais[#HEADERS], 0)) * $B$26, "")} -> 671.47205 | O4: Banco | P4: =SUMIF(Peso_Ideal_Ações[setor], "Banco", Peso_Ideal_Ações[peso]) -> 0.32156981 | Q4: =SUMIF(Peso_Ideal_Ações[setor], "Banco", Peso_Ideal_Ações[financeiro]) -> 2014.4162 | T4: BBAS3 | U4: Financeiro | V4: =IFERROR((W4/$B$24), 0) -> 0.10718994 | W4: {=IFERROR( INDEX(Ações_Nacionais[], MATCH(T4, Ações_Nacionais[Ação], 0), MATCH(Ações_Nacionais[[#HEADERS],[Peso Ideal]], Ações_Nacionais[#HEADERS], 0)) * $B$26, "")} -> 671.47205 | Y4: Financeiro | Z4: =SUMIF(Peso_Setores_Ideal[setor], "Financeiro", Peso_Setores_Ideal[peso]) -> 0.42875974 | AA4: =SUMIF(Peso_Setores_Ideal[setor], "Financeiro", Peso_Setores_Ideal[financeiro]) -> 2685.8882
A5: BBSE3 | B5: Seguradora | C5: =IFERROR((D5/$B$24), 0) -> 0.22868404 | D5: {=IFERROR(INDEX(Ações_Nacionais[], MATCH(A5, Ações_Nacionais[Ação], 0), MATCH(Ações_Nacionais[[#HEADERS],[Financeiro]], Ações_Nacionais[#HEADERS], 0)), "")} -> 1432.55 | F5: Energia | G5: =SUMIF(Setores_Ações[setor], "Energia", Setores_Ações[peso]) -> 0.20529922 | H5: =SUMIF(Setores_Ações[setor], "Energia", Setores_Ações[financeiro]) -> 1286.06 | J5: BBSE3 | K5: Seguradora | L5: =IFERROR((M5/$B$24), 0) -> 0.10718994 | M5: {=IFERROR( INDEX(Ações_Nacionais[], MATCH(J5, Ações_Nacionais[Ação], 0), MATCH(Ações_Nacionais[[#HEADERS],[Peso Ideal]], Ações_Nacionais[#HEADERS], 0)) * $B$26, "")} -> 671.47205 | O5: Energia | P5: =SUMIF(Peso_Ideal_Ações[setor], "Energia", Peso_Ideal_Ações[peso]) -> 0.21437987 | Q5: =SUMIF(Peso_Ideal_Ações[setor], "Energia", Peso_Ideal_Ações[financeiro]) -> 1342.9441 | T5: BBSE3 | U5: Financeiro | V5: =IFERROR((W5/$B$24), 0) -> 0.10718994 | W5: {=IFERROR( INDEX(Ações_Nacionais[], MATCH(T5, Ações_Nacionais[Ação], 0), MATCH(Ações_Nacionais[[#HEADERS],[Peso Ideal]], Ações_Nacionais[#HEADERS], 0)) * $B$26, "")} -> 671.47205 | Y5: Energia | Z5: =SUMIF(Peso_Setores_Ideal[setor], "Energia", Peso_Setores_Ideal[peso]) -> 0.21437987 | AA5: =SUMIF(Peso_Setores_Ideal[setor], "Energia", Peso_Setores_Ideal[financeiro]) -> 1342.9441
A6: VALE3 | B6: Commodities | C6: =IFERROR((D6/$B$24), 0) -> 0.087059729 | D6: {=IFERROR(INDEX(Ações_Nacionais[], MATCH(A6, Ações_Nacionais[Ação], 0), MATCH(Ações_Nacionais[[#HEADERS],[Financeiro]], Ações_Nacionais[#HEADERS], 0)), "")} -> 545.37 | F6: Cresc. | G6: =SUMIF(Setores_Ações[setor], "Cresc.", Setores_Ações[peso]) -> 0.046945239 | H6: =SUMIF(Setores_Ações[setor], "Cresc.", Setores_Ações[financeiro]) -> 294.08 | J6: VALE3 | K6: Commodities | L6: =IFERROR((M6/$B$24), 0) -> 0.10718994 | M6: {=IFERROR( INDEX(Ações_Nacionais[], MATCH(J6, Ações_Nacionais[Ação], 0), MATCH(Ações_Nacionais[[#HEADERS],[Peso Ideal]], Ações_Nacionais[#HEADERS], 0)) * $B$26, "")} -> 671.47205 | O6: Cresc. | P6: =SUMIF(Peso_Ideal_Ações[setor], "Cresc.", Peso_Ideal_Ações[peso]) -> 0.10718994 | Q6: =SUMIF(Peso_Ideal_Ações[setor], "Cresc.", Peso_Ideal_Ações[financeiro]) -> 671.47205 | T6: VALE3 | U6: Commodities | V6: =IFERROR((W6/$B$24), 0) -> 0.10718994 | W6: {=IFERROR( INDEX(Ações_Nacionais[], MATCH(T6, Ações_Nacionais[Ação], 0), MATCH(Ações_Nacionais[[#HEADERS],[Peso Ideal]], Ações_Nacionais[#HEADERS], 0)) * $B$26, "")} -> 671.47205 | Y6: Commodities | Z6: =SUMIF(Peso_Setores_Ideal[setor], "Commodities", Peso_Setores_Ideal[peso]) -> 0.21437987 | AA6: =SUMIF(Peso_Setores_Ideal[setor], "Commodities", Peso_Setores_Ideal[financeiro]) -> 1342.9441
A7: TAEE11 | B7: Energia | C7: =IFERROR((D7/$B$24), 0) -> 0.11789628 | D7: {=IFERROR(INDEX(Ações_Nacionais[], MATCH(A7, Ações_Nacionais[Ação], 0), MATCH(Ações_Nacionais[[#HEADERS],[Financeiro]], Ações_Nacionais[#HEADERS], 0)), "")} -> 738.54 | F7: Seguradora | G7: =SUMIF(Setores_Ações[setor], "Seguradora", Setores_Ações[peso]) -> 0.22868404 | H7: =SUMIF(Setores_Ações[setor], "Seguradora", Setores_Ações[financeiro]) -> 1432.55 | J7: TAEE11 | K7: Energia | L7: =IFERROR((M7/$B$24), 0) -> 0.10718994 | M7: {=IFERROR( INDEX(Ações_Nacionais[], MATCH(J7, Ações_Nacionais[Ação], 0), MATCH(Ações_Nacionais[[#HEADERS],[Peso Ideal]], Ações_Nacionais[#HEADERS], 0)) * $B$26, "")} -> 671.47205 | O7: Seguradora | P7: =SUMIF(Peso_Ideal_Ações[setor], "Seguradora", Peso_Ideal_Ações[peso]) -> 0.10718994 | Q7: =SUMIF(Peso_Ideal_Ações[setor], "Seguradora", Peso_Ideal_Ações[financeiro]) -> 671.47205 | T7: TAEE11 | U7: Energia | V7: =IFERROR((W7/$B$24), 0) -> 0.10718994 | W7: {=IFERROR( INDEX(Ações_Nacionais[], MATCH(T7, Ações_Nacionais[Ação], 0), MATCH(Ações_Nacionais[[#HEADERS],[Peso Ideal]], Ações_Nacionais[#HEADERS], 0)) * $B$26, "")} -> 671.47205 | Y7: Saneamento | Z7: =SUMIF(Peso_Setores_Ideal[setor], "Saneamento", Peso_Setores_Ideal[peso]) -> 0.10718994 | AA7: =SUMIF(Peso_Setores_Ideal[setor], "Saneamento", Peso_Setores_Ideal[financeiro]) -> 671.47205
A8: ITUB3 | B8: Banco | C8: =IFERROR((D8/$B$24), 0) -> 0.12072021 | D8: {=IFERROR(INDEX(Ações_Nacionais[], MATCH(A8, Ações_Nacionais[Ação], 0), MATCH(Ações_Nacionais[[#HEADERS],[Financeiro]], Ações_Nacionais[#HEADERS], 0)) + INDEX(Ações_Nacionais[], MATCH("ITUB4", Ações_Nacionais[Ação], 0), MATCH(Ações_Nacionais[[#HEADERS],[Financeiro]], Ações_Nacionais[#HEADERS], 0)), "")} -> 756.23 | F8: Saneamento | G8: =SUMIF(Setores_Ações[setor], "Saneamento", Setores_Ações[peso]) -> 0.064421996 | H8: =SUMIF(Setores_Ações[setor], "Saneamento", Setores_Ações[financeiro]) -> 403.56 | J8: ITUB3 | K8: Banco | L8: =IFERROR((M8/$B$24), 0) -> 0.10718994 | M8: {=IFERROR( INDEX(Ações_Nacionais[], MATCH(J8, Ações_Nacionais[Ação], 0), MATCH(Ações_Nacionais[[#HEADERS],[Peso Ideal]], Ações_Nacionais[#HEADERS], 0)) * $B$26, "")} -> 671.47205 | O8: Saneamento | P8: =SUMIF(Peso_Ideal_Ações[setor], "Saneamento", Peso_Ideal_Ações[peso]) -> 0.10718994 | Q8: =SUMIF(Peso_Ideal_Ações[setor], "Saneamento", Peso_Ideal_Ações[financeiro]) -> 671.47205 | T8: ITUB3 | U8: Financeiro | V8: =IFERROR((W8/$B$24), 0) -> 0.10718994 | W8: {=IFERROR( INDEX(Ações_Nacionais[], MATCH(T8, Ações_Nacionais[Ação], 0), MATCH(Ações_Nacionais[[#HEADERS],[Peso Ideal]], Ações_Nacionais[#HEADERS], 0)) * $B$26, "")} -> 671.47205 | Y8: Industria | Z8: =SUMIF(Peso_Setores_Ideal[setor], "Industria", Peso_Setores_Ideal[peso]) -> 0.10718994 | AA8: =SUMIF(Peso_Setores_Ideal[setor], "Industria", Peso_Setores_Ideal[financeiro]) -> 671.47205
A9: PETR4 | B9: Commodities | C9: =IFERROR((D9/$B$24), 0) -> 0.10141723 | D9: {=IFERROR(INDEX(Ações_Nacionais[], MATCH(A9, Ações_Nacionais[Ação], 0), MATCH(Ações_Nacionais[[#HEADERS],[Financeiro]], Ações_Nacionais[#HEADERS], 0)), "")} -> 635.31 | F9: Commodities | G9: =SUMIF(Setores_Ações[setor], "Commodities", Setores_Ações[peso]) -> 0.18847696 | H9: =SUMIF(Setores_Ações[setor], "Commodities", Setores_Ações[financeiro]) -> 1180.68 | J9: PETR4 | K9: Commodities | L9: =IFERROR((M9/$B$24), 0) -> 0.10718994 | M9: {=IFERROR( INDEX(Ações_Nacionais[], MATCH(J9, Ações_Nacionais[Ação], 0), MATCH(Ações_Nacionais[[#HEADERS],[Peso Ideal]], Ações_Nacionais[#HEADERS], 0)) * $B$26, "")} -> 671.47205 | O9: Commodities | P9: =SUMIF(Peso_Ideal_Ações[setor], "Commodities", Peso_Ideal_Ações[peso]) -> 0.21437987 | Q9: =SUMIF(Peso_Ideal_Ações[setor], "Commodities", Peso_Ideal_Ações[financeiro]) -> 1342.9441 | T9: PETR4 | U9: Commodities | V9: =IFERROR((W9/$B$24), 0) -> 0.10718994 | W9: {=IFERROR( INDEX(Ações_Nacionais[], MATCH(T9, Ações_Nacionais[Ação], 0), MATCH(Ações_Nacionais[[#HEADERS],[Peso Ideal]], Ações_Nacionais[#HEADERS], 0)) * $B$26, "")} -> 671.47205
A10: WEGE3 | B10: Cresc. | C10: =IFERROR((D10/$B$24), 0) -> 0.008273843 | D10: {=IFERROR(INDEX(Ações_Nacionais[], MATCH(A10, Ações_Nacionais[Ação], 0), MATCH(Ações_Nacionais[[#HEADERS],[Financeiro]], Ações_Nacionais[#HEADERS], 0)), "")} -> 51.83 | J10: WEGE3 | K10: Cresc. | L10: =IFERROR((M10/$B$24), 0) -> 0.10718994 | M10: {=IFERROR( INDEX(Ações_Nacionais[], MATCH(J10, Ações_Nacionais[Ação], 0), MATCH(Ações_Nacionais[[#HEADERS],[Peso Ideal]], Ações_Nacionais[#HEADERS], 0)) * $B$26, "")} -> 671.47205 | T10: WEGE3 | U10: Industria | V10: =IFERROR((W10/$B$24), 0) -> 0.10718994 | W10: {=IFERROR( INDEX(Ações_Nacionais[], MATCH(T10, Ações_Nacionais[Ação], 0), MATCH(Ações_Nacionais[[#HEADERS],[Peso Ideal]], Ações_Nacionais[#HEADERS], 0)) * $B$26, "")} -> 671.47205
A11: BRBI11 | B11: Cresc. | C11: =IFERROR((D11/$B$24), 0) -> 0.038671396 | D11: {=IFERROR(INDEX(Ações_Nacionais[], MATCH(A11, Ações_Nacionais[Ação], 0), MATCH(Ações_Nacionais[[#HEADERS],[Financeiro]], Ações_Nacionais[#HEADERS], 0)), "")} -> 242.25 | J11: BRBI11 | K11: Cresc. | L11: =IFERROR((M11/$B$24), 0) -> 0 | M11: {=IFERROR( INDEX(Ações_Nacionais[], MATCH(J11, Ações_Nacionais[Ação], 0), MATCH(Ações_Nacionais[[#HEADERS],[Peso Ideal]], Ações_Nacionais[#HEADERS], 0)) * $B$26, "")} -> 0 | T11: BRBI11 | U11: Financeiro | V11: =IFERROR((W11/$B$24), 0) -> 0 | W11: {=IFERROR( INDEX(Ações_Nacionais[], MATCH(T11, Ações_Nacionais[Ação], 0), MATCH(Ações_Nacionais[[#HEADERS],[Peso Ideal]], Ações_Nacionais[#HEADERS], 0)) * $B$26, "")} -> 0
A12: CMIG4 | B12: Energia | C12: =IFERROR((D12/$B$24), 0) -> 0.082977881 | D12: {=IFERROR(INDEX(Ações_Nacionais[], MATCH(A12, Ações_Nacionais[Ação], 0), MATCH(Ações_Nacionais[[#HEADERS],[Financeiro]], Ações_Nacionais[#HEADERS], 0)), "")} -> 519.8 | J12: CMIG4 | K12: Energia | L12: =IFERROR((M12/$B$24), 0) -> 0.10718994 | M12: {=IFERROR( INDEX(Ações_Nacionais[], MATCH(J12, Ações_Nacionais[Ação], 0), MATCH(Ações_Nacionais[[#HEADERS],[Peso Ideal]], Ações_Nacionais[#HEADERS], 0)) * $B$26, "")} -> 671.47205 | T12: CMIG4 | U12: Energia | V12: =IFERROR((W12/$B$24), 0) -> 0.10718994 | W12: {=IFERROR( INDEX(Ações_Nacionais[], MATCH(T12, Ações_Nacionais[Ação], 0), MATCH(Ações_Nacionais[[#HEADERS],[Peso Ideal]], Ações_Nacionais[#HEADERS], 0)) * $B$26, "")} -> 671.47205
A13: ISAE4 | B13: Energia | C13: =IFERROR((D13/$B$24), 0) -> 0.0044250613 | D13: {=IFERROR(INDEX(Ações_Nacionais[], MATCH(A13, Ações_Nacionais[Ação], 0), MATCH(Ações_Nacionais[[#HEADERS],[Financeiro]], Ações_Nacionais[#HEADERS], 0)), "")} -> 27.72 | J13: ISAE4 | K13: Energia | L13: =IFERROR((M13/$B$24), 0) -> 0 | M13: {=IFERROR( INDEX(Ações_Nacionais[], MATCH(J13, Ações_Nacionais[Ação], 0), MATCH(Ações_Nacionais[[#HEADERS],[Peso Ideal]], Ações_Nacionais[#HEADERS], 0)) * $B$26, "")} -> 0 | T13: ISAE4 | U13: Energia | V13: =IFERROR((W13/$B$24), 0) -> 0 | W13: {=IFERROR( INDEX(Ações_Nacionais[], MATCH(T13, Ações_Nacionais[Ação], 0), MATCH(Ações_Nacionais[[#HEADERS],[Peso Ideal]], Ações_Nacionais[#HEADERS], 0)) * $B$26, "")} -> 0
A14: SAPR4 | B14: Saneamento | C14: =IFERROR((D14/$B$24), 0) -> 0.064421996 | D14: {=IFERROR(INDEX(Ações_Nacionais[], MATCH(A14, Ações_Nacionais[Ação], 0), MATCH(Ações_Nacionais[[#HEADERS],[Financeiro]], Ações_Nacionais[#HEADERS], 0)), "")} -> 403.56 | J14: SAPR4 | K14: Saneamento | L14: =IFERROR((M14/$B$24), 0) -> 0.10718994 | M14: {=IFERROR( INDEX(Ações_Nacionais[], MATCH(J14, Ações_Nacionais[Ação], 0), MATCH(Ações_Nacionais[[#HEADERS],[Peso Ideal]], Ações_Nacionais[#HEADERS], 0)) * $B$26, "")} -> 671.47205 | T14: SAPR4 | U14: Saneamento | V14: =IFERROR((W14/$B$24), 0) -> 0.10718994 | W14: {=IFERROR( INDEX(Ações_Nacionais[], MATCH(T14, Ações_Nacionais[Ação], 0), MATCH(Ações_Nacionais[[#HEADERS],[Peso Ideal]], Ações_Nacionais[#HEADERS], 0)) * $B$26, "")} -> 671.47205
A15: ITSA4 | B15: Banco | C15: =IFERROR((D15/$B$24), 0) -> 0.044793369 | D15: {=IFERROR(INDEX(Ações_Nacionais[], MATCH(A15, Ações_Nacionais[Ação], 0), MATCH(Ações_Nacionais[[#HEADERS],[Financeiro]], Ações_Nacionais[#HEADERS], 0)), "")} -> 280.6 | J15: ITSA4 | K15: Banco | L15: =IFERROR((M15/$B$24), 0) -> 0.10718994 | M15: {=IFERROR( INDEX(Ações_Nacionais[], MATCH(J15, Ações_Nacionais[Ação], 0), MATCH(Ações_Nacionais[[#HEADERS],[Peso Ideal]], Ações_Nacionais[#HEADERS], 0)) * $B$26, "")} -> 671.47205 | T15: ITSA4 | U15: Financeiro | V15: =IFERROR((W15/$B$24), 0) -> 0.10718994 | W15: {=IFERROR( INDEX(Ações_Nacionais[], MATCH(T15, Ações_Nacionais[Ação], 0), MATCH(Ações_Nacionais[[#HEADERS],[Peso Ideal]], Ações_Nacionais[#HEADERS], 0)) * $B$26, "")} -> 671.47205
A24: Total Ações | B24: =SUM(HOME!B3) -> 6264.32
A25: Total FIIs | B25: =HOME!B4 -> 5656.11
A26: Total investido | B26: =HOME!B9 -> 16413.761
F29: Sub_Setor | G29: % do Total | H29: Total Investido
A30: ticker | B30: setor | C30: peso | D30: financeiro | F30: Log | G30: =SUMIF(Grafico_Total[setor], F30, Grafico_Total[peso]) -> 0.1543461 | H30: =SUMIF(Grafico_Total[setor], F30, Grafico_Total[financeiro]) -> 2533.4
A31: BBAS3 | B31: Financeiro | C31: =IFERROR((D31/$B$26), 0) -> 0.038416545 | D31: {=IFERROR(INDEX(Ações_Nacionais[], MATCH(A31, Ações_Nacionais[Ação], 0), MATCH(Ações_Nacionais[[#HEADERS],[Financeiro]], Ações_Nacionais[#HEADERS], 0)), "")} -> 630.56 | F31: Shopp | G31: =SUMIF(Grafico_Total[setor], F31, Grafico_Total[peso]) -> 0.060295747 | H31: =SUMIF(Grafico_Total[setor], F31, Grafico_Total[financeiro]) -> 989.68
A32: BBSE3 | B32: Financeiro | C32: =IFERROR((D32/$B$26), 0) -> 0.087277375 | D32: {=IFERROR(INDEX(Ações_Nacionais[], MATCH(A32, Ações_Nacionais[Ação], 0), MATCH(Ações_Nacionais[[#HEADERS],[Financeiro]], Ações_Nacionais[#HEADERS], 0)), "")} -> 1432.55 | F32: NTNB | G32: =SUMIF(Grafico_Total[setor], F32, Grafico_Total[peso]) -> 0.018750888 | H32: =SUMIF(Grafico_Total[setor], F32, Grafico_Total[financeiro]) -> 307.7726
A33: VALE3 | B33: Commodities | C33: =IFERROR((D33/$B$26), 0) -> 0.033226388 | D33: {=IFERROR(INDEX(Ações_Nacionais[], MATCH(A33, Ações_Nacionais[Ação], 0), MATCH(Ações_Nacionais[[#HEADERS],[Financeiro]], Ações_Nacionais[#HEADERS], 0)), "")} -> 545.37 | F33: Renda_Urbana | G33: =SUMIF(Grafico_Total[setor], F33, Grafico_Total[peso]) -> 0.10429054 | H33: =SUMIF(Grafico_Total[setor], F33, Grafico_Total[financeiro]) -> 1711.8
A34: TAEE11 | B34: Energia | C34: =IFERROR((D34/$B$26), 0) -> 0.044995171 | D34: {=IFERROR(INDEX(Ações_Nacionais[], MATCH(A34, Ações_Nacionais[Ação], 0), MATCH(Ações_Nacionais[[#HEADERS],[Financeiro]], Ações_Nacionais[#HEADERS], 0)), "")} -> 738.54 | F34: Papel | G34: =SUMIF(Grafico_Total[setor], F34, Grafico_Total[peso]) -> 0.011732229 | H34: =SUMIF(Grafico_Total[setor], F34, Grafico_Total[financeiro]) -> 192.57
A35: ITUB3 | B35: Financeiro | C35: =IFERROR((D35/$B$26), 0) -> 0.0028006987 | D35: {=IFERROR(INDEX(Ações_Nacionais[], MATCH(A35, Ações_Nacionais[Ação], 0), MATCH(Ações_Nacionais[[#HEADERS],[Financeiro]], Ações_Nacionais[#HEADERS], 0)), "")} -> 45.97 | F35: Financeiro | G35: =SUMIF(Grafico_Total[setor], F35, Grafico_Total[peso]) -> 0.14325358 | H35: =SUMIF(Grafico_Total[setor], F35, Grafico_Total[financeiro]) -> 2351.33
A36: PETR4 | B36: Commodities | C36: =IFERROR((D36/$B$26), 0) -> 0.038705936 | D36: {=IFERROR(INDEX(Ações_Nacionais[], MATCH(A36, Ações_Nacionais[Ação], 0), MATCH(Ações_Nacionais[[#HEADERS],[Financeiro]], Ações_Nacionais[#HEADERS], 0)), "")} -> 635.31 | F36: Energia | G36: =SUMIF(Grafico_Total[setor], F36, Grafico_Total[peso]) -> 0.078352547 | H36: =SUMIF(Grafico_Total[setor], F36, Grafico_Total[financeiro]) -> 1286.06
A37: WEGE3 | B37: Industria | C37: =IFERROR((D37/$B$26), 0) -> 0.0031577162 | D37: {=IFERROR(INDEX(Ações_Nacionais[], MATCH(A37, Ações_Nacionais[Ação], 0), MATCH(Ações_Nacionais[[#HEADERS],[Financeiro]], Ações_Nacionais[#HEADERS], 0)), "")} -> 51.83 | F37: Commodities | G37: =SUMIF(Grafico_Total[setor], F37, Grafico_Total[peso]) -> 0.071932324 | H37: =SUMIF(Grafico_Total[setor], F37, Grafico_Total[financeiro]) -> 1180.68
A38: BRBI11 | B38: Financeiro | C38: =IFERROR((D38/$B$26), 0) -> 0.014758957 | D38: {=IFERROR(INDEX(Ações_Nacionais[], MATCH(A38, Ações_Nacionais[Ação], 0), MATCH(Ações_Nacionais[[#HEADERS],[Financeiro]], Ações_Nacionais[#HEADERS], 0)), "")} -> 242.25 | F38: Saneamento | G38: =SUMIF(Grafico_Total[setor], F38, Grafico_Total[peso]) -> 0.024586686 | H38: =SUMIF(Grafico_Total[setor], F38, Grafico_Total[financeiro]) -> 403.56
A39: CMIG4 | B39: Energia | C39: =IFERROR((D39/$B$26), 0) -> 0.031668549 | D39: {=IFERROR(INDEX(Ações_Nacionais[], MATCH(A39, Ações_Nacionais[Ação], 0), MATCH(Ações_Nacionais[[#HEADERS],[Financeiro]], Ações_Nacionais[#HEADERS], 0)), "")} -> 519.8 | F39: Industria | G39: =SUMIF(Grafico_Total[setor], F39, Grafico_Total[peso]) -> 0.0031577162 | H39: =SUMIF(Grafico_Total[setor], F39, Grafico_Total[financeiro]) -> 51.83
A40: ISAE4 | B40: Energia | C40: =IFERROR((D40/$B$26), 0) -> 0.0016888268 | D40: {=IFERROR(INDEX(Ações_Nacionais[], MATCH(A40, Ações_Nacionais[Ação], 0), MATCH(Ações_Nacionais[[#HEADERS],[Financeiro]], Ações_Nacionais[#HEADERS], 0)), "")} -> 27.72 | F40: Renda_Fixa | G40: =SUMIF(Grafico_Total[setor], F40, Grafico_Total[peso]) -> 0.08705414 | H40: =SUMIF(Grafico_Total[setor], F40, Grafico_Total[financeiro]) -> 1428.8859
A41: SAPR4 | B41: Saneamento | C41: =IFERROR((D41/$B$26), 0) -> 0.024586686 | D41: {=IFERROR(INDEX(Ações_Nacionais[], MATCH(A41, Ações_Nacionais[Ação], 0), MATCH(Ações_Nacionais[[#HEADERS],[Financeiro]], Ações_Nacionais[#HEADERS], 0)), "")} -> 403.56 | F41: Internacional | G41: =SUMIF(Grafico_Total[setor], F41, Grafico_Total[peso]) -> 0.14153047 | H41: =SUMIF(Grafico_Total[setor], F41, Grafico_Total[financeiro]) -> 2323.0474
A42: XPLG11 | B42: Log | C42: =IFERROR((D42/$B$26), 0) -> 0.044640591 | D42: {=IFERROR(INDEX(Fiis[], MATCH(A42, Fiis[Fii], 0), MATCH(Fiis[[#HEADERS],[Financeiro]], Fiis[#HEADERS], 0)), "")} -> 732.72 | F42: Cripto | G42: =SUMIF(Grafico_Total[setor], F42, Grafico_Total[peso]) -> 0.026418408 | H42: =SUMIF(Grafico_Total[setor], F42, Grafico_Total[financeiro]) -> 433.62544
A43: HGBS11 | B43: Shopp | C43: =IFERROR((D43/$B$26), 0) -> 0.022761389 | D43: {=IFERROR(INDEX(Fiis[], MATCH(A43, Fiis[Fii], 0), MATCH(Fiis[[#HEADERS],[Financeiro]], Fiis[#HEADERS], 0)), "")} -> 373.6
A44: Tesouro Renda | B44: NTNB | C44: =IFERROR((D44/$B$26), 0) -> 0.018750888 | D44: {=IFERROR(INDEX(Carteira[], MATCH(A44, Carteira[Tipo], 0), MATCH(Carteira[[#HEADERS],[Capital]], Carteira[#HEADERS], 0)), "")} -> 307.7726
A45: BRCO11 | B45: Log | C45: =IFERROR((D45/$B$26), 0) -> 0.020132497 | D45: {=IFERROR(INDEX(Fiis[], MATCH(A45, Fiis[Fii], 0), MATCH(Fiis[[#HEADERS],[Financeiro]], Fiis[#HEADERS], 0)), "")} -> 330.45
A46: HGLG11 | B46: Log | C46: =IFERROR((D46/$B$26), 0) -> 0 | D46: {=IFERROR(INDEX(Fiis[], MATCH(A46, Fiis[Fii], 0), MATCH(Fiis[[#HEADERS],[Financeiro]], Fiis[#HEADERS], 0)), "")} -> 0
A47: LVBI11 | B47: Log | C47: =IFERROR((D47/$B$26), 0) -> 0.065147164 | D47: {=IFERROR(INDEX(Fiis[], MATCH(A47, Fiis[Fii], 0), MATCH(Fiis[[#HEADERS],[Financeiro]], Fiis[#HEADERS], 0)), "")} -> 1069.31
A48: BTLG11 | B48: Log | C48: =IFERROR((D48/$B$26), 0) -> 0.024425846 | D48: {=IFERROR(INDEX(Fiis[], MATCH(A48, Fiis[Fii], 0), MATCH(Fiis[[#HEADERS],[Financeiro]], Fiis[#HEADERS], 0)), "")} -> 400.92
A49: GGRC11 | B49: Renda_Urbana | C49: =IFERROR((D49/$B$26), 0) -> 0.059766922 | D49: {=IFERROR(INDEX(Fiis[], MATCH(A49, Fiis[Fii], 0), MATCH(Fiis[[#HEADERS],[Financeiro]], Fiis[#HEADERS], 0)), "")} -> 981
A50: GARE11 | B50: Renda_Urbana | C50: =IFERROR((D50/$B$26), 0) -> 0.044523616 | D50: {=IFERROR(INDEX(Fiis[], MATCH(A50, Fiis[Fii], 0), MATCH(Fiis[[#HEADERS],[Financeiro]], Fiis[#HEADERS], 0)), "")} -> 730.8
A51: PMLL11 | B51: Shopp | C51: =IFERROR((D51/$B$26), 0) -> 0.037534358 | D51: {=IFERROR(INDEX(Fiis[], MATCH(A51, Fiis[Fii], 0), MATCH(Fiis[[#HEADERS],[Financeiro]], Fiis[#HEADERS], 0)), "")} -> 616.08
C52: =IFERROR((D52/$B$26), 0) -> 0
A53: MXRF11 | B53: Papel | C53: =IFERROR((D53/$B$26), 0) -> 0.011732229 | D53: {=IFERROR(INDEX(Fiis[], MATCH(A53, Fiis[Fii], 0), MATCH(Fiis[[#HEADERS],[Financeiro]], Fiis[#HEADERS], 0)), "")} -> 192.57
A54: Renda_Fixa | B54: Renda_Fixa | C54: =IFERROR((D54/$B$26), 0) -> 0.08705414 | D54: {=IFERROR(INDEX(Carteira[], MATCH(A54, Carteira[Tipo], 0), MATCH(Carteira[[#HEADERS],[Capital]], Carteira[#HEADERS], 0)), "")} -> 1428.8859
A55: Etfs | B55: Internacional | C55: =IFERROR((D55/$B$26), 0) -> 0.14153047 | D55: {=IFERROR(INDEX(Carteira[], MATCH(A55, Carteira[Tipo], 0), MATCH(Carteira[[#HEADERS],[Capital]], Carteira[#HEADERS], 0)), "")} -> 2323.0474
A56: Cripto | B56: Cripto | C56: =IFERROR((D56/$B$26), 0) -> 0.026418408 | D56: {=IFERROR(INDEX(Carteira[], MATCH(A56, Carteira[Tipo], 0), MATCH(Carteira[[#HEADERS],[Capital]], Carteira[#HEADERS], 0)), "")} -> 433.62544
A60: Fundo | B60: Segmento | C60: Classificação de Risco | D60: Qtidade Cotas Atual | E60: Cotação Atual | F60: Saldo Atual | G60: Posição
A61: GGRC11 | B61: Logística | C61: Oportunidade | D61: {=IFERROR(INDEX(Fiis[], MATCH(A61, Fiis[Fii], 0), MATCH(Fiis[[#HEADERS],[QTD]], Fiis[#HEADERS], 0)), "")} -> 109 | E61: =IFERROR(__xludf.DUMMYFUNCTION("GOOGLEFINANCE(A61)"),9.0) -> 9 | F61: =D61*E61 -> 981 | G61: =IFERROR((F61/grafico!$B$25), 0) -> 0.17344076
A62: LVBI11 | B62: Logística | C62: Ancoragem | D62: {=IFERROR(INDEX(Fiis[], MATCH(A62, Fiis[Fii], 0), MATCH(Fiis[[#HEADERS],[QTD]], Fiis[#HEADERS], 0)), "")} -> 11 | E62: =IFERROR(__xludf.DUMMYFUNCTION("GOOGLEFINANCE(A62)"),97.21) -> 97.21 | F62: =D62*E62 -> 1069.31 | G62: =IFERROR((F62/grafico!$B$25), 0) -> 0.18905396
A63: GARE11 | B63: Renda Urb/Log | C63: Oportunidade | D63: {=IFERROR(INDEX(Fiis[], MATCH(A63, Fiis[Fii], 0), MATCH(Fiis[[#HEADERS],[QTD]], Fiis[#HEADERS], 0)), "")} -> 87 | E63: =IFERROR(__xludf.DUMMYFUNCTION("GOOGLEFINANCE(A63)"),8.4) -> 8.4 | F63: =D63*E63 -> 730.8 | G63: =IFERROR((F63/grafico!$B$25), 0) -> 0.12920541
A64: XPLG11 | B64: Logística | C64: Oportunidade | D64: {=IFERROR(INDEX(Fiis[], MATCH(A64, Fiis[Fii], 0), MATCH(Fiis[[#HEADERS],[QTD]], Fiis[#HEADERS], 0)), "")} -> 8 | E64: =IFERROR(__xludf.DUMMYFUNCTION("GOOGLEFINANCE(A64)"),91.59) -> 91.59 | F64: =D64*E64 -> 732.72 | G64: =IFERROR((F64/grafico!$B$25), 0) -> 0.12954486
A65: PMLL11 | B65: Shoppings | C65: Oportunidade | D65: {=IFERROR(INDEX(Fiis[], MATCH(A65, Fiis[Fii], 0), MATCH(Fiis[[#HEADERS],[QTD]], Fiis[#HEADERS], 0)), "")} -> 6 | E65: =IFERROR(__xludf.DUMMYFUNCTION("GOOGLEFINANCE(A65)"),102.68) -> 102.68 | F65: =D65*E65 -> 616.08 | G65: =IFERROR((F65/grafico!$B$25), 0) -> 0.10892292
A66: BTLG11 | B66: Logística | C66: Ancoragem | D66: {=IFERROR(INDEX(Fiis[], MATCH(A66, Fiis[Fii], 0), MATCH(Fiis[[#HEADERS],[QTD]], Fiis[#HEADERS], 0)), "")} -> 4 | E66: =IFERROR(__xludf.DUMMYFUNCTION("GOOGLEFINANCE(A66)"),100.23) -> 100.23 | F66: =D66*E66 -> 400.92 | G66: =IFERROR((F66/grafico!$B$25), 0) -> 0.070882638
A67: HGBS11 | B67: Shoppings | C67: Oportunidade | D67: {=IFERROR(INDEX(Fiis[], MATCH(A67, Fiis[Fii], 0), MATCH(Fiis[[#HEADERS],[QTD]], Fiis[#HEADERS], 0)), "")} -> 20 | E67: =IFERROR(__xludf.DUMMYFUNCTION("GOOGLEFINANCE(A67)"),18.68) -> 18.68 | F67: =D67*E67 -> 373.6 | G67: =IFERROR((F67/grafico!$B$25), 0) -> 0.066052464
A68: BRCO11 | B68: Logística | C68: Oportunidade | D68: {=IFERROR(INDEX(Fiis[], MATCH(A68, Fiis[Fii], 0), MATCH(Fiis[[#HEADERS],[QTD]], Fiis[#HEADERS], 0)), "")} -> 3 | E68: =IFERROR(__xludf.DUMMYFUNCTION("GOOGLEFINANCE(A68)"),110.15) -> 110.15 | F68: =D68*E68 -> 330.45 | G68: =IFERROR((F68/grafico!$B$25), 0) -> 0.058423546
A69: MXRF11 | B69: CRI | C69: Ancoragem | D69: {=IFERROR(INDEX(Fiis[], MATCH(A69, Fiis[Fii], 0), MATCH(Fiis[[#HEADERS],[QTD]], Fiis[#HEADERS], 0)), "")} -> 21 | E69: =IFERROR(__xludf.DUMMYFUNCTION("GOOGLEFINANCE(A69)"),9.17) -> 9.17 | F69: =D69*E69 -> 192.57 | G69: =IFERROR((F69/grafico!$B$25), 0) -> 0.034046368
A70: HGLG11 | B70: Logística | C70: Oportunidade | D70: {=IFERROR(INDEX(Fiis[], MATCH(A70, Fiis[Fii], 0), MATCH(Fiis[[#HEADERS],[QTD]], Fiis[#HEADERS], 0)), "")} -> 0 | E70: =IFERROR(__xludf.DUMMYFUNCTION("GOOGLEFINANCE(A70)"),146.45) -> 146.45 | F70: =D70*E70 -> 0 | G70: =IFERROR((F70/grafico!$B$25), 0) -> 0
A71: KNRI11 | B71: Lajes/Log | C71: Ancoragem | D71: {=IFERROR(INDEX(Fiis[], MATCH(A71, Fiis[Fii], 0), MATCH(Fiis[[#HEADERS],[QTD]], Fiis[#HEADERS], 0)), "")} -> 0 | E71: =IFERROR(__xludf.DUMMYFUNCTION("GOOGLEFINANCE(A71)"),157.0) -> 157 | F71: =D71*E71 -> 0 | G71: =IFERROR((F71/grafico!$B$25), 0) -> 0
A72: HGRU11 | B72: Renda Urbana | C72: Ancoragem | D72: {=IFERROR(INDEX(Fiis[], MATCH(A72, Fiis[Fii], 0), MATCH(Fiis[[#HEADERS],[QTD]], Fiis[#HEADERS], 0)), "")} -> 2 | E72: =IFERROR(__xludf.DUMMYFUNCTION("GOOGLEFINANCE(A72)"),114.33) -> 114.33 | F72: =D72*E72 -> 228.66 | G72: =IFERROR((F72/grafico!$B$25), 0) -> 0.040427078
A73: PCIP11 | B73: CRI | C73: Oportunidade | D73: {=IFERROR(INDEX(Fiis[], MATCH(A73, Fiis[Fii], 0), MATCH(Fiis[[#HEADERS],[QTD]], Fiis[#HEADERS], 0)), "")} -> 0 | E73: =IFERROR(__xludf.DUMMYFUNCTION("GOOGLEFINANCE(A73)"),73.79) -> 73.79 | F73: =D73*E73 -> 0 | G73: =IFERROR((F73/grafico!$B$25), 0) -> 0

Sheet FERIADOS
A1: 45658
A2: 45719
A3: 45720
A4: 45765
A5: 45767
A6: 45768
A7: 45778
A8: 45827
A9: 45907
A10: 45942
A11: 45963
A12: 45976
... A42: 46746

Sheet Status_Script
A1: Nome | B1: Status | C1: Data/Hora
A4: Selic_IPCA | B4: OK ✅ | C4: 46268.443
A5: Titulos_IPCA | B5: OK ✅ | C5: 46275.456
A6: Feriados | B6: OK ✅ | C6: 46267.882
