Workbook

Sheet CMIG4
A1: | | B1: Feito | C1: 46058 | D1: Atual | E1: 46247 | F1: Não | G1: 46058 | H1: Não | I1: 46058 | J1: Ultimo_Balanco | K1: {=IFERROR(INDEX(Indicador_Ações[], MATCH($J$2, Indicador_Ações[Stock], 0), MATCH(Indicador_Ações[[#HEADERS],[ult_balanco_processado]], Indicador_Ações[#HEADERS], 0)),"")} -> 46203
A2: Balanço Patrimonial Anual | J2: CMIG4 | K2: =IFERROR(__xludf.DUMMYFUNCTION("(GOOGLEFINANCE(""BVMF:"" & J2))"),11.28) -> 11.28 | L2: {=IFERROR(INDEX(Indicador_Ações[], MATCH($J$2, Indicador_Ações[Stock], 0), MATCH(Indicador_Ações[[#HEADERS],[qtd_acao]], Indicador_Ações[#HEADERS], 0)),"")} -> 2861780000 | M2: Numero_Papel
A3: Ano | B3: 1_T | C3: AH% (2/1) | D3: 2_T | E3: AH% (3/2) | F3: 3_T | G3: AH% (4/3) | H3: 4_T | J3: BP | K3: 1000 | L3: =IFERROR(K22/K14,0) -> 0.089136821 | M3: Margem_Liquida_Ajustada | N3: DMPL Acumulado
A4: Ativo Total | B4: =B5+B6 -> 68174293 | C4: =IFERROR(SUM((D4/B4)-1),0) -> 0.039413038 | D4: =D5+D6 -> 70861249 | E4: =IFERROR(SUM((F4/D4)-1),0) -> -0.08624045 | F4: =F5+F6 -> 64750143 | G4: =IFERROR(SUM((H4/F4)-1),0) -> 0.035180355 | H4: =H5+H6 -> 67028076 | J4: Ativo | K4: {=IFERROR(INDEX(Indicador_Ações[], MATCH($J$2, Indicador_Ações[Stock], 0), MATCH(Indicador_Ações[[#HEADERS],[ativo]], Indicador_Ações[#HEADERS], 0)),"")} -> 70861300000 | L4: =IFERROR(K19/K14,0) -> 0.16436566 | M4: MARGEM BRUTA | N4: JCP acionistas Liquido | O4: 657957
A5: Ativo Circulante | B5: 14417420 | C5: =IFERROR(SUM((D5/B5)-1),0) -> 0.090381289 | D5: 15720485 | E5: =IFERROR(SUM((F5/D5)-1),0) -> -0.15736951 | F5: 13246560 | G5: =IFERROR(SUM((H5/F5)-1),0) -> 0.093097982 | H5: 14479788 | J5: Valor_de_mercado | K5: =K2*L2 -> 32280878400 | L5: =IFERROR(K16/K14,0) -> 0.13740098 | M5: MARGEM EBIT | N5: Dividendos | O5: 0
A6: Ativo Nao Circ. | B6: 53756873 | C6: =IFERROR(SUM((D6/B6)-1),0) -> 0.025743517 | D6: 55140764 | E6: =IFERROR(SUM((F6/D6)-1),0) -> -0.065961745 | F6: 51503583 | G6: =IFERROR(SUM((H6/F6)-1),0) -> 0.020284123 | H6: 52548288 | J6: Valor_da_firma | K6: =SUM(K5,K10) -> 51551468400 | L6: =IFERROR(K17/K14,0) -> 0.19372224 | M6: MARGEM_EBITDA_Ajustada | N6: Dividendos e JCP | O6: =SUM(O4:O5) -> 657957
J7: Disponibilidade | K7: {=IFERROR(INDEX(Indicador_Ações[], MATCH($J$2, Indicador_Ações[Stock], 0), MATCH(Indicador_Ações[[#HEADERS],[disponibilidades]], Indicador_Ações[#HEADERS], 0)),"")} -> 3082110000 | L7: =K22/L2 -> 1.3623689 | M7: LPA_Ajustado | N7: Aliquota | O7: =ABS(SUM(B67,D67,F67,H67)/SUM(B66,D66,F66,H66)) -> 0.10938791
A8: Estoque | B8: 0 | C8: =IFERROR(SUM((D8/B8)-1),0) -> 0 | D8: 0 | E8: =IFERROR(SUM((F8/D8)-1),0) -> 0 | F8: 0 | G8: =IFERROR(SUM((H8/F8)-1),0) -> 0 | H8: 0 | J8: Patrimônio líq | K8: {=IFERROR(INDEX(Indicador_Ações[], MATCH($J$2, Indicador_Ações[Stock], 0), MATCH(Indicador_Ações[[#HEADERS],[patrimonio_liquido]], Indicador_Ações[#HEADERS], 0)),"")} -> 29181600000 | L8: {=IFERROR(INDEX(O6*K3,0)/L2,"")} -> 0.2299118 | M8: DPA Liquido | N8: NOPAT | O8: =K16*(1-O7) -> 5352445083
A9: Caixa | B9: 1377560 | C9: =IFERROR(SUM((D9/B9)-1),0) -> 0.56972909 | D9: 2162396 | E9: =IFERROR(SUM((F9/D9)-1),0) -> -0.32866875 | F9: 1451684 | G9: =IFERROR(SUM((H9/F9)-1),0) -> 0.30995175 | H9: 1901636 | J9: Dívida bruta | K9: {=IFERROR(INDEX(Indicador_Ações[], MATCH($J$2, Indicador_Ações[Stock], 0), MATCH(Indicador_Ações[[#HEADERS],[divida_bruta]], Indicador_Ações[#HEADERS], 0)),"")} -> 22352700000 | L9: =IFERROR(L8/L7,0) -> 0.16875885 | M9: Payout_Ajustado
A10: Títulos e valores mobiliários | B10: 414962 | C10: =IFERROR(SUM((D10/B10)-1),0) -> 1.2163788 | D10: 919713 | E10: =IFERROR(SUM((F10/D10)-1),0) -> -0.059098871 | F10: 865359 | G10: =IFERROR(SUM((H10/F10)-1),0) -> -0.12209615 | H10: 759702 | J10: Dívida líq | K10: =K9-K7 -> 19270590000 | L10: =IFERROR(K14/K4,0) -> 0.61725512 | M10: GIRO ATIVOS
A11: Disponibilidades | B11: =SUM(B9,B10) -> 1792522 | C11: =IFERROR(SUM((D11/B11)-1),0) -> 0.71942604 | D11: =SUM(D9,D10) -> 3082109 | E11: =IFERROR(SUM((F11/D11)-1),0) -> -0.24822808 | F11: =SUM(F9,F10) -> 2317043 | G11: =IFERROR(SUM((H11/F11)-1),0) -> 0.14859241 | H11: =SUM(H9,H10) -> 2661338 | J11: Capital_Investido | K11: =SUM(K8,K9) -> 51534300000 | L11: =IFERROR(K22/K8,0) -> 0.13360474 | M11: ROE
J12: Razão de Divida | K12: =K9/K11 -> 0.43374413 | L12: =O8/K11 -> 0.1038618 | M12: ROIC
A13: Passivo Total | B13: =SUM(B14+B15) -> 39280917 | C13: =IFERROR(SUM((D13/B13)-1),0) -> 0.060950181 | D13: =SUM(D14+D15) -> 41675096 | E13: =IFERROR(SUM((F13/D13)-1),0) -> -0.13580321 | F13: =SUM(F14+F15) -> 36015484 | G13: =IFERROR(SUM((H13/F13)-1),0) -> 0.067495664 | H13: =SUM(H14+H15) -> 38446373 | J13: DRE | L13: =IFERROR(K22/K4,0) -> 0.055020159 | M13: ROA
A14: Passivo Circ. | B14: 15478646 | C14: =IFERROR(SUM((D14/B14)-1),0) -> -0.13019511 | D14: 13463402 | E14: =IFERROR(SUM((F14/D14)-1),0) -> 0.10548693 | F14: 14883615 | G14: =IFERROR(SUM((H14/F14)-1),0) -> -0.02829353 | H14: 14462505 | J14: Receita_Liquida | K14: {=IFERROR(INDEX(Indicador_Ações[], MATCH($J$2, Indicador_Ações[Stock], 0), MATCH(Indicador_Ações[[#HEADERS],[receita_liquida_12m]], Indicador_Ações[#HEADERS], 0)),"")} -> 43739500000 | L14: =K6/K17 -> 6.0839795 | M14: EV/EBITDA
A15: Passivo Não Circ. | B15: 23802271 | C15: =IFERROR(SUM((D15/B15)-1),0) -> 0.1852522 | D15: 28211694 | E15: =IFERROR(SUM((F15/D15)-1),0) -> -0.25095356 | F15: 21131869 | G15: =IFERROR(SUM((H15/F15)-1),0) -> 0.13496199 | H15: 23983868 | J15: Cagr_receita_5a | K15: {=IFERROR(INDEX(Indicador_Ações[], MATCH($J$2, Indicador_Ações[Stock], 0), MATCH(Indicador_Ações[[#HEADERS],[cagr_receita_5a]], Indicador_Ações[#HEADERS], 0)),"")} -> 6.1 | L15: =K17/K6 -> 0.1643661 | M15: Earnings_Yield_Greenblatt
A16: Emprést. CP | B16: 3083137 | C16: =IFERROR(SUM((D16/B16)-1),0) -> -0.5072616 | D16: 1519180 | E16: =IFERROR(SUM((F16/D16)-1),0) -> 0.96314525 | F16: 2982371 | G16: =IFERROR(SUM((H16/F16)-1),0) -> 0.023227157 | H16: 3051643 | J16: EBIT | K16: {=IFERROR(INDEX(Indicador_Ações[], MATCH($J$2, Indicador_Ações[Stock], 0), MATCH(Indicador_Ações[[#HEADERS],[ebit_12m]], Indicador_Ações[#HEADERS], 0)),"")} -> 6009850000 | L16: =IFERROR(K10/K17,0) -> 2.2742684 | M16: DÍVIDA LÍQUIDA / EBITDA Ajustado
A17: Emprést. LP | B17: 16527380 | C17: =IFERROR(SUM((D17/B17)-1),0) -> 0.26054638 | D17: 20833529 | E17: =IFERROR(SUM((F17/D17)-1),0) -> -0.40341274 | F17: 12429018 | G17: =IFERROR(SUM((H17/F17)-1),0) -> 0.32059411 | H17: 16413688 | J17: EBITDA Ajustado | K17: =SUM(B70,D70,F70,H70)*K3 -> 8473314000 | L17: =IFERROR(SUM(B5,D5,F5,H5)/SUM(B14,D14,F14,H14),0) -> 0.99272725 | M17: LIQUIDEZ CORRENTE_Media
J18: Custo_Mercadoria | K18: =SUM(B33,D33,F33,H33)*1000 -> -36550266000 | L18: =IFERROR(SUM(B58,D58,F58,H58)/ABS(SUM(B61,D61,F61,H61)),0) -> 2.4898526 | M18: Indice de Cobertura de Juros MEDIA
A19: ENDIVIDAMENTO / CAIXA | J19: Lucro bruto | K19: =IFERROR(SUM(B44,D44,F44,H44),"")*1000 -> 7189272000 | L19: =IFERROR(K4/K8,0) -> 2.428287 | M19: Alavancagem_Financeira
A20: Dívida bruta | B20: =SUM(B17,B16) -> 19610517 | C20: =IFERROR(SUM((D20/B20)-1),0) -> 0.13983272 | D20: =SUM(D17,D16) -> 22352709 | E20: =IFERROR(SUM((F20/D20)-1),0) -> -0.31053596 | F20: =SUM(F17,F16) -> 15411389 | G20: =IFERROR(SUM((H20/F20)-1),0) -> 0.26304845 | H20: =SUM(H17,H16) -> 19465331 | J20: Despesas operacionais | K20: =IFERROR(SUM(B55,D55,F55,H55),"")*1000 -> -551913000 | L20: =K10/K8 -> 0.66036783 | M20: DL/PL
A21: Dívida líq | B21: =SUM(B20-B11) -> 17817995 | C21: =IFERROR(SUM((D21/B21)-1),0) -> 0.081524605 | D21: =SUM(D20-D11) -> 19270600 | E21: =IFERROR(SUM((F21/D21)-1),0) -> -0.32050139 | F21: =SUM(F20-F11) -> 13094346 | G21: =IFERROR(SUM((H21/F21)-1),0) -> 0.28330143 | H21: =SUM(H20-H11) -> 16803993 | J21: Inflação | K21: ='Indicadores_Ações'!$B$4 -> 0.044430246 | M21: CPM
J22: Lucro_Anual_Ajustado | K22: =SUM(B71,D71,F71,H71)*1000000 -> 3898800000 | L22: ='Indicadores_Ações'!$B$3 -> 0.139 | M22: RF
A23: Patrimônio líq. | B23: =B4-B13 -> 28893376 | C23: =IFERROR(SUM((D23/B23)-1),0) -> 0.010133015 | D23: =D4-D13 -> 29186153 | E23: =IFERROR(SUM((F23/D23)-1),0) -> -0.015469459 | F23: =F4-F13 -> 28734659 | G23: =IFERROR(SUM((H23/F23)-1),0) -> -0.0053230491 | H23: =H4-H13 -> 28581703 | J23: Lucro_Liquido_Fundamentus | K23: {=IFERROR(INDEX(Indicador_Ações[], MATCH($J$2, Indicador_Ações[Stock], 0), MATCH(Indicador_Ações[[#HEADERS],[lucro_liquido_12m]], Indicador_Ações[#HEADERS], 0)),"")} -> 4595100000 | L23: =K24 -> 0.91 | M23: Beta (B)
J24: Beta | K24: {=IFERROR(INDEX(Indicador_Ações[], MATCH($J$2, Indicador_Ações[Stock], 0), MATCH(Indicador_Ações[[#HEADERS],[beta_ibov_3a]], Indicador_Ações[#HEADERS], 0)),"")} -> 0.91 | L24: =L22+0.02 -> 0.159 | M24: RM
A25: Reserva de Capital | B25: 393093 | C25: =IFERROR(SUM((D25/B25)-1),0) -> 0 | D25: 393093 | E25: =IFERROR(SUM((F25/D25)-1),0) -> 0 | F25: 393093 | G25: =IFERROR(SUM((H25/F25)-1),0) -> 0 | H25: 393093 | L25: =L22+L23*(L24-L22) -> 0.1572 | M25: KE
A26: Reserva de Lucro | B26: 14217595 | C26: =IFERROR(SUM((D26/B26)-1),0) -> 0 | D26: 14217595 | E26: =IFERROR(SUM((F26/D26)-1),0) -> -0.045151589 | F26: 13575648 | G26: =IFERROR(SUM((H26/F26)-1),0) -> 0.047286656 | H26: 14217595
A27: Lucro ou Prejuizo Acumulados | B27: 323712 | C27: =IFERROR(SUM((D27/B27)-1),0) -> 0.97121207 | D27: 638105 | E27: =IFERROR(SUM((F27/D27)-1),0) -> 1.0206126 | F27: 1289363 | G27: =IFERROR(SUM((H27/F27)-1),0) -> -1 | H27: 0 | J27: Ticker | K27: Valores | L27: Ano | M27: VLF | N27: VLP | O27: Cresc
J28: Preço_Mercado | K28: =K2 -> 11.28 | L28: 1 | M28: =K33 -> 3898800000 | O28: 5 | Q28: Ano | R28: Fluxo
A29: DRE Analise Trimestral | J29: Numero_Papel | K29: =L2 -> 2861780000 | L29: 2 | M29: =M28*(1+O28/100) -> 4093740000 | N29: =M29/(1+K34)^L28 -> 3537625302 | O29: 5 | Q29: 0 | R29: =-K6 -> -51551468400
A30: Trimestre | B30: 1_T | C30: AH% (2/1) | D30: 2_T | E30: AH% (3/2) | F30: 3_T | G30: AH% (4/3) | H30: 4_T | J30: Market | K30: =K5 -> 32280878400 | L30: 3 | M30: =M29*(1+O29/100) -> 4298427000 | N30: =M30/(1+K34)^L29 -> 3209908890 | O30: 5 | Q30: 1 | R30: =M29 -> 4093740000
A31: Receita Bruta | J31: Taxa_Cresc | K31: =SUM(O28:O36)/6 -> 5 | L31: 4 | M31: =M30*(1+O30/100) -> 4513348350 | N31: =M31/(1+K34)^L30 -> 2912551274 | O31: 5 | Q31: 2 | R31: =M30 -> 4298427000
A32: Receita Liquida | B32: 10462543 | C32: =IFERROR(SUM((D32/B32)-1),0) -> 0.066302714 | D32: 11156238 | E32: =IFERROR(SUM((F32/D32)-1),0) -> -0.048089419 | F32: 10619741 | G32: =IFERROR(SUM((H32/F32)-1),0) -> 0.082984604 | H32: 11501016 | J32: Taxa_Gordon | K32: 0.04 | L32: 5 | M32: =M31*(1+O31/100) -> 4739015768 | N32: =M32/(1+K34)^L31 -> 2642740095 | O32: 5 | Q32: 3 | R32: =M31 -> 4513348350
A33: Custo Mercadoria (CMV) | B33: =SUM(B34,B38,B39) -> -8737422 | C33: =IFERROR(SUM((D33/B33)-1),0) -> 0.040539875 | D33: =SUM(D34,D38,D39) -> -9091636 | E33: =IFERROR(SUM((F33/D33)-1),0) -> 0.0030407069 | F33: =SUM(F34,F38,F39) -> -9119281 | G33: =IFERROR(SUM((H33/F33)-1),0) -> 0.052925883 | H33: =SUM(H34,H38,H39) -> -9601927 | J33: Lucro_Ajustado_Planilha | K33: =$K$22 -> 3898800000 | L33: 6 | M33: =M32*(1+O32/100) -> 4975966556 | N33: =M33/(1+K34)^L32 -> 2397923522 | O33: 5 | Q33: 4 | R33: =M32 -> 4739015768
A34: Custos com energia elétrica e gás | B34: =SUM(B35:B37) -> -5846956 | C34: =IFERROR(SUM((D34/B34)-1),0) -> -0.0055957322 | D34: =SUM(D35:D37) -> -5814238 | E34: =IFERROR(SUM((F34/D34)-1),0) -> 0.061192026 | F34: =SUM(F35:F37) -> -6170023 | G34: =IFERROR(SUM((H34/F34)-1),0) -> 0.0014259266 | H34: =SUM(H35:H37) -> -6178821 | J34: Taxa_desconto_KE | K34: =L25 -> 0.1572 | L34: 7 | M34: =M33*(1+O33/100) -> 5224764884 | N34: =M34/(1+K34)^L33 -> 2175786120 | Q34: 5 | R34: =M33 -> 4975966556
A35: Energia elétrica comprada para revenda | B35: -4915028 | C35: =IFERROR(SUM((D35/B35)-1),0) -> -0.026402901 | D35: -4785257 | E35: =IFERROR(SUM((F35/D35)-1),0) -> 0.078952917 | F35: -5163067 | G35: =IFERROR(SUM((H35/F35)-1),0) -> 0.0073446655 | H35: -5200988 | J35: Valor_ação_Proj | K35: =K36/K29 -> 11.727333 | L35: Perpétuo | M35: =IFERROR( M34 * (1 + K32) / (K34 -K32 ), 0 ) -> 46363101357 | N35: =M35/(1+K34)^L34 -> 16684511845 | Q35: 6 | R35: =M34+M35 -> 51587866240
A36: Encargos de uso da rede básica | B36: -718658 | C36: =IFERROR(SUM((D36/B36)-1),0) -> 0.15563453 | D36: -830506 | E36: =IFERROR(SUM((F36/D36)-1),0) -> -0.077615333 | F36: -766046 | G36: =IFERROR(SUM((H36/F36)-1),0) -> -0.020126729 | H36: -750628 | J36: Market_Proj | K36: =N36 -> 33561047049 | N36: =SUM(N28:N35) -> 33561047049 | Q36: TIR | R36: =IFERROR(IRR(R29:R35),0) -> 0.075215283
A37: Gás comprado para revenda | B37: -213270 | C37: =IFERROR(SUM((D37/B37)-1),0) -> -0.069372157 | D37: -198475 | E37: =IFERROR(SUM((F37/D37)-1),0) -> 0.21380527 | F37: -240910 | G37: =IFERROR(SUM((H37/F37)-1),0) -> -0.056888465 | H37: -227205
A38: Custos de construção de infraestrutura | B38: -1482436 | C38: =IFERROR(SUM((D38/B38)-1),0) -> 0.18257382 | D38: -1753090 | E38: =IFERROR(SUM((F38/D38)-1),0) -> -0.086132486 | F38: -1602092 | G38: =IFERROR(SUM((H38/F38)-1),0) -> 0.14575755 | H38: -1835609
A39: Custos de operação | B39: =SUM(B40:B43) -> -1408030 | C39: =IFERROR(SUM((D39/B39)-1),0) -> 0.082582047 | D39: =SUM(D40:D43) -> -1524308 | E39: =IFERROR(SUM((F39/D39)-1),0) -> -0.11621142 | F39: =SUM(F40:F43) -> -1347166 | G39: =IFERROR(SUM((H39/F39)-1),0) -> 0.17839747 | H39: =SUM(H40:H43) -> -1587497
A40: Pessoal (reversões) | B40: -365592 | C40: =IFERROR(SUM((D40/B40)-1),0) -> 0.15102902 | D40: -420807 | E40: =IFERROR(SUM((F40/D40)-1),0) -> -0.19866827 | F40: -337206 | G40: =IFERROR(SUM((H40/F40)-1),0) -> 0.1314597 | H40: -381535
A41: Participação d empregados e adm no resultado | B41: -45054 | C41: =IFERROR(SUM((D41/B41)-1),0) -> 0.18480046 | D41: -53380 | E41: =IFERROR(SUM((F41/D41)-1),0) -> -0.10417759 | F41: -47819 | G41: =IFERROR(SUM((H41/F41)-1),0) -> 0.63485226 | H41: -78177
A42: Serviços de terceiros | B42: -596063 | C42: =IFERROR(SUM((D42/B42)-1),0) -> 0.073799246 | D42: -640052 | E42: =IFERROR(SUM((F42/D42)-1),0) -> -0.087247599 | F42: -584209 | G42: =IFERROR(SUM((H42/F42)-1),0) -> 0.20597423 | H42: -704541
A43: Depreciação e amortização | B43: -401321 | C43: =IFERROR(SUM((D43/B43)-1),0) -> 0.021798012 | D43: -410069 | E43: =IFERROR(SUM((F43/D43)-1),0) -> -0.078369738 | F43: -377932 | G43: =IFERROR(SUM((H43/F43)-1),0) -> 0.11989458 | H43: -423244
A44: Lucro Bruto | B44: =B32+B33 -> 1725121 | C44: =IFERROR(SUM((D44/B44)-1),0) -> 0.19678678 | D44: =D32+D33 -> 2064602 | E44: =IFERROR(SUM((F44/D44)-1),0) -> -0.27324492 | F44: =F32+F33 -> 1500460 | G44: =IFERROR(SUM((H44/F44)-1),0) -> 0.26567119 | H44: =H32+H33 -> 1899089
A45: DESPESAS E OUTRAS RECEITAS
A46: Despesa Administrativa (%) | B46: =ABS(B47)/B32 -> 0.019222382 | C46: =IFERROR(SUM((D46/B46)-1),0) -> 0.58561828 | D46: =ABS(D47)/D32 -> 0.030479361 | E46: =IFERROR(SUM((F46/D46)-1),0) -> -0.18519641 | F46: =ABS(F47)/F32 -> 0.024834692 | G46: =IFERROR(SUM((H46/F46)-1),0) -> 1.3966667 | H46: =ABS(H47)/H32 -> 0.059520481
A47: Despesas gerais e administrativas | B47: =SUM(B48:B51) -> -201115 | C47: =IFERROR(SUM((D47/B47)-1),0) -> 0.69074907 | D47: =SUM(D48:D51) -> -340035 | E47: =IFERROR(SUM((F47/D47)-1),0) -> -0.22437984 | F47: =SUM(F48:F51) -> -263738 | G47: =IFERROR(SUM((H47/F47)-1),0) -> -3.5955532 | H47: =SUM(H48:H51) -> 684546
A48: Obrigações pós-emprego (reversões) | B48: -50233 | C48: =IFERROR(SUM((D48/B48)-1),0) -> 0 | D48: -50233 | E48: =IFERROR(SUM((F48/D48)-1),0) -> 1.0961718 | F48: -105297 | G48: =IFERROR(SUM((H48/F48)-1),0) -> -11.137193 | H48: 1067416
A49: Materiais | B49: -32348 | C49: =IFERROR(SUM((D49/B49)-1),0) -> -0.24752689 | D49: -24341 | E49: =IFERROR(SUM((F49/D49)-1),0) -> 0.33178588 | F49: -32417 | G49: =IFERROR(SUM((H49/F49)-1),0) -> 1.0118765 | H49: -65219
A50: Provisões (reversões) | B50: -84000 | C50: =IFERROR(SUM((D50/B50)-1),0) -> 1.5612976 | D50: -215149 | E50: =IFERROR(SUM((F50/D50)-1),0) -> -0.52866153 | F50: -101408 | G50: =IFERROR(SUM((H50/F50)-1),0) -> 1.9795973 | H50: -302155
A51: Perda esperada com outros créditos | B51: -34534 | C51: =IFERROR(SUM((D51/B51)-1),0) -> 0.45688307 | D51: -50312 | E51: =IFERROR(SUM((F51/D51)-1),0) -> -0.51073303 | F51: -24616 | G51: =IFERROR(SUM((H51/F51)-1),0) -> -0.37049074 | H51: -15496
A52: Perdas de créditos esperadas | B52: -83363 | C52: =IFERROR(SUM((D52/B52)-1),0) -> -3.1234001 | D52: 177013 | E52: =IFERROR(SUM((F52/D52)-1),0) -> -1.3406755 | F52: -60304 | G52: =IFERROR(SUM((H52/F52)-1),0) -> -0.21413173 | H52: -47391
A53: Outros custos e despesas | B53: -131804 | C53: =IFERROR(SUM((D53/B53)-1),0) -> 0.24212467 | D53: -163717 | E53: =IFERROR(SUM((F53/D53)-1),0) -> -0.42257066 | F53: -94535 | G53: =IFERROR(SUM((H53/F53)-1),0) -> 1.4083038 | H53: -227669
A54: Outras receitas | B54: 26191 | C54: =IFERROR(SUM((D54/B54)-1),0) -> -1 | D54: 0 | E54: =IFERROR(SUM((F54/D54)-1),0) -> 0 | F54: 0 | G54: =IFERROR(SUM((H54/F54)-1),0) -> 0 | H54: 174008
A55: Despesa Operacionais | B55: =SUM(B52,B47,B53,B54) -> -390091 | C55: =IFERROR(SUM((D55/B55)-1),0) -> -0.16240313 | D55: =SUM(D52,D47,D53,D54) -> -326739 | E55: =IFERROR(SUM((F55/D55)-1),0) -> 0.2810745 | F55: =SUM(F52,F47,F53,F54) -> -418577 | G55: =IFERROR(SUM((H55/F55)-1),0) -> -2.3939944 | H55: =SUM(H52,H47,H53,H54) -> 583494
A57: Resultado de equivalência patrimonial | B57: 52325 | C57: =IFERROR(SUM((D57/B57)-1),0) -> 0.74645007 | D57: 91383 | E57: =IFERROR(SUM((F57/D57)-1),0) -> -0.55453421 | F57: 40708 | G57: =IFERROR(SUM((H57/F57)-1),0) -> -0.00051586912 | H57: 40687
A58: Lucro Operacional (EBIT)(LAJIR) | B58: =SUM(B44,B55,B57) -> 1387355 | C58: =IFERROR(SUM((D58/B58)-1),0) -> 0.31851329 | D58: =SUM(D44,D55,D57) -> 1829246 | E58: =IFERROR(SUM((F58/D58)-1),0) -> -0.38630944 | F58: =SUM(F44,F55,F57) -> 1122591 | G58: =IFERROR(SUM((H58/F58)-1),0) -> 1.2477198 | H58: =SUM(H44,H55,H57) -> 2523270
A60: Receita Financeira | B60: 257960 | C60: =IFERROR(SUM((D60/B60)-1),0) -> 0.12493797 | D60: 290189 | E60: =IFERROR(SUM((F60/D60)-1),0) -> -0.11456671 | F60: 256943 | G60: =IFERROR(SUM((H60/F60)-1),0) -> -0.026017444 | H60: 250258
A61: Despesa Financeira | B61: -596384 | C61: =IFERROR(SUM((D61/B61)-1),0) -> 0.82113202 | D61: -1086094 | E61: =IFERROR(SUM((F61/D61)-1),0) -> -0.50924598 | F61: -533005 | G61: =IFERROR(SUM((H61/F61)-1),0) -> 0.014416375 | H61: -540689
A62: Resultado Financeiro | B62: =B60+B61 -> -338424 | C62: =IFERROR(SUM((D62/B62)-1),0) -> 1.3517983 | D62: =D60+D61 -> -795905 | E62: =IFERROR(SUM((F62/D62)-1),0) -> -0.65314705 | F62: =F60+F61 -> -276062 | G62: =IFERROR(SUM((H62/F62)-1),0) -> 0.052049902 | H62: =H60+H61 -> -290431
A65: EBITIDA (LAJIDA) IFRS | B65: =B68-B67-B62-B43 -> 1788676 | C65: =IFERROR(SUM((D65/B65)-1),0) -> 0.25193998 | D65: =D68-D67-D62-D43 -> 2239315 | E65: =IFERROR(SUM((F65/D65)-1),0) -> -0.32991875 | F65: =F68-F67-F62-F43 -> 1500523 | G65: =IFERROR(SUM((H65/F65)-1),0) -> 0.963658 | H65: =H68-H67-H62-H43 -> 2946514
A66: Resultado antes do Imposto | B66: =B58+B62 -> 1048931 | C66: =IFERROR(SUM((D66/B66)-1),0) -> -0.014862751 | D66: =D58+D62 -> 1033341 | E66: =IFERROR(SUM((F66/D66)-1),0) -> -0.18078447 | F66: =F58+F62 -> 846529 | G66: =IFERROR(SUM((H66/F66)-1),0) -> 1.6376403 | H66: =H58+H62 -> 2232839
A67: Impostos | B67: -69952 | C67: =IFERROR(SUM((D67/B67)-1),0) -> 0.25653305 | D67: -87897 | E67: =IFERROR(SUM((F67/D67)-1),0) -> -0.43357566 | F67: -49787 | G67: =IFERROR(SUM((H67/F67)-1),0) -> 6.1702452 | H67: -356985
A68: Lucro Liquido IFRS | B68: =B66+B67 -> 978979 | C68: =IFERROR(SUM((D68/B68)-1),0) -> -0.034255076 | D68: =D66+D67 -> 945444 | E68: =IFERROR(SUM((F68/D68)-1),0) -> -0.15728272 | F68: =F66+F67 -> 796742 | G68: =IFERROR(SUM((H68/F68)-1),0) -> 1.3544058 | H68: =H66+H67 -> 1875854
A69: Participação dos acionistas não-controladores | B69: 434 | C69: =IFERROR(SUM((D69/B69)-1),0) -> -0.050691244 | D69: 412 | E69: =IFERROR(SUM((F69/D69)-1),0) -> 0.053398058 | F69: 434 | G69: =IFERROR(SUM((H69/F69)-1),0) -> 0 | H69: 434
A70: EBITIDA (LAJIDA) Ajustado | B70: =B68-B67-B62-B43-B69 -> 1788242 | C70: =IFERROR(SUM((D70/B70)-1),0) -> 0.25201343 | D70: =D68-D67-D62-D43-D69 -> 2238903 | E70: =IFERROR(SUM((F70/D70)-1),0) -> -0.32998928 | F70: =F68-F67-F62-F43-F69 -> 1500089 | G70: =IFERROR(SUM((H70/F70)-1),0) -> 0.96393681 | H70: =H68-H67-H62-H43-H69 -> 2946080
A71: Lucro_Liquido_Ajustado | B71: 979 | C71: =IFERROR(SUM((D71/B71)-1),0) -> 0.14075587 | D71: 1116.8 | E71: =IFERROR(SUM((F71/D71)-1),0) -> -0.30157593 | F71: 780 | G71: =IFERROR(SUM((H71/F71)-1),0) -> 0.31153846 | H71: 1023
A73: DFC
A74: FCO – Fluxo Operacional | B74: 1_T | C74: AH% (2/1) | D74: 2_T | E74: AH% (3/2) | F74: 3_T | G74: AH% (4/3) | H74: 4_T
A75: Lucro Líquido | B75: 978979 | C75: =IFERROR(SUM((D75/B75)-1),0) -> 0.96574492 | D75: 1924423 | E75: =IFERROR(SUM((F75/D75)-1),0) -> 0.57125694 | F75: 3023763 | G75: =IFERROR(SUM((H75/F75)-1),0) -> 0.62037071 | H75: 4899617
A76: Ajustes Não Caixa (subtotal) | B76: 900310 | C76: =IFERROR(SUM((D76/B76)-1),0) -> 1.769034 | D76: 2492989 | E76: =IFERROR(SUM((F76/D76)-1),0) -> 0.66185571 | F76: 4142988 | G76: =IFERROR(SUM((H76/F76)-1),0) -> 0.35902156 | H76: 5630410
A77: Variação Ativos | B77: 647216 | C77: =IFERROR(SUM((D77/B77)-1),0) -> 0.22217312 | D77: 791010 | E77: =IFERROR(SUM((F77/D77)-1),0) -> -0.77831127 | F77: 175358 | G77: =IFERROR(SUM((H77/F77)-1),0) -> -0.39380011 | H77: 106302
A78: Variação Passivos | B78: -27096 | C78: =IFERROR(SUM((D78/B78)-1),0) -> 31.88323 | D78: -891004 | E78: =IFERROR(SUM((F78/D78)-1),0) -> -1.2975217 | F78: 265093 | G78: =IFERROR(SUM((H78/F78)-1),0) -> -2.0174241 | H78: -269712
A79: Operacional antes de juros/IR | B79: =SUM(B76:B78) -> 1520430 | C79: =IFERROR(SUM((D79/B79)-1),0) -> 0.57389357 | D79: =SUM(D76:D78) -> 2392995 | E79: =IFERROR(SUM((F79/D79)-1),0) -> 0.9153567 | F79: =SUM(F76:F78) -> 4583439 | G79: =IFERROR(SUM((H79/F79)-1),0) -> 0.1927725 | H79: =SUM(H76:H78) -> 5467000
A80: Juros Recebidos | B80: 86574 | C80: =IFERROR(SUM((D80/B80)-1),0) -> 1.9268372 | D80: 253388 | E80: =IFERROR(SUM((F80/D80)-1),0) -> 0.25027231 | F80: 316804 | G80: =IFERROR(SUM((H80/F80)-1),0) -> 0.4871561 | H80: 471137
A81: Dividendos Recebidos | B81: 65372 | C81: =IFERROR(SUM((D81/B81)-1),0) -> 1.2137306 | D81: 144716 | E81: =IFERROR(SUM((F81/D81)-1),0) -> 0.13796678 | F81: 164682 | G81: =IFERROR(SUM((H81/F81)-1),0) -> 0.6337669 | H81: 269052
A82: Juros Pagos | B82: -438460 | C82: =IFERROR(SUM((D82/B82)-1),0) -> 1.0856999 | D82: -914496 | E82: =IFERROR(SUM((F82/D82)-1),0) -> 0.089980711 | F82: -996783 | G82: =IFERROR(SUM((H82/F82)-1),0) -> 0.39924939 | H82: -1394748
A83: Juros sobre arrendamentos pagos | B83: -6413 | C83: =IFERROR(SUM((D83/B83)-1),0) -> 0.93138937 | D83: -12386 | E83: =IFERROR(SUM((F83/D83)-1),0) -> -1 | F83: 0 | G83: =IFERROR(SUM((H83/F83)-1),0) -> 0 | H83: 0
A84: IR/CS Pagos | B84: -108465 | C84: =IFERROR(SUM((D84/B84)-1),0) -> 0.75223344 | D84: -190056 | E84: =IFERROR(SUM((F84/D84)-1),0) -> 2.3892379 | F84: -644145 | G84: =IFERROR(SUM((H84/F84)-1),0) -> 0.1424555 | H84: -735907
A85: Liquidação | B85: 0 | C85: =IFERROR(SUM((D85/B85)-1),0) -> 0 | D85: 0 | E85: =IFERROR(SUM((F85/D85)-1),0) -> 0 | F85: 0 | G85: =IFERROR(SUM((H85/F85)-1),0) -> 0 | H85: 0
A86: FCO | B86: =SUM(B79:B85) -> 1119038 | C86: =IFERROR(SUM((D86/B86)-1),0) -> 0.49607163 | D86: =SUM(D79:D85) -> 1674161 | E86: =IFERROR(SUM((F86/D86)-1),0) -> 1.0452017 | F86: =SUM(F79:F85) -> 3423997 | G86: =IFERROR(SUM((H86/F86)-1),0) -> 0.19057756 | H86: =SUM(H79:H85) -> 4076534
A87: CAPEX
A88: Imobilizado | B88: -52406 | C88: =IFERROR(SUM((D88/B88)-1),0) -> 0.56613747 | D88: -82075 | E88: =IFERROR(SUM((F88/D88)-1),0) -> 4.5996832 | F88: -459594 | G88: =IFERROR(SUM((H88/F88)-1),0) -> 0.52130359 | H88: -699182
A89: Intangível | B89: -40785 | C89: =IFERROR(SUM((D89/B89)-1),0) -> 0.57305382 | D89: -64157 | E89: =IFERROR(SUM((F89/D89)-1),0) -> 3.7529498 | F89: -304935 | G89: =IFERROR(SUM((H89/F89)-1),0) -> 0.24160231 | H89: -378608
A90: Ativos de Contrato | B90: -1819515 | C90: =IFERROR(SUM((D90/B90)-1),0) -> 0.54338821 | D90: -2808218 | E90: =IFERROR(SUM((F90/D90)-1),0) -> 0.35069357 | F90: -3793042 | G90: =IFERROR(SUM((H90/F90)-1),0) -> 0.42003226 | H90: -5386242
A91: CAPEX | B91: =SUM(B88:B90) -> -1912706 | C91: =IFERROR(SUM((D91/B91)-1),0) -> 0.54464408 | D91: =SUM(D88:D90) -> -2954450 | E91: =IFERROR(SUM((F91/D91)-1),0) -> 0.54261233 | F91: =SUM(F88:F90) -> -4557571 | G91: =IFERROR(SUM((H91/F91)-1),0) -> 0.41830637 | H91: =SUM(H88:H90) -> -6464032
A92: FCI – Investimentos | B92: -1626372 | C92: =IFERROR(SUM((D92/B92)-1),0) -> 0.93688652 | D92: -3150098 | E92: =IFERROR(SUM((F92/D92)-1),0) -> 0.50924701 | F92: -4754276 | G92: =IFERROR(SUM((H92/F92)-1),0) -> 0.40145713 | H92: -6662914
A93: FCF – Financiamento
A94: Antecipação de CDE | B94: 0 | C94: =IFERROR(SUM((D94/B94)-1),0) -> 0 | D94: 709761 | E94: =IFERROR(SUM((F94/D94)-1),0) -> -1 | F94: 0 | G94: =IFERROR(SUM((H94/F94)-1),0) -> 0 | H94: 0
A95: Captações | B95: 0 | C95: =IFERROR(SUM((D95/B95)-1),0) -> 0 | D95: 4575156 | E95: =IFERROR(SUM((F95/D95)-1),0) -> 0.13298607 | F95: 5183588 | G95: =IFERROR(SUM((H95/F95)-1),0) -> 0.80122552 | H95: 9336811
A96: Dividendos/JCP | B96: 0 | C96: =IFERROR(SUM((D96/B96)-1),0) -> 0 | D96: -1415670 | E96: =IFERROR(SUM((F96/D96)-1),0) -> 0.25387696 | F96: -1775076 | G96: =IFERROR(SUM((H96/F96)-1),0) -> 1.2355696 | H96: -3968306
A97: Amortizações | B97: 0 | C97: =IFERROR(SUM((D97/B97)-1),0) -> 0 | D97: -2098565 | E97: =IFERROR(SUM((F97/D97)-1),0) -> 0.17407276 | F97: -2463868 | G97: =IFERROR(SUM((H97/F97)-1),0) -> 0.094701908 | H97: -2697201
A98: Arrendamentos | B98: -16742 | C98: =IFERROR(SUM((D98/B98)-1),0) -> 1.0299247 | D98: -33985 | E98: =IFERROR(SUM((F98/D98)-1),0) -> 0.79211417 | F98: -60905 | G98: =IFERROR(SUM((H98/F98)-1),0) -> 0.33834661 | H98: -81512
A99: FCF | B99: =SUM(B94:B98) -> -16742 | C99: =IFERROR(SUM((D99/B99)-1),0) -> -104.73295 | D99: =SUM(D94:D98) -> 1736697 | E99: =IFERROR(SUM((F99/D99)-1),0) -> -0.49113806 | F99: =SUM(F94:F98) -> 883739 | G99: =IFERROR(SUM((H99/F99)-1),0) -> 1.9304942 | H99: =SUM(H94:H98) -> 2589792
A101: Fechamento | B101: =SUM(B86,B92,B99) -> -524076 | C101: =IFERROR(SUM((D101/B101)-1),0) -> -1.4975614 | D101: =SUM(D86,D92,D99) -> 260760 | E101: =IFERROR(SUM((F101/D101)-1),0) -> -2.7124559 | F101: =SUM(F86,F92,F99) -> -446540 | G101: =IFERROR(SUM((H101/F101)-1),0) -> -1.007641 | H101: =SUM(H86,H92,H99) -> 3412
A102: Caixa Inicial | B102: 1901636 | C102: =IFERROR(SUM((D102/B102)-1),0) -> 0 | D102: 1901636 | E102: =IFERROR(SUM((F102/D102)-1),0) -> -0.0017942445 | F102: 1898224 | G102: =IFERROR(SUM((H102/F102)-1),0) -> 0 | H102: 1898224
A103: Caixa Final | B103: =SUM(B101:B102) -> 1377560 | C103: =IFERROR(SUM((D103/B103)-1),0) -> 0.56972909 | D103: =SUM(D101:D102) -> 2162396 | E103: =IFERROR(SUM((F103/D103)-1),0) -> -0.32866875 | F103: =SUM(F101:F102) -> 1451684 | G103: =IFERROR(SUM((H103/F103)-1),0) -> 0.30995175 | H103: =SUM(H101:H102) -> 1901636

Sheet TAEE11
B1: Feito | C1: 46058 | D1: Atual | E1: 46245 | F1: Não | G1: 46058 | H1: Não | I1: 46058 | J1: Ultimo_Balanco | K1: {=IFERROR(INDEX(Indicador_Ações[], MATCH($J$2, Indicador_Ações[Stock], 0), MATCH(Indicador_Ações[[#HEADERS],[ult_balanco_processado]], Indicador_Ações[#HEADERS], 0)),"")} -> 46203
A2: Balanço Patrimonial Anual | J2: TAEE11 | K2: =IFERROR(__xludf.DUMMYFUNCTION("(GOOGLEFINANCE(""BVMF:"" & J2))"),40.99) -> 40.99 | L2: {=IFERROR(INDEX(Indicador_Ações[], MATCH($J$2, Indicador_Ações[Stock], 0), MATCH(Indicador_Ações[[#HEADERS],[qtd_acao]], Indicador_Ações[#HEADERS], 0)),"")/3} -> 344500000 | M2: Numero_Papel
A3: Ano | B3: 1_T | C3: AH% (2/1) | D3: 2_T | E3: AH% (3/2) | F3: 3_T | G3: AH% (4/3) | H3: 4_T | J3: BP | K3: 1000 | L3: =IFERROR(K23/K15,0) -> 0.39398172 | M3: MARGEM LÍQUIDA | N3: DMPL Acumulado
A4: Ativo Total | B4: =B5+B6 -> 14173294 | C4: =IFERROR(SUM((D4/B4)-1),0) -> -0.071774776 | D4: =D5+D6 -> 13156009 | E4: =IFERROR(SUM((F4/D4)-1),0) -> -0.0033959387 | F4: =F5+F6 -> 13111332 | G4: =IFERROR(SUM((H4/F4)-1),0) -> 0.040110417 | H4: =H5+H6 -> 13637233 | J4: Ativo | K4: {=IFERROR(INDEX(Indicador_Ações[], MATCH($J$2, Indicador_Ações[Stock], 0), MATCH(Indicador_Ações[[#HEADERS],[ativo]], Indicador_Ações[#HEADERS], 0)),"")} -> 22700900000 | L4: =IFERROR(K20/K15,0) -> 0.64439464 | M4: MARGEM BRUTA | N4: JCP acionistas Liquido | O4: 192574
A5: Ativo Circulante | B5: 2148240 | C5: =IFERROR(SUM((D5/B5)-1),0) -> -0.48169059 | D5: 1113453 | E5: =IFERROR(SUM((F5/D5)-1),0) -> 0.60106174 | F5: 1782707 | G5: =IFERROR(SUM((H5/F5)-1),0) -> 0.053283013 | H5: 1877695 | J5: Valor_de_mercado | K5: =K2*L2 -> 14121055000 | L5: =IFERROR(K17/K15,0) -> 0.79629558 | M5: MARGEM EBIT | N5: Dividendos | O5: 260226
A6: Ativo Nao Circ. | B6: 12025054 | C6: =IFERROR(SUM((D6/B6)-1),0) -> 0.0014554612 | D6: 12042556 | E6: =IFERROR(SUM((F6/D6)-1),0) -> -0.059284009 | F6: 11328625 | G6: =IFERROR(SUM((H6/F6)-1),0) -> 0.038037538 | H6: 11759538 | J6: Valor_da_firma | K6: =SUM(K5,K10) -> 24534795000 | L6: =IFERROR(K18/K15,0) -> 0.84157113 | M6: MARGEM EBITDA | N6: Dividendos remanescentes | O6: 0
J7: Disponibilidade | K7: {=IFERROR(INDEX(Indicador_Ações[], MATCH($J$2, Indicador_Ações[Stock], 0), MATCH(Indicador_Ações[[#HEADERS],[disponibilidades]], Indicador_Ações[#HEADERS], 0)),"")} -> 544160000 | L7: =K23/L2 -> 3.0064499 | M7: LPA | N7: Dividendos e JCP | O7: =SUM(O4:O6) -> 452800
A8: Estoque | B8: 23030 | C8: =IFERROR(SUM((D8/B8)-1),0) -> -0.014155449 | D8: 22704 | E8: =IFERROR(SUM((F8/D8)-1),0) -> -0.69256519 | F8: 6980 | G8: =IFERROR(SUM((H8/F8)-1),0) -> 1.9524355 | H8: 20608 | J8: Patrimônio líq | K8: {=IFERROR(INDEX(Indicador_Ações[], MATCH($J$2, Indicador_Ações[Stock], 0), MATCH(Indicador_Ações[[#HEADERS],[patrimonio_liquido]], Indicador_Ações[#HEADERS], 0)),"")} -> 8070920000 | L8: {=IFERROR(INDEX(O7*K3,0)/L2,"")} -> 1.3143687 | M8: DPA Liquido | N8: Aliquota | O8: =ABS(SUM(B47,D47,F47,H47)/SUM(B46,D46,F46,H46)) -> 0.08728999
A9: Caixa | B9: 1091121 | C9: =IFERROR(SUM((D9/B9)-1),0) -> -0.80904134 | D9: 208359 | E9: =IFERROR(SUM((F9/D9)-1),0) -> 1.9271834 | F9: 609905 | G9: =IFERROR(SUM((H9/F9)-1),0) -> 0.21592051 | H9: 741596 | J9: Dívida bruta | K9: {=IFERROR(INDEX(Indicador_Ações[], MATCH($J$2, Indicador_Ações[Stock], 0), MATCH(Indicador_Ações[[#HEADERS],[divida_bruta]], Indicador_Ações[#HEADERS], 0)),"")} -> 10957900000 | L9: =IFERROR(L8/L7,0) -> 0.43718295 | M9: Payout_Ajustado | N9: NOPAT | O9: =K17*(1-O8) -> 1910619675
A10: Títulos e valores mobiliários | B10: 512539 | C10: =IFERROR(SUM((D10/B10)-1),0) -> -0.34482839 | D10: 335801 | E10: =IFERROR(SUM((F10/D10)-1),0) -> 0.37968321 | F10: 463299 | G10: =IFERROR(SUM((H10/F10)-1),0) -> 0.17451149 | H10: 544150 | J10: Dívida líq | K10: =K9-K7 -> 10413740000 | L10: =IFERROR(K14/K4,0) -> 0.19754283 | M10: GIRO ATIVOS
A11: Disponibilidades | B11: =SUM(B9,B10) -> 1603660 | C11: =IFERROR(SUM((D11/B11)-1),0) -> -0.6606762 | D11: =SUM(D9,D10) -> 544160 | E11: =IFERROR(SUM((F11/D11)-1),0) -> 0.97222141 | F11: =SUM(F9,F10) -> 1073204 | G11: =IFERROR(SUM((H11/F11)-1),0) -> 0.19804436 | H11: =SUM(H9,H10) -> 1285746 | J11: Capital_Investido | K11: =SUM(K8,K9) -> 19028820000 | L11: =IFERROR(K24/K8,0) -> 0.20139835 | M11: ROE
J12: Razão de Divida | K12: =K9/K11 -> 0.57585809 | L12: =O9/K11 -> 0.10040663 | M12: ROIC
A13: Passivo Total | B13: =SUM(B14+B15) -> 12906356 | C13: =IFERROR(SUM((D13/B13)-1),0) -> -0.059554145 | D13: =SUM(D14+D15) -> 12137729 | E13: =IFERROR(SUM((F13/D13)-1),0) -> -0.015778158 | F13: =SUM(F14+F15) -> 11946218 | G13: =IFERROR(SUM((H13/F13)-1),0) -> 0.051332899 | H13: =SUM(H14+H15) -> 12559452 | J13: DRE | L13: =IFERROR(K24/K4,0) -> 0.071603769 | M13: ROA
A14: Passivo Circ. | B14: 1669914 | C14: =IFERROR(SUM((D14/B14)-1),0) -> -0.5010755 | D14: 833161 | E14: =IFERROR(SUM((F14/D14)-1),0) -> 1.4281573 | F14: 2023046 | G14: =IFERROR(SUM((H14/F14)-1),0) -> 0.12095227 | H14: 2267738 | J14: Receita_IFRS | K14: {=IFERROR(INDEX(Indicador_Ações[], MATCH($J$2, Indicador_Ações[Stock], 0), MATCH(Indicador_Ações[[#HEADERS],[receita_liquida_12m]], Indicador_Ações[#HEADERS], 0)),"")} -> 4484400000 | L14: =K6/K18 -> 11.089819 | M14: EV/EBITDA
A15: Passivo Não Circ. | B15: 11236442 | C15: =IFERROR(SUM((D15/B15)-1),0) -> 0.0060629512 | D15: 11304568 | E15: =IFERROR(SUM((F15/D15)-1),0) -> -0.12219804 | F15: 9923172 | G15: =IFERROR(SUM((H15/F15)-1),0) -> 0.037139536 | H15: 10291714 | J15: Receita REG | K15: =IFERROR(SUM(B33,D33,F33,H33),"")*K3 -> 2628858000 | L15: =K18/K6 -> 0.090172793 | M15: Earnings_Yield_Greenblatt
A16: Emprést. CP | B16: 1083543 | C16: =IFERROR(SUM((D16/B16)-1),0) -> -0.8291586 | D16: 185114 | E16: =IFERROR(SUM((F16/D16)-1),0) -> 4.7919282 | F16: 1072167 | G16: =IFERROR(SUM((H16/F16)-1),0) -> 0.25012428 | H16: 1340342 | J16: Cagr_receita_5a | K16: {=IFERROR(INDEX(Indicador_Ações[], MATCH($J$2, Indicador_Ações[Stock], 0), MATCH(Indicador_Ações[[#HEADERS],[cagr_receita_5a]], Indicador_Ações[#HEADERS], 0)),"")} -> 13 | L16: =IFERROR(K10/K18,0) -> 4.7070496 | M16: DÍVIDA LÍQUIDA / EBITDA
A17: Emprést. LP | B17: 10598903 | C17: =IFERROR(SUM((D17/B17)-1),0) -> 0.016330275 | D17: 10771986 | E17: =IFERROR(SUM((F17/D17)-1),0) -> -0.1444702 | F17: 9215755 | G17: =IFERROR(SUM((H17/F17)-1),0) -> 0.045327919 | H17: 9633486 | J17: EBIT Reg | K17: =SUM(B39,D39,F39,H39)*K3 -> 2093348000 | L17: =IFERROR(SUM(B5,D5,F5,H5)/SUM(B14,D14,F14,H14),0) -> 1.0188753 | M17: LIQUIDEZ CORRENTE
J18: EBITDA Reg | K18: =IFERROR(SUM(B45,D45,F45,H45),"")*K3 -> 2212371000 | L18: =SUM(B39,D39,F39,H39)/ABS(SUM(B42,D42,F42,H42)) -> 1.6186636 | M18: Indice de Cobertura de Juros MEDIA
A19: ENDIVIDAMENTO / CAIXA | J19: Custo_Mercadoria | K19: =SUM(B32,D32,F32,H32)*K3 -> -284037000 | L19: =IFERROR(K4/K8,0) -> 2.8126781 | M19: Alavancagem_Financeira
A20: Dívida bruta | B20: =SUM(B17,B16) -> 11682446 | C20: =IFERROR(SUM((D20/B20)-1),0) -> -0.062088539 | D20: =SUM(D17,D16) -> 10957100 | E20: =IFERROR(SUM((F20/D20)-1),0) -> -0.061072547 | F20: =SUM(F17,F16) -> 10287922 | G20: =IFERROR(SUM((H20/F20)-1),0) -> 0.066670995 | H20: =SUM(H17,H16) -> 10973828 | J20: Lucro bruto | K20: =IFERROR(SUM(B36,D36,F36,H36),"")*K3 -> 1694022000 | L20: =K10/K8 -> 1.2902792 | M20: DL/PL
A21: Dívida líq | B21: =SUM(B20-B11) -> 10078786 | C21: =IFERROR(SUM((D21/B21)-1),0) -> 0.033154191 | D21: =SUM(D20-D11) -> 10412940 | E21: =IFERROR(SUM((F21/D21)-1),0) -> -0.11507048 | F21: =SUM(F20-F11) -> 9214718 | G21: =IFERROR(SUM((H21/F21)-1),0) -> 0.051370427 | H21: =SUM(H20-H11) -> 9688082 | J21: Despesas operacionais REG | K21: =IFERROR(SUM(B34,D34,F34,H34),"")*K3 -> -416487000 | M21: CPM
J22: Inflação | K22: ='Indicadores_Ações'!$B$4 -> 0.044430246 | L22: ='Indicadores_Ações'!$B$3 -> 0.139 | M22: RF
A23: Patrimônio líq. | B23: =B4-B13 -> 1266938 | C23: =IFERROR(SUM((D23/B23)-1),0) -> -0.1962669 | D23: =D4-D13 -> 1018280 | E23: =IFERROR(SUM((F23/D23)-1),0) -> 0.14419806 | F23: =F4-F13 -> 1165114 | G23: =IFERROR(SUM((H23/F23)-1),0) -> -0.074956614 | H23: =H4-H13 -> 1077781 | J23: Lucro_Anual REG_Planilha | K23: =SUM(B48,D48,F48,H48)*K3 -> 1035722000 | L23: =K25 -> 0.71 | M23: Beta (B)
J24: Lucro_Liquido_Fundamentus | K24: {=IFERROR(INDEX(Indicador_Ações[], MATCH($J$2, Indicador_Ações[Stock], 0), MATCH(Indicador_Ações[[#HEADERS],[lucro_liquido_12m]], Indicador_Ações[#HEADERS], 0)),"")} -> 1625470000 | L24: =L22+0.01 -> 0.149 | M24: RM
A25: Reserva de Capital | B25: 594507 | C25: =IFERROR(SUM((D25/B25)-1),0) -> 0 | D25: 594507 | E25: =IFERROR(SUM((F25/D25)-1),0) -> 0 | F25: 594507 | G25: =IFERROR(SUM((H25/F25)-1),0) -> 0 | H25: 594507 | J25: Beta | K25: {=IFERROR(INDEX(Indicador_Ações[], MATCH($J$2, Indicador_Ações[Stock], 0), MATCH(Indicador_Ações[[#HEADERS],[beta_ibov_3a]], Indicador_Ações[#HEADERS], 0)),"")} -> 0.71 | L25: =L22+L23*(L24-L22) -> 0.1461 | M25: KE
A26: Reserva de Lucro | B26: 3784357 | C26: =IFERROR(SUM((D26/B26)-1),0) -> -0.021781507 | D26: 3701928 | E26: =IFERROR(SUM((F26/D26)-1),0) -> -0.10085636 | F26: 3328565 | G26: =IFERROR(SUM((H26/F26)-1),0) -> 0.13693348 | H26: 3784357
A27: Lucro ou Prejuizo Acumulados | B27: -6526972 | C27: =IFERROR(SUM((D27/B27)-1),0) -> 0 | D27: -6526972 | E27: =IFERROR(SUM((F27/D27)-1),0) -> -0.069832228 | F27: -6071179 | G27: =IFERROR(SUM((H27/F27)-1),0) -> 0.075074874 | H27: -6526972
J28: Ticker | K28: Valores | L28: Ano | M28: VLF | N28: VLP | O28: Cresc | Q28: Ano | R28: Fluxo
A29: DRE Analise Trimestral | J29: Preço_Mercado | K29: =K2 -> 40.99 | L29: 1 | M29: =K34 -> 1035722000 | O29: 8 | Q29: 0 | R29: =-K6 -> -24534795000
A30: Trimestre | B30: 1_T | C30: AH% (2/1) | D30: 2_T | E30: AH% (3/2) | F30: 3_T | G30: AH% (4/3) | H30: 4_T | J30: Numero_Papel | K30: =L2 -> 344500000 | L30: 2 | M30: =M29*(1+O29/100) -> 1118579760 | N30: =M30/(1+K35)^L29 -> 9.7598792e+08 | O30: 8 | Q30: 1 | R30: =M30 -> 1118579760
A31: Receita Operacional Bruta | B31: 722684 | C31: =IFERROR(SUM((D31/B31)-1),0) -> 0.038560422 | D31: 750551 | E31: =IFERROR(SUM((F31/D31)-1),0) -> -0.036224054 | F31: 723363 | G31: =IFERROR(SUM((H31/F31)-1),0) -> -0.009768263 | H31: 716297 | J31: Market | K31: =P21 | L31: 3 | M31: =M30*(1+O30/100) -> 1208066141 | N31: =M31/(1+K35)^L30 -> 9.1969894e+08 | O31: 8 | Q31: 2 | R31: =M31 -> 1208066141
A32: Deduções da receita Bruta | B32: -67152 | C32: =IFERROR(SUM((D32/B32)-1),0) -> 0.062976531 | D32: -71381 | E32: =IFERROR(SUM((F32/D32)-1),0) -> 0.021168098 | F32: -72892 | G32: =IFERROR(SUM((H32/F32)-1),0) -> -0.0038412995 | H32: -72612 | J32: Taxa_Cresc | K32: =SUM(O29:O37)/6 -> 8 | L32: 4 | M32: =M31*(1+O31/100) -> 1304711432 | N32: =M32/(1+K35)^L31 -> 8.6665636e+08 | O32: 8 | Q32: 3 | R32: =M32 -> 1304711432
A33: Receita Operacional Liquida | B33: =SUM(B31,B32) -> 655532 | C33: =IFERROR(SUM((D33/B33)-1),0) -> 0.036059262 | D33: =SUM(D31,D32) -> 679170 | E33: =IFERROR(SUM((F33/D33)-1),0) -> -0.042255989 | F33: =SUM(F31,F32) -> 650471 | G33: =IFERROR(SUM((H33/F33)-1),0) -> -0.01043244 | H33: =SUM(H31,H32) -> 643685 | J33: Taxa_Gordon | K33: 0.04 | L33: 5 | M33: =M32*(1+O32/100) -> 1409088347 | N33: =M33/(1+K35)^L32 -> 8.1667295e+08 | O33: 8 | Q33: 4 | R33: =M33 -> 1409088347
A34: Custos e Despesas | B34: -93403 | C34: =IFERROR(SUM((D34/B34)-1),0) -> 0.092170487 | D34: -102012 | E34: =IFERROR(SUM((F34/D34)-1),0) -> -0.0031662942 | F34: -101689 | G34: =IFERROR(SUM((H34/F34)-1),0) -> 0.17400112 | H34: -119383 | J34: Receita_LL_REG | K34: =$K$23 -> 1035722000 | L34: 6 | M34: =M33*(1+O33/100) -> 1521815414 | N34: =M34/(1+K35)^L33 -> 7.6957228e+08 | O34: 8 | Q34: 5 | R34: =M34 -> 1521815414
A35: Depreciações e Amortizações | B35: -128467 | C35: =IFERROR(SUM((D35/B35)-1),0) -> -0.0047483011 | D35: -127857 | E35: =IFERROR(SUM((F35/D35)-1),0) -> 0.027069304 | F35: -131318 | G35: =IFERROR(SUM((H35/F35)-1),0) -> -0.0046528275 | H35: -130707 | J35: Taxa_desconto_KE | K35: =L25 -> 0.1461 | L35: 7 | M35: =M34*(1+O34/100) -> 1643560648 | N35: =M35/(1+K35)^L34 -> 7.2518808e+08 | Q35: 6 | R35: =M35+M36 -> 17753862942
A36: Lucro Operacional Bruto | B36: =B33+B34+B35 -> 433662 | C36: =IFERROR(SUM((D36/B36)-1),0) -> 0.036062648 | D36: =D33+D34+D35 -> 449301 | E36: =IFERROR(SUM((F36/D36)-1),0) -> -0.070858956 | F36: =F33+F34+F35 -> 417464 | G36: =IFERROR(SUM((H36/F36)-1),0) -> -0.057176188 | H36: =H33+H34+H35 -> 393595 | J36: Valor_ação_Proj | K36: =K37/K30 -> 32.731441 | L36: Perpétuo | M36: =IFERROR( M35 * (1 + K33) / (K35 -K33 ), 0 ) -> 16110302294 | N36: =M36/(1+K35)^L35 -> 6202204788 | Q36: TIR | R36: =IFERROR(IRR(R29:R35),0) -> -0.0017091351
J37: Market_Proj | K37: =N37 -> 11275981336 | N37: =SUM(N29:N36) -> 11275981336
A38: Resultado de equivalência patrimonial | B38: 90423 | C38: =IFERROR(SUM((D38/B38)-1),0) -> 0.0046669542 | D38: 90845 | E38: =IFERROR(SUM((F38/D38)-1),0) -> 0.17244758 | F38: 106511 | G38: =IFERROR(SUM((H38/F38)-1),0) -> 0.047281501 | H38: 111547
A39: Lucro Operacional (EBIT)(LAJIR) | B39: =SUM(B36,B38) -> 524085 | C39: =IFERROR(SUM((D39/B39)-1),0) -> 0.030645792 | D39: =SUM(D36,D38) -> 540146 | E39: =IFERROR(SUM((F39/D39)-1),0) -> -0.029938202 | F39: =SUM(F36,F38) -> 523975 | G39: =IFERROR(SUM((H39/F39)-1),0) -> -0.035942555 | H39: =SUM(H36,H38) -> 505142
A41: Receita Financeira | B41: 34240 | C41: =IFERROR(SUM((D41/B41)-1),0) -> 0.076372664 | D41: 36855 | E41: =IFERROR(SUM((F41/D41)-1),0) -> 0.21978022 | F41: 44955 | G41: =IFERROR(SUM((H41/F41)-1),0) -> -0.18961183 | H41: 36431
A42: Despesa Financeira | B42: -342554 | C42: =IFERROR(SUM((D42/B42)-1),0) -> 0.17757784 | D42: -403384 | E42: =IFERROR(SUM((F42/D42)-1),0) -> -0.32587559 | F42: -271931 | G42: =IFERROR(SUM((H42/F42)-1),0) -> 0.012712784 | H42: -275388
A43: Resultado Financeiro | B43: =B41+B42 -> -308314 | C43: =IFERROR(SUM((D43/B43)-1),0) -> 0.18881724 | D43: =D41+D42 -> -366529 | E43: =IFERROR(SUM((F43/D43)-1),0) -> -0.38074204 | F43: =F41+F42 -> -226976 | G43: =IFERROR(SUM((H43/F43)-1),0) -> 0.052785317 | H43: =H41+H42 -> -238957
A45: EBITIDA (LAJIDA) | B45: =B48-B47-B38-B43-B35 -> 562129 | C45: =IFERROR(SUM((D45/B45)-1),0) -> 0.026735856 | D45: =D48-D47-D38-D43-D35 -> 577158 | E45: =IFERROR(SUM((F45/D45)-1),0) -> -0.049165047 | F45: =F48-F47-F38-F43-F35 -> 548782 | G45: =IFERROR(SUM((H45/F45)-1),0) -> -0.044607877 | H45: =H48-H47-H38-H43-H35 -> 524302
A46: Resultado antes do Imposto | B46: =B39+B43 -> 215771 | C46: =IFERROR(SUM((D46/B46)-1),0) -> -0.19536453 | D46: =D39+D43 -> 173617 | E46: =IFERROR(SUM((F46/D46)-1),0) -> 0.71065621 | F46: =F39+F43 -> 296999 | G46: =IFERROR(SUM((H46/F46)-1),0) -> -0.10375119 | H46: =H39+H43 -> 266185
A47: Impostos | B47: -23197 | C47: =IFERROR(SUM((D47/B47)-1),0) -> -2.4296676 | D47: 33164 | E47: =IFERROR(SUM((F47/D47)-1),0) -> -0.20802678 | F47: 26265 | G47: =IFERROR(SUM((H47/F47)-1),0) -> 0.78633162 | H47: 46918
A48: Lucro Liquido | B48: =B46+B47 -> 192574 | C48: =IFERROR(SUM((D48/B48)-1),0) -> 0.073774237 | D48: =D46+D47 -> 206781 | E48: =IFERROR(SUM((F48/D48)-1),0) -> 0.56331578 | F48: =F46+F47 -> 323264 | G48: =IFERROR(SUM((H48/F48)-1),0) -> -0.031432513 | H48: =H46+H47 -> 313103
A50: DFC
A51: FCO – Fluxo Operacional | B51: 1_T | C51: AH% (2/1) | D51: 2_T | E51: AH% (3/2) | F51: 3_T | G51: AH% (4/3) | H51: 4_T
A52: Lucro Líquido | B52: =B48 -> 192574 | C52: =IFERROR(SUM((D52/B52)-1),0) -> 1.0737742 | D52: =SUM(B52,D48) -> 399355 | E52: =IFERROR(SUM((F52/D52)-1),0) -> 0.80946526 | F52: =SUM(D52,F48) -> 722619 | G52: =IFERROR(SUM((H52/F52)-1),0) -> 0.43328919 | H52: =SUM(F52,H48) -> 1035722
A53: Ajustes Não Caixa (subtotal) | B53: 587038 | C53: =IFERROR(SUM((D53/B53)-1),0) -> 1.0508996 | D53: 1203956 | E53: =IFERROR(SUM((F53/D53)-1),0) -> 0.39621298 | F53: 1680979 | G53: =IFERROR(SUM((H53/F53)-1),0) -> 0.33888942 | H53: 2250645
A54: Variação Ativos e Passivo | B54: 8018 | C54: =IFERROR(SUM((D54/B54)-1),0) -> 8.5137191 | D54: 76281 | E54: =IFERROR(SUM((F54/D54)-1),0) -> 11.817831 | F54: 977757 | G54: =IFERROR(SUM((H54/F54)-1),0) -> 0.18107771 | H54: 1154807
A55: IR e contribuição social pagos | B55: -13738 | C55: =IFERROR(SUM((D55/B55)-1),0) -> 0.34626583 | D55: -18495 | E55: =IFERROR(SUM((F55/D55)-1),0) -> -0.27591241 | F55: -13392 | G55: =IFERROR(SUM((H55/F55)-1),0) -> 0.73304958 | H55: -23209
A56: FCO | B56: =SUM(B53:B55) -> 581318 | C56: =IFERROR(SUM((D56/B56)-1),0) -> 1.170485 | D56: =SUM(D53:D55) -> 1261742 | E56: =IFERROR(SUM((F56/D56)-1),0) -> 1.0965808 | F56: =SUM(F53:F55) -> 2645344 | G56: =IFERROR(SUM((H56/F56)-1),0) -> 0.27856453 | H56: =SUM(H53:H55) -> 3382243
A57: CAPEX
A58: Imobilizado e Intangível | B58: -323609 | C58: =IFERROR(SUM((D58/B58)-1),0) -> 0.48748953 | D58: -481365 | E58: =IFERROR(SUM((F58/D58)-1),0) -> -1 | F58: 0 | G58: =IFERROR(SUM((H58/F58)-1),0) -> 0 | H58: -1895606
A59: Ativos de Contrato | B59: 43308 | C59: =IFERROR(SUM((D59/B59)-1),0) -> 4.344486 | D59: 231459 | E59: =IFERROR(SUM((F59/D59)-1),0) -> -3.1293058 | F59: -492847 | G59: =IFERROR(SUM((H59/F59)-1),0) -> 0.15161703 | H59: -567571
A60: (Adições) baixas no investimento | B60: 0 | C60: =IFERROR(SUM((D60/B60)-1),0) -> 0 | D60: 0 | E60: =IFERROR(SUM((F60/D60)-1),0) -> 0 | F60: -1386146 | G60: =IFERROR(SUM((H60/F60)-1),0) -> -1 | H60: 0
A61: CAPEX | B61: =SUM(B58:B60) -> -280301 | C61: =IFERROR(SUM((D61/B61)-1),0) -> -0.108437 | D61: =SUM(D58:D60) -> -249906 | E61: =IFERROR(SUM((F61/D61)-1),0) -> 6.5187991 | F61: =SUM(F58:F60) -> -1878993 | G61: =IFERROR(SUM((H61/F61)-1),0) -> 0.3109027 | H61: =SUM(H58:H60) -> -2463177
A62: FCI – Investimentos | B62: =B61 -> -280301 | C62: =IFERROR(SUM((D62/B62)-1),0) -> -0.108437 | D62: =D61 -> -249906 | E62: =IFERROR(SUM((F62/D62)-1),0) -> 6.5187991 | F62: =F61 -> -1878993 | G62: =IFERROR(SUM((H62/F62)-1),0) -> 0.3109027 | H62: =H61 -> -2463177
A64: FCF – Financiamento
A65: Pagamento de Empréstimos Principal | B65: -908 | C65: =IFERROR(SUM((D65/B65)-1),0) -> 1.4372247 | D65: -2213 | E65: =IFERROR(SUM((F65/D65)-1),0) -> 169.95617 | F65: -378326 | G65: =IFERROR(SUM((H65/F65)-1),0) -> 0.0024000465 | H65: -379234
A66: Pagamento de Empréstimos Juros | B66: -617 | C66: =IFERROR(SUM((D66/B66)-1),0) -> 1.3727715 | D66: -1464 | E66: =IFERROR(SUM((F66/D66)-1),0) -> 15.30806 | F66: -23875 | G66: =IFERROR(SUM((H66/F66)-1),0) -> 0.019225131 | H66: -24334
A67: Captação de debêntures | B67: 799590 | C67: =IFERROR(SUM((D67/B67)-1),0) -> -0.0022486524 | D67: 797792 | E67: =IFERROR(SUM((F67/D67)-1),0) -> 0.75518055 | F67: 1400269 | G67: =IFERROR(SUM((H67/F67)-1),0) -> 0.63777031 | H67: 2293319
A68: Pagamento de debêntures - principal | B68: -248306 | C68: =IFERROR(SUM((D68/B68)-1),0) -> 3.5624471 | D68: -1132883 | E68: =IFERROR(SUM((F68/D68)-1),0) -> -0.35991625 | F68: -725140 | G68: =IFERROR(SUM((H68/F68)-1),0) -> 0.45699865 | H68: -1056528
A69: Pagamento de debêntures - juros | B69: -200465 | C69: =IFERROR(SUM((D69/B69)-1),0) -> 0.97397551 | D69: -395713 | E69: =IFERROR(SUM((F69/D69)-1),0) -> 0.42565192 | F69: -564149 | G69: =IFERROR(SUM((H69/F69)-1),0) -> 0.36287577 | H69: -768865
A70: Pagamento/Recebimento financeiros | B70: 1428 | C70: =IFERROR(SUM((D70/B70)-1),0) -> -115.55672 | D70: -163587 | E70: =IFERROR(SUM((F70/D70)-1),0) -> -1.0270804 | F70: 4430 | G70: =IFERROR(SUM((H70/F70)-1),0) -> 5.2503386 | H70: 27689
A71: Arrendamentos | B71: 0 | C71: =IFERROR(SUM((D71/B71)-1),0) -> 0 | D71: 0 | E71: =IFERROR(SUM((F71/D71)-1),0) -> 0 | F71: 0 | G71: =IFERROR(SUM((H71/F71)-1),0) -> 0 | H71: 0
A72: Pagamento de dividendos e JCP | B72: -302214 | C72: =IFERROR(SUM((D72/B72)-1),0) -> 1.1408836 | D72: -647005 | E72: =IFERROR(SUM((F72/D72)-1),0) -> -0.040763209 | F72: -620631 | G72: =IFERROR(SUM((H72/F72)-1),0) -> 0.644283 | H72: -1020493
A73: FCF | B73: =SUM(B65:B72) -> 48508 | C73: =IFERROR(SUM((D73/B73)-1),0) -> -32.851921 | D73: =SUM(D65:D72) -> -1545073 | E73: =IFERROR(SUM((F73/D73)-1),0) -> -0.41269959 | F73: =SUM(F65:F72) -> -907422 | G73: =IFERROR(SUM((H73/F73)-1),0) -> 0.023168934 | H73: =SUM(H65:H72) -> -928446
A75: Fechamento | B75: =SUM(B56,B62,B73) -> 349525 | C75: =IFERROR(SUM((D75/B75)-1),0) -> -2.5256047 | D75: =SUM(D56,D62,D73) -> -533237 | E75: =IFERROR(SUM((F75/D75)-1),0) -> -0.73544409 | F75: =SUM(F56,F62,F73) -> -141071 | G75: =IFERROR(SUM((H75/F75)-1),0) -> -0.93350866 | H75: =SUM(H56,H62,H73) -> -9380
A76: Caixa Inicial | B76: 741596 | C76: =IFERROR(SUM((D76/B76)-1),0) -> 0 | D76: 741596 | E76: =IFERROR(SUM((F76/D76)-1),0) -> 0.012648396 | F76: 750976 | G76: =IFERROR(SUM((H76/F76)-1),0) -> 0 | H76: 750976
A77: Caixa Final | B77: =SUM(B75:B76) -> 1091121 | C77: =IFERROR(SUM((D77/B77)-1),0) -> -0.80904134 | D77: =SUM(D75:D76) -> 208359 | E77: =IFERROR(SUM((F77/D77)-1),0) -> 1.9271834 | F77: =SUM(F75:F76) -> 609905 | G77: =IFERROR(SUM((H77/F77)-1),0) -> 0.21592051 | H77: =SUM(H75:H76) -> 741596

Sheet ISAE4
B1: Feito | C1: 46058 | D1: Atual | E1: 46237 | F1: Não | G1: 46058 | H1: Não | I1: 46058 | J1: Ultimo_Balanco | K1: {=IFERROR(INDEX(Indicador_Ações[], MATCH($J$2, Indicador_Ações[Stock], 0), MATCH(Indicador_Ações[[#HEADERS],[ult_balanco_processado]], Indicador_Ações[#HEADERS], 0)),"")} -> 46203
A2: Balanço Patrimonial Anual | J2: ISAE4 | K2: =IFERROR(__xludf.DUMMYFUNCTION("(GOOGLEFINANCE(""BVMF:"" & J2))"),27.74) -> 27.74 | L2: {=IFERROR(INDEX(Indicador_Ações[], MATCH($J$2, Indicador_Ações[Stock], 0), MATCH(Indicador_Ações[[#HEADERS],[qtd_acao]], Indicador_Ações[#HEADERS], 0)),"")} -> 703328000 | M2: Numero_Papel
A3: Ano | B3: 1_T | C3: AH% (2/1) | D3: 2_T | E3: AH% (3/2) | F3: 3_T | G3: AH% (4/3) | H3: 4_T | J3: BP | K3: 1000 | L3: =IFERROR(K23/K15,0) -> 0.34823637 | M3: MARGEM LÍQUIDA | N3: DMPL Acumulado
A4: Ativo Total | B4: =B5+B6 -> 30704682 | C4: =IFERROR(SUM((D4/B4)-1),0) -> 0.041641662 | D4: =D5+D6 -> 31983276 | E4: =IFERROR(SUM((F4/D4)-1),0) -> -0.086219842 | F4: =F5+F6 -> 29225683 | G4: =IFERROR(SUM((H4/F4)-1),0) -> 0.039946748 | H4: =H5+H6 -> 30393154 | J4: Ativo | K4: {=IFERROR(INDEX(Indicador_Ações[], MATCH($J$2, Indicador_Ações[Stock], 0), MATCH(Indicador_Ações[[#HEADERS],[ativo]], Indicador_Ações[#HEADERS], 0)),"")} -> 49954800000 | L4: =IFERROR(K20/K15,0) -> 0.67030512 | M4: MARGEM BRUTA | N4: JCP acionistas Liquido | O4: 279322
A5: Ativo Circulante | B5: 2420425 | C5: =IFERROR(SUM((D5/B5)-1),0) -> 0.19946538 | D5: 2903216 | E5: =IFERROR(SUM((F5/D5)-1),0) -> 0.25989144 | F5: 3657737 | G5: =IFERROR(SUM((H5/F5)-1),0) -> -0.11223224 | H5: 3247221 | J5: Valor_de_mercado | K5: =K2*L2 -> 19510318720 | L5: =IFERROR(K17/K15,0) -> 0.29077953 | M5: MARGEM EBIT | N5: JCP acionistas Liquido 2 | O5: 0
A6: Ativo Nao Circ. | B6: 28284257 | C6: =IFERROR(SUM((D6/B6)-1),0) -> 0.028135899 | D6: 29080060 | E6: =IFERROR(SUM((F6/D6)-1),0) -> -0.12077396 | F6: 25567946 | G6: =IFERROR(SUM((H6/F6)-1),0) -> 0.061717394 | H6: 27145933 | J6: Valor_da_firma | K6: =SUM(K5,K10) -> 35478758720 | L6: =IFERROR(K18/K15,0) -> 0.80006764 | M6: MARGEM EBITDA | N6: Dividendos | O6: 2357
J7: Disponibilidade | K7: {=IFERROR(INDEX(Indicador_Ações[], MATCH($J$2, Indicador_Ações[Stock], 0), MATCH(Indicador_Ações[[#HEADERS],[disponibilidades]], Indicador_Ações[#HEADERS], 0)),"")} -> 1757260000 | L7: =K23/L2 -> 2.3086696 | M7: LPA | N7: Dividendos e JCP | O7: =SUM(O4:O6) -> 281679
A8: Estoque | B8: 49774 | C8: =IFERROR(SUM((D8/B8)-1),0) -> 0.098545425 | D8: 54679 | E8: =IFERROR(SUM((F8/D8)-1),0) -> -0.10075166 | F8: 49170 | G8: =IFERROR(SUM((H8/F8)-1),0) -> -0.022696766 | H8: 48054 | J8: Patrimônio líq | K8: {=IFERROR(INDEX(Indicador_Ações[], MATCH($J$2, Indicador_Ações[Stock], 0), MATCH(Indicador_Ações[[#HEADERS],[patrimonio_liquido]], Indicador_Ações[#HEADERS], 0)),"")} -> 22159400000 | L8: {=IFERROR(INDEX(O7*K3,0)/L2,"")} -> 0.40049451 | M8: DPA Liquido | N8: Aliquota | O8: =ABS(SUM(B47,D47,F47,H47)/SUM(B46,D46,F46,H46)) -> 0.027844665
A9: Caixa | B9: 639620 | C9: =IFERROR(SUM((D9/B9)-1),0) -> -0.26722273 | D9: 468699 | E9: =IFERROR(SUM((F9/D9)-1),0) -> 0.53440908 | F9: 719176 | G9: =IFERROR(SUM((H9/F9)-1),0) -> 0.88557738 | H9: 1356062 | J9: Dívida bruta | K9: {=IFERROR(INDEX(Indicador_Ações[], MATCH($J$2, Indicador_Ações[Stock], 0), MATCH(Indicador_Ações[[#HEADERS],[divida_bruta]], Indicador_Ações[#HEADERS], 0)),"")} -> 17725700000 | L9: =IFERROR(L8/L7,0) -> 0.17347415 | M9: Payout_Ajustado | N9: NOPAT | O9: =K17*(1-O8) -> 1318090005
A10: Títulos e valores mobiliários | B10: 669456 | C10: =IFERROR(SUM((D10/B10)-1),0) -> 0.92479416 | D10: 1288565 | E10: =IFERROR(SUM((F10/D10)-1),0) -> 0.32006224 | F10: 1700986 | G10: =IFERROR(SUM((H10/F10)-1),0) -> -0.52443818 | H10: 808924 | J10: Dívida líq | K10: =K9-K7 -> 15968440000 | L10: =IFERROR(K14/K4,0) -> 0.21368317 | M10: GIRO ATIVOS
A11: Disponibilidades | B11: =SUM(B9,B10) -> 1309076 | C11: =IFERROR(SUM((D11/B11)-1),0) -> 0.34236973 | D11: =SUM(D9,D10) -> 1757264 | E11: =IFERROR(SUM((F11/D11)-1),0) -> 0.37723302 | F11: =SUM(F9,F10) -> 2420162 | G11: =IFERROR(SUM((H11/F11)-1),0) -> -0.10543757 | H11: =SUM(H9,H10) -> 2164986 | J11: Capital_Investido | K11: =SUM(K8,K9) -> 39885100000 | L11: =IFERROR(K24/K8,0) -> 0.12713205 | M11: ROE
J12: Razão de Divida | K12: =K9/K11 -> 0.44441909 | L12: =O9/K11 -> 0.033047178 | M12: ROIC
A13: Passivo Total | B13: =SUM(B14+B15) -> 20087970 | C13: =IFERROR(SUM((D13/B13)-1),0) -> 0.056154106 | D13: =SUM(D14+D15) -> 21215992 | E13: =IFERROR(SUM((F13/D13)-1),0) -> -0.12589975 | F13: =SUM(F14+F15) -> 18544904 | G13: =IFERROR(SUM((H13/F13)-1),0) -> 0.073316691 | H13: =SUM(H14+H15) -> 19904555 | J13: DRE | L13: =IFERROR(K24/K4,0) -> 0.056394381 | M13: ROA
A14: Passivo Circ. | B14: 1618504 | C14: =IFERROR(SUM((D14/B14)-1),0) -> -0.16030112 | D14: 1359056 | E14: =IFERROR(SUM((F14/D14)-1),0) -> 0.16557154 | F14: 1584077 | G14: =IFERROR(SUM((H14/F14)-1),0) -> 0.19128616 | H14: 1887089 | J14: Receita_IFRS | K14: {=IFERROR(INDEX(Indicador_Ações[], MATCH($J$2, Indicador_Ações[Stock], 0), MATCH(Indicador_Ações[[#HEADERS],[receita_liquida_12m]], Indicador_Ações[#HEADERS], 0)),"")} -> 10674500000 | L14: =K6/K18 -> 9.510342 | M14: EV/EBITDA
A15: Passivo Não Circ. | B15: 18469466 | C15: =IFERROR(SUM((D15/B15)-1),0) -> 0.075122367 | D15: 19856936 | E15: =IFERROR(SUM((F15/D15)-1),0) -> -0.14584874 | F15: 16960827 | G15: =IFERROR(SUM((H15/F15)-1),0) -> 0.06229879 | H15: 18017466 | J15: Receita REG | K15: =IFERROR(SUM(B32,D32,F32,H32),"")*K3 -> 4662787000 | L15: =K18/K6 -> 0.10514869 | M15: Earnings_Yield_Greenblatt
A16: Emprést. CP | B16: 390701 | C16: =IFERROR(SUM((D16/B16)-1),0) -> 0.13336285 | D16: 442806 | E16: =IFERROR(SUM((F16/D16)-1),0) -> -0.034931776 | F16: 427338 | G16: =IFERROR(SUM((H16/F16)-1),0) -> 0.3714741 | H16: 586083 | J16: Cagr_receita_5a | K16: {=IFERROR(INDEX(Indicador_Ações[], MATCH($J$2, Indicador_Ações[Stock], 0), MATCH(Indicador_Ações[[#HEADERS],[cagr_receita_5a]], Indicador_Ações[#HEADERS], 0)),"")} -> 17 | L16: =IFERROR(K10/K18,0) -> 4.2804577 | M16: DÍVIDA LÍQUIDA / EBITDA
A17: Emprést. LP | B17: 15855349 | C17: =IFERROR(SUM((D17/B17)-1),0) -> 0.087016628 | D17: 17235028 | E17: =IFERROR(SUM((F17/D17)-1),0) -> -0.16850103 | F17: 14330908 | G17: =IFERROR(SUM((H17/F17)-1),0) -> 0.072202124 | H17: 15365630 | J17: EBIT Reg | K17: =SUM(B42,D42,F42,H42)*K3 -> 1355843000 | L17: =IFERROR(SUM(B5,D5,F5,H5)/SUM(B14,D14,F14,H14),0) -> 1.8962814 | M17: LIQUIDEZ CORRENTE
J18: EBITDA Reg | K18: =IFERROR(SUM(B45,D45,F45,H45),"")*K3 -> 3730545000 | L18: =SUM(B42,D42,F42,H42)/ABS(SUM(B37,D37,F37,H37)) -> 0.64220647 | M18: Indice de Cobertura de Juros MEDIA
A19: ENDIVIDAMENTO / CAIXA | J19: Custo_Mercadoria | K19: =SUM(B31,D31,F31,H31)*K3 -> -715567000 | L19: =IFERROR(K4/K8,0) -> 2.254339 | M19: Alavancagem_Financeira
A20: Dívida bruta | B20: =SUM(B17,B16) -> 16246050 | C20: =IFERROR(SUM((D20/B20)-1),0) -> 0.088131207 | D20: =SUM(D17,D16) -> 17677834 | E20: =IFERROR(SUM((F20/D20)-1),0) -> -0.1651553 | F20: =SUM(F17,F16) -> 14758246 | G20: =IFERROR(SUM((H20/F20)-1),0) -> 0.080867808 | H20: =SUM(H17,H16) -> 15951713 | J20: Lucro bruto | K20: =IFERROR(SUM(B34,D34,F34,H34),"")*K3 -> 3125490000 | L20: =K10/K8 -> 0.72061698 | M20: DL/PL
A21: Dívida líq | B21: =SUM(B20-B11) -> 14936974 | C21: =IFERROR(SUM((D21/B21)-1),0) -> 0.06584975 | D21: =SUM(D20-D11) -> 15920570 | E21: =IFERROR(SUM((F21/D21)-1),0) -> -0.22502247 | F21: =SUM(F20-F11) -> 12338084 | G21: =IFERROR(SUM((H21/F21)-1),0) -> 0.11741231 | H21: =SUM(H20-H11) -> 13786727 | J21: Despesas operacionais REG | K21: =IFERROR(SUM(B33,D33,F33,H33),"")*K3 -> -1537297000 | M21: CPM
J22: Inflação | K22: ='Indicadores_Ações'!$B$4 -> 0.044430246 | L22: ='Indicadores_Ações'!$B$3 -> 0.139 | M22: RF
A23: Patrimônio líq. | B23: =B4-B13 -> 10616712 | C23: =IFERROR(SUM((D23/B23)-1),0) -> 0.014182545 | D23: =D4-D13 -> 10767284 | E23: =IFERROR(SUM((F23/D23)-1),0) -> -0.0080340595 | F23: =F4-F13 -> 10680779 | G23: =IFERROR(SUM((H23/F23)-1),0) -> -0.01799307 | H23: =H4-H13 -> 10488599 | J23: Lucro_Anual REG_Planilha | K23: =SUM(B48,D48,F48,H48)*K3 -> 1623752000 | L23: =K25 -> 0.81 | M23: Beta (B)
J24: Lucro_Liquido_Fundamentus | K24: {=IFERROR(INDEX(Indicador_Ações[], MATCH($J$2, Indicador_Ações[Stock], 0), MATCH(Indicador_Ações[[#HEADERS],[lucro_liquido_12m]], Indicador_Ações[#HEADERS], 0)),"")} -> 2817170000 | L24: =L22+0.02 -> 0.159 | M24: RM
A25: Reserva de Capital | B25: 666 | C25: =IFERROR(SUM((D25/B25)-1),0) -> 0 | D25: 666 | E25: =IFERROR(SUM((F25/D25)-1),0) -> 0 | F25: 666 | G25: =IFERROR(SUM((H25/F25)-1),0) -> 0 | H25: 666 | J25: Beta | K25: {=IFERROR(INDEX(Indicador_Ações[], MATCH($J$2, Indicador_Ações[Stock], 0), MATCH(Indicador_Ações[[#HEADERS],[beta_ibov_3a]], Indicador_Ações[#HEADERS], 0)),"")} -> 0.81 | L25: =L22+L23*(L24-L22) -> 0.1552 | M25: KE
A26: Reserva de Lucro | B26: 3859010 | C26: =IFERROR(SUM((D26/B26)-1),0) -> 0.05488247 | D26: 4070802 | E26: =IFERROR(SUM((F26/D26)-1),0) -> -0.055397438 | F26: 3845290 | G26: =IFERROR(SUM((H26/F26)-1),0) -> -0.026741546 | H26: 3742461
A28: DRE Analise Trimestral | J28: Ticker | K28: Valores | L28: Ano | M28: VLF | N28: VLP | O28: Cresc | Q28: Ano | R28: Fluxo
A29: Trimestre | B29: 1_T | C29: AH% (2/1) | D29: 2_T | E29: AH% (3/2) | F29: 3_T | G29: AH% (4/3) | H29: 4_T | J29: Preço_Mercado | K29: =K2 -> 27.74 | L29: 1 | M29: =K34 -> 1623752000 | O29: 10 | Q29: 0 | R29: =-K6 -> -35478758720
A30: Receita Operacional Bruta | B30: 1393479 | C30: =IFERROR(SUM((D30/B30)-1),0) -> 0.019869693 | D30: 1421167 | E30: =IFERROR(SUM((F30/D30)-1),0) -> -0.12003164 | F30: 1250582 | G30: =IFERROR(SUM((H30/F30)-1),0) -> 0.050011914 | H30: 1313126 | J30: Numero_Papel | K30: =L2 -> 703328000 | L30: 2 | M30: =M29*(1+O29/100) -> 1786127200 | N30: =M30/(1+K35)^L29 -> 1546162742 | O30: 10 | Q30: 1 | R30: =M30 -> 1786127200
A31: Deduções da receita Bruta | B31: -167215 | C31: =IFERROR(SUM((D31/B31)-1),0) -> 0.063259875 | D31: -177793 | E31: =IFERROR(SUM((F31/D31)-1),0) -> 0.0025647804 | F31: -178249 | G31: =IFERROR(SUM((H31/F31)-1),0) -> 0.078884033 | H31: -192310 | J31: Market | K31: =P21 | L31: 3 | M31: =M30*(1+O30/100) -> 1964739920 | N31: =M31/(1+K35)^L30 -> 1472281005 | O31: 10 | Q31: 2 | R31: =M31 -> 1964739920
A32: Receita Operacional Liquida | B32: =SUM(B30,B31) -> 1226264 | C32: =IFERROR(SUM((D32/B32)-1),0) -> 0.01395295 | D32: =SUM(D30,D31) -> 1243374 | E32: =IFERROR(SUM((F32/D32)-1),0) -> -0.13756199 | F32: =SUM(F30,F31) -> 1072333 | G32: =IFERROR(SUM((H32/F32)-1),0) -> 0.045212635 | H32: =SUM(H30,H31) -> 1120816 | J32: Taxa_Cresc | K32: =SUM(O29:O37)/6 -> 9.5 | L32: 4 | M32: =M31*(1+O31/100) -> 2161213912 | N32: =M32/(1+K35)^L31 -> 1401929627 | O32: 9 | Q32: 3 | R32: =M32 -> 2161213912
A33: Custos e Despesas | B33: -349209 | C33: =IFERROR(SUM((D33/B33)-1),0) -> 0.25040019 | D33: -436651 | E33: =IFERROR(SUM((F33/D33)-1),0) -> -0.18643264 | F33: -355245 | G33: =IFERROR(SUM((H33/F33)-1),0) -> 0.11526411 | H33: -396192 | J33: Taxa_Gordon | K33: 0.04 | L33: 5 | M33: =M32*(1+O32/100) -> 2355723164 | N33: =M33/(1+K35)^L32 -> 1322804098 | O33: 9 | Q33: 4 | R33: =M33 -> 2355723164
A34: Lucro Operacional Bruto | B34: =B32+B33 -> 877055 | C34: =IFERROR(SUM((D34/B34)-1),0) -> -0.080191094 | D34: =D32+D33 -> 806723 | E34: =IFERROR(SUM((F34/D34)-1),0) -> -0.11111001 | F34: =F32+F33 -> 717088 | G34: =IFERROR(SUM((H34/F34)-1),0) -> 0.01050917 | H34: =H32+H33 -> 724624 | J34: Receita_LL_REG | K34: =$K$23 -> 1623752000 | L34: 6 | M34: =M33*(1+O33/100) -> 2567738249 | N34: =M34/(1+K35)^L33 -> 1248144448 | O34: 9 | Q34: 5 | R34: =M34 -> 2567738249
J35: Taxa_desconto_KE | K35: =L25 -> 0.1552 | L35: 7 | M35: =M34*(1+O34/100) -> 2798834691 | N35: =M35/(1+K35)^L34 -> 1177698622 | Q35: 6 | R35: =M35+M36 -> 28066092321
A36: Receita Financeira | B36: 64291 | C36: =IFERROR(SUM((D36/B36)-1),0) -> -0.016207556 | D36: 63249 | E36: =IFERROR(SUM((F36/D36)-1),0) -> 0.60377239 | F36: 101437 | G36: =IFERROR(SUM((H36/F36)-1),0) -> 0.11006832 | H36: 112602 | J36: Valor_ação_Proj | K36: =K37/K30 -> 24.700599 | L36: Perpétuo | M36: =IFERROR( M35 * (1 + K33) / (K35 -K33 ), 0 ) -> 25267257629 | N36: =M36/(1+K35)^L35 -> 9203602363 | Q36: TIR | R36: =IFERROR(IRR(R29:R35),0) -> 0.017886036
A37: Despesa Financeira | B37: -547195 | C37: =IFERROR(SUM((D37/B37)-1),0) -> 0.28321348 | D37: -702168 | E37: =IFERROR(SUM((F37/D37)-1),0) -> -0.43806753 | F37: -394571 | G37: =IFERROR(SUM((H37/F37)-1),0) -> 0.18430397 | H37: -467292 | J37: Market_Proj | K37: =N37 -> 17372622905 | N37: =SUM(N29:N36) -> 17372622905
A38: Resultado Financeiro | B38: =B36+B37 -> -482904 | C38: =IFERROR(SUM((D38/B38)-1),0) -> 0.32307664 | D38: =D36+D37 -> -638919 | E38: =IFERROR(SUM((F38/D38)-1),0) -> -0.54120319 | F38: =F36+F37 -> -293134 | G38: =IFERROR(SUM((H38/F38)-1),0) -> 0.2099927 | H38: =H36+H37 -> -354690
A40: Resultado de equivalência patrimonial | B40: 83784 | C40: =IFERROR(SUM((D40/B40)-1),0) -> -0.053876635 | D40: 79270 | E40: =IFERROR(SUM((F40/D40)-1),0) -> 0.26611581 | F40: 100365 | G40: =IFERROR(SUM((H40/F40)-1),0) -> -0.11099487 | H40: 89225
A41: Outras Receitas/Despesas Operacionais | B41: -25391 | C41: =IFERROR(SUM((D41/B41)-1),0) -> 1.4379111 | D41: -61901 | E41: =IFERROR(SUM((F41/D41)-1),0) -> -1.0619215 | F41: 3833 | G41: =IFERROR(SUM((H41/F41)-1),0) -> -12.809027 | H41: -45264
A42: Lucro Operacional (EBIT)(LAJIR) | B42: =SUM(B34,B38) -> 394151 | C42: =IFERROR(SUM((D42/B42)-1),0) -> -0.57426469 | D42: =SUM(D34,D38) -> 167804 | E42: =IFERROR(SUM((F42/D42)-1),0) -> 1.5264833 | F42: =SUM(F34,F38) -> 423954 | G42: =IFERROR(SUM((H42/F42)-1),0) -> -0.12741948 | H42: =SUM(H34,H38) -> 369934
A44: Depreciações e Amortizações | B44: -169511 | C44: =IFERROR(SUM((D44/B44)-1),0) -> 0.31006247 | D44: -222070 | E44: =IFERROR(SUM((F44/D44)-1),0) -> -0.24545864 | F44: -167561 | G44: =IFERROR(SUM((H44/F44)-1),0) -> 0.042223429 | H44: -174636
A45: EBITIDA (LAJIDA) | B45: =B48-B47-B40-B38-B44 -> 1021175 | C45: =IFERROR(SUM((D45/B45)-1),0) -> -0.053157392 | D45: =D48-D47-D40-D38-D44 -> 966892 | E45: =IFERROR(SUM((F45/D45)-1),0) -> -0.08109489 | F45: =F48-F47-F40-F38-F44 -> 888482 | G45: =IFERROR(SUM((H45/F45)-1),0) -> -0.038814517 | H45: =H48-H47-H40-H38-H44 -> 853996
A46: Resultado antes do Imposto | B46: =SUM(B40:B41,B42) -> 452544 | C46: =IFERROR(SUM((D46/B46)-1),0) -> -0.59081769 | D46: =SUM(D40:D41,D42) -> 185173 | E46: =IFERROR(SUM((F46/D46)-1),0) -> 1.8522085 | F46: =SUM(F40:F41,F42) -> 528152 | G46: =IFERROR(SUM((H46/F46)-1),0) -> -0.21633356 | H46: =SUM(H40:H41,H42) -> 413895
A47: Impostos | B47: -84721 | C47: =IFERROR(SUM((D47/B47)-1),0) -> -1.0406511 | D47: 3444 | E47: =IFERROR(SUM((F47/D47)-1),0) -> 10.571719 | F47: 39853 | G47: =IFERROR(SUM((H47/F47)-1),0) -> 1.1431762 | H47: 85412
A48: Lucro Liquido | B48: =B46+B47 -> 367823 | C48: =IFERROR(SUM((D48/B48)-1),0) -> -0.48720716 | D48: =D46+D47 -> 188617 | E48: =IFERROR(SUM((F48/D48)-1),0) -> 2.01142 | F48: =F46+F47 -> 568005 | G48: =IFERROR(SUM((H48/F48)-1),0) -> -0.12094612 | H48: =H46+H47 -> 499307
A50: DFC
A51: FCO – Fluxo Operacional | B51: 1_T | C51: AH% (2/1) | D51: 2_T | E51: AH% (3/2) | F51: 3_T | G51: AH% (4/3) | H51: 4_T
A52: Lucro Líquido | B52: =B48 -> 367823 | C52: =IFERROR(SUM((D52/B52)-1),0) -> 0.51279284 | D52: =SUM(B52,D48) -> 556440 | E52: =IFERROR(SUM((F52/D52)-1),0) -> 1.0207839 | F52: =SUM(D52,F48) -> 1124445 | G52: =IFERROR(SUM((H52/F52)-1),0) -> 0.44404751 | H52: =SUM(F52,H48) -> 1623752
A53: Ajustes Não Caixa (subtotal) | B53: 1695046 | C53: =IFERROR(SUM((D53/B53)-1),0) -> 0.14033719 | D53: 1932924 | E53: =IFERROR(SUM((F53/D53)-1),0) -> 0.37684668 | F53: 2661340 | G53: =IFERROR(SUM((H53/F53)-1),0) -> 0.3600021 | H53: 3619428
A54: Variação Ativos | B54: -125449 | C54: =IFERROR(SUM((D54/B54)-1),0) -> 1.1645848 | D54: -271545 | E54: =IFERROR(SUM((F54/D54)-1),0) -> -3.386702 | F54: 648097 | G54: =IFERROR(SUM((H54/F54)-1),0) -> -0.484392 | H54: 334164
A55: Variação Passivo | B55: 26705 | C55: =IFERROR(SUM((D55/B55)-1),0) -> 0.93169818 | D55: 51586 | E55: =IFERROR(SUM((F55/D55)-1),0) -> -2.7926763 | F55: -92477 | G55: =IFERROR(SUM((H55/F55)-1),0) -> -1.4300204 | H55: 39767
A56: FCO | B56: =SUM(B53,B54,B55) -> 1596302 | C56: =IFERROR(SUM((D56/B56)-1),0) -> 0.073083289 | D56: =SUM(D53,D54,D55) -> 1712965 | E56: =IFERROR(SUM((F56/D56)-1),0) -> 0.87800685 | F56: =SUM(F53,F54,F55) -> 3216960 | G56: =IFERROR(SUM((H56/F56)-1),0) -> 0.24134556 | H56: =SUM(H53,H54,H55) -> 3993359
A58: CAPEX
A59: Imobilizado | B59: -1973093 | C59: =IFERROR(SUM((D59/B59)-1),0) -> 0.1255288 | D59: -2220773 | E59: =IFERROR(SUM((F59/D59)-1),0) -> 0.51281828 | F59: -3359626 | G59: =IFERROR(SUM((H59/F59)-1),0) -> 0.56403778 | H59: -5254582
A60: Intangível | B60: 0 | C60: =IFERROR(SUM((D60/B60)-1),0) -> 0 | D60: 0 | E60: =IFERROR(SUM((F60/D60)-1),0) -> 0 | F60: 0 | G60: =IFERROR(SUM((H60/F60)-1),0) -> 0 | H60: 0
A61: Ativos de Contrato | B61: -753780 | C61: =IFERROR(SUM((D61/B61)-1),0) -> 1.340204 | D61: -1763999 | E61: =IFERROR(SUM((F61/D61)-1),0) -> 1.8874132 | F61: -5093394 | G61: =IFERROR(SUM((H61/F61)-1),0) -> 0.36439357 | H61: -6949394
A62: CAPEX | B62: =SUM(B59:B61) -> -2726873 | C62: =IFERROR(SUM((D62/B62)-1),0) -> 0.46129724 | D62: =SUM(D59:D61) -> -3984772 | E62: =IFERROR(SUM((F62/D62)-1),0) -> 1.1213309 | F62: =SUM(F59:F61) -> -8453020 | G62: =IFERROR(SUM((H62/F62)-1),0) -> 0.44374153 | H62: =SUM(H59:H61) -> -12203976
A63: Resgates de Aplicações financeiras | B63: 1016158 | C63: =IFERROR(SUM((D63/B63)-1),0) -> 0.33213142 | D63: 1353656 | E63: =IFERROR(SUM((F63/D63)-1),0) -> 2.0401557 | F63: 4115325 | G63: =IFERROR(SUM((H63/F63)-1),0) -> 0.62990262 | H63: 6707579
A64: Caixa Restrito | B64: -570 | C64: =IFERROR(SUM((D64/B64)-1),0) -> 1.0754386 | D64: -1183 | E64: =IFERROR(SUM((F64/D64)-1),0) -> -1.7387997 | F64: 874 | G64: =IFERROR(SUM((H64/F64)-1),0) -> -0.7173913 | H64: 247
A65: Dividendos recebidos | B65: 58915 | C65: =IFERROR(SUM((D65/B65)-1),0) -> 1.9802257 | D65: 175580 | E65: =IFERROR(SUM((F65/D65)-1),0) -> -1 | F65: 0 | G65: =IFERROR(SUM((H65/F65)-1),0) -> 0 | H65: 661221
A66: FCI – Investimentos | B66: =SUM(B62:B65) -> -1652370 | C66: =IFERROR(SUM((D66/B66)-1),0) -> 0.48678504 | D66: =SUM(D62:D65) -> -2456719 | E66: =IFERROR(SUM((F66/D66)-1),0) -> 0.7652898 | F66: =SUM(F62:F65) -> -4336821 | G66: =IFERROR(SUM((H66/F66)-1),0) -> 0.11485556 | H66: =SUM(H62:H65) -> -4834929
A68: FCF – Financiamento
A69: Emissão debêntures | B69: 3837665 | C69: =IFERROR(SUM((D69/B69)-1),0) -> 0.24801227 | D69: 4789453 | E69: =IFERROR(SUM((F69/D69)-1),0) -> -0.58088178 | F69: 2007347 | G69: =IFERROR(SUM((H69/F69)-1),0) -> 0.95362436 | H69: 3921602
A70: Pag de Emp e debêntures Principal | B70: -3656998 | C70: =IFERROR(SUM((D70/B70)-1),0) -> 0.011460493 | D70: -3698909 | E70: =IFERROR(SUM((F70/D70)-1),0) -> -0.72149301 | F70: -1030172 | G70: =IFERROR(SUM((H70/F70)-1),0) -> 0.71940996 | H70: -1771288
A71: Pag de Emp e debêntures Juros | B71: -417819 | C71: =IFERROR(SUM((D71/B71)-1),0) -> 0.35979934 | D71: -568150 | E71: =IFERROR(SUM((F71/D71)-1),0) -> 0.26659509 | F71: -719616 | G71: =IFERROR(SUM((H71/F71)-1),0) -> 0.6035052 | H71: -1153908
A72: Amortizações | B72: =SUM(B70:B71) -> -4074817 | C72: =IFERROR(SUM((D72/B72)-1),0) -> 0.04717807 | D72: =SUM(D70:D71) -> -4267059 | E72: =IFERROR(SUM((F72/D72)-1),0) -> -0.58993114 | F72: =SUM(F70:F71) -> -1749788 | G72: =IFERROR(SUM((H72/F72)-1),0) -> 0.67174309 | H72: =SUM(H70:H71) -> -2925196
A73: Arrendamentos | B73: -5966 | C73: =IFERROR(SUM((D73/B73)-1),0) -> 1.0068723 | D73: -11973 | E73: =IFERROR(SUM((F73/D73)-1),0) -> -0.073415184 | F73: -11094 | G73: =IFERROR(SUM((H73/F73)-1),0) -> 0.53749775 | H73: -17057
A74: Pagamento/Recebimento financeiros | B74: -3958 | C74: =IFERROR(SUM((D74/B74)-1),0) -> -3.4656392 | D74: 9759 | E74: =IFERROR(SUM((F74/D74)-1),0) -> 0.39973358 | F74: 13660 | G74: =IFERROR(SUM((H74/F74)-1),0) -> -0.64502196 | H74: 4849
A75: Dividendos/JCP | B75: -413298 | C75: =IFERROR(SUM((D75/B75)-1),0) -> 0.60607842 | D75: -663789 | E75: =IFERROR(SUM((F75/D75)-1),0) -> 1.0124392 | F75: -1335835 | G75: =IFERROR(SUM((H75/F75)-1),0) -> 0.27359517 | H75: -1701313
A76: FCF | B76: =SUM(B69,B75,B72,B73,B74) -> -660374 | C76: =IFERROR(SUM((D76/B76)-1),0) -> -0.78253384 | D76: =SUM(D69,D75,D72,D73,D74) -> -143609 | E76: =IFERROR(SUM((F76/D76)-1),0) -> 6.4905472 | F76: =SUM(F69,F75,F72,F73,F74) -> -1075710 | G76: =IFERROR(SUM((H76/F76)-1),0) -> -0.33335657 | H76: =SUM(H69,H75,H72,H73,H74) -> -717115
A78: Fechamento | B78: =SUM(B56,B66,B76) -> -716442 | C78: =IFERROR(SUM((D78/B78)-1),0) -> 0.23856921 | D78: =SUM(D56,D66,D76) -> -887363 | E78: =IFERROR(SUM((F78/D78)-1),0) -> 1.4742648 | F78: =SUM(F56,F66,F76) -> -2195571 | G78: =IFERROR(SUM((H78/F78)-1),0) -> -0.29007762 | H78: =SUM(H56,H66,H76) -> -1558685
A79: Caixa Inicial | B79: 1356062 | C79: =IFERROR(SUM((D79/B79)-1),0) -> 0 | D79: 1356062 | E79: =IFERROR(SUM((F79/D79)-1),0) -> 1.1494202 | F79: 2914747 | G79: =IFERROR(SUM((H79/F79)-1),0) -> 0 | H79: 2914747
A80: Caixa Final | B80: =SUM(B78:B79) -> 639620 | C80: =IFERROR(SUM((D80/B80)-1),0) -> -0.26722273 | D80: =SUM(D78:D79) -> 468699 | E80: =IFERROR(SUM((F80/D80)-1),0) -> 0.53440908 | F80: =SUM(F78:F79) -> 719176 | G80: =IFERROR(SUM((H80/F80)-1),0) -> 0.88557738 | H80: =SUM(H78:H79) -> 1356062

Sheet SAPR4
B1: Feito | C1: 46058 | D1: Atual | E1: 46247 | F1: Não | G1: 46058 | H1: Não | I1: 46058 | J1: Ultimo_Balanco | K1: {=IFERROR(INDEX(Indicador_Ações[], MATCH($J$2, Indicador_Ações[Stock], 0), MATCH(Indicador_Ações[[#HEADERS],[ult_balanco_processado]], Indicador_Ações[#HEADERS], 0)),"")} -> 46203
A2: Balanço Patrimonial Anual | J2: SAPR4 | K2: =IFERROR(__xludf.DUMMYFUNCTION("(GOOGLEFINANCE(""BVMF:"" & J2))"),6.83) -> 6.83 | L2: {=IFERROR(INDEX(Indicador_Ações[], MATCH($J$2, Indicador_Ações[Stock], 0), MATCH(Indicador_Ações[[#HEADERS],[qtd_acao]], Indicador_Ações[#HEADERS], 0)),"")} -> 1511210000 | M2: Numero_Papel
A3: Ano | B3: 1_T | C3: AH% (2/1) | D3: 2_T | E3: AH% (3/2) | F3: 3_T | G3: AH% (4/3) | H3: 4_T | J3: BP | K3: 1000 | L3: =IFERROR(K22/K14,0) -> 0.060356984 | M3: Margem_Liquida | N3: DMPL Acumulado
A4: Ativo Total | B4: =B5+B6 -> 26827910 | C4: =IFERROR(SUM((D4/B4)-1),0) -> -0.01100902 | D4: =D5+D6 -> 26532561 | E4: =IFERROR(SUM((F4/D4)-1),0) -> -0.019991285 | F4: =F5+F6 -> 26002141 | G4: =IFERROR(SUM((H4/F4)-1),0) -> 0.017836339 | H4: =H5+H6 -> 26465924 | J4: Ativo | K4: {=IFERROR(INDEX(Indicador_Ações[], MATCH($J$2, Indicador_Ações[Stock], 0), MATCH(Indicador_Ações[[#HEADERS],[ativo]], Indicador_Ações[#HEADERS], 0)),"")} -> 26532600000 | L4: =IFERROR(K19/K14,0) -> 0.53760275 | M4: MARGEM BRUTA | N4: JCP acionistas Liquido | O4: 91430
A5: Ativo Circulante | B5: 7025965 | C5: =IFERROR(SUM((D5/B5)-1),0) -> -0.099903003 | D5: 6324050 | E5: =IFERROR(SUM((F5/D5)-1),0) -> 0.18396328 | F5: 7487443 | G5: =IFERROR(SUM((H5/F5)-1),0) -> -0.03537643 | H5: 7222564 | J5: Valor_de_mercado | K5: =K2*L2 -> 10321564300 | L5: =IFERROR(K16/K14,0) -> 0.33712864 | M5: MARGEM EBIT | N5: Dividendos | O5: 0
A6: Ativo Nao Circ. | B6: 19801945 | C6: =IFERROR(SUM((D6/B6)-1),0) -> 0.020531619 | D6: 20208511 | E6: =IFERROR(SUM((F6/D6)-1),0) -> -0.083816814 | F6: 18514698 | G6: =IFERROR(SUM((H6/F6)-1),0) -> 0.039355867 | H6: 19243360 | J6: Valor_da_firma | K6: =SUM(K5,K10) -> 12909144300 | L6: =IFERROR(K17/K14,0) -> 0.39293364 | M6: MARGEM_EBITDA | N6: Dividendos e JCP | O6: =SUM(O4:O5) -> 91430
J7: Disponibilidade | K7: {=IFERROR(INDEX(Indicador_Ações[], MATCH($J$2, Indicador_Ações[Stock], 0), MATCH(Indicador_Ações[[#HEADERS],[disponibilidades]], Indicador_Ações[#HEADERS], 0)),"")} -> 4662450000 | L7: =K22/L2 -> 0.30124933 | M7: LPA | N7: Aliquota | O7: =ABS(SUM(B51,D51,F51,H51)/SUM(B50,D50,F50,H50)) -> 0.096882512
A8: Estoque | B8: 79524 | C8: =IFERROR(SUM((D8/B8)-1),0) -> 0.025250239 | D8: 81532 | E8: =IFERROR(SUM((F8/D8)-1),0) -> -0.053071187 | F8: 77205 | G8: =IFERROR(SUM((H8/F8)-1),0) -> 0.25643417 | H8: 97003 | J8: Patrimônio líq | K8: {=IFERROR(INDEX(Indicador_Ações[], MATCH($J$2, Indicador_Ações[Stock], 0), MATCH(Indicador_Ações[[#HEADERS],[patrimonio_liquido]], Indicador_Ações[#HEADERS], 0)),"")} -> 12103900000 | L8: {=IFERROR(INDEX(O6*K3,0)/L2,"")} -> 0.060501188 | M8: DPA Liquido | N8: NOPAT | O8: =K16*(1-O7) -> 2296483274
A9: Caixa | B9: 54662 | C9: =IFERROR(SUM((D9/B9)-1),0) -> 0.10420402 | D9: 60358 | E9: =IFERROR(SUM((F9/D9)-1),0) -> -0.50694191 | F9: 29760 | G9: =IFERROR(SUM((H9/F9)-1),0) -> -0.37153898 | H9: 18703 | J9: Dívida bruta | K9: {=IFERROR(INDEX(Indicador_Ações[], MATCH($J$2, Indicador_Ações[Stock], 0), MATCH(Indicador_Ações[[#HEADERS],[divida_bruta]], Indicador_Ações[#HEADERS], 0)),"")} -> 7250030000 | L9: =IFERROR(L8/L7,0) -> 0.20083427 | M9: Payout
A10: Títulos e valores mobiliários | B10: 5304820 | C10: =IFERROR(SUM((D10/B10)-1),0) -> -0.13246915 | D10: 4602095 | E10: =IFERROR(SUM((F10/D10)-1),0) -> 0.27121431 | F10: 5850249 | G10: =IFERROR(SUM((H10/F10)-1),0) -> -0.044582889 | H10: 5589428 | J10: Dívida líq | K10: =K9-K7 -> 2587580000 | L10: =IFERROR(K14/K4,0) -> 0.28427821 | M10: GIRO ATIVOS
A11: Disponibilidades | B11: =SUM(B9,B10) -> 5359482 | C11: =IFERROR(SUM((D11/B11)-1),0) -> -0.13005529 | D11: =SUM(D9,D10) -> 4662453 | E11: =IFERROR(SUM((F11/D11)-1),0) -> 0.26114065 | F11: =SUM(F9,F10) -> 5880009 | G11: =IFERROR(SUM((H11/F11)-1),0) -> -0.046237684 | H11: =SUM(H9,H10) -> 5608131 | J11: Capital_Investido | K11: =SUM(K8,K9) -> 19353930000 | L11: =IFERROR(K22/K8,0) -> 0.037611927 | M11: ROE
J12: Razão de Divida | K12: =K9/K11 -> 0.37460247 | L12: =O8/K11 -> 0.11865721 | M12: ROIC
A13: Passivo Total | B13: =SUM(B14+B15) -> 14127448 | C13: =IFERROR(SUM((D13/B13)-1),0) -> 0.021322889 | D13: =SUM(D14+D15) -> 14428686 | E13: =IFERROR(SUM((F13/D13)-1),0) -> -0.031690481 | F13: =SUM(F14+F15) -> 13971434 | G13: =IFERROR(SUM((H13/F13)-1),0) -> 0.01050064 | H13: =SUM(H14+H15) -> 14118143 | J13: DRE | L13: =IFERROR(K22/K4,0) -> 0.017158175 | M13: ROA
A14: Passivo Circ. | B14: 6491367 | C14: =IFERROR(SUM((D14/B14)-1),0) -> -0.47529111 | D14: 3406078 | E14: =IFERROR(SUM((F14/D14)-1),0) -> 0.72321421 | F14: 5869402 | G14: =IFERROR(SUM((H14/F14)-1),0) -> 0.026467092 | H14: 6024748 | J14: Receita_Liquida | K14: {=IFERROR(INDEX(Indicador_Ações[], MATCH($J$2, Indicador_Ações[Stock], 0), MATCH(Indicador_Ações[[#HEADERS],[receita_liquida_12m]], Indicador_Ações[#HEADERS], 0)),"")} -> 7542640000 | L14: =K6/K17 -> 4.3556689 | M14: EV/EBITDA
A15: Passivo Não Circ. | B15: 7636081 | C15: =IFERROR(SUM((D15/B15)-1),0) -> 0.44349019 | D15: 11022608 | E15: =IFERROR(SUM((F15/D15)-1),0) -> -0.26496234 | F15: 8102032 | G15: =IFERROR(SUM((H15/F15)-1),0) -> -0.0010660289 | H15: 8093395 | J15: Cagr_receita_5a | K15: {=IFERROR(INDEX(Indicador_Ações[], MATCH($J$2, Indicador_Ações[Stock], 0), MATCH(Indicador_Ações[[#HEADERS],[cagr_receita_5a]], Indicador_Ações[#HEADERS], 0)),"")} -> 8.5 | L15: =K17/K6 -> 0.22958586 | M15: Earnings_Yield_Greenblatt
A16: Emprést. CP | B16: 1369898 | C16: =IFERROR(SUM((D16/B16)-1),0) -> -0.089703759 | D16: 1247013 | E16: =IFERROR(SUM((F16/D16)-1),0) -> -0.24220598 | F16: 944979 | G16: =IFERROR(SUM((H16/F16)-1),0) -> 0.055398056 | H16: 997329 | J16: EBIT | K16: {=IFERROR(INDEX(Indicador_Ações[], MATCH($J$2, Indicador_Ações[Stock], 0), MATCH(Indicador_Ações[[#HEADERS],[ebit_12m]], Indicador_Ações[#HEADERS], 0)),"")} -> 2542840000 | L16: =IFERROR(K10/K17,0) -> 0.87307428 | M16: DÍVIDA LÍQUIDA / EBITDA Ajustado
A17: Emprést. LP | B17: 5910965 | C17: =IFERROR(SUM((D17/B17)-1),0) -> 0.015572753 | D17: 6003015 | E17: =IFERROR(SUM((F17/D17)-1),0) -> 0.051259409 | F17: 6310726 | G17: =IFERROR(SUM((H17/F17)-1),0) -> 0.013407174 | H17: 6395335 | J17: EBITDA | K17: =SUM(B49,D49,F49,H49)*K3 -> 2963757000 | L17: =IFERROR(SUM(B5,D5,F5,H5)/SUM(B14,D14,F14,H14),0) -> 1.2876534 | M17: LIQUIDEZ CORRENTE_Media
J18: Custo_Mercadoria | K18: =SUM(B32,D32,F32,H32)*K3 -> -3150783000 | L18: =SUM(B42,D42,F42,H42)/ABS(SUM(B45,D45,F45,H45)) -> 0.75895491 | M18: Indice de Cobertura de Juros MEDIA
A19: ENDIVIDAMENTO / CAIXA | J19: Lucro bruto | K19: =IFERROR(SUM(B33,D33,F33,H33),"")*K3 -> 4054944000 | L19: =IFERROR(K4/K8,0) -> 2.1920703 | M19: Alavancagem_Financeira
A20: Dívida bruta | B20: =SUM(B17,B16) -> 7280863 | C20: =IFERROR(SUM((D20/B20)-1),0) -> -0.0042350749 | D20: =SUM(D17,D16) -> 7250028 | E20: =IFERROR(SUM((F20/D20)-1),0) -> 0.00078303146 | F20: =SUM(F17,F16) -> 7255705 | G20: =IFERROR(SUM((H20/F20)-1),0) -> 0.018876043 | H20: =SUM(H17,H16) -> 7392664 | J20: Despesas operacionais | K20: =IFERROR(SUM(B32,D32,F32,H32),"")*K3 -> -3150783000 | L20: =K10/K8 -> 0.21378068 | M20: DL/PL
A21: Dívida líq | B21: =SUM(B20-B11) -> 1921381 | C21: =IFERROR(SUM((D21/B21)-1),0) -> 0.34672665 | D21: =SUM(D20-D11) -> 2587575 | E21: =IFERROR(SUM((F21/D21)-1),0) -> -0.46834546 | F21: =SUM(F20-F11) -> 1375696 | G21: =IFERROR(SUM((H21/F21)-1),0) -> 0.29718557 | H21: =SUM(H20-H11) -> 1784533 | J21: Inflação | K21: ='Indicadores_Ações'!$B$4 -> 0.044430246 | M21: CPM
J22: Lucro_Liquido_Fundamentus | K22: {=IFERROR(INDEX(Indicador_Ações[], MATCH($J$2, Indicador_Ações[Stock], 0), MATCH(Indicador_Ações[[#HEADERS],[lucro_liquido_12m]], Indicador_Ações[#HEADERS], 0)),"")} -> 455251000 | L22: ='Indicadores_Ações'!$B$3 -> 0.139 | M22: RF
A23: Patrimônio líq. | B23: =B4-B13 -> 12700462 | C23: =IFERROR(SUM((D23/B23)-1),0) -> -0.046973646 | D23: =D4-D13 -> 12103875 | E23: =IFERROR(SUM((F23/D23)-1),0) -> -0.0060450062 | F23: =F4-F13 -> 12030707 | G23: =IFERROR(SUM((H23/F23)-1),0) -> 0.026355392 | H23: =H4-H13 -> 12347781 | J23: Lucro_Planilha | K23: =SUM(B52,D52,F52,H52)*K3 -> 2079568000 | L23: =K24 -> 0.73 | M23: Beta (B)
J24: Beta | K24: {=IFERROR(INDEX(Indicador_Ações[], MATCH($J$2, Indicador_Ações[Stock], 0), MATCH(Indicador_Ações[[#HEADERS],[beta_ibov_3a]], Indicador_Ações[#HEADERS], 0)),"")} -> 0.73 | L24: =L22+0.02 -> 0.159 | M24: RM
A25: Reserva de Capital | B25: 0 | C25: =IFERROR(SUM((D25/B25)-1),0) -> 0 | D25: 0 | E25: =IFERROR(SUM((F25/D25)-1),0) -> 0 | F25: 0 | G25: =IFERROR(SUM((H25/F25)-1),0) -> 0 | H25: 0 | L25: =L22+L23*(L24-L22) -> 0.1536 | M25: KE
A26: Reserva de Lucro | B26: 6088560 | C26: =IFERROR(SUM((D26/B26)-1),0) -> -0.015016687 | D26: 5997130 | E26: =IFERROR(SUM((F26/D26)-1),0) -> -0.24983467 | F26: 4498839 | G26: =IFERROR(SUM((H26/F26)-1),0) -> 0.3533625 | H26: 6088560
A27: Lucro ou Prejuizo Acumulados | B27: 353621 | C27: =IFERROR(SUM((D27/B27)-1),0) -> -1.4258486 | D27: -150589 | E27: =IFERROR(SUM((F27/D27)-1),0) -> -9.6386456 | F27: 1300885 | G27: =IFERROR(SUM((H27/F27)-1),0) -> -1 | H27: 0 | J27: Ticker | K27: Valores | L27: Ano | M27: VLF | N27: VLP | O27: Cresc | Q27: Ano | R27: Fluxo
J28: Preço_Mercado | K28: =K2 -> 6.83 | L28: 1 | M28: =K33 -> 1180945000 | O28: 6 | Q28: 0 | R28: =-K6 -> -12909144300
A29: DRE Analise Trimestral | J29: Numero_Papel | K29: =L2 -> 1511210000 | L29: 2 | M29: =M28*(1+O28/100) -> 1251801700 | N29: =M29/(1+K34)^L28 -> 1085126300 | O29: 6 | Q29: 1 | R29: =M29 -> 1251801700
A30: Trimestre | B30: 1_T | C30: AH% (2/1) | D30: 2_T | E30: AH% (3/2) | F30: 3_T | G30: AH% (4/3) | H30: 4_T | J30: Market | K30: =K5 -> 10321564300 | L30: 3 | M30: =M29*(1+O29/100) -> 1326909802 | N30: =M30/(1+K34)^L29 -> 997082072 | O30: 6 | Q30: 2 | R30: =M30 -> 1326909802
A31: Receita Liquida | B31: 1946354 | C31: =IFERROR(SUM((D31/B31)-1),0) -> -0.023219825 | D31: 1901160 | E31: =IFERROR(SUM((F31/D31)-1),0) -> -0.051015696 | F31: 1804171 | G31: =IFERROR(SUM((H31/F31)-1),0) -> -0.1386393 | H31: =IFERROR(B83- SUM(B31,D31,F31),"") -> 1554042 | J31: Taxa_Cresc | K31: =SUM(O28:O36)/6 -> 6 | L31: 4 | M31: =M30*(1+O30/100) -> 1406524390 | N31: =M31/(1+K34)^L30 -> 9.1618152e+08 | O31: 6 | Q31: 3 | R31: =M31 -> 1406524390
A32: Custo Mercadoria (CMV) | B32: -789461 | C32: =IFERROR(SUM((D32/B32)-1),0) -> 0.050929685 | D32: -829668 | E32: =IFERROR(SUM((F32/D32)-1),0) -> -0.052455922 | F32: -786147 | G32: =IFERROR(SUM((H32/F32)-1),0) -> -0.051695166 | H32: =IFERROR(B84- SUM(B32,D32,F32),"") -> -745507 | J32: Taxa_Gordon | K32: 0.04 | L32: 5 | M32: =M31*(1+O31/100) -> 1490915854 | N32: =M32/(1+K34)^L31 -> 8.4184501e+08 | O32: 6 | Q32: 4 | R32: =M32 -> 1490915854
A33: Lucro Bruto | B33: =B31+B32 -> 1156893 | C33: =IFERROR(SUM((D33/B33)-1),0) -> -0.073819273 | D33: =D31+D32 -> 1071492 | E33: =IFERROR(SUM((F33/D33)-1),0) -> -0.049900513 | F33: =F31+F32 -> 1018024 | G33: =IFERROR(SUM((H33/F33)-1),0) -> -0.20578002 | H33: =H31+H32 -> 808535 | J33: Lucro_Ajustado_Planilha | K33: =L46 -> 1180945000 | L33: 6 | M33: =M32*(1+O32/100) -> 1580370805 | N33: =M33/(1+K34)^L32 -> 7.7353997e+08 | O33: 6 | Q33: 5 | R33: =M33 -> 1580370805
A34: DESPESAS E OUTRAS RECEITAS | J34: Taxa_desconto_KE | K34: =L25 -> 0.1536 | L34: 7 | M34: =M33*(1+O33/100) -> 1675193053 | N34: =M34/(1+K34)^L33 -> 7.1077702e+08 | Q34: 6 | R34: =M34+M35 -> 17011467482
A35: Despesas com Vendas | B35: -138018 | C35: =IFERROR(SUM((D35/B35)-1),0) -> 0.12220145 | D35: -154884 | E35: =IFERROR(SUM((F35/D35)-1),0) -> -0.16647943 | F35: -129099 | G35: =IFERROR(SUM((H35/F35)-1),0) -> 1.2002262 | H35: =IFERROR(B87- SUM(B35,D35,F35),"") -> -284047 | J35: Valor_ação_Proj | K35: =K36/K29 -> 7.255943 | L35: Perpétuo | M35: =IFERROR( M34 * (1 + K32) / (K34 -K32 ), 0 ) -> 15336274429 | N35: =M35/(1+K34)^L34 -> 5640701782 | Q35: TIR | R35: =IFERROR(IRR(R28:R34),0) -> 0.13281138
A36: Despesa Administrativa | B36: -287230 | C36: =IFERROR(SUM((D36/B36)-1),0) -> 0.019357309 | D36: -292790 | E36: =IFERROR(SUM((F36/D36)-1),0) -> -0.023443424 | F36: -285926 | G36: =IFERROR(SUM((H36/F36)-1),0) -> 0.81354966 | H36: =IFERROR(B88- SUM(B36,D36,F36),"") -> -518541 | J36: Market_Proj | K36: =N36 -> 10965253677 | N36: =SUM(N28:N35) -> 10965253677
A37: Despesa Administrativa (%) | B37: =ABS(B36)/B31 -> 0.14757336 | C37: =IFERROR(SUM((D37/B37)-1),0) -> 0.04358927 | D37: =ABS(D36)/D31 -> 0.15400598 | E37: =IFERROR(SUM((F37/D37)-1),0) -> 0.029054508 | F37: =ABS(F36)/F31 -> 0.15848054 | G37: =IFERROR(SUM((H37/F37)-1),0) -> 1.1054474 | H37: =ABS(H36)/H31 -> 0.33367245
A38: Outras receitas | B38: 746 | C38: =IFERROR(SUM((D38/B38)-1),0) -> 3.4651475 | D38: 3331 | E38: =IFERROR(SUM((F38/D38)-1),0) -> -0.64755329 | F38: 1174 | G38: =IFERROR(SUM((H38/F38)-1),0) -> 1759.2879 | H38: =IFERROR(B90- SUM(B38,D38,F38),"") -> 2066578
A39: Outras despesas | B39: -61349 | C39: =IFERROR(SUM((D39/B39)-1),0) -> 3.2664265 | D39: -261741 | E39: =IFERROR(SUM((F39/D39)-1),0) -> -0.22247183 | F39: -203511 | G39: =IFERROR(SUM((H39/F39)-1),0) -> 4.7158974 | H39: =IFERROR(B91- SUM(B39,D39,F39),"") -> -1163248
A40: Perdas Não Recuperabilidade de Ativos | B40: 0 | C40: =IFERROR(SUM((D40/B40)-1),0) -> 0 | D40: 0 | E40: =IFERROR(SUM((F40/D40)-1),0) -> 0 | F40: 0 | G40: =IFERROR(SUM((H40/F40)-1),0) -> 0 | H40: =IFERROR(B92- SUM(B40,D40,F40),"") -> -8883
A41: Despesas/Receitas Operacionais | B41: =SUM(B35,B36,B39,B38,B40) -> -485851 | C41: =IFERROR(SUM((D41/B41)-1),0) -> 0.45329329 | D41: =SUM(D35,D36,D39,D38,D40) -> -706084 | E41: =IFERROR(SUM((F41/D41)-1),0) -> -0.12565361 | F41: =SUM(F35,F36,F39,F38,F40) -> -617362 | G41: =IFERROR(SUM((H41/F41)-1),0) -> -1.1487928 | H41: =SUM(H35,H36,H39,H38,H40) -> 91859
A42: Lucro Operacional (EBIT)(LAJIR) | B42: =SUM(B33,B41) -> 671042 | C42: =IFERROR(SUM((D42/B42)-1),0) -> -0.4554618 | D42: =SUM(D33,D41) -> 365408 | E42: =IFERROR(SUM((F42/D42)-1),0) -> 0.096478457 | F42: =SUM(F33,F41) -> 400662 | G42: =IFERROR(SUM((H42/F42)-1),0) -> 1.2472658 | H42: =SUM(H33,H41) -> 900394
A44: Receita Financeira | B44: 311274 | C44: =IFERROR(SUM((D44/B44)-1),0) -> -0.12514698 | D44: 272319 | E44: =IFERROR(SUM((F44/D44)-1),0) -> 0.39340259 | F44: 379450 | G44: =IFERROR(SUM((H44/F44)-1),0) -> 4.4869074 | H44: =IFERROR(B96- SUM(B44,D44,F44),"") -> 2082007 | L44: T2 negativo n recorrente
A45: Despesa Financeira | B45: -383737 | C45: =IFERROR(SUM((D45/B45)-1),0) -> 1.4018507 | D45: -921679 | E45: =IFERROR(SUM((F45/D45)-1),0) -> -0.64129377 | F45: -330612 | G45: =IFERROR(SUM((H45/F45)-1),0) -> 3.3672734 | H45: =IFERROR(B97- SUM(B45,D45,F45),"") -> -1443873 | J45: Recorrente | K45: =SUM(B52,F52)/2 -> 299541 | L45: T4 2025 n recorrente
A46: Resultado Financeiro | B46: =B44+B45 -> -72463 | C46: =IFERROR(SUM((D46/B46)-1),0) -> 7.961263 | D46: =D44+D45 -> -649360 | E46: =IFERROR(SUM((F46/D46)-1),0) -> -1.0752094 | F46: =F44+F45 -> 48838 | G46: =IFERROR(SUM((H46/F46)-1),0) -> 12.066342 | H46: =H44+H45 -> 638134 | J46: Possivel Recorrente anual | L46: =((H52+D52)-K45)*1000 -> 1180945000
J47: Estou usando esse de cima trocar a receita da tabela a baixo quando deixar de ter N recorrente.
A48: Depreciações e Amortizações | B48: -172400 | C48: =IFERROR(SUM((D48/B48)-1),0) -> 0.01450116 | D48: -174900 | E48: =IFERROR(SUM((F48/D48)-1),0) -> -0.11435106 | F48: -154900 | G48: =IFERROR(SUM((H48/F48)-1),0) -> -0.19915429 | H48: =IFERROR(B100- SUM(B48,D48,F48),"") -> -124051
A49: EBITIDA (LAJIDA) | B49: =B52-B51-B46-B48 -> 843442 | C49: =IFERROR(SUM((D49/B49)-1),0) -> -0.35940112 | D49: =D52-D51-D46-D48 -> 540308 | E49: =IFERROR(SUM((F49/D49)-1),0) -> 0.028232045 | F49: =F52-F51-F46-F48 -> 555562 | G49: =IFERROR(SUM((H49/F49)-1),0) -> 0.84397961 | H49: =H52-H51-H46-H48 -> 1024445
A50: Resultado antes do Imposto | B50: =B42+B46 -> 598579 | C50: =IFERROR(SUM((D50/B50)-1),0) -> -1.4743768 | D50: =D42+D46 -> -283952 | E50: =IFERROR(SUM((F50/D50)-1),0) -> -2.583014 | F50: =F42+F46 -> 449500 | G50: =IFERROR(SUM((H50/F50)-1),0) -> 2.4227542 | H50: =H42+H46 -> 1538528
A51: Impostos | B51: -245898 | C51: =IFERROR(SUM((D51/B51)-1),0) -> -0.10041969 | D51: -221205 | E51: =IFERROR(SUM((F51/D51)-1),0) -> -0.081851676 | F51: -203099 | G51: =IFERROR(SUM((H51/F51)-1),0) -> -3.2014633 | H51: =IFERROR(B103- SUM(B51,D51,F51),"") -> 447115
A52: Lucro Liquido | B52: =B50+B51 -> 352681 | C52: =IFERROR(SUM((D52/B52)-1),0) -> -2.432334 | D52: =D50+D51 -> -505157 | E52: =IFERROR(SUM((F52/D52)-1),0) -> -1.4877711 | F52: =F50+F51 -> 246401 | G52: =IFERROR(SUM((H52/F52)-1),0) -> 7.0585834 | H52: =H50+H51 -> 1985643
A54: DFC
A55: FCO – Fluxo Operacional | B55: 1_T | C55: AH% (2/1) | D55: 2_T | E55: AH% (3/2) | F55: 3_T | G55: AH% (4/3) | H55: 4_T
A56: Lucro Líquido | B56: =B52 -> 352681 | C56: =IFERROR(SUM((D56/B56)-1),0) -> 2.7143084 | D56: 1309966 | E56: =IFERROR(SUM((F56/D56)-1),0) -> 0.31166916 | F56: 1718242 | G56: =IFERROR(SUM((H56/F56)-1),0) -> 0.21028819 | H56: 2079568
A57: Ajustes Não Caixa (subtotal) | B57: 752199 | C57: =IFERROR(SUM((D57/B57)-1),0) -> -0.016659155 | D57: 739668 | E57: =IFERROR(SUM((F57/D57)-1),0) -> 3.0090852 | F57: 2965392 | G57: =IFERROR(SUM((H57/F57)-1),0) -> 0.26516191 | H57: 3751701
A58: Variação Ativos e Passivo | B58: -99727 | C58: =IFERROR(SUM((D58/B58)-1),0) -> -6.7185918 | D58: 570298 | E58: =IFERROR(SUM((F58/D58)-1),0) -> 5.0330617 | F58: 3440643 | G58: =IFERROR(SUM((H58/F58)-1),0) -> -0.038353296 | H58: 3308683
A59: FCO | B59: =SUM(B57,B58) -> 652472 | C59: =IFERROR(SUM((D59/B59)-1),0) -> 1.0076969 | D59: =SUM(D57,D58) -> 1309966 | E59: =IFERROR(SUM((F59/D59)-1),0) -> 3.89023 | F59: =SUM(F57,F58) -> 6406035 | G59: =IFERROR(SUM((H59/F59)-1),0) -> 0.10214571 | H59: =SUM(H57,H58) -> 7060384
A61: CAPEX
A62: Imobilizado/Intangível/Ativo de Contrato | B62: -579197 | C62: =IFERROR(SUM((D62/B62)-1),0) -> 0.95869626 | D62: -1134471 | E62: =IFERROR(SUM((F62/D62)-1),0) -> 0.6236995 | F62: -1842040 | G62: =IFERROR(SUM((H62/F62)-1),0) -> 0.41984865 | H62: -2615418
A63: CAPEX | B63: =B62 -> -579197 | C63: =IFERROR(SUM((D63/B63)-1),0) -> 0.95869626 | D63: =D62 -> -1134471 | E63: =IFERROR(SUM((F63/D63)-1),0) -> 0.6236995 | F63: =F62 -> -1842040 | G63: =IFERROR(SUM((H63/F63)-1),0) -> 0.41984865 | H63: =H62 -> -2615418
A64: FCI – Investimentos | B64: =B63 -> -579197 | C64: =IFERROR(SUM((D64/B64)-1),0) -> 0.95869626 | D64: =D63 -> -1134471 | E64: =IFERROR(SUM((F64/D64)-1),0) -> 0.6236995 | F64: =F63 -> -1842040 | G64: =IFERROR(SUM((H64/F64)-1),0) -> 0.41984865 | H64: =H63 -> -2615418
A66: FCF – Financiamento
A67: Emissão debêntures | B67: 241079 | C67: =IFERROR(SUM((D67/B67)-1),0) -> 0.59205903 | D67: 383812 | E67: =IFERROR(SUM((F67/D67)-1),0) -> 1.038782 | F67: 782509 | G67: =IFERROR(SUM((H67/F67)-1),0) -> 0.15536307 | H67: 904082
A68: Pag de Emp e debêntures Principal | B68: -305213 | C68: =IFERROR(SUM((D68/B68)-1),0) -> 0.79731204 | D68: -548563 | E68: =IFERROR(SUM((F68/D68)-1),0) -> -0.46498579 | F68: -293489 | G68: =IFERROR(SUM((H68/F68)-1),0) -> 0.31339846 | H68: -385468
A69: Pag de Emp e debêntures Juros | B69: -201508 | C69: =IFERROR(SUM((D69/B69)-1),0) -> 0.56797249 | D69: -315959 | E69: =IFERROR(SUM((F69/D69)-1),0) -> 0.31442687 | F69: -415305 | G69: =IFERROR(SUM((H69/F69)-1),0) -> 0.26338956 | H69: -524692
A70: Amortizações | B70: =SUM(B68:B69) -> -506721 | C70: =IFERROR(SUM((D70/B70)-1),0) -> 0.70611046 | D70: =SUM(D68:D69) -> -864522 | E70: =IFERROR(SUM((F70/D70)-1),0) -> -0.18013191 | F70: =SUM(F68:F69) -> -708794 | G70: =IFERROR(SUM((H70/F70)-1),0) -> 0.28409665 | H70: =SUM(H68:H69) -> -910160
A71: Arrendamentos | B71: -37312 | C71: =IFERROR(SUM((D71/B71)-1),0) -> 1.0680478 | D71: -77163 | E71: =IFERROR(SUM((F71/D71)-1),0) -> 0.39735365 | F71: -107824 | G71: =IFERROR(SUM((H71/F71)-1),0) -> 0.3486886 | H71: -145421
A72: Pagamento/Recebimento financeiros | B72: -8903 | C72: =IFERROR(SUM((D72/B72)-1),0) -> 0.83005728 | D72: -16293 | E72: =IFERROR(SUM((F72/D72)-1),0) -> 0.50690481 | F72: -24552 | G72: =IFERROR(SUM((H72/F72)-1),0) -> 0.63648583 | H72: -40179
A73: Custo na Captação | B73: 0 | C73: =IFERROR(SUM((D73/B73)-1),0) -> 0 | D73: 0 | E73: =IFERROR(SUM((F73/D73)-1),0) -> 0 | F73: -5002 | G73: =IFERROR(SUM((H73/F73)-1),0) -> 0 | H73: -5002
A74: Depósitos Vinculados | B74: -10067 | C74: =IFERROR(SUM((D74/B74)-1),0) -> 1.264925 | D74: -22801 | E74: =IFERROR(SUM((F74/D74)-1),0) -> -0.63400728 | F74: -8345 | G74: =IFERROR(SUM((H74/F74)-1),0) -> 2.3755542 | H74: -28169
A75: Dividendos/JCP | B75: 0 | C75: =IFERROR(SUM((D75/B75)-1),0) -> 0 | D75: -524206 | E75: =IFERROR(SUM((F75/D75)-1),0) -> -0.21264732 | F75: -412735 | G75: =IFERROR(SUM((H75/F75)-1),0) -> 1.9382897e-05 | H75: -412743
A76: FCF | B76: =SUM(B67,B75,B70,B71,B72,B73,B74) -> -321924 | C76: =IFERROR(SUM((D76/B76)-1),0) -> 2.4827257 | D76: =SUM(D67,D75,D70,D71,D72,D73,D74) -> -1121173 | E76: =IFERROR(SUM((F76/D76)-1),0) -> -0.56764656 | F76: =SUM(F67,F75,F70,F71,F72,F73,F74) -> -484743 | G76: =IFERROR(SUM((H76/F76)-1),0) -> 0.31531966 | H76: =SUM(H67,H75,H70,H71,H72,H73,H74) -> -637592
A78: Fechamento | B78: =SUM(B59,B64,B76) -> -248649 | C78: =IFERROR(SUM((D78/B78)-1),0) -> 2.8032648 | D78: =SUM(D59,D64,D76) -> -945678 | E78: =IFERROR(SUM((F78/D78)-1),0) -> -5.313574 | F78: =SUM(F59,F64,F76) -> 4079252 | G78: =IFERROR(SUM((H78/F78)-1),0) -> -0.066648984 | H78: =SUM(H59,H64,H76) -> 3807374
A79: Caixa Inicial | B79: 5608131 | C79: =IFERROR(SUM((D79/B79)-1),0) -> 0 | D79: 5608131 | E79: =IFERROR(SUM((F79/D79)-1),0) -> -0.67890247 | F79: 1800757 | G79: =IFERROR(SUM((H79/F79)-1),0) -> 0 | H79: 1800757
A80: Caixa Final | B80: =SUM(B78:B79) -> 5359482 | C80: =IFERROR(SUM((D80/B80)-1),0) -> -0.13005529 | D80: =SUM(D78:D79) -> 4662453 | E80: =IFERROR(SUM((F80/D80)-1),0) -> 0.26114065 | F80: =SUM(F78:F79) -> 5880009 | G80: =IFERROR(SUM((H80/F80)-1),0) -> -0.046237684 | H80: =SUM(H78:H79) -> 5608131
A82: DRE Final Anual
A83: Receita Liquida | B83: 7205727
A84: Custo Mercadoria (CMV) | B84: -3150783
A85: Lucro Bruto | B85: =B83+B84 -> 4054944
A86: DESPESAS E OUTRAS RECEITAS
A87: Despesas com Vendas | B87: -706048
A88: Despesa Administrativa | B88: -1384487
A89: Despesa Administrativa (%) | B89: =ABS(B88)/B83 -> 0.19213703
A90: Outras receitas | B90: 2071829
A91: Outras despesas | B91: -1689849
A92: Perdas Não Recuperabilidade de Ativos | B92: -8883
A93: Despesas/Receitas Operacionais | B93: =SUM(B87,B88,B91,B90,B92) -> -1717438
A94: Lucro Operacional (EBIT)(LAJIR) | B94: =SUM(B85,B93) -> 2337506
A96: Receita Financeira | B96: 3045050
A97: Despesa Financeira | B97: -3079901
A98: Resultado Financeiro | B98: =B96+B97 -> -34851
A100: Depreciações e Amortizações | B100: -626251
A101: EBITIDA (LAJIDA) | B101: =B104-B103-B98-B100 -> 2963757
A102: Resultado antes do Imposto | B102: =B94+B98 -> 2302655
A103: Impostos | B103: -223087
A104: Lucro Liquido | B104: =B102+B103 -> 2079568

Sheet WEGE3
B1: Feito | C1: 46058 | D1: Atual | E1: 46225 | F1: Não | G1: 46058 | H1: Não | I1: 46058 | J1: Ultimo_Balanco | K1: {=IFERROR(INDEX(Indicador_Ações[], MATCH($J$2, Indicador_Ações[Stock], 0), MATCH(Indicador_Ações[[#HEADERS],[ult_balanco_processado]], Indicador_Ações[#HEADERS], 0)),"")} -> 46203
A2: Balanço Patrimonial Anual | J2: WEGE3 | K2: =IFERROR(__xludf.DUMMYFUNCTION("(GOOGLEFINANCE(""BVMF:"" & J2))"),51.79) -> 51.79 | L2: {=IFERROR(INDEX(Indicador_Ações[], MATCH($J$2, Indicador_Ações[Stock], 0), MATCH(Indicador_Ações[[#HEADERS],[qtd_acao]], Indicador_Ações[#HEADERS], 0)),"")} -> 4197320000 | M2: Numero_Papel
A3: Ano | B3: 1_T | C3: AH% (2/1) | D3: 2_T | E3: AH% (3/2) | F3: 3_T | G3: AH% (4/3) | H3: 4_T | J3: BP | K3: 1000 | L3: =IFERROR(K22/K14,0) -> 0.15584398 | M3: Margem_Liquida | N3: DMPL Acumulado
A4: Ativo Total | B4: =B5+B6 -> 43377646 | C4: =IFERROR(SUM((D4/B4)-1),0) -> 0.075817507 | D4: =D5+D6 -> 46666431 | E4: =IFERROR(SUM((F4/D4)-1),0) -> -0.11082819 | F4: =F5+F6 -> 41494475 | G4: =IFERROR(SUM((H4/F4)-1),0) -> 0.027727908 | H4: =H5+H6 -> 42645030 | J4: Ativo | K4: {=IFERROR(INDEX(Indicador_Ações[], MATCH($J$2, Indicador_Ações[Stock], 0), MATCH(Indicador_Ações[[#HEADERS],[ativo]], Indicador_Ações[#HEADERS], 0)),"")} -> 46666400000 | L4: =IFERROR(K19/K14,0) -> 0.34093109 | M4: MARGEM BRUTA | N4: JCP acionistas Liquido | O4: 91430
A5: Ativo Circulante | B5: 27341315 | C5: =IFERROR(SUM((D5/B5)-1),0) -> 0.099256821 | D5: 30055127 | E5: =IFERROR(SUM((F5/D5)-1),0) -> -0.10909906 | F5: 26776141 | G5: =IFERROR(SUM((H5/F5)-1),0) -> 0.0050307473 | H5: 26910845 | J5: Valor_de_mercado | K5: =K2*L2 -> 217379202800 | L5: =IFERROR(K16/K14,0) -> 0.20931942 | M5: MARGEM EBIT | N5: Dividendos | O5: 0
A6: Ativo Nao Circ. | B6: 16036331 | C6: =IFERROR(SUM((D6/B6)-1),0) -> 0.035854398 | D6: 16611304 | E6: =IFERROR(SUM((F6/D6)-1),0) -> -0.11395674 | F6: 14718334 | G6: =IFERROR(SUM((H6/F6)-1),0) -> 0.069019428 | H6: 15734185 | J6: Valor_da_firma | K6: =SUM(K5,K10) -> 213644412800 | L6: =IFERROR(K17/K14,0) -> 0.22427095 | M6: MARGEM_EBITDA | N6: Dividendos e JCP | O6: =SUM(O4:O5) -> 91430
J7: Disponibilidade | K7: {=IFERROR(INDEX(Indicador_Ações[], MATCH($J$2, Indicador_Ações[Stock], 0), MATCH(Indicador_Ações[[#HEADERS],[disponibilidades]], Indicador_Ações[#HEADERS], 0)),"")} -> 8801140000 | L7: =K22/L2 -> 1.4900103 | M7: LPA | N7: Aliquota | O7: =ABS(SUM(B52,D52,F52,H52)/SUM(B51,D51,F51,H51)) -> 0.16835707
A8: Estoque | B8: 10027505 | C8: =IFERROR(SUM((D8/B8)-1),0) -> 0.067874112 | D8: 10708113 | E8: =IFERROR(SUM((F8/D8)-1),0) -> -0.066916552 | F8: 9991563 | G8: =IFERROR(SUM((H8/F8)-1),0) -> -0.0080577984 | H8: 9911053 | J8: Patrimônio líq | K8: {=IFERROR(INDEX(Indicador_Ações[], MATCH($J$2, Indicador_Ações[Stock], 0), MATCH(Indicador_Ações[[#HEADERS],[patrimonio_liquido]], Indicador_Ações[#HEADERS], 0)),"")} -> 18861400000 | L8: {=IFERROR(INDEX(O6*K3,0)/L2,"")} -> 0.021782947 | M8: DPA Liquido | N8: NOPAT | O8: =K16*(1-O7) -> 6985825589
A9: Caixa | B9: 6360547 | C9: =IFERROR(SUM((D9/B9)-1),0) -> 0.21848891 | D9: 7750256 | E9: =IFERROR(SUM((F9/D9)-1),0) -> -0.17208064 | F9: 6416587 | G9: =IFERROR(SUM((H9/F9)-1),0) -> -0.018715401 | H9: 6296498 | J9: Dívida bruta | K9: {=IFERROR(INDEX(Indicador_Ações[], MATCH($J$2, Indicador_Ações[Stock], 0), MATCH(Indicador_Ações[[#HEADERS],[divida_bruta]], Indicador_Ações[#HEADERS], 0)),"")} -> 5066350000 | L9: =IFERROR(L8/L7,0) -> 0.014619327 | M9: Payout
A10: Títulos e valores mobiliários | B10: 1025221 | C10: =IFERROR(SUM((D10/B10)-1),0) -> 0.025033627 | D10: 1050886 | E10: =IFERROR(SUM((F10/D10)-1),0) -> -0.12576245 | F10: 918724 | G10: =IFERROR(SUM((H10/F10)-1),0) -> 0.070361719 | H10: 983367 | J10: Dívida líq | K10: =K9-K7 -> -3734790000 | L10: =IFERROR(K14/K4,0) -> 0.85993777 | M10: GIRO ATIVOS
A11: Disponibilidades | B11: =SUM(B9,B10) -> 7385768 | C11: =IFERROR(SUM((D11/B11)-1),0) -> 0.19163532 | D11: =SUM(D9,D10) -> 8801142 | E11: =IFERROR(SUM((F11/D11)-1),0) -> -0.16655009 | F11: =SUM(F9,F10) -> 7335311 | G11: =IFERROR(SUM((H11/F11)-1),0) -> -0.0075587797 | H11: =SUM(H9,H10) -> 7279865 | J11: Capital_Investido | K11: =SUM(K8,K9) -> 23927750000 | L11: =IFERROR(K22/K8,0) -> 0.33157931 | M11: ROE
J12: Razão de Divida | K12: =K9/K11 -> 0.21173533 | L12: =O8/K11 -> 0.29195497 | M12: ROIC
A13: Passivo Total | B13: =SUM(B14+B15) -> 24294017 | C13: =IFERROR(SUM((D13/B13)-1),0) -> 0.089776014 | D13: =SUM(D14+D15) -> 26475037 | E13: =IFERROR(SUM((F13/D13)-1),0) -> -0.31717164 | F13: =SUM(F14+F15) -> 18077906 | G13: =IFERROR(SUM((H13/F13)-1),0) -> 0.332658 | H13: =SUM(H14+H15) -> 24091666 | J13: DRE | L13: =IFERROR(K22/K4,0) -> 0.13401612 | M13: ROA
A14: Passivo Circ. | B14: 17662876 | C14: =IFERROR(SUM((D14/B14)-1),0) -> 0.071493567 | D14: 18925658 | E14: =IFERROR(SUM((F14/D14)-1),0) -> -0.2045298 | F14: 15054797 | G14: =IFERROR(SUM((H14/F14)-1),0) -> 0.15487449 | H14: 17386401 | J14: Receita_Liquida | K14: {=IFERROR(INDEX(Indicador_Ações[], MATCH($J$2, Indicador_Ações[Stock], 0), MATCH(Indicador_Ações[[#HEADERS],[receita_liquida_12m]], Indicador_Ações[#HEADERS], 0)),"")} -> 40130200000 | L14: =K6/K17 -> 23.738168 | M14: EV/EBITDA
A15: Passivo Não Circ. | B15: 6631141 | C15: =IFERROR(SUM((D15/B15)-1),0) -> 0.13847361 | D15: 7549379 | E15: =IFERROR(SUM((F15/D15)-1),0) -> -0.59955527 | F15: 3023109 | G15: =IFERROR(SUM((H15/F15)-1),0) -> 1.2180031 | H15: 6705265 | J15: Cagr_receita_5a | K15: {=IFERROR(INDEX(Indicador_Ações[], MATCH($J$2, Indicador_Ações[Stock], 0), MATCH(Indicador_Ações[[#HEADERS],[cagr_receita_5a]], Indicador_Ações[#HEADERS], 0)),"")} -> 11.2 | L15: =K17/K6 -> 0.04212625 | M15: Earnings_Yield_Greenblatt
A16: Emprést. CP | B16: 3099649 | C16: =IFERROR(SUM((D16/B16)-1),0) -> 0.020456832 | D16: 3163058 | E16: =IFERROR(SUM((F16/D16)-1),0) -> -0.095241693 | F16: 2861803 | G16: =IFERROR(SUM((H16/F16)-1),0) -> 0.24023701 | H16: 3549314 | J16: EBIT | K16: {=IFERROR(INDEX(Indicador_Ações[], MATCH($J$2, Indicador_Ações[Stock], 0), MATCH(Indicador_Ações[[#HEADERS],[ebit_12m]], Indicador_Ações[#HEADERS], 0)),"")} -> 8400030000 | L16: =IFERROR(K10/K17,0) -> -0.41497491 | M16: DÍVIDA LÍQUIDA / EBITDA Ajustado
A17: Emprést. LP | B17: 992832 | C17: =IFERROR(SUM((D17/B17)-1),0) -> 0.91702927 | D17: 1903288 | E17: =IFERROR(SUM((F17/D17)-1),0) -> -0.48034559 | F17: 989052 | G17: =IFERROR(SUM((H17/F17)-1),0) -> 0.053036645 | H17: 1041508 | J17: EBITDA | K17: =IFERROR(SUM(B50,D50,F50,H50),"")*K3 -> 9000038000 | L17: =IFERROR(SUM(B5,D5,F5,H5)/SUM(B14,D14,F14,H14),0) -> 1.6092113 | M17: LIQUIDEZ CORRENTE_Media
J18: Custo_Mercadoria | K18: =SUM(B32,D32,F32,H32)*K3 -> -27122477000 | L18: =SUM(B43,D43,F43,H43)/ABS(SUM(B46,D46,F46,H46)) -> 3.6803267 | M18: Indice de Cobertura de Juros MEDIA
A19: ENDIVIDAMENTO / CAIXA | J19: Lucro bruto | K19: =IFERROR(SUM(B33,D33,F33,H33),"")*K3 -> 13681633000 | L19: =IFERROR(K4/K8,0) -> 2.4741748 | M19: Alavancagem_Financeira
A20: Dívida bruta | B20: =SUM(B17,B16) -> 4092481 | C20: =IFERROR(SUM((D20/B20)-1),0) -> 0.23796445 | D20: =SUM(D17,D16) -> 5066346 | E20: =IFERROR(SUM((F20/D20)-1),0) -> -0.23991472 | F20: =SUM(F17,F16) -> 3850855 | G20: =IFERROR(SUM((H20/F20)-1),0) -> 0.19215655 | H20: =SUM(H17,H16) -> 4590822 | J20: Despesas operacionais | K20: =IFERROR(SUM(B41,D41,F41,H41),"")*K3 -> -5682892000 | L20: =K10/K8 -> -0.19801234 | M20: DL/PL
A21: Dívida líq | B21: =SUM(B20-B11) -> -3293287 | C21: =IFERROR(SUM((D21/B21)-1),0) -> 0.13406332 | D21: =SUM(D20-D11) -> -3734796 | E21: =IFERROR(SUM((F21/D21)-1),0) -> -0.067029096 | F21: =SUM(F20-F11) -> -3484456 | G21: =IFERROR(SUM((H21/F21)-1),0) -> -0.22827466 | H21: =SUM(H20-H11) -> -2689043 | J21: Inflação | K21: ='Indicadores_Ações'!$B$4 -> 0.044430246 | M21: CPM
J22: Lucro_Liquido_Fundamentus | K22: {=IFERROR(INDEX(Indicador_Ações[], MATCH($J$2, Indicador_Ações[Stock], 0), MATCH(Indicador_Ações[[#HEADERS],[lucro_liquido_12m]], Indicador_Ações[#HEADERS], 0)),"")} -> 6254050000 | L22: ='Indicadores_Ações'!$B$3 -> 0.139 | M22: RF
A23: Patrimônio líq. | B23: =B4-B13 -> 19083629 | C23: =IFERROR(SUM((D23/B23)-1),0) -> 0.058047922 | D23: =D4-D13 -> 20191394 | E23: =IFERROR(SUM((F23/D23)-1),0) -> 0.15973018 | F23: =F4-F13 -> 23416569 | G23: =IFERROR(SUM((H23/F23)-1),0) -> -0.20768222 | H23: =H4-H13 -> 18553364 | J23: Lucro_Planilha | K23: =SUM(B53,D53,F53,H53)*K3 -> 6775958000 | L23: =K24 -> 0.69 | M23: Beta (B)
J24: Beta | K24: {=IFERROR(INDEX(Indicador_Ações[], MATCH($J$2, Indicador_Ações[Stock], 0), MATCH(Indicador_Ações[[#HEADERS],[beta_ibov_3a]], Indicador_Ações[#HEADERS], 0)),"")} -> 0.69 | L24: =L22+0.01 -> 0.149 | M24: RM
A25: Reserva de Capital | B25: -162371 | C25: =IFERROR(SUM((D25/B25)-1),0) -> -0.0077168953 | D25: -161118 | E25: =IFERROR(SUM((F25/D25)-1),0) -> 0.04316712 | F25: -168073 | G25: =IFERROR(SUM((H25/F25)-1),0) -> 0.026756231 | H25: -172570 | L25: =L22+L23*(L24-L22) -> 0.1459 | M25: KE
A26: Reserva de Lucro | B26: 2575748 | C26: =IFERROR(SUM((D26/B26)-1),0) -> 0 | D26: 2575748 | E26: =IFERROR(SUM((F26/D26)-1),0) -> 1.0174136 | F26: 5196349 | G26: =IFERROR(SUM((H26/F26)-1),0) -> -0.50431582 | H26: 2575748
A27: Lucro ou Prejuizo Acumulados | B27: 1041678 | C27: =IFERROR(SUM((D27/B27)-1),0) -> 1.0796331 | D27: 2166308 | E27: =IFERROR(SUM((F27/D27)-1),0) -> 0.33190571 | F27: 2885318 | G27: =IFERROR(SUM((H27/F27)-1),0) -> -1 | H27: 0 | J27: Ticker | K27: Valores | L27: Ano | M27: VLF | N27: VLP | O27: Cresc | Q27: Ano | R27: Fluxo
J28: Preço_Mercado | K28: =K2 -> 51.79 | L28: 1 | M28: =K33 -> 6775958000 | O28: 25 | Q28: 0 | R28: =-K6 -> -213644412800
A29: DRE Analise Trimestral | J29: Numero_Papel | K29: =L2 -> 4197320000 | L29: 2 | M29: =M28*(1+O28/100) -> 8469947500 | N29: =M29/(1+K34)^L28 -> 7391524130 | O29: 25 | Q29: 1 | R29: =M29 -> 8469947500
A30: Trimestre | B30: 1_T | C30: AH% (2/1) | D30: 2_T | E30: AH% (3/2) | F30: 3_T | G30: AH% (4/3) | H30: 4_T | J30: Market | K30: =K5 -> 217379202800 | L30: 3 | M30: =M29*(1+O29/100) -> 10587434375 | N30: =M30/(1+K34)^L29 -> 8063011748 | O30: 25 | Q30: 2 | R30: =M30 -> 10587434375
A31: Receita Liquida | B31: 9468313 | C31: =IFERROR(SUM((D31/B31)-1),0) -> 0.071315978 | D31: 10143555 | E31: =IFERROR(SUM((F31/D31)-1),0) -> 0.012615597 | F31: 10271522 | G31: =IFERROR(SUM((H31/F31)-1),0) -> 0.063203681 | H31: =IFERROR(B87- SUM(B31,D31,F31),"") -> 10920720 | J31: Taxa_Cresc | K31: =SUM(O28:O36)/6 -> 25 | L31: 4 | M31: =M30*(1+O30/100) -> 13234292969 | N31: =M31/(1+K34)^L30 -> 8795501078 | O31: 25 | Q31: 3 | R31: =M31 -> 13234292969
A32: Custo Mercadoria (CMV) | B32: -6472497 | C32: =IFERROR(SUM((D32/B32)-1),0) -> 0.046115587 | D32: -6770980 | E32: =IFERROR(SUM((F32/D32)-1),0) -> 0.0076789475 | F32: -6822974 | G32: =IFERROR(SUM((H32/F32)-1),0) -> 0.034156953 | H32: =IFERROR(B88- SUM(B32,D32,F32),"") -> -7056026 | J32: Taxa_Gordon | K32: 0.06 | L32: 5 | M32: =M31*(1+O31/100) -> 16542866211 | N32: =M32/(1+K34)^L31 -> 9594533857 | O32: 25 | Q32: 4 | R32: =M32 -> 16542866211
A33: Lucro Bruto | B33: =B31+B32 -> 2995816 | C33: =IFERROR(SUM((D33/B33)-1),0) -> 0.12576173 | D33: =D31+D32 -> 3372575 | E33: =IFERROR(SUM((F33/D33)-1),0) -> 0.022526704 | F33: =F31+F32 -> 3448548 | G33: =IFERROR(SUM((H33/F33)-1),0) -> 0.12067282 | H33: =H31+H32 -> 3864694 | J33: Lucro_Ajustado_Planilha | K33: =K23 -> 6775958000 | L33: 6 | M33: =M32*(1+O32/100) -> 20678582764 | N33: =M33/(1+K34)^L32 -> 10466155268 | O33: 25 | Q33: 5 | R33: =M33 -> 20678582764
A34: DESPESAS E OUTRAS RECEITAS | J34: Taxa_desconto_KE | K34: =L25 -> 0.1459 | L34: 7 | M34: =M33*(1+O33/100) -> 25848228455 | N34: =M34/(1+K34)^L33 -> 11416959669 | Q34: 6 | R34: =M34+M35 -> 344813562120
A35: Despesas com Vendas | B35: -801527 | C35: =IFERROR(SUM((D35/B35)-1),0) -> 0.053960752 | D35: -844778 | E35: =IFERROR(SUM((F35/D35)-1),0) -> -0.03134433 | F35: -818299 | G35: =IFERROR(SUM((H35/F35)-1),0) -> 0.086188545 | H35: =IFERROR(B91- SUM(B35,D35,F35),"") -> -888827 | J35: Valor_ação_Proj | K35: =K36/K29 -> 42.568654 | L35: Perpétuo | M35: =IFERROR( M34 * (1 + K32) / (K34 -K32 ), 0 ) -> 318965333665 | N35: =M35/(1+K34)^L34 -> 122946578985 | Q35: TIR | R35: =IFERROR(IRR(R28:R34),0) -> 0.12833071
A36: Despesa Administrativa | B36: -387507 | C36: =IFERROR(SUM((D36/B36)-1),0) -> 0.083913323 | D36: -420024 | E36: =IFERROR(SUM((F36/D36)-1),0) -> -0.11269832 | F36: -372688 | G36: =IFERROR(SUM((H36/F36)-1),0) -> -0.10471225 | H36: =IFERROR(B92- SUM(B36,D36,F36),"") -> -333663 | J36: Market_Proj | K36: =N36 -> 178674264734 | N36: =SUM(N28:N35) -> 178674264734
A37: Despesa Administrativa (%) | B37: =ABS(B36)/B31 -> 0.040926721 | C37: =IFERROR(SUM((D37/B37)-1),0) -> 0.011758758 | D37: =ABS(D36)/D31 -> 0.041407968 | E37: =IFERROR(SUM((F37/D37)-1),0) -> -0.1237527 | F37: =ABS(F36)/F31 -> 0.03628362 | G37: =IFERROR(SUM((H37/F37)-1),0) -> -0.15793393 | H37: =ABS(H36)/H31 -> 0.030553205
A38: Resultado de equivalência patrimonial | B38: -80 | C38: =IFERROR(SUM((D38/B38)-1),0) -> 27.8 | D38: -2304 | E38: =IFERROR(SUM((F38/D38)-1),0) -> 0.56684028 | F38: -3610 | G38: =IFERROR(SUM((H38/F38)-1),0) -> 0.55734072 | H38: =IFERROR(B94- SUM(B38,D38,F38),"") -> -5622
A39: Outras receitas | B39: 204210 | C39: =IFERROR(SUM((D39/B39)-1),0) -> -0.31673767 | D39: 139529 | E39: =IFERROR(SUM((F39/D39)-1),0) -> -0.69154083 | F39: 43039 | G39: =IFERROR(SUM((H39/F39)-1),0) -> -4.8105207 | H39: =IFERROR(B95- SUM(B39,D39,F39),"") -> -164001
A40: Outras despesas | B40: -162160 | C40: =IFERROR(SUM((D40/B40)-1),0) -> 0.77821288 | D40: -288355 | E40: =IFERROR(SUM((F40/D40)-1),0) -> -0.097830799 | F40: -260145 | G40: =IFERROR(SUM((H40/F40)-1),0) -> 0.2150147 | H40: =IFERROR(B96- SUM(B40,D40,F40),"") -> -316080
A41: Despesas/Receitas Operacionais | B41: =SUM(B35,B36,B38,B40,B39) -> -1147064 | C41: =IFERROR(SUM((D41/B41)-1),0) -> 0.23439669 | D41: =SUM(D35,D36,D38,D40,D39) -> -1415932 | E41: =IFERROR(SUM((F41/D41)-1),0) -> -0.0029867254 | F41: =SUM(F35,F36,F38,F40,F39) -> -1411703 | G41: =IFERROR(SUM((H41/F41)-1),0) -> 0.21002293 | H41: =SUM(H35,H36,H38,H40,H39) -> -1708193
A43: Lucro Operacional (EBIT)(LAJIR) | B43: =SUM(B33,B41) -> 1848752 | C43: =IFERROR(SUM((D43/B43)-1),0) -> 0.058358828 | D43: =SUM(D33,D41) -> 1956643 | E43: =IFERROR(SUM((F43/D43)-1),0) -> 0.040989593 | F43: =SUM(F33,F41) -> 2036845 | G43: =IFERROR(SUM((H43/F43)-1),0) -> 0.058745756 | H43: =SUM(H33,H41) -> 2156501
A45: Receita Financeira | B45: 461720 | C45: =IFERROR(SUM((D45/B45)-1),0) -> 0.25634367 | D45: 580079 | E45: =IFERROR(SUM((F45/D45)-1),0) -> 0.57873152 | F45: 915789 | G45: =IFERROR(SUM((H45/F45)-1),0) -> -0.60173577 | H45: =IFERROR(B101- SUM(B45,D45,F45),"") -> 364726
A46: Despesa Financeira | B46: -421450 | C46: =IFERROR(SUM((D46/B46)-1),0) -> 0.31576699 | D46: -554530 | E46: =IFERROR(SUM((F46/D46)-1),0) -> 0.591115 | F46: -882321 | G46: =IFERROR(SUM((H46/F46)-1),0) -> -0.64289981 | H46: =IFERROR(B102- SUM(B46,D46,F46),"") -> -315077
A47: Resultado Financeiro | B47: =B45+B46 -> 40270 | C47: =IFERROR(SUM((D47/B47)-1),0) -> -0.36555749 | D47: =D45+D46 -> 25549 | E47: =IFERROR(SUM((F47/D47)-1),0) -> 0.30995342 | F47: =F45+F46 -> 33468 | G47: =IFERROR(SUM((H47/F47)-1),0) -> 0.48347675 | H47: =H45+H46 -> 49649
A49: Depreciação/Amortização | B49: -254050 | C49: =IFERROR(SUM((D49/B49)-1),0) -> 0.0076284196 | D49: -255988 | E49: =IFERROR(SUM((F49/D49)-1),0) -> -0.067718018 | F49: -238653 | G49: =IFERROR(SUM((H49/F49)-1),0) -> 0.058465638 | H49: =IFERROR(B105- SUM(B49,D49,F49),"") -> -252606
A50: EBITIDA (LAJIDA) | B50: =B53-B52-B47-B49 -> 2102802 | C50: =IFERROR(SUM((D50/B50)-1),0) -> 0.052229834 | D50: =D53-D52-D47-D49 -> 2212631 | E50: =IFERROR(SUM((F50/D50)-1),0) -> 0.028412781 | F50: =F53-F52-F47-F49 -> 2275498 | G50: =IFERROR(SUM((H50/F50)-1),0) -> 0.058716378 | H50: =H53-H52-H47-H49 -> 2409107
A51: Resultado antes do Imposto | B51: =B43+B47 -> 1889022 | C51: =IFERROR(SUM((D51/B51)-1),0) -> 0.049321818 | D51: =D43+D47 -> 1982192 | E51: =IFERROR(SUM((F51/D51)-1),0) -> 0.044456339 | F51: =F43+F47 -> 2070313 | G51: =IFERROR(SUM((H51/F51)-1),0) -> 0.065611818 | H51: =H43+H47 -> 2206150
A52: Impostos | B52: -309321 | C52: =IFERROR(SUM((D52/B52)-1),0) -> 0.08511223 | D52: -335648 | E52: =IFERROR(SUM((F52/D52)-1),0) -> -0.030058275 | F52: -325559 | G52: =IFERROR(SUM((H52/F52)-1),0) -> 0.23231427 | H52: =IFERROR(B108- SUM(B52,D52,F52),"") -> -401191
A53: Lucro Liquido | B53: =B51+B52 -> 1579701 | C53: =IFERROR(SUM((D53/B53)-1),0) -> 0.042313704 | D53: =D51+D52 -> 1646544 | E53: =IFERROR(SUM((F53/D53)-1),0) -> 0.059646144 | F53: =F51+F52 -> 1744754 | G53: =IFERROR(SUM((H53/F53)-1),0) -> 0.034506297 | H53: =H51+H52 -> 1804959
A56: DFC
A57: FCO – Fluxo Operacional | B57: 1_T | C57: AH% (2/1) | D57: 2_T | E57: AH% (3/2) | F57: 3_T | G57: AH% (4/3) | H57: 4_T
A58: Lucro Líquido Antes do imposto | B58: =B51 -> 1889022 | C58: =IFERROR(SUM((D58/B58)-1),0) -> 1.0493218 | D58: =SUM(B58,D51) -> 3871214 | E58: =IFERROR(SUM((F58/D58)-1),0) -> 0.53479684 | F58: =SUM(D58,F51) -> 5941527 | G58: =IFERROR(SUM((H58/F58)-1),0) -> 0.37131027 | H58: =SUM(F58,H51) -> 8147677
A59: Ajustes Não Caixa (subtotal) | B59: 2328690 | C59: =IFERROR(SUM((D59/B59)-1),0) -> 1.0687348 | D59: 4817442 | E59: =IFERROR(SUM((F59/D59)-1),0) -> 0.60393296 | F59: 7726854 | G59: =IFERROR(SUM((H59/F59)-1),0) -> 0.34760784 | H59: 10412769
A60: Variação Ativos e Passivo | B60: -1066241 | C60: =IFERROR(SUM((D60/B60)-1),0) -> 1.2192018 | D60: -2366204 | E60: =IFERROR(SUM((F60/D60)-1),0) -> 0.47431202 | F60: -3488523 | G60: =IFERROR(SUM((H60/F60)-1),0) -> 0.13564853 | H60: -3961736
A61: FCO | B61: =SUM(B59,B60) -> 1262449 | C61: =IFERROR(SUM((D61/B61)-1),0) -> 0.94165309 | D61: =SUM(D59,D60) -> 2451238 | E61: =IFERROR(SUM((F61/D61)-1),0) -> 0.72905732 | F61: =SUM(F59,F60) -> 4238331 | G61: =IFERROR(SUM((H61/F61)-1),0) -> 0.52206918 | H61: =SUM(H59,H60) -> 6451033
A63: CAPEX
A64: Imobilizado | B64: -607415 | C64: =IFERROR(SUM((D64/B64)-1),0) -> 1.2368331 | D64: -1358686 | E64: =IFERROR(SUM((F64/D64)-1),0) -> 0.27762412 | F64: -1735890 | G64: =IFERROR(SUM((H64/F64)-1),0) -> 0.47673528 | H64: -2563450
A65: Intangível | B65: -14821 | C65: =IFERROR(SUM((D65/B65)-1),0) -> 1.8620201 | D65: -42418 | E65: =IFERROR(SUM((F65/D65)-1),0) -> 2.3319817 | F65: -141336 | G65: =IFERROR(SUM((H65/F65)-1),0) -> -0.095269429 | H65: -127871
A66: CAPEX | B66: =SUM(B64:B65) -> -622236 | C66: =IFERROR(SUM((D66/B66)-1),0) -> 1.2517244 | D66: =SUM(D64:D65) -> -1401104 | E66: =IFERROR(SUM((F66/D66)-1),0) -> 0.33981917 | F66: =SUM(F64:F65) -> -1877226 | G66: =IFERROR(SUM((H66/F66)-1),0) -> 0.43366915 | H66: =SUM(H64:H65) -> -2691321
A67: Venda de Ativo Imobilizado e Intangível | B67: 4969 | C67: =IFERROR(SUM((D67/B67)-1),0) -> 0.59207084 | D67: 7911 | E67: =IFERROR(SUM((F67/D67)-1),0) -> 2.5735052 | F67: 28270 | G67: =IFERROR(SUM((H67/F67)-1),0) -> 0.76098337 | H67: 49783
A68: Aquisição de empresa | B68: -26149 | C68: =IFERROR(SUM((D68/B68)-1),0) -> 0 | D68: -26149 | E68: =IFERROR(SUM((F69/D68)-1),0) -> 1.4420054 | F68: -135436 | G68: =IFERROR(SUM((H68/F69)-1),0) -> 2.1410517 | H68: -200575
A69: Aplicações financeiras | B69: -2235 | C69: =IFERROR(SUM((D69/B69)-1),0) -> -0.13691275 | D69: -1929 | E69: =IFERROR(SUM((#REF!/D69)-1),0) -> 0 | F69: -63856 | G69: =IFERROR(SUM((H69/#REF!)-1),0) -> 0 | H69: -75379
A70: Resgate de aplicações financeiras | B70: 962 | C70: =IFERROR(SUM((D70/B70)-1),0) -> 3.6226611 | D70: 4447 | E70: =IFERROR(SUM((F70/D70)-1),0) -> 0.14841466 | F70: 5107 | G70: =IFERROR(SUM((H70/F70)-1),0) -> 0.30840024 | H70: 6682
A71: FCI – Investimentos | B71: =SUM(B66:B70) -> -644689 | C71: =IFERROR(SUM((D71/B71)-1),0) -> 1.197686 | D71: =SUM(D66:D70) -> -1416824 | E71: =IFERROR(SUM((F71/D71)-1),0) -> 0.44205702 | F71: =SUM(F66:F70) -> -2043141 | G71: =IFERROR(SUM((H71/F71)-1),0) -> 0.42467407 | H71: =SUM(H66:H70) -> -2910810
A73: FCF – Financiamento
A74: Emissão debêntures | B74: 758746 | C74: =IFERROR(SUM((D74/B74)-1),0) -> 2.3231002 | D74: 2521389 | E74: =IFERROR(SUM((F74/D74)-1),0) -> 0.92734164 | F74: 4859578 | G74: =IFERROR(SUM((H74/F74)-1),0) -> 0.28577276 | H74: 6248313
A75: Pag de Emp e debêntures Principal | B75: -1114376 | C75: =IFERROR(SUM((D75/B75)-1),0) -> 0.69909348 | D75: -1893429 | E75: =IFERROR(SUM((F75/D75)-1),0) -> 1.3561866 | F75: -4461272 | G75: =IFERROR(SUM((H75/F75)-1),0) -> 0.17245978 | H75: -5230662
A76: Dividendos/JCP | B76: -5049 | C76: =IFERROR(SUM((D76/B76)-1),0) -> -0.26460685 | D76: -3713 | E76: =IFERROR(SUM((F76/D76)-1),0) -> 850.57608 | F76: -3161902 | G76: =IFERROR(SUM((H76/F76)-1),0) -> 0.70301578 | H76: -5384769
A77: Liquidação de ações em tesouraria | B77: 3592 | C77: =IFERROR(SUM((D77/B77)-1),0) -> 0 | D77: 3592 | E77: =IFERROR(SUM((F77/D77)-1),0) -> 0.18624722 | F77: 4261 | G77: =IFERROR(SUM((H77/F77)-1),0) -> 0 | H77: 4261
A78: Amortizações | B78: =SUM(B77,B75) -> -1110784 | C78: =IFERROR(SUM((D78/B78)-1),0) -> 0.70135418 | D78: =SUM(D77,D75) -> -1889837 | E78: =IFERROR(SUM((F78/D78)-1),0) -> 1.3584103 | F78: =SUM(F77,F75) -> -4457011 | G78: =IFERROR(SUM((H78/F78)-1),0) -> 0.17262466 | H78: =SUM(H77,H75) -> -5226401
A79: FCF | B79: =SUM(B74,B76,B78) -> -357087 | C79: =IFERROR(SUM((D79/B79)-1),0) -> -2.7582242 | D79: =SUM(D74,D76,D78) -> 627839 | E79: =IFERROR(SUM((F79/D79)-1),0) -> -5.3949723 | F79: =SUM(F74,F76,F78) -> -2759335 | G79: =IFERROR(SUM((H79/F79)-1),0) -> 0.58112625 | H79: =SUM(H74,H76,H78) -> -4362857
A81: Variação Cambial | B81: -196624 | C81: =IFERROR(SUM((D81/B81)-1),0) -> 0.060374115 | D81: -208495 | E81: =IFERROR(SUM((F81/D81)-1),0) -> 0.75959615 | F81: -366867 | G81: =IFERROR(SUM((H81/F81)-1),0) -> -0.37724843 | H81: -228467
A82: Fechamento | B82: =SUM(B61,B71,B79,B81) -> 64049 | C82: =IFERROR(SUM((D82/B82)-1),0) -> 21.697591 | D82: =SUM(D61,D71,D79,D81) -> 1453758 | E82: =IFERROR(SUM((F82/D82)-1),0) -> -1.6404175 | F82: =SUM(F61,F71,F79,F81) -> -931012 | G82: =IFERROR(SUM((H82/F82)-1),0) -> 0.1289876 | H82: =SUM(H61,H71,H79,H81) -> -1051101
A83: Caixa Inicial | B83: 6296498 | C83: =IFERROR(SUM((D83/B83)-1),0) -> 0 | D83: 6296498 | E83: =IFERROR(SUM((F83/D83)-1),0) -> 0.16693422 | F83: 7347599 | G83: =IFERROR(SUM((H83/F83)-1),0) -> 0 | H83: 7347599
A84: Caixa Final | B84: =SUM(B82:B83) -> 6360547 | C84: =IFERROR(SUM((D84/B84)-1),0) -> 0.21848891 | D84: =SUM(D82:D83) -> 7750256 | E84: =IFERROR(SUM((F84/D84)-1),0) -> -0.17208064 | F84: =SUM(F82:F83) -> 6416587 | G84: =IFERROR(SUM((H84/F84)-1),0) -> -0.018715401 | H84: =SUM(H82:H83) -> 6296498
A86: DRE Final Anual
A87: Receita Liquida | B87: 40804110 | F87: DMPL Acumulado
A88: Custo Mercadoria (CMV) | B88: -27122477 | F88: JCP acionistas Liquido | G88: 858238
A89: Lucro Bruto | B89: =B87+B88 -> 13681633 | F89: Dividendos | G89: 0
A90: DESPESAS E OUTRAS RECEITAS | F90: Dividendos e JCP | G90: =SUM(G88:G89) -> 858238
A91: Despesas com Vendas | B91: -3353431
A92: Despesa Administrativa | B92: -1513882
A93: Despesa Administrativa (%) | B93: =ABS(B92)/B87 -> 0.037101214
A94: Resultado de equivalência patrimonial | B94: -11616
A95: Outras receitas | B95: 222777
A96: Outras despesas | B96: -1026740
A97: Despesas/Receitas Operacionais | B97: =SUM(B91,B92,B95,B94,B96) -> -5682892
A99: Lucro Operacional (EBIT)(LAJIR) | B99: =SUM(B89,B97) -> 7998741
A101: Receita Financeira | B101: 2322314
A102: Despesa Financeira | B102: -2173378
A103: Resultado Financeiro | B103: =B101+B102 -> 148936
A105: Depreciações e Amortizações | B105: -1001297
A106: EBITIDA (LAJIDA) | B106: =B109-B108-B103-B105 -> 9000038
A107: Resultado antes do Imposto | B107: =B99+B103 -> 8147677
A108: Impostos | B108: -1371719
A109: Lucro Liquido | B109: =B107+B108 -> 6775958

Sheet Petr4
B1: Feito | C1: 46058 | D1: Atual | E1: 46240 | F1: Não | G1: 46058 | H1: Não | I1: 46058 | J1: Ultimo_Balanco | K1: {=IFERROR(INDEX(Indicador_Ações[], MATCH($J$2, Indicador_Ações[Stock], 0), MATCH(Indicador_Ações[[#HEADERS],[ult_balanco_processado]], Indicador_Ações[#HEADERS], 0)),"")} -> 46203
A2: Balanço Patrimonial Anual | J2: PETR4 | K2: =IFERROR(__xludf.DUMMYFUNCTION("(GOOGLEFINANCE(""BVMF:"" & J2))"),48.83) -> 48.83 | L2: {=IFERROR(INDEX(Indicador_Ações[], MATCH($J$2, Indicador_Ações[Stock], 0), MATCH(Indicador_Ações[[#HEADERS],[qtd_acao]], Indicador_Ações[#HEADERS], 0)),"")} -> 12888700000 | M2: Numero_Papel
A3: Ano | B3: 1_T | C3: AH% (2/1) | D3: 2_T | E3: AH% (3/2) | F3: 3_T | G3: AH% (4/3) | H3: 4_T | J3: BP | K3: 1000000 | L3: =IFERROR(K22/K14,0) -> 0.2431681 | M3: Margem_Liquida | N3: DMPL Acumulado
A4: Ativo Total | B4: =B5+B6 -> 1246068 | C4: =IFERROR(SUM((D4/B4)-1),0) -> 0.026443982 | D4: =D5+D6 -> 1279019 | E4: =IFERROR(SUM((F4/D4)-1),0) -> -0.052369042 | F4: =F5+F6 -> 1212038 | G4: =IFERROR(SUM((H4/F4)-1),0) -> 0.0093652179 | H4: =H5+H6 -> 1223389 | J4: Ativo | K4: {=IFERROR(INDEX(Indicador_Ações[], MATCH($J$2, Indicador_Ações[Stock], 0), MATCH(Indicador_Ações[[#HEADERS],[ativo]], Indicador_Ações[#HEADERS], 0)),"")} -> 1279020000000 | L4: =IFERROR(K19/K14,0) -> 0.50595359 | M4: MARGEM BRUTA | N4: JCP acionistas Liquido | O4: 8072
A5: Ativo Circulante | B5: 140533 | C5: =IFERROR(SUM((D5/B5)-1),0) -> 0.10273744 | D5: 154971 | E5: =IFERROR(SUM((F5/D5)-1),0) -> -0.036200321 | F5: 149361 | G5: =IFERROR(SUM((H5/F5)-1),0) -> -0.062499582 | H5: 140026 | J5: Valor_de_mercado | K5: =K2*L2 -> 629355221000 | L5: =IFERROR(K16/K14,0) -> 0.4275916 | M5: MARGEM EBIT | N5: Dividendos | O5: 9037
A6: Ativo Nao Circ. | B6: 1105535 | C6: =IFERROR(SUM((D6/B6)-1),0) -> 0.016745738 | D6: 1124048 | E6: =IFERROR(SUM((F6/D6)-1),0) -> -0.054598202 | F6: 1062677 | G6: =IFERROR(SUM((H6/F6)-1),0) -> 0.019465934 | H6: 1083363 | J6: Valor_da_firma | K6: =SUM(K5,K10) -> 942124221000 | L6: =IFERROR(K17/K14,0) -> 0.50560718 | M6: MARGEM_EBITDA_Ajustada | N6: Dividendos e JCP | O6: =SUM(O4:O5) -> 17109
J7: Disponibilidade | K7: {=IFERROR(INDEX(Indicador_Ações[], MATCH($J$2, Indicador_Ações[Stock], 0), MATCH(Indicador_Ações[[#HEADERS],[disponibilidades]], Indicador_Ações[#HEADERS], 0)),"")} -> 53764000000 | L7: =K24/L2 -> 8.1728956 | M7: LPA_FCL | N7: Aliquota | O7: =ABS(SUM(B57,D57,F57,H57)/SUM(B56,D56,F56,H56)) -> 0.2605672
A8: Estoque | B8: 48556 | C8: =IFERROR(SUM((D8/B8)-1),0) -> 0.036061455 | D8: 50307 | E8: =IFERROR(SUM((F8/D8)-1),0) -> -0.080207526 | F8: 46272 | G8: =IFERROR(SUM((H8/F8)-1),0) -> -0.023750864 | H8: 45173 | J8: Patrimônio líq | K8: {=IFERROR(INDEX(Indicador_Ações[], MATCH($J$2, Indicador_Ações[Stock], 0), MATCH(Indicador_Ações[[#HEADERS],[patrimonio_liquido]], Indicador_Ações[#HEADERS], 0)),"")} -> 480950000000 | L8: {=IFERROR(INDEX(O6*K3,0)/L2,"")} -> 1.3274419 | M8: DPA Liquido | N8: NOPAT | O8: =K16*(1-O7) -> 173419915064
A9: Caixa | B9: 34294 | C9: =IFERROR(SUM((D9/B9)-1),0) -> -0.021403161 | D9: 33560 | E9: =IFERROR(SUM((F9/D9)-1),0) -> 0.42058999 | F9: 47675 | G9: =IFERROR(SUM((H9/F9)-1),0) -> -0.2531096 | H9: 35608 | J9: Dívida bruta | K9: {=IFERROR(INDEX(Indicador_Ações[], MATCH($J$2, Indicador_Ações[Stock], 0), MATCH(Indicador_Ações[[#HEADERS],[divida_bruta]], Indicador_Ações[#HEADERS], 0)),"")} -> 366533000000 | L9: =L8/L7 -> 0.16242002 | M9: PAYOUT FCL
A10: Títulos e valores mobiliários | B10: 13306 | C10: =IFERROR(SUM((D10/B10)-1),0) -> 0.51841275 | D10: 20204 | E10: =IFERROR(SUM((F10/D10)-1),0) -> -0.29093249 | F10: 14326 | G10: =IFERROR(SUM((H10/F10)-1),0) -> 0.047047327 | H10: 15000 | J10: Dívida líq | K10: =K9-K7 -> 312769000000 | L10: =IFERROR(K14/K4,0) -> 0.42883849 | M10: GIRO ATIVOS
A11: Disponibilidades | B11: =SUM(B9,B10) -> 47600 | C11: =IFERROR(SUM((D11/B11)-1),0) -> 0.1294958 | D11: =SUM(D9,D10) -> 53764 | E11: =IFERROR(SUM((F11/D11)-1),0) -> 0.15320661 | F11: =SUM(F9,F10) -> 62001 | G11: =IFERROR(SUM((H11/F11)-1),0) -> -0.1837551 | H11: =SUM(H9,H10) -> 50608 | J11: Capital_Investido | K11: =SUM(K8,K9) -> 847483000000 | L11: =IFERROR(K22/K8,0) -> 0.27731781 | M11: ROE
J12: Razão de Divida | K12: =K9/K11 -> 0.43249599 | L12: =O8/K11 -> 0.20462937 | M12: ROIC
A13: Passivo Total | B13: =SUM(B14+B15) -> 799696 | C13: =IFERROR(SUM((D13/B13)-1),0) -> -0.0031649527 | D13: =SUM(D14+D15) -> 797165 | E13: =IFERROR(SUM((F13/D13)-1),0) -> -0.012654846 | F13: =SUM(F14+F15) -> 787077 | G13: =IFERROR(SUM((H13/F13)-1),0) -> 0.023790557 | H13: =SUM(H14+H15) -> 805802 | J13: DRE | L13: =IFERROR(K22/K4,0) -> 0.10427984 | M13: ROA
A14: Passivo Circ. | B14: 189166 | C14: =IFERROR(SUM((D14/B14)-1),0) -> -0.041201907 | D14: 181372 | E14: =IFERROR(SUM((F14/D14)-1),0) -> 0.0054859626 | F14: 182367 | G14: =IFERROR(SUM((H14/F14)-1),0) -> 0.087740655 | H14: 198368 | J14: Receita_Liquida | K14: {=IFERROR(INDEX(Indicador_Ações[], MATCH($J$2, Indicador_Ações[Stock], 0), MATCH(Indicador_Ações[[#HEADERS],[receita_liquida_12m]], Indicador_Ações[#HEADERS], 0)),"")} -> 548493000000 | L14: =K6/K17 -> 3.3972214 | M14: EV/EBITDA
A15: Passivo Não Circ. | B15: 610530 | C15: =IFERROR(SUM((D15/B15)-1),0) -> 0.008620379 | D15: 615793 | E15: =IFERROR(SUM((F15/D15)-1),0) -> -0.017997931 | F15: 604710 | G15: =IFERROR(SUM((H15/F15)-1),0) -> 0.0045046386 | H15: 607434 | J15: Cagr_receita_5a | K15: {=IFERROR(INDEX(Indicador_Ações[], MATCH($J$2, Indicador_Ações[Stock], 0), MATCH(Indicador_Ações[[#HEADERS],[cagr_receita_5a]], Indicador_Ações[#HEADERS], 0)),"")} -> -2.3 | L15: =K17/K6 -> 0.29435821 | M15: Earnings_Yield_Greenblatt
A16: Emprést. CP | B16: 12970 | C16: =IFERROR(SUM((D16/B16)-1),0) -> -0.42706245 | D16: 7431 | E16: =IFERROR(SUM((F16/D16)-1),0) -> 0.77593864 | F16: 13197 | G16: =IFERROR(SUM((H16/F16)-1),0) -> -0.088656513 | H16: 12027 | J16: EBIT | K16: {=IFERROR(INDEX(Indicador_Ações[], MATCH($J$2, Indicador_Ações[Stock], 0), MATCH(Indicador_Ações[[#HEADERS],[ebit_12m]], Indicador_Ações[#HEADERS], 0)),"")} -> 234531000000 | L16: =IFERROR(K10/K17,0) -> 1.1278189 | M16: DÍVIDA LÍQUIDA / EBITDA Ajustado
A17: Emprést. LP | B17: 130754 | C17: =IFERROR(SUM((D17/B17)-1),0) -> -0.034041024 | D17: 126303 | E17: =IFERROR(SUM((F17/D17)-1),0) -> 0.079728906 | F17: 136373 | G17: =IFERROR(SUM((H17/F17)-1),0) -> -0.021345868 | H17: 133462 | J17: EBITDA Ajustado | K17: =SUM(B59,D59,F59,H59)*K3 -> 277322000000 | L17: =SUM(B5,D5,F5,H5)/SUM(B14,D14,F14,H14) -> 0.77853324 | M17: LIQUIDEZ CORRENTE MEDIA
A18: Arrendamentos | B18: 227967 | C18: =IFERROR(SUM((D18/B18)-1),0) -> 0.02119605 | D18: 232799 | E18: =IFERROR(SUM((F18/D18)-1),0) -> -0.027001834 | F18: 226513 | G18: =IFERROR(SUM((H18/F18)-1),0) -> 0.053078631 | H18: 238536 | J18: Custo_Mercadoria | K18: =SUM(B33,D33,F33,H33)*K3 -> -270981000000 | L18: =SUM(B46,D46,F46,H46)/ABS(SUM(B49,D49,F49,H49)) -> 8.176747 | M18: Indice de Cobertura de Juros MEDIA
A19: ENDIVIDAMENTO / CAIXA | J19: Lucro bruto | K19: =IFERROR(SUM(B34,D34,F34,H34),"")*K3 -> 277512000000 | L19: =IFERROR(K4/K8,0) -> 2.6593617 | M19: Alavancagem_Financeira
A20: Dívida Financeira | B20: =SUM(B17,B16) -> 143724 | C20: =IFERROR(SUM((D20/B20)-1),0) -> -0.069508224 | D20: =SUM(D17,D16) -> 133734 | E20: =IFERROR(SUM((F20/D20)-1),0) -> 0.11841417 | F20: =SUM(F17,F16) -> 149570 | G20: =IFERROR(SUM((H20/F20)-1),0) -> -0.027284883 | H20: =SUM(H17,H16) -> 145489 | J20: Despesas operacionais | K20: =IFERROR(SUM(B44,D44,F44,H44),"")*K3 -> -91352000000 | L20: =K10/K8 -> 0.650315 | M20: DL/PL
A21: Divida Bruta | B21: =SUM(B18,B20) -> 371691 | C21: =IFERROR(SUM((D21/B21)-1),0) -> -0.013877118 | D21: =SUM(D18,D20) -> 366533 | E21: =IFERROR(SUM((F21/D21)-1),0) -> 0.026054953 | F21: =SUM(F18,F20) -> 376083 | G21: =IFERROR(SUM((H21/F21)-1),0) -> 0.021117679 | H21: =SUM(H18,H20) -> 384025 | J21: Inflação | K21: ='Indicadores_Ações'!$B$4 -> 0.044430246 | L21: Vendas
A22: Dívida líq | B22: =SUM(B21-B11) -> 324091 | C22: =IFERROR(SUM((D22/B22)-1),0) -> -0.034934633 | D22: =SUM(D21-D11) -> 312769 | E22: =IFERROR(SUM((F22/D22)-1),0) -> 0.0041979864 | F22: =SUM(F21-F11) -> 314082 | G22: =IFERROR(SUM((H22/F22)-1),0) -> 0.061560357 | H22: =SUM(H21-H11) -> 333417 | J22: Lucro_Liquido_Fundamentus | K22: {=IFERROR(INDEX(Indicador_Ações[], MATCH($J$2, Indicador_Ações[Stock], 0), MATCH(Indicador_Ações[[#HEADERS],[lucro_liquido_12m]], Indicador_Ações[#HEADERS], 0)),"")} -> 133376000000 | L22: Dólar médio de venda | M22: =SUM(B62,D62,F62,H62)/4 -> 5.2875
J23: Lucro_Ajustado_Planilha | K23: =SUM(B60,D60,F60,H60)*K3 -> 133736000000 | L23: Brent (US$/bbl) | M23: =SUM(B63,D63,F63,H63)/4 -> 79.4725
A24: Patrimônio líq. | B24: =B4-B13 -> 446372 | C24: =IFERROR(SUM((D24/B24)-1),0) -> 0.079489753 | D24: =D4-D13 -> 481854 | E24: =IFERROR(SUM((F24/D24)-1),0) -> -0.11807103 | F24: =F4-F13 -> 424961 | G24: =IFERROR(SUM((H24/F24)-1),0) -> -0.017352181 | H24: =H4-H13 -> 417587 | J24: FCL | K24: =(SUM(B70,D70,F70,H70)+SUM(B74,D74,F74,H74))*K3 -> 105338000000 | L24: ROCE (Capital Empregado) | M24: =SUM(B64,D64,F64,H64)/4 -> 0.07075
A25: Reserva de Capital | B25: 3106 | C25: =IFERROR(SUM((D25/B25)-1),0) -> 0.0003219575 | D25: 3107 | E25: =IFERROR(SUM((F25/D25)-1),0) -> -0.00032185388 | F25: 3106 | G25: =IFERROR(SUM((H25/F25)-1),0) -> 0 | H25: 3106 | J25: Beta | K25: {=IFERROR(INDEX(Indicador_Ações[], MATCH($J$2, Indicador_Ações[Stock], 0), MATCH(Indicador_Ações[[#HEADERS],[beta_ibov_3a]], Indicador_Ações[#HEADERS], 0)),"")} -> 0.59 | M25: CPM
A26: Reserva de Lucro | B26: 158278 | C26: =IFERROR(SUM((D26/B26)-1),0) -> -0.050998875 | D26: 150206 | E26: =IFERROR(SUM((F26/D26)-1),0) -> -0.46416921 | F26: 80485 | G26: =IFERROR(SUM((H26/F26)-1),0) -> 0.96655277 | H26: 158278 | L26: ='Indicadores_Ações'!$B$3 -> 0.139 | M26: RF
A27: Lucro ou Prejuizo Acumulados | B27: 32755 | C27: =IFERROR(SUM((D27/B27)-1),0) -> 1.3292627 | D27: 76295 | E27: =IFERROR(SUM((F27/D27)-1),0) -> -0.019490137 | F27: 74808 | G27: =IFERROR(SUM((H27/F27)-1),0) -> -1 | H27: 0 | L27: =K25 -> 0.59 | M27: Beta (B)
L28: =L26+0.15 -> 0.289 | M28: RM
A29: DRE Analise Trimestral | L29: =L26+L27*(L28-L26) -> 0.2275 | M29: KE
A30: Trimestre | B30: A | C30: AH% (A/B) | D30: B | E30: AH% (A/B) | F30: A | G30: AH% (A/B) | H30: A
A31: Receita Bruta | J31: Ticker | K31: Valores | L31: Ano | M31: VLF | N31: VLP | O31: Cresc | Q31: Ano | R31: Fluxo
A32: Receita Liquida | B32: 123686 | C32: =IFERROR(SUM((D32/B32)-1),0) -> 0.37064825 | D32: 169530 | E32: =IFERROR(SUM((F32/D32)-1),0) -> -0.24552587 | F32: 127906 | G32: =IFERROR(SUM((H32/F32)-1),0) -> -0.0041827592 | H32: 127371 | J32: Preço_Mercado | K32: =K2 -> 48.83 | L32: 1 | M32: =K37 -> 105338000000 | O32: 6 | Q32: 0 | R32: =-K6 -> -942124221000
A33: Custo Mercadoria (CMV) | B33: -64084 | C33: =IFERROR(SUM((D33/B33)-1),0) -> 0.11150989 | D33: -71230 | E33: =IFERROR(SUM((F33/D33)-1),0) -> -0.062347326 | F33: -66789 | G33: =IFERROR(SUM((H33/F33)-1),0) -> 0.031277606 | H33: -68878 | J33: Numero_Papel | K33: =L2 -> 12888700000 | L33: 2 | M33: =M32*(1+O32/100) -> 111658280000 | N33: =M33/(1+K38)^L32 -> 90963975560 | O33: 6 | Q33: 1 | R33: =M33 -> 111658280000
A34: Lucro Bruto | B34: =B32+B33 -> 59602 | C34: =IFERROR(SUM((D34/B34)-1),0) -> 0.64927351 | D34: =D32+D33 -> 98300 | E34: =IFERROR(SUM((F34/D34)-1),0) -> -0.37826043 | F34: =F32+F33 -> 61117 | G34: =IFERROR(SUM((H34/F34)-1),0) -> -0.042934045 | H34: =H32+H33 -> 58493 | J34: Market | K34: =K5 -> 629355221000 | L34: 3 | M34: =M33*(1+O33/100) -> 118357776800 | N34: =M34/(1+K38)^L33 -> 78551376044 | O34: 6 | Q34: 2 | R34: =M34 -> 118357776800
A35: DESPESAS E OUTRAS RECEITAS | J35: Taxa_Cresc | K35: =SUM(O32:O40)/6 -> 6 | L35: 4 | M35: =M34*(1+O34/100) -> 125459243408 | N35: =M35/(1+K38)^L34 -> 67832552836 | O35: 6 | Q35: 3 | R35: =M35 -> 125459243408
A36: Despesas com Vendas | B36: -7969 | C36: =IFERROR(SUM((D36/B36)-1),0) -> 0.105032 | D36: -8806 | E36: =IFERROR(SUM((F36/D36)-1),0) -> -0.15909607 | F36: -7405 | G36: =IFERROR(SUM((H36/F36)-1),0) -> 0.065496286 | H36: -7890 | J36: Taxa_Gordon | K36: 0.04 | L36: 5 | M36: =M35*(1+O35/100) -> 132986798012 | N36: =M36/(1+K38)^L35 -> 58576379639 | O36: 6 | Q36: 4 | R36: =M36 -> 132986798012
A37: Despesa Administrativa | B37: -2517 | C37: =IFERROR(SUM((D37/B37)-1),0) -> 0.11680572 | D37: -2811 | E37: =IFERROR(SUM((F37/D37)-1),0) -> -0.029171113 | F37: -2729 | G37: =IFERROR(SUM((H37/F37)-1),0) -> 0.045804324 | H37: -2854 | J37: FCL | K37: =K24 -> 105338000000 | L37: 6 | M37: =M36*(1+O36/100) -> 140966005893 | N37: =M37/(1+K38)^L36 -> 50583268771 | O37: 6 | Q37: 5 | R37: =M37 -> 140966005893
A38: Despesa Administrativa (%) | B38: =ABS(B37)/B32 -> 0.020349918 | C38: =IFERROR(SUM((D38/B38)-1),0) -> -0.18519889 | D38: =ABS(D37)/D32 -> 0.016581136 | E38: =IFERROR(SUM((F38/D38)-1),0) -> 0.28676232 | F38: =ABS(F37)/F32 -> 0.021335981 | G38: =IFERROR(SUM((H38/F38)-1),0) -> 0.050197045 | H38: =ABS(H37)/H32 -> 0.022406984 | J38: Taxa_desconto_KE | K38: =L29 -> 0.2275 | L38: 7 | M38: =M37*(1+O37/100) -> 149423966247 | N38: =M38/(1+K38)^L37 -> 43680867534 | Q38: 6 | R38: =M38+M39 -> 978228899029
A39: Custos exploratórios | B39: -726 | C39: =IFERROR(SUM((D39/B39)-1),0) -> -0.29476584 | D39: -512 | E39: =IFERROR(SUM((F39/D39)-1),0) -> 1.6230469 | F39: -1343 | G39: =IFERROR(SUM((H39/F39)-1),0) -> 0.90171258 | H39: -2554 | J39: Valor_ação_Proj | K39: =K40/K33 -> 45.587826 | L39: Perpétuo | M39: =IFERROR( M38 * (1 + K36) / (K38 -K36 ), 0 ) -> 828804932782 | N39: =M39/(1+K38)^L38 -> 197379398713 | Q39: TIR | R39: =IFERROR(IRR(R32:R38),0) -> 0.12034905
A40: Custos com pesquisa | B40: -1316 | C40: =IFERROR(SUM((D40/B40)-1),0) -> 0.13525836 | D40: -1494 | E40: =IFERROR(SUM((F40/D40)-1),0) -> -0.15127175 | F40: -1268 | G40: =IFERROR(SUM((H40/F40)-1),0) -> 0.0031545741 | H40: -1272 | J40: Market_Proj | K40: =N40 -> 587567819097 | N40: =SUM(N32:N39) -> 587567819097
A41: Tributárias | B41: -2483 | C41: =IFERROR(SUM((D41/B41)-1),0) -> 1.4075715 | D41: -5978 | E41: =IFERROR(SUM((F41/D41)-1),0) -> -0.8643359 | F41: -811 | G41: =IFERROR(SUM((H41/F41)-1),0) -> 1.4488286 | H41: -1986
A42: Reversão (Perda) | B42: 2180 | C42: =IFERROR(SUM((D42/B42)-1),0) -> -1.5311927 | D42: -1158 | E42: =IFERROR(SUM((F42/D42)-1),0) -> -2.3290155 | F42: 1539 | G42: =IFERROR(SUM((H42/F42)-1),0) -> -6.5490578 | H42: -8540
A43: Outras receitas (despesas) | B43: -5554 | C43: =IFERROR(SUM((D43/B43)-1),0) -> 0.027907814 | D43: -5709 | E43: =IFERROR(SUM((F43/D43)-1),0) -> -0.010509721 | F43: -5649 | G43: =IFERROR(SUM((H43/F43)-1),0) -> -0.33846699 | H43: -3737
A44: Despesas/Receitas Operacionais | B44: =SUM(B36,B37,B39,B43,B40,B41,B42) -> -18385 | C44: =IFERROR(SUM((D44/B44)-1),0) -> 0.43965189 | D44: =SUM(D36,D37,D39,D43,D40,D41,D42) -> -26468 | E44: =IFERROR(SUM((F44/D44)-1),0) -> -0.33255252 | F44: =SUM(F36,F37,F39,F43,F40,F41,F42) -> -17666 | G44: =IFERROR(SUM((H44/F44)-1),0) -> 0.63211819 | H44: =SUM(H36,H37,H39,H43,H40,H41,H42) -> -28833
A46: Lucro Operacional (EBIT)(LAJIR) | B46: =SUM(B34,B44) -> 41217 | C46: =IFERROR(SUM((D46/B46)-1),0) -> 0.74277604 | D46: =SUM(D34,D44) -> 71832 | E46: =IFERROR(SUM((F46/D46)-1),0) -> -0.39510246 | F46: =SUM(F34,F44) -> 43451 | G46: =IFERROR(SUM((H46/F46)-1),0) -> -0.317392 | H46: =SUM(H34,H44) -> 29660
A48: Receita Financeira | B48: 1758 | C48: =IFERROR(SUM((D48/B48)-1),0) -> 0.097269625 | D48: 1929 | E48: =IFERROR(SUM((F48/D48)-1),0) -> 0.16848108 | F48: 2254 | G48: =IFERROR(SUM((H48/F48)-1),0) -> 0.038154392 | H48: 2340
A49: Despesa Financeira | B49: -5179 | C49: =IFERROR(SUM((D49/B49)-1),0) -> 0.022977409 | D49: -5298 | E49: =IFERROR(SUM((F49/D49)-1),0) -> 0.15043413 | F49: -6095 | G49: =IFERROR(SUM((H49/F49)-1),0) -> 0.016406891 | H49: -6195
A50: Var. monetárias e cambiais, líquidas | B50: 11287 | C50: =IFERROR(SUM((D50/B50)-1),0) -> -0.8367148 | D50: 1843 | E50: =IFERROR(SUM((F50/D50)-1),0) -> 1.7981552 | F50: 5157 | G50: =IFERROR(SUM((H50/F50)-1),0) -> -2.6786892 | H50: -8657
A51: Resultado Financeiro | B51: =B48+B49+B50 -> 7866 | C51: =IFERROR(SUM((D51/B51)-1),0) -> -1.1939995 | D51: =D48+D49+D50 -> -1526 | E51: =IFERROR(SUM((F51/D51)-1),0) -> -1.8623853 | F51: =F48+F49+F50 -> 1316 | G51: =IFERROR(SUM((H51/F51)-1),0) -> -10.507599 | H51: =H48+H49+H50 -> -12512
A53: Depreciações e Amortizações | B53: -21614 | C53: =IFERROR(SUM((D53/B53)-1),0) -> -0.0051355603 | D53: -21503 | E53: =IFERROR(SUM((F53/D53)-1),0) -> 0.041203553 | F53: -22389 | G53: =IFERROR(SUM((H53/F53)-1),0) -> -0.014203403 | H53: -22071
A54: Resultado de participações | B54: 53 | C54: =IFERROR(SUM((D54/B54)-1),0) -> 8.8867925 | D54: 524 | E54: =IFERROR(SUM((F54/D54)-1),0) -> -0.64885496 | F54: 184 | G54: =IFERROR(SUM((H54/F54)-1),0) -> -7.3858696 | H54: -1175
A55: EBITIDA (LAJIDA) | B55: =B58-B57-B51-B53 -> 62884 | C55: =IFERROR(SUM((D55/B55)-1),0) -> 0.49257363 | D55: =D58-D57-D51-D53 -> 93859 | E55: =IFERROR(SUM((F55/D55)-1),0) -> -0.29656186 | F55: =F58-F57-F51-F53 -> 66024 | G55: =IFERROR(SUM((H55/F55)-1),0) -> -0.23427844 | H55: =H58-H57-H51-H53 -> 50556
A56: Resultado antes do Imposto | B56: =B46+B51+B54 -> 49136 | C56: =IFERROR(SUM((D56/B56)-1),0) -> 0.44150928 | D56: =D46+D51+D54 -> 70830 | E56: =IFERROR(SUM((F56/D56)-1),0) -> -0.36536778 | F56: =F46+F51+F54 -> 44951 | G56: =IFERROR(SUM((H56/F56)-1),0) -> -0.64465752 | H56: =H46+H51+H54 -> 15973
A57: Impostos | B57: -16375 | C57: =IFERROR(SUM((D57/B57)-1),0) -> 0.11969466 | D57: -18335 | E57: =IFERROR(SUM((F57/D57)-1),0) -> -0.33984183 | F57: -12104 | G57: =IFERROR(SUM((H57/F57)-1),0) -> -0.97356246 | H57: -320
A58: Lucro Liquido | B58: =B56+B57 -> 32761 | C58: =IFERROR(SUM((D58/B58)-1),0) -> 0.60236257 | D58: =D56+D57 -> 52495 | E58: =IFERROR(SUM((F58/D58)-1),0) -> -0.37428327 | F58: =F56+F57 -> 32847 | G58: =IFERROR(SUM((H58/F58)-1),0) -> -0.52345724 | H58: =H56+H57 -> 15653
A59: EBITIDA (LAJIDA) Ajustado | B59: 59643 | C59: =IFERROR(SUM((D59/B59)-1),0) -> 0.5734118 | D59: 93843 | E59: =IFERROR(SUM((F59/D59)-1),0) -> -0.31893695 | F59: 63913 | G59: =IFERROR(SUM((H59/F59)-1),0) -> -0.062428614 | H59: 59923
A60: Lucro_Liquido_Ajustado | B60: 23811 | C60: =IFERROR(SUM((D60/B60)-1),0) -> 1.3419008 | D60: 55763 | E60: =IFERROR(SUM((F60/D60)-1),0) -> -0.48874702 | F60: 28509 | G60: =IFERROR(SUM((H60/F60)-1),0) -> -0.10017889 | H60: 25653
A61: Vendas
A62: Dólar médio de venda | B62: 5.26 | C62: =IFERROR(SUM((D62/B62)-1),0) -> -0.039923954 | D62: 5.05 | E62: =IFERROR(SUM((F62/D62)-1),0) -> 0.079207921 | F62: 5.45 | G62: =IFERROR(SUM((H62/F62)-1),0) -> -0.011009174 | H62: 5.39
A63: Brent (US$/bbl) | B63: 80.61 | C63: =IFERROR(SUM((D63/B63)-1),0) -> 0.29661332 | D63: 104.52 | E63: =IFERROR(SUM((F63/D63)-1),0) -> -0.33916954 | F63: 69.07 | G63: =IFERROR(SUM((H63/F63)-1),0) -> -0.077891994 | H63: 63.69
A64: ROCE (Capital Empregado) | B64: 0.067 | C64: =IFERROR(SUM((D64/B64)-1),0) -> 0.3880597 | D64: 0.093 | E64: =IFERROR(SUM((F64/D64)-1),0) -> -0.38709677 | F64: 0.057 | G64: =IFERROR(SUM((H64/F64)-1),0) -> 0.15789474 | H64: 0.066
A66: DFC
A67: FCO – Fluxo Operacional | B67: A | C67: AH% (A/B) | D67: B | E67: AH% (A/B) | F67: A | G67: AH% (A/B) | H67: A
A68: Lucro Líquido | B68: =B58 -> 32761 | C68: =IFERROR(SUM((D68/B68)-1),0) -> 0.60236257 | D68: =D58 -> 52495 | E68: =IFERROR(SUM((F68/D68)-1),0) -> -0.37428327 | F68: =F58 -> 32847 | G68: =IFERROR(SUM((H68/F68)-1),0) -> -0.52345724 | H68: =H58 -> 15653
A69: Ajustes Não Caixa (subtotal) | B69: 43975 | C69: =IFERROR(SUM((D69/B69)-1),0) -> 0.40563957 | D69: 61813 | E69: =IFERROR(SUM((F69/D69)-1),0) -> -0.13197871 | F69: 53655 | G69: =IFERROR(SUM((H69/F69)-1),0) -> 0.023502004 | H69: 54916
A70: FCO | B70: =SUM(B69) -> 43975 | C70: =IFERROR(SUM((D70/B70)-1),0) -> 0.40563957 | D70: =SUM(D69) -> 61813 | E70: =IFERROR(SUM((F70/D70)-1),0) -> -0.13197871 | F70: =SUM(F69) -> 53655 | G70: =IFERROR(SUM((H70/F70)-1),0) -> 0.023502004 | H70: =SUM(H69) -> 54916
A72: CAPEX
A73: Imobilizado e Intangível | B73: -23734 | C73: =IFERROR(SUM((D73/B73)-1),0) -> -0.029240752 | D73: -23040 | E73: =IFERROR(SUM((F73/D73)-1),0) -> 0.15577257 | F73: -26629 | G73: =IFERROR(SUM((H73/F73)-1),0) -> 0.33756431 | H73: -35618
A74: CAPEX | B74: =SUM(B73) -> -23734 | C74: =IFERROR(SUM((D74/B74)-1),0) -> -0.029240752 | D74: =SUM(D73) -> -23040 | E74: =IFERROR(SUM((F74/D74)-1),0) -> 0.15577257 | F74: =SUM(F73) -> -26629 | G74: =IFERROR(SUM((H74/F74)-1),0) -> 0.33756431 | H74: =SUM(H73) -> -35618
A75: Reduções (adições) | B75: -164 | C75: =IFERROR(SUM((D75/B75)-1),0) -> -0.024390244 | D75: -160 | E75: =IFERROR(SUM((F75/D75)-1),0) -> -0.93125 | F75: -11 | G75: =IFERROR(SUM((H75/F75)-1),0) -> -4.3636364 | H75: 37
A76: Recebimentos pela venda de ativos | B76: 1311 | C76: =IFERROR(SUM((D76/B76)-1),0) -> -0.58504958 | D76: 544 | E76: =IFERROR(SUM((F76/D76)-1),0) -> -0.24080882 | F76: 413 | G76: =IFERROR(SUM((H76/F76)-1),0) -> -0.23244552 | H76: 317
A77: Compensação financeira | B77: 1645 | C77: =IFERROR(SUM((D77/B77)-1),0) -> -1 | D77: 0 | E77: =IFERROR(SUM((F78/D77)-1),0) -> 0 | F77: 0 | G77: =IFERROR(SUM((H77/F78)-1),0) -> -1 | H77: 0
A78: Resgates (investimentos) | B78: 2121 | C78: =IFERROR(SUM((D78/B78)-1),0) -> -4.1074965 | D78: -6591 | E78: =IFERROR(SUM((#REF!/D78)-1),0) -> 0 | F78: -143 | G78: =IFERROR(SUM((H78/#REF!)-1),0) -> 0 | H78: -237
A79: Dividendos recebidos | B79: 9 | C79: =IFERROR(SUM((D79/B79)-1),0) -> 37.666667 | D79: 348 | E79: =IFERROR(SUM((F79/D79)-1),0) -> 0.24425287 | F79: 433 | G79: =IFERROR(SUM((H79/F79)-1),0) -> -0.71362587 | H79: 124
A80: FCI – Investimentos | B80: =SUM(B74:B79) -> -18812 | C80: =IFERROR(SUM((D80/B80)-1),0) -> 0.5362003 | D80: =SUM(D74:D79) -> -28899 | E80: =IFERROR(SUM((F80/D80)-1),0) -> -0.1024949 | F80: =SUM(F74:F79) -> -25937 | G80: =IFERROR(SUM((H80/F80)-1),0) -> 0.36395882 | H80: =SUM(H74:H79) -> -35377
A82: FCF – Financiamento
A83: Participação de não acionistas | B83: -712 | C83: =IFERROR(SUM((D83/B83)-1),0) -> -0.53370787 | D83: -332 | E83: =IFERROR(SUM((F83/D83)-1),0) -> 1.0271084 | F83: -673 | G83: =IFERROR(SUM((H83/F83)-1),0) -> -0.72362556 | H83: -186
A84: Captações | B84: 6948 | C84: =IFERROR(SUM((D84/B84)-1),0) -> -0.55512378 | D84: 3091 | E84: =IFERROR(SUM((F84/D84)-1),0) -> 2.9097379 | F84: 12085 | G84: =IFERROR(SUM((H84/F84)-1),0) -> -0.99784857 | H84: 26
A85: Pag de Emp e debêntures Principal | B85: -3613 | C85: =IFERROR(SUM((D85/B85)-1),0) -> 2.4453363 | D85: -12448 | E85: =IFERROR(SUM((F85/D85)-1),0) -> -0.84736504 | F85: -1900 | G85: =IFERROR(SUM((H85/F85)-1),0) -> 3.0878947 | H85: -7767
A86: Pag de Emp e debêntures Juros | B86: -3103 | C86: =IFERROR(SUM((D86/B86)-1),0) -> -0.20528521 | D86: -2466 | E86: =IFERROR(SUM((F86/D86)-1),0) -> 0.18815896 | F86: -2930 | G86: =IFERROR(SUM((H86/F86)-1),0) -> -0.17576792 | H86: -2415
A87: Arrendamentos | B87: -12834 | C87: =IFERROR(SUM((D87/B87)-1),0) -> 0.091709522 | D87: -14011 | E87: =IFERROR(SUM((F87/D87)-1),0) -> -0.061237599 | F87: -13153 | G87: =IFERROR(SUM((H87/F87)-1),0) -> 0.077244735 | H87: -14169
A88: Dividendos pagos a acionistas | B88: -11639 | C88: =IFERROR(SUM((D88/B88)-1),0) -> -0.34384397 | D88: -7637 | E88: =IFERROR(SUM((F88/D88)-1),0) -> 0.43682074 | F88: -10973 | G88: =IFERROR(SUM((H88/F88)-1),0) -> -0.2638294 | H88: -8078
A89: Dividendos pagos a não acionistas | B89: 0 | C89: =IFERROR(SUM((D89/B89)-1),0) -> 0 | D89: -38 | E89: =IFERROR(SUM((F89/D89)-1),0) -> 0.34210526 | F89: -51 | G89: =IFERROR(SUM((H89/F89)-1),0) -> -0.98039216 | H89: -1
A90: FCF | B90: =SUM(B83:B89) -> -24953 | C90: =IFERROR(SUM((D90/B90)-1),0) -> 0.35618964 | D90: =SUM(D83:D89) -> -33841 | E90: =IFERROR(SUM((F90/D90)-1),0) -> -0.48006856 | F90: =SUM(F83:F89) -> -17595 | G90: =IFERROR(SUM((H90/F90)-1),0) -> 0.85223075 | H90: =SUM(H83:H89) -> -32590
A92: Variação Cambial | B92: -1524 | C92: =IFERROR(SUM((D92/B92)-1),0) -> -1.1266404 | D92: 193 | E92: =IFERROR(SUM((F92/D92)-1),0) -> -4.238342 | F92: -625 | G92: =IFERROR(SUM((H92/F92)-1),0) -> -2.5744 | H92: 984
A93: Fechamento | B93: =SUM(B70,B80,B90,B92) -> -1314 | C93: =IFERROR(SUM((D93/B93)-1),0) -> -0.4414003 | D93: =SUM(D70,D80,D90,D92) -> -734 | E93: =IFERROR(SUM((F93/D93)-1),0) -> -13.940055 | F93: =SUM(F70,F80,F90,F92) -> 9498 | G93: =IFERROR(SUM((H93/F93)-1),0) -> -2.270478 | H93: =SUM(H70,H80,H90,H92) -> -12067
A94: Caixa Inicial | B94: 35608 | C94: =IFERROR(SUM((D94/B94)-1),0) -> -0.03690182 | D94: 34294 | E94: =IFERROR(SUM((F94/D94)-1),0) -> 0.1132268 | F94: 38177 | G94: =IFERROR(SUM((H94/F94)-1),0) -> 0.24878854 | H94: 47675
A95: Caixa Final | B95: =SUM(B93:B94) -> 34294 | C95: =IFERROR(SUM((D95/B95)-1),0) -> -0.021403161 | D95: =SUM(D93:D94) -> 33560 | E95: =IFERROR(SUM((F95/D95)-1),0) -> 0.42058999 | F95: =SUM(F93:F94) -> 47675 | G95: =IFERROR(SUM((H95/F95)-1),0) -> -0.2531096 | H95: =SUM(H93:H94) -> 35608

Sheet Vale3
B1: Feito | C1: 46058 | D1: Atual | E1: 46233 | F1: Não | G1: 46058 | H1: Não | I1: 46058 | J1: Ultimo_Balanco | K1: {=IFERROR(INDEX('Indicadores_Ações'!$A$10:$L$23, MATCH($J$2, 'Indicadores_Ações'!$A$10:$A$23, 0), MATCH('Indicadores_Ações'!$B$9, 'Indicadores_Ações'!$A$9:$L$9, 0)),"")} -> 46203
A2: Balanço Patrimonial Anual | J2: VALE3 | K2: =IFERROR(__xludf.DUMMYFUNCTION("(GOOGLEFINANCE(""BVMF:"" & J2))"),77.84) -> 77.84 | L2: {=IFERROR(INDEX(Indicador_Ações[], MATCH($J$2, Indicador_Ações[Stock], 0), MATCH(Indicador_Ações[[#HEADERS],[qtd_acao]], Indicador_Ações[#HEADERS], 0)),"")} -> 4439160000 | M2: Numero_Papel
A3: Ano | B3: 1_T | C3: AH% (2/1) | D3: 2_T | E3: AH% (3/2) | F3: 3_T | G3: AH% (4/3) | H3: 4_T | J3: BP | K3: 1000000 | L3: =IFERROR(K23/K14,0) -> 0.18619795 | M3: Margem_Liquida_Proforma | N3: DMPL Acumulado
A4: Ativo Total | B4: =B5+B6 -> 457173 | C4: =IFERROR(SUM((D4/B4)-1),0) -> 0.010910531 | D4: =D5+D6 -> 462161 | E4: =IFERROR(SUM((F4/D4)-1),0) -> 0.049316147 | F4: =F5+F6 -> 484953 | G4: =IFERROR(SUM((H4/F4)-1),0) -> -0.01826775 | H4: =H5+H6 -> 476094 | J4: Ativo | K4: {=IFERROR(INDEX(Indicador_Ações[], MATCH($J$2, Indicador_Ações[Stock], 0), MATCH(Indicador_Ações[[#HEADERS],[ativo]], Indicador_Ações[#HEADERS], 0)),"")} -> 462161000000 | L4: =IFERROR(K19/K14,0) -> 0.34258881 | M4: MARGEM BRUTA | N4: JCP acionistas Liquido | O4: 0
A5: Ativo Circulante | B5: 87427 | C5: =IFERROR(SUM((D5/B5)-1),0) -> 0.045569447 | D5: 91411 | E5: =IFERROR(SUM((F5/D5)-1),0) -> -0.040793778 | F5: 87682 | G5: =IFERROR(SUM((H5/F5)-1),0) -> 0.14784106 | H5: 100645 | J5: Valor_de_mercado | K5: =K2*L2 -> 345544214400 | L5: =IFERROR(K16/K14,0) -> 0.33242231 | M5: MARGEM EBIT | N5: Dividendos | O5: 9143
A6: Ativo Nao Circ. | B6: 369746 | C6: =IFERROR(SUM((D6/B6)-1),0) -> 0.0027153776 | D6: 370750 | E6: =IFERROR(SUM((F6/D6)-1),0) -> 0.071533378 | F6: 397271 | G6: =IFERROR(SUM((H6/F6)-1),0) -> -0.054929758 | H6: 375449 | J6: Valor_da_firma | K6: =SUM(K5,K10) -> 413736214400 | L6: =IFERROR(K17/K14,0) -> 0.41737248 | M6: MARGEM_EBITDA_Proforma | N6: Dividendos e JCP | O6: =SUM(O4:O5) -> 9143
J7: Disponibilidade | K7: {=IFERROR(INDEX(Indicador_Ações[], MATCH($J$2, Indicador_Ações[Stock], 0), MATCH(Indicador_Ações[[#HEADERS],[disponibilidades]], Indicador_Ações[#HEADERS], 0)),"")} -> 29842000000 | L7: =K23/L2 -> 9.1467755 | M7: LPA_Proforma | N7: Aliquota | O7: =ABS(SUM(B55,D55,F55,H55)/SUM(B54,D54,F54,H54)) -> 0.55752444
A8: Estoque | B8: 32020 | C8: =IFERROR(SUM((D8/B8)-1),0) -> 0.012617114 | D8: 32424 | E8: =IFERROR(SUM((F8/D8)-1),0) -> -0.086880089 | F8: 29607 | G8: =IFERROR(SUM((H8/F8)-1),0) -> 0.10332016 | H8: 32666 | J8: Patrimônio líq | K8: {=IFERROR(INDEX(Indicador_Ações[], MATCH($J$2, Indicador_Ações[Stock], 0), MATCH(Indicador_Ações[[#HEADERS],[patrimonio_liquido]], Indicador_Ações[#HEADERS], 0)),"")} -> 196635000000 | L8: {=IFERROR(INDEX(O6*K3,0)/L2,"")} -> 2.0596239 | M8: DPA Liquido | N8: NOPAT | O8: =K16*(1-O7) -> 32075495486
A9: Caixa | B9: 26540 | C9: =IFERROR(SUM((D9/B9)-1),0) -> 0.087829691 | D9: 28871 | E9: =IFERROR(SUM((F9/D9)-1),0) -> 0.087284819 | F9: 31391 | G9: =IFERROR(SUM((H9/F9)-1),0) -> 0.29218566 | H9: 40563 | J9: Dívida bruta | K9: {=IFERROR(INDEX(Indicador_Ações[], MATCH($J$2, Indicador_Ações[Stock], 0), MATCH(Indicador_Ações[[#HEADERS],[divida_bruta]], Indicador_Ações[#HEADERS], 0)),"")} -> 98034000000 | L9: =L8/L7 -> 0.22517486 | M9: PAYOUT FCL
A10: Títulos e valores mobiliários | B10: 1012 | C10: =IFERROR(SUM((D10/B10)-1),0) -> -0.040513834 | D10: 971 | E10: =IFERROR(SUM((F10/D10)-1),0) -> 0.03192585 | F10: 1002 | G10: =IFERROR(SUM((H10/F10)-1),0) -> 0.063872255 | H10: 1066 | J10: Dívida líq | K10: =K9-K7 -> 68192000000 | L10: =IFERROR(K14/K4,0) -> 0.47184639 | M10: GIRO ATIVOS
A11: Disponibilidades | B11: =SUM(B9,B10) -> 27552 | C11: =IFERROR(SUM((D11/B11)-1),0) -> 0.083115563 | D11: =SUM(D9,D10) -> 29842 | E11: =IFERROR(SUM((F11/D11)-1),0) -> 0.085483547 | F11: =SUM(F9,F10) -> 32393 | G11: =IFERROR(SUM((H11/F11)-1),0) -> 0.28512333 | H11: =SUM(H9,H10) -> 41629 | J11: Capital_Investido | K11: =SUM(K8,K9) -> 294669000000 | L11: =IFERROR(K23/K8,0) -> 0.20649427 | M11: ROE
J12: Razão de Divida | K12: =K9/K11 -> 0.33269194 | L12: =O8/K11 -> 0.10885263 | M12: ROIC
A13: Passivo Total | B13: =SUM(B14+B15) -> 261258 | C13: =IFERROR(SUM((D13/B13)-1),0) -> -0.0021587856 | D13: =SUM(D14+D15) -> 260694 | E13: =IFERROR(SUM((F13/D13)-1),0) -> -0.0018182237 | F13: =SUM(F14+F15) -> 260220 | G13: =IFERROR(SUM((H13/F13)-1),0) -> 0.10355853 | H13: =SUM(H14+H15) -> 287168 | J13: DRE | L13: =IFERROR(K23/K4,0) -> 0.087856829 | M13: ROA_Proforma
A14: Passivo Circ. | B14: 70512 | C14: =IFERROR(SUM((D14/B14)-1),0) -> 0.087800658 | D14: 76703 | E14: =IFERROR(SUM((F14/D14)-1),0) -> -0.076176942 | F14: 70860 | G14: =IFERROR(SUM((H14/F14)-1),0) -> 0.23228902 | H14: 87320 | J14: Receita_Liquida | K14: {=IFERROR(INDEX(Indicador_Ações[], MATCH($J$2, Indicador_Ações[Stock], 0), MATCH(Indicador_Ações[[#HEADERS],[receita_liquida_12m]], Indicador_Ações[#HEADERS], 0)),"")} -> 218069000000 | L14: =K6/K17 -> 4.5457526 | M14: EV/EBITDA_Proforma
A15: Passivo Não Circ. | B15: 190746 | C15: =IFERROR(SUM((D15/B15)-1),0) -> -0.035413587 | D15: 183991 | E15: =IFERROR(SUM((F15/D15)-1),0) -> 0.029180775 | F15: 189360 | G15: =IFERROR(SUM((H15/F15)-1),0) -> 0.055386565 | H15: 199848 | J15: Cagr_receita_5a | K15: {=IFERROR(INDEX(Indicador_Ações[], MATCH($J$2, Indicador_Ações[Stock], 0), MATCH(Indicador_Ações[[#HEADERS],[cagr_receita_5a]], Indicador_Ações[#HEADERS], 0)),"")} -> -2.4 | L15: =K17/K6 -> 0.21998558 | M15: Earnings_Yield_Greenblatt_Proforma
A16: Emprést. CP | B16: 3117 | C16: =IFERROR(SUM((D16/B16)-1),0) -> 0.81552775 | D16: 5659 | E16: =IFERROR(SUM((F16/D16)-1),0) -> -0.55857925 | F16: 2498 | G16: =IFERROR(SUM((H16/F16)-1),0) -> 0.13971177 | H16: 2847 | J16: EBIT | K16: {=IFERROR(INDEX(Indicador_Ações[], MATCH($J$2, Indicador_Ações[Stock], 0), MATCH(Indicador_Ações[[#HEADERS],[ebit_12m]], Indicador_Ações[#HEADERS], 0)),"")} -> 72491000000 | L16: =IFERROR(K10/K17,0) -> 0.7492309 | M16: DÍVIDA LÍQUIDA / EBITDA_Proforma
A17: Emprést. LP | B17: 91856 | C17: =IFERROR(SUM((D17/B17)-1),0) -> -0.030068803 | D17: 89094 | E17: =IFERROR(SUM((F17/D17)-1),0) -> 0.037106876 | F17: 92400 | G17: =IFERROR(SUM((H17/F17)-1),0) -> 0.049047619 | H17: 96932 | J17: EBITDA Proforma | K17: =SUM(B53,D53,F53,H53)*K3 -> 91016000000 | L17: =SUM(B5,D5,F5,H5)/SUM(B14,D14,F14,H14) -> 1.2022626 | M17: LIQUIDEZ CORRENTE MEDIA
A18: Arrendamento CP | B18: 837 | C18: =IFERROR(SUM((D18/B18)-1),0) -> 0.045400239 | D18: 875 | E18: =IFERROR(SUM((F18/D18)-1),0) -> 3.256 | F18: 3724 | G18: =IFERROR(SUM((H18/F18)-1),0) -> -0.012352309 | H18: 3678 | J18: Custo_Mercadoria | K18: =SUM(B33,D33,F33,H33)*K3 -> -138887000000 | L18: =SUM(B44,D44,F44,H44)/ABS(SUM(B47,D47,F47,H47)) -> 3.6103061 | M18: Indice de Cobertura de Juros MEDIA
A19: Arrendamento LP | B19: 2510 | C19: =IFERROR(SUM((D19/B19)-1),0) -> -0.041434263 | D19: 2406 | E19: =IFERROR(SUM((F19/D19)-1),0) -> -1 | F19: 0 | G19: =IFERROR(SUM((H19/F19)-1),0) -> 0 | H19: 0 | J19: Lucro bruto | K19: =IFERROR(SUM(B34,D34,F34,H34),"")*K3 -> 74708000000 | L19: =IFERROR(K4/K8,0) -> 2.3503496 | M19: Alavancagem_Financeira
A20: ENDIVIDAMENTO / CAIXA | J20: Despesas operacionais | K20: =IFERROR(SUM(B42,D42,F42,H42),"")*K3 -> -41569000000 | L20: =K10/K8 -> 0.34679482 | M20: DL/PL
A21: Divida Financeira | B21: =SUM(B17,B16) -> 94973 | C21: =IFERROR(SUM((D21/B21)-1),0) -> -0.0023164478 | D21: =SUM(D17,D16) -> 94753 | E21: =IFERROR(SUM((F21/D21)-1),0) -> 0.0015302946 | F21: =SUM(F17,F16) -> 94898 | G21: =IFERROR(SUM((H21/F21)-1),0) -> 0.051434171 | H21: =SUM(H17,H16) -> 99779 | J21: Inflação | K21: ='Indicadores_Ações'!$B$4 -> 0.044430246 | M21: CPM
A22: Dívida bruta | B22: =SUM(B18,B19,B21) -> 98320 | C22: =IFERROR(SUM((D22/B22)-1),0) -> -0.002908869 | D22: =SUM(D18,D19,D21) -> 98034 | E22: =IFERROR(SUM((F22/D22)-1),0) -> 0.0059979191 | F22: =SUM(F18,F19,F21) -> 98622 | G22: =IFERROR(SUM((H22/F22)-1),0) -> 0.049025572 | H22: =SUM(H18,H19,H21) -> 103457 | J22: Lucro_Liquido_Fundamentus | K22: {=IFERROR(INDEX(Indicador_Ações[], MATCH($J$2, Indicador_Ações[Stock], 0), MATCH(Indicador_Ações[[#HEADERS],[lucro_liquido_12m]], Indicador_Ações[#HEADERS], 0)),"")} -> 10369000000 | L22: ='Indicadores_Ações'!$B$3 -> 0.139 | M22: RF
A23: Dívida líq | B23: =SUM(B22-B11) -> 70768 | C23: =IFERROR(SUM((D23/B23)-1),0) -> -0.036400633 | D23: =SUM(D22-D11) -> 68192 | E23: =IFERROR(SUM((F23/D23)-1),0) -> -0.028786368 | F23: =SUM(F22-F11) -> 66229 | G23: =IFERROR(SUM((H23/F23)-1),0) -> -0.066451252 | H23: =SUM(H22-H11) -> 61828 | J23: Lucro_proforma_Planilha | K23: =SUM(B57,D57,F57,H57)*K3 -> 40604000000 | L23: =K24 -> 0.85 | M23: Beta (B)
J24: Beta | K24: {=IFERROR(INDEX(Indicador_Ações[], MATCH($J$2, Indicador_Ações[Stock], 0), MATCH(Indicador_Ações[[#HEADERS],[beta_ibov_3a]], Indicador_Ações[#HEADERS], 0)),"")} -> 0.85 | L24: =L22+0.02 -> 0.159 | M24: RM
A25: Patrimônio líq. | B25: =B4-B13 -> 195915 | C25: =IFERROR(SUM((D25/B25)-1),0) -> 0.02833882 | D25: =D4-D13 -> 201467 | E25: =IFERROR(SUM((F25/D25)-1),0) -> 0.11548293 | F25: =F4-F13 -> 224733 | G25: =IFERROR(SUM((H25/F25)-1),0) -> -0.1593313 | H25: =H4-H13 -> 188926 | L25: =L22+L23*(L24-L22) -> 0.156 | M25: KE
A26: Reserva de Capital | B26: 3634 | C26: =IFERROR(SUM((D26/B26)-1),0) -> 0 | D26: 3634 | E26: =IFERROR(SUM((F26/D26)-1),0) -> 0 | F26: 3634 | G26: =IFERROR(SUM((H26/F26)-1),0) -> 0 | H26: 3634
A27: Reserva de Lucro | B27: 89212 | C27: =IFERROR(SUM((D27/B27)-1),0) -> -0.0056046272 | D27: 88712 | E27: =IFERROR(SUM((F27/D27)-1),0) -> 0 | F27: 88712 | G27: =IFERROR(SUM((H27/F27)-1),0) -> 0 | H27: 88712 | J27: Ticker | K27: Valores | L27: Ano | M27: VLF | N27: VLP | O27: Cresc | Q27: Ano | R27: Fluxo
A28: Lucro ou Prejuizo Acumulados | B28: 9953 | C28: =IFERROR(SUM((D28/B28)-1),0) -> 0.68793329 | D28: 16800 | E28: =IFERROR(SUM((F28/D28)-1),0) -> 0 | F28: 16800 | G28: =IFERROR(SUM((H28/F28)-1),0) -> 0 | H28: 16800 | J28: Preço_Mercado | K28: =K2 -> 77.84 | L28: 1 | M28: =K33 -> 40604000000 | O28: 4 | Q28: 0 | R28: =-K6 -> -413736214400
J29: Numero_Papel | K29: =L2 -> 4439160000 | L29: 2 | M29: =M28*(1+O28/100) -> 42228160000 | N29: =M29/(1+K34)^L28 -> 36529550173 | O29: 4 | Q29: 1 | R29: =M29 -> 42228160000
A30: DRE Analise Trimestral | J30: Market | K30: =K5 -> 345544214400 | L30: 3 | M30: =M29*(1+O29/100) -> 43917286400 | N30: =M30/(1+K34)^L29 -> 32863955173 | O30: 4 | Q30: 2 | R30: =M30 -> 43917286400
A31: Trimestre | B31: 1_T | C31: AH% (2/1) | D31: 2_T | E31: AH% (3/2) | F31: 3_T | G31: AH% (4/3) | H31: 4_T | J31: Taxa_Cresc | K31: =SUM(O28:O36)/6 -> 4 | L31: 4 | M31: =M30*(1+O30/100) -> 45673977856 | N31: =M31/(1+K34)^L30 -> 29566188045 | O31: 4 | Q31: 3 | R31: =M31 -> 45673977856
A32: Receita Liquida | B32: 48680 | C32: =IFERROR(SUM((D32/B32)-1),0) -> 0.088989318 | D32: 53012 | E32: =IFERROR(SUM((F32/D32)-1),0) -> 0.069588018 | F32: 56701 | G32: =IFERROR(SUM((H32/F32)-1),0) -> -0.026436924 | H32: =IFERROR(B91- SUM(B32,D32,F32),"") -> 55202 | J32: Taxa_Gordon | K32: 0.01 | L32: 5 | M32: =M31*(1+O31/100) -> 47500936970 | N32: =M32/(1+K34)^L31 -> 26599338725 | O32: 4 | Q32: 4 | R32: =M32 -> 47500936970
A33: Custo Mercadoria (CMV) | B33: -32423 | C33: =IFERROR(SUM((D33/B33)-1),0) -> 0.13601456 | D33: -36833 | E33: =IFERROR(SUM((F33/D33)-1),0) -> -0.020525073 | F33: -36077 | G33: =IFERROR(SUM((H33/F33)-1),0) -> -0.069933753 | H33: =IFERROR(B92- SUM(B33,D33,F33),"") -> -33554 | J33: Lucro_proforma | K33: =K23 -> 40604000000 | L33: 6 | M33: =M32*(1+O32/100) -> 49400974449 | N33: =M33/(1+K34)^L32 -> 23930200930 | O33: 4 | Q33: 5 | R33: =M33 -> 49400974449
A34: Lucro Bruto | B34: =B32+B33 -> 16257 | C34: =IFERROR(SUM((D34/B34)-1),0) -> -0.0047979332 | D34: =D32+D33 -> 16179 | E34: =IFERROR(SUM((F34/D34)-1),0) -> 0.27473886 | F34: =F32+F33 -> 20624 | G34: =IFERROR(SUM((H34/F34)-1),0) -> 0.049650892 | H34: =H32+H33 -> 21648 | J34: Taxa_desconto_KE | K34: =L25 -> 0.156 | L34: 7 | M34: =M33*(1+O33/100) -> 51377013427 | N34: =M34/(1+K34)^L33 -> 21528900490 | Q34: 6 | R34: =M34+M35 -> 406793339189
A35: DESPESAS E OUTRAS RECEITAS | J35: Valor_ação_Proj | K35: =K36/K29 -> 67.54718 | L35: Perpétuo | M35: =IFERROR( M34 * (1 + K32) / (K34 -K32 ), 0 ) -> 355416325762 | N35: =M35/(1+K34)^L34 -> 128834606195 | Q35: TIR | R35: =IFERROR(IRR(R28:R34),0) -> 0.093102519
A36: Com vendas e administrativas | B36: -800 | C36: =IFERROR(SUM((D36/B36)-1),0) -> 0.11 | D36: -888 | E36: =IFERROR(SUM((F36/D36)-1),0) -> -0.033783784 | F36: -858 | G36: =IFERROR(SUM((H36/F36)-1),0) -> 0.18881119 | H36: =IFERROR(B95- SUM(B36,D36,F36),"") -> -1020 | J36: Market_Proj | K36: =N36 -> 299852739731 | N36: =SUM(N28:N35) -> 299852739731
A37: Despesa Administrativa (%) | B37: =ABS(B36)/B32 -> 0.016433854 | C37: =IFERROR(SUM((D37/B37)-1),0) -> 0.019293745 | D37: =ABS(D36)/D32 -> 0.016750924 | E37: =IFERROR(SUM((F37/D37)-1),0) -> -0.096646372 | F37: =ABS(F36)/F32 -> 0.015132008 | G37: =IFERROR(SUM((H37/F37)-1),0) -> 0.22109313 | H37: =ABS(H36)/H32 -> 0.018477591
A38: Pesquisa e desenvolvimento | B38: -685 | C38: =IFERROR(SUM((D38/B38)-1),0) -> 0.36642336 | D38: -936 | E38: =IFERROR(SUM((F38/D38)-1),0) -> -0.12393162 | F38: -820 | G38: =IFERROR(SUM((H38/F38)-1),0) -> 0.71585366 | H38: =IFERROR(B97- SUM(B38,D38,F38),"") -> -1407
A39: Pré-operacionais e paradas de operação | B39: -258 | C39: =IFERROR(SUM((D39/B39)-1),0) -> 0.96899225 | D39: -508 | E39: =IFERROR(SUM((F39/D39)-1),0) -> -0.45866142 | F39: -275 | G39: =IFERROR(SUM((H39/F39)-1),0) -> 0.69454545 | H39: =IFERROR(B98- SUM(B39,D39,F39),"") -> -466
A40: Outras receitas (despesas) | B40: -1405 | C40: =IFERROR(SUM((D40/B40)-1),0) -> 1.2042705 | D40: -3097 | E40: =IFERROR(SUM((F40/D40)-1),0) -> -0.35550533 | F40: -1996 | G40: =IFERROR(SUM((H40/F40)-1),0) -> -0.49749499 | H40: =IFERROR(B99- SUM(B40,D40,F40),"") -> -1003
A41: Reversão (Perda) | B41: -628 | C41: =IFERROR(SUM((D41/B41)-1),0) -> -1.1369427 | D41: 86 | E41: =IFERROR(SUM((F41/D41)-1),0) -> -18.069767 | F41: -1468 | G41: =IFERROR(SUM((H41/F41)-1),0) -> 14.760899 | H41: =IFERROR(B100- SUM(B41,D41,F41),"") -> -23137
A42: Despesas/Receitas Operacionais | B42: =SUM(B36,B38,B41,B39,B40) -> -3776 | C42: =IFERROR(SUM((D42/B42)-1),0) -> 0.41498941 | D42: =SUM(D36,D38,D41,D39,D40) -> -5343 | E42: =IFERROR(SUM((F42/D42)-1),0) -> 0.013849897 | F42: =SUM(F36,F38,F41,F39,F40) -> -5417 | G42: =IFERROR(SUM((H42/F42)-1),0) -> 3.9904006 | H42: =SUM(H36,H38,H41,H39,H40) -> -27033
A44: Lucro Operacional (EBIT)(LAJIR) | B44: =SUM(B34,B42) -> 12481 | C44: =IFERROR(SUM((D44/B44)-1),0) -> -0.13180034 | D44: =SUM(D34,D42) -> 10836 | E44: =IFERROR(SUM((F44/D44)-1),0) -> 0.40337763 | F44: =SUM(F34,F42) -> 15207 | G44: =IFERROR(SUM((H44/F44)-1),0) -> -1.3541132 | H44: =SUM(H34,H42) -> -5385
A46: Receita Financeira | B46: 674 | C46: =IFERROR(SUM((D46/B46)-1),0) -> -0.089020772 | D46: 614 | E46: =IFERROR(SUM((F46/D46)-1),0) -> 0.32736156 | F46: 815 | G46: =IFERROR(SUM((H46/F46)-1),0) -> -0.14110429 | H46: =IFERROR(B105- SUM(B46,D46,F46),"") -> 700
A47: Despesa Financeira | B47: -2199 | C47: =IFERROR(SUM((D47/B47)-1),0) -> -0.062301046 | D47: -2062 | E47: =IFERROR(SUM((F47/D47)-1),0) -> 0.048496605 | F47: -2162 | G47: =IFERROR(SUM((H47/F47)-1),0) -> 0.27474561 | H47: =IFERROR(B106- SUM(B47,D47,F47),"") -> -2756
A48: Outros itens financeiros, líquido | B48: 1736 | C48: =IFERROR(SUM((D48/B48)-1),0) -> -1.5760369 | D48: -1000 | E48: =IFERROR(SUM((F48/D48)-1),0) -> -0.49 | F48: -510 | G48: =IFERROR(SUM((H48/F48)-1),0) -> -2.7137255 | H48: =IFERROR(B107- SUM(B48,D48,F48),"") -> 874
A49: Resultado de participações | B49: 187 | D49: 506 | F49: 877 | H49: =IFERROR(B108- SUM(B49,D49,F49),"") -> -2740
A50: Resultado Financeiro | B50: =B46+B47+B48+B49 -> 398 | C50: =IFERROR(SUM((D50/B50)-1),0) -> -5.879397 | D50: =D46+D47+D48+D49 -> -1942 | E50: =IFERROR(SUM((F50/D50)-1),0) -> -0.4953656 | F50: =F46+F47+F48+F49 -> -980 | G50: =IFERROR(SUM((H50/F50)-1),0) -> 3.0020408 | H50: =H46+H47+H48+H49 -> -3922
A51: Depreciação, amortização e exaustão | B51: 4435 | C51: =IFERROR(SUM((D51/B51)-1),0) -> 0.037880496 | D51: 4603 | E51: =IFERROR(SUM((F51/D51)-1),0) -> -0.10145557 | F51: 4136 | G51: =IFERROR(SUM((H51/F51)-1),0) -> 0.12403288 | H51: 4649
A52: LAJIDA (EBITDA) ajustado | B52: 20105 | C52: =IFERROR(SUM((D52/B52)-1),0) -> -0.079035066 | D52: 18516 | E52: =IFERROR(SUM((F52/D52)-1),0) -> 0.28348455 | F52: 23765 | G52: =IFERROR(SUM((H52/F52)-1),0) -> 0.043088576 | H52: 24789
A53: LAJIDA (EBITDA) proforma | B53: 20444 | C53: =IFERROR(SUM((D53/B53)-1),0) -> 0.0032772452 | D53: 20511 | E53: =IFERROR(SUM((F53/D53)-1),0) -> 0.16708108 | F53: 23938 | G53: =IFERROR(SUM((H53/F53)-1),0) -> 0.091277467 | H53: 26123
A54: Resultado antes do Imposto | B54: =B44+B50 -> 12879 | C54: =IFERROR(SUM((D54/B54)-1),0) -> -0.30941843 | D54: =D44+D50 -> 8894 | E54: =IFERROR(SUM((F54/D54)-1),0) -> 0.59961772 | F54: =F44+F50 -> 14227 | G54: =IFERROR(SUM((H54/F54)-1),0) -> -1.6541787 | H54: =H44+H50 -> -9307
A55: Impostos | B55: -2680 | C55: =IFERROR(SUM((D55/B55)-1),0) -> -0.30858209 | D55: -1853 | E55: =IFERROR(SUM((F55/D55)-1),0) -> -1.2396114 | F55: 444 | G55: =IFERROR(SUM((H55/F55)-1),0) -> -25.308559 | H55: =IFERROR(B114- SUM(B55,D55,F55),"") -> -10793
A56: Lucro Liquido | B56: =B54+B55 -> 10199 | C56: =IFERROR(SUM((D56/B56)-1),0) -> -0.3096382 | D56: =D54+D55 -> 7041 | E56: =IFERROR(SUM((F56/D56)-1),0) -> 1.0836529 | F56: =F54+F55 -> 14671 | G56: =IFERROR(SUM((H56/F56)-1),0) -> -2.3700498 | H56: =H54+H55 -> -20100
A57: Lucro líquido proforma (Acionista) | B57: 9953 | C57: =IFERROR(SUM((D57/B57)-1),0) -> -0.21390536 | D57: 7824 | E57: =IFERROR(SUM((F57/D57)-1),0) -> 0.90810327 | F57: 14929 | G57: =IFERROR(SUM((H57/F57)-1),0) -> -0.47096256 | H57: 7898
A59: DFC
A60: FCO – Fluxo Operacional | B60: 1_T | C60: AH% (2/1) | D60: 2_T | E60: AH% (3/2) | F60: 3_T | G60: AH% (4/3) | H60: 4_T
A61: Lucro Líquido | B61: 12881 | C61: =IFERROR(SUM((D61/B61)-1),0) -> 1.2408198 | D61: 28864 | E61: =IFERROR(SUM((F61/D61)-1),0) -> 0.75301414 | F61: 50599 | G61: =IFERROR(SUM((H61/F61)-1),0) -> 0.46807249 | H61: 74283
A62: FCO | B62: 9777 | C62: =IFERROR(SUM((D62/B62)-1),0) -> 1.2630664 | D62: 22126 | E62: =IFERROR(SUM((F62/D62)-1),0) -> 0.53755762 | F62: 34020 | G62: =IFERROR(SUM((H62/F62)-1),0) -> 0.43342152 | H62: 48765
A64: CAPEX
A65: Imobilizado e Intangível | B65: -6244 | C65: =IFERROR(SUM((D65/B65)-1),0) -> 1.0070468 | D65: -12532 | E65: =IFERROR(SUM((F65/D65)-1),0) -> 0.72031599 | F65: -21559 | G65: =IFERROR(SUM((H65/F65)-1),0) -> 0.54877313 | H65: -33390
A66: CAPEX | B66: =SUM(B65) -> -6244 | C66: =IFERROR(SUM((D66/B66)-1),0) -> 1.0070468 | D66: =SUM(D65) -> -12532 | E66: =IFERROR(SUM((F66/D66)-1),0) -> 0.72031599 | F66: =SUM(F65) -> -21559 | G66: =IFERROR(SUM((H66/F66)-1),0) -> 0.54877313 | H66: =SUM(H65) -> -33390
A67: Pagamentos relacionados ao rompimento | B67: -675 | C67: =IFERROR(SUM((D67/B67)-1),0) -> 5.3496296 | D67: -4286 | E67: =IFERROR(SUM((F67/D67)-1),0) -> 1.7475502 | F67: -11776 | G67: =IFERROR(SUM((H67/F67)-1),0) -> 0.080672554 | H67: -12726
A68: Recebimentos (pagamentos) | B68: 0 | C68: =IFERROR(SUM((D68/B68)-1),0) -> 0 | D68: 0 | E68: =IFERROR(SUM((F68/D68)-1),0) -> 0 | F68: 5332 | G68: =IFERROR(SUM((H68/F68)-1),0) -> -0.12340585 | H68: 4674
A69: Dividendos recebidos | B69: 146 | C69: =IFERROR(SUM((D69/B69)-1),0) -> 1.2191781 | D69: 324 | E69: =IFERROR(SUM((F70/D69)-1),0) -> 2.3611111 | F69: 766 | G69: =IFERROR(SUM((H69/F70)-1),0) -> 0.5785124 | H69: 1719
A70: Aplicações financeiras | B70: 306 | C70: =IFERROR(SUM((D70/B70)-1),0) -> 0.96732026 | D70: 602 | E70: =IFERROR(SUM((#REF!/D70)-1),0) -> 0 | F70: 1089 | G70: =IFERROR(SUM((H70/#REF!)-1),0) -> 0 | H70: 1865
A71: Outras atividades de investimentos | B71: -220 | C71: =IFERROR(SUM((D71/B71)-1),0) -> -0.95454545 | D71: -10 | E71: =IFERROR(SUM((F71/D71)-1),0) -> 3.8 | F71: -48 | G71: =IFERROR(SUM((H71/F71)-1),0) -> 11.604167 | H71: -605
A72: FCI – Investimentos | B72: =SUM(B66:B71) -> -6687 | C72: =IFERROR(SUM((D72/B72)-1),0) -> 1.378047 | D72: =SUM(D66:D71) -> -15902 | E72: =IFERROR(SUM((F72/D72)-1),0) -> 0.64733996 | F72: =SUM(F66:F71) -> -26196 | G72: =IFERROR(SUM((H72/F72)-1),0) -> 0.4682776 | H72: =SUM(H66:H71) -> -38463
A74: FCF – Financiamento
A75: Captações | B75: 5016 | C75: =IFERROR(SUM((D75/B75)-1),0) -> 0.16188198 | D75: 5828 | E75: =IFERROR(SUM((F75/D75)-1),0) -> 3.1628346 | F75: 24261 | G75: =IFERROR(SUM((H75/F75)-1),0) -> 0.093236058 | H75: 26523
A76: Pag de Emp e debêntures Principal | B76: -5864 | C76: =IFERROR(SUM((D76/B76)-1),0) -> 0.070770805 | D76: -6279 | E76: =IFERROR(SUM((F76/D76)-1),0) -> 0.30148113 | F76: -8172 | G76: =IFERROR(SUM((H76/F76)-1),0) -> 0.015540871 | H76: -8299
A77: Arrendamentos | B77: -186 | C77: =IFERROR(SUM((D77/B77)-1),0) -> 1.3817204 | D77: -443 | E77: =IFERROR(SUM((F77/D77)-1),0) -> 0.33182844 | F77: -590 | G77: =IFERROR(SUM((H77/F77)-1),0) -> 0.64576271 | H77: -971
A78: Dividendos e JCP | B78: -14465 | C78: =IFERROR(SUM((D78/B78)-1),0) -> 0 | D78: -14465 | E78: =IFERROR(SUM((F78/D78)-1),0) -> 0.34503975 | F78: -19456 | G78: =IFERROR(SUM((H78/F78)-1),0) -> 0.026469984 | H78: -19971
A79: Programa de recompra de ações | B79: -386 | C79: =IFERROR(SUM((D79/B79)-1),0) -> 1.8264249 | D79: -1091 | E79: =IFERROR(SUM((F79/D79)-1),0) -> -1 | F79: 0 | G79: =IFERROR(SUM((H79/F79)-1),0) -> 0 | H79: 0
A80: Emissão de títulos subordinados | B80: 0 | C80: =IFERROR(SUM((D80/B80)-1),0) -> 0 | D80: 0 | E80: =IFERROR(SUM((F80/D80)-1),0) -> 0 | F80: 0 | G80: =IFERROR(SUM((H80/F80)-1),0) -> 0 | H80: 3957
A81: FCF | B81: =SUM(B75:B80) -> -15885 | C81: =IFERROR(SUM((D81/B81)-1),0) -> 0.035568146 | D81: =SUM(D75:D80) -> -16450 | E81: =IFERROR(SUM((F81/D81)-1),0) -> -0.75945289 | F81: =SUM(F75:F80) -> -3957 | G81: =IFERROR(SUM((H81/F81)-1),0) -> -1.313116 | H81: =SUM(H75:H80) -> 1239
A83: Fechamento | B83: =SUM(B62,B72,B81) -> -12795 | C83: =IFERROR(SUM((D83/B83)-1),0) -> -0.20078156 | D83: =SUM(D62,D72,D81) -> -10226 | E83: =IFERROR(SUM((F83/D83)-1),0) -> -1.3781537 | F83: =SUM(F62,F72,F81) -> 3867 | G83: =IFERROR(SUM((H83/F83)-1),0) -> 1.9844841 | H83: =SUM(H62,H72,H81) -> 11541
A84: Caixa Inicial | B84: 40563 | C84: =IFERROR(SUM((D84/B84)-1),0) -> 0 | D84: 40563 | E84: =IFERROR(SUM((F84/D84)-1),0) -> -0.24386756 | F84: 30671 | G84: =IFERROR(SUM((H84/F84)-1),0) -> 0 | H84: 30671
A85: Variação Cambial | B85: -1228 | C85: =IFERROR(SUM((D85/B85)-1),0) -> 0.19381107 | D85: -1466 | E85: =IFERROR(SUM((F85/D85)-1),0) -> 0.69781719 | F85: -2489 | G85: =IFERROR(SUM((H85/F85)-1),0) -> -0.33748493 | H85: -1649
A86: Transferência dos Ativos de Energia | B86: 0 | C86: =IFERROR(SUM((D86/B86)-1),0) -> 0 | D86: 0 | E86: =IFERROR(SUM((F86/D86)-1),0) -> 0 | F86: -658 | G86: =IFERROR(SUM((H86/F86)-1),0) -> -1 | H86: 0
A87: Caixa e equivalentes de caixa | B87: 0 | C87: =IFERROR(SUM((D87/B87)-1),0) -> 0 | D87: 0 | E87: =IFERROR(SUM((F87/D87)-1),0) -> 0 | F87: 0 | G87: =IFERROR(SUM((H87/F87)-1),0) -> 0 | H87: 0
A88: Caixa Final | B88: =SUM(B83:B87) -> 26540 | C88: =IFERROR(SUM((D88/B88)-1),0) -> 0.087829691 | D88: =SUM(D83:D87) -> 28871 | E88: =IFERROR(SUM((F88/D88)-1),0) -> 0.087284819 | F88: =SUM(F83:F87) -> 31391 | G88: =IFERROR(SUM((H88/F88)-1),0) -> 0.29218566 | H88: =SUM(H83:H87) -> 40563
A90: DRE Final Anual
A91: Receita Liquida | B91: 213595
A92: Custo Mercadoria (CMV) | B92: -138887
A93: Lucro Bruto | B93: =B91+B92 -> 74708
A94: DESPESAS E OUTRAS RECEITAS
A95: Com vendas e administrativas | B95: -3566
A96: Despesa Administrativa (%) | B96: =ABS(B95)/B91 -> 0.016695147
A97: Pesquisa e desenvolvimento | B97: -3848
A98: Pré-operacionais e paradas de operação | B98: -1507
A99: Outras receitas (despesas) | B99: -7501
A100: Reversão (Perda) | B100: -25147
A101: Despesas/Receitas Operacionais | B101: =SUM(B95,B97,B100,B98,B99) -> -41569
A103: Lucro Operacional (EBIT)(LAJIR) | B103: =SUM(B93,B101) -> 33139
A105: Receita Financeira | B105: 2803
A106: Despesa Financeira | B106: -9179
A107: Outros itens financeiros, líquido | B107: 1100
A108: Resultado de participações | B108: -1170
A109: Resultado Financeiro | B109: =B105+B106+B107+B108 -> -6446
...

Sheet BBAS3
B1: Feito | C1: 46058 | D1: Atual | E1: 46246 | F1: Não | G1: 46058 | H1: Não | I1: 46058 | J1: Ultimo_Balanco | K1: {=IFERROR(INDEX('Indicadores_Ações'!$A$10:$L$23, MATCH($J$2, 'Indicadores_Ações'!$A$10:$A$23, 0), MATCH('Indicadores_Ações'!$B$9, 'Indicadores_Ações'!$A$9:$L$9, 0)),"")} -> 46203
A2: Balanço Patrimonial | C2: ▸ | J2: BBAS3 | K2: =IFERROR(__xludf.DUMMYFUNCTION("(GOOGLEFINANCE(""BVMF:"" & J2))"),22.43) -> 22.43 | L2: {=IFERROR(INDEX(Indicador_Ações[], MATCH($J$2, Indicador_Ações[Stock], 0), MATCH(Indicador_Ações[[#HEADERS],[qtd_acao]], Indicador_Ações[#HEADERS], 0)),"")} -> 5730830000 | M2: Numero_Papel
A3: Ano | B3: 1_T | C3: AH% (2/1) | D3: 2_T | E3: AH% (3/2) | F3: 3_T | G3: AH% (4/3) | H3: 4_T | J3: BP | K3: 1000 | L3: =K13/K4 -> 0.041485102 | M3: Margem financeira (NII / Ativo médio) | N3: RF | O3: ='Indicadores_Ações'!$B$3 -> 0.139
A4: Liquidez imediata | B4: =SUM(B5:B7) -> 440832926 | C4: =IFERROR(SUM((D4/B4)-1),0) -> -0.24117771 | D4: =SUM(D5:D7) -> 334513850 | E4: =IFERROR(SUM((F4/D4)-1),0) -> 0.49240963 | F4: =SUM(F5:F7) -> 499231692 | G4: =IFERROR(SUM((H4/F4)-1),0) -> -0.34051202 | H4: =SUM(H5:H7) -> 329237298 | J4: Ativo | K4: {=IFERROR(INDEX(Indicador_Ações[], MATCH($J$2, Indicador_Ações[Stock], 0), MATCH(Indicador_Ações[[#HEADERS],[ativo]], Indicador_Ações[#HEADERS], 0)),"")} -> 2541610000000 | L4: =K27/SUM(K15,K20) -> 0.042698635 | M4: MARGEM LÍQUIDA | N4: Beta (B) | O4: =K28 -> 1
A5: ▸Disponibilidades | B5: 23946939 | C5: =IFERROR(SUM((D5/B5)-1),0) -> 0.13012857 | D5: 27063120 | E5: =IFERROR(SUM((F5/D5)-1),0) -> -0.12306279 | F5: 23732657 | G5: =IFERROR(SUM((H5/F5)-1),0) -> -0.16832536 | H5: 19737849 | J5: Valor_de_mercado/Firma | K5: =K2*L2 -> 128542516900 | L5: =K21/SUM(K15,K20) -> 0.043890566 | M5: MARGEM OPERACIONAL | N5: RM | O5: =O3+0.02 -> 0.159
A6: ▸Depósitos no Banco Central | B6: 118584591 | C6: =IFERROR(SUM((D6/B6)-1),0) -> -0.0052045295 | D6: 117967414 | E6: =IFERROR(SUM((F6/D6)-1),0) -> 0.021793061 | F6: 120538285 | G6: =IFERROR(SUM((H6/F6)-1),0) -> -0.0043318353 | H6: 120016133 | J6: Patrimônio líq | K6: {=IFERROR(INDEX(Indicador_Ações[], MATCH($J$2, Indicador_Ações[Stock], 0), MATCH(Indicador_Ações[[#HEADERS],[patrimonio_liquido]], Indicador_Ações[#HEADERS], 0)),"")} -> 181333000000 | L6: =ABS(K24/SUM(K13,K20)) -> 0.35779104 | M6: Índice de eficiência | N6: KE | O6: =O3+O4*(O5-O3) -> 0.159
A7: ▸Aplicações interfinanceiras de liquidez | B7: 298301396 | C7: =IFERROR(SUM((D7/B7)-1),0) -> -0.36479239 | D7: 189483316 | E7: =IFERROR(SUM((F7/D7)-1),0) -> 0.87330873 | F7: 354960750 | G7: =IFERROR(SUM((H7/F7)-1),0) -> -0.46618516 | H7: 189483316 | J7: Capital de terceiros (equiv. Dívida bruta) | L7: =K27/L2 -> 2.5273128 | M7: LPA | N7: Excess Return
J8: Captação Total Media ≈ Dív bruta | K8: =SUM(SUM(B34,D34,F34,H34),SUM(B38,D38,F38,H38),SUM(B41,D41,F41,H41))/4*K3 -> 2246528605500 | L8: =K21/L2 -> 2.5978626 | M8: ROPA | N8: g | O8: =L12*(1-L10) -> 0.0628087
A9: Ativos financeiros | B9: =SUM(B10:B12) -> 740434709 | C9: =IFERROR(SUM((D9/B9)-1),0) -> 0.028820467 | D9: =SUM(D10:D12) -> 761774383 | E9: =IFERROR(SUM((F9/D9)-1),0) -> -0.023473911 | F9: =SUM(F10:F12) -> 743892559 | G9: =IFERROR(SUM((H9/F9)-1),0) -> -0.038126941 | H9: =SUM(H10:H12) -> 715530211 | J9: Qualidade da carteira (equiv. Dív líq) | L9: {=IFERROR(INDEX(L25*K3,0)/L2,"")} -> 0.31264703 | M9: DPA Liquido | N9: PL_Proj | O9: =K6*(1+O8) -> 192722289934
A10: ▸Títulos e valores mobiliários | B10: 660739749 | C10: =IFERROR(SUM((D10/B10)-1),0) -> 0.031633776 | D10: 681641442 | E10: =IFERROR(SUM((F10/D10)-1),0) -> -0.028320146 | F10: 662337257 | G10: =IFERROR(SUM((H10/F10)-1),0) -> -0.033691161 | H10: 640022346 | J10: Carteira Crédito Media ≈ Dív líq | K10: =SUM(B15,D15,F15,H15)/4*K3 -> 1231356943500 | L10: =L9/L7 -> 0.1237073 | M10: PAYOUT | N10: Roe_Proj | O10: 0.13
A11: ▸Derivativos | B11: 6360961 | C11: =IFERROR(SUM((D11/B11)-1),0) -> -0.054429669 | D11: 6014736 | E11: =IFERROR(SUM((F11/D11)-1),0) -> 0.60804265 | F11: 9671952 | G11: =IFERROR(SUM((H11/F11)-1),0) -> -0.5184546 | H11: 4657484 | J11: DRE | L11: =IFERROR(K15/K4,0) -> 0.11976352 | M11: GIRO ATIVOS | N11: Excesso_ano_n | O11: =O9*(O10-O6) -> -5588946408
A12: ▸Outros ativos financeiros | B12: 73333999 | C12: =IFERROR(SUM((D12/B12)-1),0) -> 0.010693621 | D12: 74118205 | E12: =IFERROR(SUM((F12/D12)-1),0) -> -0.030152579 | F12: 71883350 | G12: =IFERROR(SUM((H12/F12)-1),0) -> -0.014370073 | H12: 70850381 | J12: ── equiv. EBITDA ── | L12: =L4*L11*L19 -> 0.071675479 | M12: ROE_DuPont | N12: PV_Excesso_n | O12: =(O11/(1+O6)) -> -4822214330
J13: NII (Resultado Interm.) ≈ EBITDA | K13: =SUM(B85,D85,F85,H85)*K3 -> 105438951000 | L13: =IFERROR(K27/K4,0) -> 0.0056985926 | M13: ROA | N13: Perpetuidade do Excesso | O13: =O11/(O6-O8) -> -58102410381
A14: Carteira de crédito líquida | B14: =SUM(B15,B16) -> 1131255586 | C14: =IFERROR(SUM((D14/B14)-1),0) -> 0.0047679004 | D14: =SUM(D15,D16) -> 1136649300 | E14: =IFERROR(SUM((F14/D14)-1),0) -> -0.020401608 | F14: =SUM(F15,F16) -> 1113459826 | G14: =IFERROR(SUM((H14/F14)-1),0) -> 0.011367011 | H14: =SUM(H15,H16) -> 1126116536 | J14: ── equiv. Receita Líquida ── | L14: =IFERROR(ABS(SUM(B16,D16,F16,H16))/SUM(B15,D15,F15,H15),0) -> 0.084854868 | M14: Cobertura de crédito (BP) | N14: PV_Perpetuidade | O14: =O13/(1+O6) -> -50131501623
A15: ▸Carteira de crédito | B15: 1235304143 | C15: =IFERROR(SUM((D15/B15)-1),0) -> 0.008554639 | D15: 1245871724 | E15: =IFERROR(SUM((F15/D15)-1),0) -> -0.025305048 | F15: 1214344880 | G15: =IFERROR(SUM((H15/F15)-1),0) -> 0.012815261 | H15: 1229907027 | J15: Receita_Total ≈ Rec. Líq. | K15: =SUM(B64,D64,F64,H64)*K3 -> 304392156000 | L15: =IFERROR(ABS(SUM(B87,D87,F87,H87))/(SUM(B15,D15,F15,H15)/4),0) -> 0.0539142 | M15: Custo do crédito (PCLD / Carteira de crédito) | N15: VL | O15: =K6 + O12 + O14 -> 126379284047
A16: ▸(–) Perdas esperadas / PCLD | B16: -104048557 | C16: =IFERROR(SUM((D16/B16)-1),0) -> 0.049725505 | D16: -109222424 | E16: =IFERROR(SUM((F16/D16)-1),0) -> -0.076333867 | F16: -100885054 | G16: =IFERROR(SUM((H16/F16)-1),0) -> 0.028799479 | H16: -103790491 | J16: ── equiv. CMV ── | L16: =SUM(K10/4/K13) -> 2.9195969 | M16: Qualidade da carteira / NII | N16: P_Ação | O16: =O15/L2 -> 22.052527
J17: Custo_Captacao ≈ CMV | K17: =SUM(B74,D74,F74,H74)*K3 -> -198953205000 | L17: =K13/(K10/4) -> 0.34251304 | M17: Spread NII
A18: Ativos fiscais | B18: =SUM(B19,B20) -> 104127395 | C18: =IFERROR(SUM((D18/B18)-1),0) -> 0.061057477 | D18: =SUM(D19,D20) -> 110485151 | E18: =IFERROR(SUM((F18/D18)-1),0) -> -0.11822569 | F18: =SUM(F19,F20) -> 97422968 | G18: =IFERROR(SUM((H18/F18)-1),0) -> 0.037506946 | H18: =SUM(H19,H20) -> 101077006 | J18: ── equiv. Lucro Bruto ── | L18: =ABS(K23)/K13 -> 0.62963093 | M18: PCLD / NII
A19: ▸Créditos tributários correntes | B19: 11093424 | C19: =IFERROR(SUM((D19/B19)-1),0) -> 0.089975016 | D19: 12091555 | E19: =IFERROR(SUM((F19/D19)-1),0) -> 0.10460069 | F19: 13356340 | G19: =IFERROR(SUM((H19/F19)-1),0) -> -0.070968843 | H19: 12408456 | J19: NII_após_PCLD ≈ Lucro Bruto | K19: =SUM(B88,D88,F88,H88)*K3 -> 39051326000 | L19: =IFERROR(K4/K6,0) -> 14.016257 | M19: Alavancagem
A20: ▸Créditos tributários diferidos | B20: 93033971 | C20: =IFERROR(SUM((D20/B20)-1),0) -> 0.057609333 | D20: 98393596 | E20: =IFERROR(SUM((F20/D20)-1),0) -> -0.14560874 | F20: 84066628 | G20: =IFERROR(SUM((H20/F20)-1),0) -> 0.054741365 | H20: 88668550 | J20: Receitas de serviços | K20: =SUM(B90,D90,F90,H90)*K3 -> 34813063000 | L20: =SUM(K49,M49,O49,Q49)/4 -> 0.1452 | M20: Índice de Basileia
J21: Resultado operacional | K21: =SUM(B103,D103,F103,H103)*K3 -> 14887909000
A22: Investimentos | B22: =SUM(B23:B24) -> 20455483 | C22: =IFERROR(SUM((D22/B22)-1),0) -> -0.0025834638 | D22: =SUM(D23,D24) -> 20402637 | E22: =IFERROR(SUM((F22/D22)-1),0) -> -0.023730266 | F22: =SUM(F23,F24) -> 19918477 | G22: =IFERROR(SUM((H22/F22)-1),0) -> 0.030826704 | H22: =SUM(H23,H24) -> 20532498 | J22: ── equiv. Despesas Operacionais ── | M22: DMPL Acumulado
A23: ▸Participações controladas e coligadas | B23: 20311356 | C23: =IFERROR(SUM((D23/B23)-1),0) -> -0.0027586046 | D23: 20255325 | E23: =IFERROR(SUM((F23/D23)-1),0) -> -0.023632452 | F23: 19776642 | G23: =IFERROR(SUM((H23/F23)-1),0) -> 0.030948935 | H23: 20388708 | J23: PCLD ≈ principal desp. | K23: =SUM(B87,D87,F87,H87)*K3 -> -66387625000 | L23: 1791727 | M23: JCP acionistas Liquido
A24: ▸Outros investimentos | B24: 144127 | C24: =IFERROR(SUM((D24/B24)-1),0) -> 0.022098566 | D24: 147312 | E24: =IFERROR(SUM((F24/D24)-1),0) -> -0.037179592 | F24: 141835 | G24: =IFERROR(SUM((H24/F24)-1),0) -> 0.013783622 | H24: 143790 | J24: Despesas_Admin | K24: =SUM(B92,D92,F92,H92)*K3 -> -50180914000 | L24: 0 | M24: Dividendos
J25: Inflação | K25: ='Indicadores_Ações'!$B$4 -> 0.044430246 | L25: =SUM(L23:L24) -> 1791727 | M25: Dividendos e JCP
A26: Ativos operacionais não financeiros | B26: =SUM(B27:B28) -> 29802726 | C26: =IFERROR(SUM((D26/B26)-1),0) -> 0.023947977 | D26: =SUM(D27,D28) -> 30516441 | E26: =IFERROR(SUM((F26/D26)-1),0) -> -0.11035648 | F26: =SUM(F27,F28) -> 27148754 | G26: =IFERROR(SUM((H26/F26)-1),0) -> 0.088667679 | H26: =SUM(H27,H28) -> 29555971 | J26: Lucro_Ajustado | K26: =SUM(B110,D110,F110,H110)*1000000 -> 16866000000
A27: ▸Imobilizado | B27: 18073325 | C27: =IFERROR(SUM((D27/B27)-1),0) -> 0.010048345 | D27: 18254932 | E27: =IFERROR(SUM((F27/D27)-1),0) -> -0.16301156 | F27: 15279167 | G27: =IFERROR(SUM((H27/F27)-1),0) -> 0.14673948 | H27: 17521224 | J27: Lucro_Anual_Fundamentus | K27: {=IFERROR(INDEX(Indicador_Ações[], MATCH($J$2, Indicador_Ações[Stock], 0), MATCH(Indicador_Ações[[#HEADERS],[lucro_liquido_12m]], Indicador_Ações[#HEADERS], 0)),"")} -> 14483600000
A28: ▸Intangível | B28: 11729401 | C28: =IFERROR(SUM((D28/B28)-1),0) -> 0.045365317 | D28: 12261509 | E28: =IFERROR(SUM((F28/D28)-1),0) -> -0.031963603 | F28: 11869587 | G28: =IFERROR(SUM((H28/F28)-1),0) -> 0.013914553 | H28: 12034747 | J28: Beta | K28: {=IFERROR(INDEX(Indicador_Ações[], MATCH($J$2, Indicador_Ações[Stock], 0), MATCH(Indicador_Ações[[#HEADERS],[beta_ibov_3a]], Indicador_Ações[#HEADERS], 0)),"")} -> 1
J29: Balanço Patrimonial
A30: Outros ativos não financeiros | B30: 47962269 | C30: =IFERROR(SUM((D30/B30)-1),0) -> -0.19152028 | D30: 38776522 | E30: =IFERROR(SUM((F30/D30)-1),0) -> -0.029032129 | F30: 37650757 | G30: =IFERROR(SUM((H30/F30)-1),0) -> 0.057502111 | H30: 39815755 | J30: INDICADORES DE ESTRUTURA E ENDIVIDAMENTO
K31: 1_T | L31: AH% (A/B) | M31: 2_T | N31: AH% (A/B) | O31: 3_T | P31: AH% (A/B) | Q31: 4_T
A32: Ativo Total (analítico) | B32: =SUM(B4,B9,B14,B18,B22,B26) -> 2466908825 | C32: =IFERROR(SUM((D32/B32)-1),0) -> -0.029416192 | D32: =SUM(D4,D9,D14,D18,D22,D26) -> 2394341762 | E32: =IFERROR(SUM((F32/D32)-1),0) -> 0.044576975 | F32: =SUM(F4,F9,F14,F18,F22,F26) -> 2501074276 | G32: =IFERROR(SUM((H32/F32)-1),0) -> -0.071579144 | H32: =SUM(H4,H9,H14,H18,H22,H26) -> 2322049520 | J32: Alavancagem | K32: =IFERROR(B32/B61,0) -> 12.973892 | L32: =IFERROR(SUM((M32/K32)-1),0) -> -0.0020863468 | M32: =IFERROR(D32/D61,0) -> 12.946824 | N32: =IFERROR(SUM((O32/M32)-1),0) -> 0.055676642 | O32: =IFERROR(F32/F61,0) -> 13.66766 | P32: =IFERROR(SUM((Q32/O32)-1),0) -> -0.11140184 | Q32: =IFERROR(H32/H61,0) -> 12.145057
J33: Funding core | K33: =IFERROR(B34/B51,0) -> 0.74613352 | L33: =IFERROR(SUM((M33/K33)-1),0) -> 0.0070369299 | M33: =IFERROR(D34/D51,0) -> 0.75138401 | N33: =IFERROR(SUM((O33/M33)-1),0) -> -0.045707925 | O33: =IFERROR(F34/F51,0) -> 0.71703981 | P33: =IFERROR(SUM((Q33/O33)-1),0) -> 0.0033239593 | Q33: =IFERROR(H34/H51,0) -> 0.71942322
A34: Depósitos | B34: =SUM(B35:B36) -> 1798549866 | C34: =IFERROR(SUM((D34/B34)-1),0) -> 0.00048802372 | D34: =SUM(D35:D36) -> 1799427601 | E34: =IFERROR(SUM((F34/D34)-1),0) -> -0.062717656 | F34: =SUM(F35:F36) -> 1686571719 | G34: =IFERROR(SUM((H34/F34)-1),0) -> -0.036520844 | H34: =SUM(H35:H36) -> 1624976696 | J34: Dependência de mercado | K34: =IFERROR(SUM(B36,B38)/B51,0) -> 0.48432635 | L34: =IFERROR(SUM((M34/K34)-1),0) -> -0.015855437 | M34: =IFERROR(SUM(D36,D38)/D51,0) -> 0.47664715 | N34: =IFERROR(SUM((O34/M34)-1),0) -> 0.037463684 | O34: =IFERROR(SUM(F36,F38)/F51,0) -> 0.4945041 | P34: =IFERROR(SUM((Q34/O34)-1),0) -> -0.052259132 | Q34: =IFERROR(SUM(H36,H38)/H51,0) -> 0.46866175
A35: ▸Recursos de clientes | B35: 934977009 | C35: =IFERROR(SUM((D35/B35)-1),0) -> 0.020366092 | D35: 954018837 | E35: =IFERROR(SUM((F35/D35)-1),0) -> -0.06571906 | F35: 891321616 | G35: =IFERROR(SUM((H35/F35)-1),0) -> 0.0074224981 | H35: 897937449 | J35: Exposição a crédito | K35: =IFERROR(B14/B32,0) -> 0.45857211 | L35: =IFERROR(SUM((M35/K35)-1),0) -> 0.035220134 | M35: =IFERROR(D14/D32,0) -> 0.47472308 | N35: =IFERROR(SUM((O35/M35)-1),0) -> -0.062205644 | O35: =IFERROR(F14/F32,0) -> 0.44519263 | P35: =IFERROR(SUM((Q35/O35)-1),0) -> 0.089341116 | Q35: =IFERROR(H14/H32,0) -> 0.48496663
A36: ▸Recursos de instituições financeiras | B36: 863572857 | C36: =IFERROR(SUM((D36/B36)-1),0) -> -0.021033654 | D36: 845408764 | E36: =IFERROR(SUM((F36/D36)-1),0) -> -0.059330661 | F36: 795250103 | G36: =IFERROR(SUM((H36/F36)-1),0) -> -0.085772835 | H36: 727039247 | J36: Cobertura de crédito (BP) | K36: =IFERROR(ABS(B16)/B15,0) -> 0.084229101 | L36: =IFERROR(SUM((M36/K36)-1),0) -> 0.040821651 | M36: =IFERROR(ABS(D16)/D15,0) -> 0.087667472 | N36: =IFERROR(SUM((O36/M36)-1),0) -> -0.05235363 | O36: =IFERROR(ABS(F16)/F15,0) -> 0.083077761 | P36: =IFERROR(SUM((Q36/O36)-1),0) -> 0.015781968 | Q36: =IFERROR(ABS(H16)/H15,0) -> 0.084388892
J37: Ativos líquidos | K37: =IFERROR(B4/B32,0) -> 0.17869851 | L37: =IFERROR(SUM((M37/K37)-1),0) -> -0.21817953 | M37: =IFERROR(D4/D32,0) -> 0.13971015 | N37: =IFERROR(SUM((O37/M37)-1),0) -> 0.42872155 | O37: =IFERROR(F4/F32,0) -> 0.1996069 | P37: =IFERROR(SUM((Q37/O37)-1),0) -> -0.289667 | Q37: =IFERROR(H4/H32,0) -> 0.14178737
A38: Instrumentos de dívida | B38: =B39 -> 303892571 | C38: =IFERROR(SUM((D38/B38)-1),0) -> -0.025727513 | D38: =D39 -> 296074171 | E38: =IFERROR(SUM((F38/D38)-1),0) -> 0.24255498 | F38: =F39 -> 367888435 | G38: =IFERROR(SUM((H38/F38)-1),0) -> -0.098810703 | H38: =H39 -> 331537120 | J38: Índice de capital próprio | K38: =IFERROR(B61/B32,0) -> 0.077077874 | L38: =IFERROR(SUM((M38/K38)-1),0) -> 0.0020907088 | M38: =IFERROR(D61/D32,0) -> 0.077239021 | N38: =IFERROR(SUM((O38/M38)-1),0) -> -0.052740242 | O38: =IFERROR(F61/F32,0) -> 0.073165416 | P38: =IFERROR(SUM((Q38/O38)-1),0) -> 0.12536808 | Q38: =IFERROR(H61/H32,0) -> 0.082338024
A39: ▸Recursos de títulos|valores mobiliários | B39: 303892571 | C39: =IFERROR(SUM((D39/B39)-1),0) -> -0.025727513 | D39: 296074171 | E39: =IFERROR(SUM((F39/D39)-1),0) -> 0.24255498 | F39: 367888435 | G39: =IFERROR(SUM((H39/F39)-1),0) -> -0.098810703 | H39: 331537120 | J39: Visão integrada (importante)
A41: Passivos financeiros | B41: =SUM(B42:B43) -> 199898951 | C41: =IFERROR(SUM((D41/B41)-1),0) -> -0.044531669 | D41: =SUM(D42:D43) -> 190997117 | E41: =IFERROR(SUM((F41/D41)-1),0) -> -0.0094189589 | F41: =SUM(F42:F43) -> 189198123 | G41: =IFERROR(SUM((H41/F41)-1),0) -> 0.041775938 | H41: =SUM(H42:H43) -> 197102052 | J41: DRE Analise Trismestral
A42: ▸Derivativos passivos | B42: 6512590 | C42: =IFERROR(SUM((D42/B42)-1),0) -> -0.13792454 | D42: 5614344 | E42: =IFERROR(SUM((F42/D42)-1),0) -> 0.58425259 | F42: 8894539 | G42: =IFERROR(SUM((H42/F42)-1),0) -> -0.49691221 | H42: 4474734 | J42: EFICIÊNCIA
A43: ▸Outras obrigações financeiras | B43: 193386361 | C43: =IFERROR(SUM((D43/B43)-1),0) -> -0.041386517 | D43: 185382773 | E43: =IFERROR(SUM((F43/D43)-1),0) -> -0.027398387 | F43: 180303584 | G43: =IFERROR(SUM((H43/F43)-1),0) -> 0.068349911 | H43: 192627318 | J43: Crescimento do NII | K43: =IFERROR(B85/H85,"")-1 -> -0.13237936 | L43: =IFERROR(SUM((M43/K43)-1),0) -> -2.1392627 | M43: =IFERROR(D85/B85,"")-1 -> 0.15081486 | N43: =IFERROR(SUM((O43/M43)-1),0) -> -2.1946311 | O43: =IFERROR(F85/D85,"")-1 -> -0.18016813 | P43: =IFERROR(SUM((Q43/O43)-1),0) -> -2.2301315 | Q43: =IFERROR(H85/F85,"")-1 -> 0.2216305
J44: Participação de receitas de serviços | K44: =IFERROR(B90/(B64+B90),"") -> 0.10514993 | L44: =IFERROR(SUM((M44/K44)-1),0) -> -0.0551136 | M44: =IFERROR(D90/(D64+D90),"") -> 0.099354743 | N44: =IFERROR(SUM((O44/M44)-1),0) -> 0.1397213 | O44: =IFERROR(F90/(F64+F90),"") -> 0.11323672 | P44: =IFERROR(SUM((Q44/O44)-1),0) -> -0.1568925 | Q44: =IFERROR(H90/(H64+H90),"") -> 0.095470725
A45: Outras obrigações | B45: =SUM(B46:B49) -> 108151919 | C45: =IFERROR(SUM((D45/B45)-1),0) -> 0.0015414798 | D45: =SUM(D46:D49) -> 108318633 | E45: =IFERROR(SUM((F45/D45)-1),0) -> 0.0014245564 | F45: =SUM(F46:F49) -> 108472939 | G45: =IFERROR(SUM((H45/F45)-1),0) -> -0.03104283 | H45: =SUM(H46:H49) -> 105105632 | J45: Índice de eficiência | K45: =IFERROR(ABS(B92)/(B85+B90),"") -> 0.38155817 | L45: =IFERROR(SUM((M45/K45)-1),0) -> -0.10396923 | M45: =IFERROR(ABS(D92)/(D85+D90),"") -> 0.34188786 | N45: =IFERROR(SUM((O45/M45)-1),0) -> 0.091356276 | O45: =IFERROR(ABS(F92)/(F85+F90),"") -> 0.37312146 | P45: =IFERROR(SUM((Q45/O45)-1),0) -> -0.089927098 | Q45: =IFERROR(ABS(H92)/(H85+H90),"") -> 0.33956773
A46: ▸Outras obrigações | B46: 50426054 | C46: =IFERROR(SUM((D46/B46)-1),0) -> 0.04262489 | D46: 52575459 | E46: =IFERROR(SUM((F46/D46)-1),0) -> 0.023772232 | F46: 53825295 | G46: =IFERROR(SUM((H46/F46)-1),0) -> -0.1318753 | H46: 46727068 | J46: Crescimento das despesas adm | K46: =IFERROR(ABS(B92/H92)-1,0) -> 0.0096000817 | L46: =IFERROR(SUM((M46/K46)-1),0) -> -0.60078701 | M46: =IFERROR(ABS(D92/B92)-1,"") -> 0.0038324773 | N46: =IFERROR(SUM((O46/M46)-1),0) -> -24.307261 | O46: =IFERROR(ABS(F92/D92)-1,"") -> -0.08932455 | P46: =IFERROR(SUM((Q46/O46)-1),0) -> -1.934705 | Q46: =IFERROR(ABS(H92/F92)-1,"") -> 0.083492106
A47: ▸Provisões | B47: 37647460 | C47: =IFERROR(SUM((D47/B47)-1),0) -> 0.033581841 | D47: 38911731 | E47: =IFERROR(SUM((F47/D47)-1),0) -> -0.092668327 | F47: 35305846 | G47: =IFERROR(SUM((H47/F47)-1),0) -> 0.053614492 | H47: 37198751 | J47: Impacto das provisões operacionais | K47: =IFERROR(ABS(B101)/B64,"") -> 0.035059946 | L47: =IFERROR(SUM((M47/K47)-1),0) -> -0.013063008 | M47: =IFERROR(ABS(D101)/D64,"") -> 0.034601958 | N47: =IFERROR(SUM((O47/M47)-1),0) -> 0.60969214 | O47: =IFERROR(ABS(F101)/F64,"") -> 0.055698499 | P47: =IFERROR(SUM((Q47/O47)-1),0) -> -0.253338 | Q47: =IFERROR(ABS(H101)/H64,"") -> 0.041587953
A48: ▸Passivos fiscais correntes | B48: 4216882 | C48: =IFERROR(SUM((D48/B48)-1),0) -> 0.1910293 | D48: 5022430 | E48: =IFERROR(SUM((F48/D48)-1),0) -> 0.35722449 | F48: 6816565 | G48: =IFERROR(SUM((H48/F48)-1),0) -> -0.057383154 | H48: 6425409 | J48: SOLIDEZ
A49: ▸Passivos fiscais diferidos | B49: 15861523 | C49: =IFERROR(SUM((D49/B49)-1),0) -> -0.25549312 | D49: 11809013 | E49: =IFERROR(SUM((F49/D49)-1),0) -> 0.060650285 | F49: 12525233 | G49: =IFERROR(SUM((H49/F49)-1),0) -> 0.17797441 | H49: 14754404 | J49: Índice de Basileia | K49: 0.1423 | L49: =IFERROR(SUM((M49/K49)-1),0) -> -0.022487702 | M49: 0.1391 | N49: =IFERROR(SUM((O49/M49)-1),0) -> 0.064701653 | O49: 0.1481 | P49: =IFERROR(SUM((Q49/O49)-1),0) -> 0.021607022 | Q49: 0.1513
A51: Passivo Total | B51: =SUM(B34,B38,B41,B45) -> 2410493307 | C51: =IFERROR(SUM((D51/B51)-1),0) -> -0.006503144 | D51: =SUM(D34,D38,D41,D45) -> 2394817522 | E51: =IFERROR(SUM((F51/D51)-1),0) -> -0.01782445 | F51: =SUM(F34,F38,F41,F45) -> 2352131216 | G51: =IFERROR(SUM((H51/F51)-1),0) -> -0.0397128 | H51: =SUM(H34,H38,H41,H45) -> 2258721500
A53: ▸Capital | B53: 120000000 | C53: =IFERROR(SUM((D53/B53)-1),0) -> 0 | D53: 120000000 | E53: =IFERROR(SUM((F53/D53)-1),0) -> 0 | F53: 120000000 | G53: =IFERROR(SUM((H53/F53)-1),0) -> 0 | H53: 120000000 | J53: Ticker | K53: Valores | L53: Ano | M53: VLF | N53: VLP | O53: Cresc
A54: ▸Instrumento elegível ao capital principal | B54: 4100000 | C54: =IFERROR(SUM((D54/B54)-1),0) -> 0 | D54: 4100000 | E54: =IFERROR(SUM((F54/D54)-1),0) -> 0.24390244 | F54: 5100000 | G54: =IFERROR(SUM((H54/F54)-1),0) -> -0.19607843 | H54: 4100000 | J54: Preço_Mercado | K54: =K2 -> 22.43 | L54: 1 | M54: =K59 -> 16866000000 | O54: 0
A55: Capital social | B55: =SUM(B53:B54) -> 124100000 | C55: =IFERROR(SUM((D55/B55)-1),0) -> 0 | D55: =SUM(D53:D54) -> 124100000 | E55: =IFERROR(SUM((F55/D55)-1),0) -> 0.0080580177 | F55: =SUM(F53:F54) -> 125100000 | G55: =IFERROR(SUM((H55/F55)-1),0) -> -0.0079936051 | H55: =SUM(H53:H54) -> 124100000 | J55: Numero_Papel | K55: =L2 -> 5730830000 | L55: 2 | M55: =M54*(1+O54/100) -> 16866000000 | N55: =M55/(1+K60)^L54 -> 14552200173 | O55: 6
A56: ▸Reserva de Capital | B56: 1417307 | C56: =IFERROR(SUM((D56/B56)-1),0) -> 0.0065920792 | D56: 1426650 | E56: =IFERROR(SUM((F56/D56)-1),0) -> -0.0067185364 | F56: 1417065 | G56: =IFERROR(SUM((H56/F56)-1),0) -> 0.00017077551 | H56: 1417307 | J56: Market | K56: =K54*K55 -> 128542516900 | L56: 3 | M56: =M55*(1+O55/100) -> 17877960000 | N56: =M56/(1+K60)^L55 -> 13309173583 | O56: 6
A57: ▸Reserva de Lucro | B57: 81486681 | C57: =IFERROR(SUM((D57/B57)-1),0) -> 0.064833405 | D57: 86769740 | E57: =IFERROR(SUM((F57/D57)-1),0) -> -0.12616893 | F57: 75822095 | G57: =IFERROR(SUM((H57/F57)-1),0) -> 0.085454273 | H57: 82301417 | J57: Taxa_Cresc | K57: =SUM(O54:O62)/6 -> 5 | L57: 4 | M57: =M56*(1+O56/100) -> 18950637600 | N57: =M57/(1+K60)^L56 -> 12172324416 | O57: 6
A58: ▸Outros resultados abrangentes | B58: -19894936 | C58: =IFERROR(SUM((D58/B58)-1),0) -> 0.37521307 | D58: -27359776 | E58: =IFERROR(SUM((F58/D58)-1),0) -> -0.18201885 | F58: -22379781 | G58: =IFERROR(SUM((H58/F58)-1),0) -> -0.12159476 | H58: -19658517 | J58: Taxa_Gordon | K58: 0.04 | L58: 5 | M58: =M57*(1+O57/100) -> 20087675856 | N58: =M58/(1+K60)^L57 -> 11132583159 | O58: 6
A59: ▸Lucro ou Prejuizo Acumulados | B59: 3035035 | C59: =IFERROR(SUM((D59/B59)-1),0) -> -1 | D59: 0 | E59: =IFERROR(SUM((F59/D59)-1),0) -> 0 | F59: 3032762 | G59: =IFERROR(SUM((H59/F59)-1),0) -> 0 | H59: 3032762 | J59: Lucro_Ajustado_Planilha | K59: =K26 -> 16866000000 | L59: 6 | M59: =M58*(1+O58/100) -> 21292936407 | N59: =M59/(1+K60)^L58 -> 10181655003 | O59: 6
J60: Taxa_desconto_KE | K60: =O6 -> 0.159 | L60: 7 | M60: =M59*(1+O59/100) -> 22570512592 | N60: =M60/(1+K60)^L59 -> 9311953670
A61: Patrimônio líq. | B61: =SUM(B55:B59) -> 190144087 | C61: =IFERROR(SUM((D61/B61)-1),0) -> -0.027386984 | D61: =SUM(D55:D59) -> 184936614 | E61: =IFERROR(SUM((F61/D61)-1),0) -> -0.010514267 | F61: =SUM(F55:F59) -> 182992141 | G61: =IFERROR(SUM((H61/F61)-1),0) -> 0.044815192 | H61: =SUM(H55:H59) -> 191192969 | J61: Valor_ação_Proj | K61: =K62/K55 -> 24.582326 | L61: Perpétuo | M61: =IFERROR( M60 * (1 + K58) / (K60 -K58 ), 0 ) -> 197254899962 | N61: =M61/(1+K60)^L60 -> 70217238972
J62: Market_Proj | K62: =N62 -> 140877128975 | N62: =SUM(N54:N61) -> 140877128975
A63: DRE Analise Trismestral | B63: 1_T | C63: AH% (2/1) | D63: 2_T | E63: AH% (3/2) | F63: 3_T | G63: AH% (4/3) | H63: 4_T
A64: Receita de intermediação financeira | B64: =B113 -> 75071108 | C64: =IFERROR(SUM((D64/B64)-1),0) -> 0.10188326 | D64: =SUM(D113-B113) -> 82719597 | E64: =IFERROR(SUM((F64/D64)-1),0) -> -0.23961402 | F64: =SUM(F113-D113) -> 62898822 | G64: =IFERROR(SUM((H64/F64)-1),0) -> 0.33075034 | H64: =SUM(H113-F113) -> 83702629
A65: Receitas de juros | B65: =SUM(B66:B68) -> 51675974 | C65: =IFERROR(SUM((D65/B65)-1),0) -> 0.12772837 | D65: =SUM(D66:D68) -> 58276462 | E65: =IFERROR(SUM((F65/D65)-1),0) -> -0.12911276 | F65: =SUM(F66:F68) -> 50752227 | G65: =IFERROR(SUM((H65/F65)-1),0) -> 0.29559609 | H65: =SUM(H66:H68) -> 65754387 | J65: Ano | K65: Fluxo
A66: ▸Carteira de crédito | B66: =B115 -> 43000221 | C66: =IFERROR(SUM((D66/B66)-1),0) -> 0.11235254 | D66: =SUM(D115-B115) -> 47831405 | E66: =IFERROR(SUM((F66/D66)-1),0) -> -0.29295755 | F66: =SUM(F115-D115) -> 33818834 | G66: =IFERROR(SUM((H66/F66)-1),0) -> 0.54304273 | H66: =SUM(H115-F115) -> 52183906 | J66: 0 | K66: =-K5 -> -128542516900
A67: ▸Aplicações interfinanceiras | B67: =B116 -> 6052171 | C67: =IFERROR(SUM((D67/B67)-1),0) -> 0.23775369 | D67: =SUM(D116-B116) -> 7491097 | E67: =IFERROR(SUM((F67/D67)-1),0) -> 1.0304349 | F67: =SUM(F116-D116) -> 15210185 | G67: =IFERROR(SUM((H67/F67)-1),0) -> -0.2846183 | H67: =SUM(H116-F116) -> 10881088 | J67: 1 | K67: =M55 -> 16866000000
A68: ▸Aplicações compulsórias | B68: =B117 -> 2623582 | C68: =IFERROR(SUM((D68/B68)-1),0) -> 0.12592631 | D68: =SUM(D117-B117) -> 2953960 | E68: =IFERROR(SUM((F68/D68)-1),0) -> -0.41664478 | F68: =SUM(F117-D117) -> 1723208 | G68: =IFERROR(SUM((H68/F68)-1),0) -> 0.56068971 | H68: =SUM(H117-F117) -> 2689393 | J68: 2 | K68: =M56 -> 17877960000
B69: =B118 | J69: 3 | K69: =M57 -> 18950637600
A70: Receitas com títulos | B70: =SUM(B71:B72) -> 24415634 | C70: =IFERROR(SUM((D70/B70)-1),0) -> 0.015446988 | D70: =SUM(D71:D72) -> 24792782 | E70: =IFERROR(SUM((F70/D70)-1),0) -> -0.4225448 | F70: =SUM(F71:F72) -> 14316721 | G70: =IFERROR(SUM((H70/F70)-1),0) -> 0.22305073 | H70: =SUM(H71:H72) -> 17510076 | J70: 4 | K70: =M58 -> 20087675856
A71: ▸Títulos e valores mobiliários | B71: =B120 -> 24251112 | C71: =IFERROR(SUM((D71/B71)-1),0) -> 0.012541074 | D71: =SUM(D120-B120) -> 24555247 | E71: =IFERROR(SUM((F71/D71)-1),0) -> -0.7039772 | F71: =SUM(F120-D120) -> 7268913 | G71: =IFERROR(SUM((H71/F71)-1),0) -> 2.3454372 | H71: =SUM(H120-F120) -> 24317692 | J71: 5 | K71: =M59 -> 21292936407
A72: ▸Outros ativos financeiros (parte de títulos) | B72: =B121 -> 164522 | C72: =IFERROR(SUM((D72/B72)-1),0) -> 0.44378867 | D72: =SUM(D121-B121) -> 237535 | E72: =IFERROR(SUM((F72/D72)-1),0) -> 28.670609 | F72: =SUM(F121-D121) -> 7047808 | G72: =IFERROR(SUM((H72/F72)-1),0) -> -1.9659196 | H72: =SUM(H121-F121) -> -6807616 | J72: 6 | K72: =M60+M61 -> 219825412554
B73: =B122 | J73: TIR | K73: =IFERROR(IRR(K66:K72),0) -> 0.2015351
A74: Custo de captação | B74: =B123 -> -50243641 | C74: =IFERROR(SUM((D74/B74)-1),0) -> 0.077704122 | D74: =SUM(D123-B123) -> -54147779 | E74: =IFERROR(SUM((F74/D74)-1),0) -> -0.27098146 | F74: =SUM(F123-D123) -> -39474735 | G74: =IFERROR(SUM((H74/F74)-1),0) -> 0.39550145 | H74: =SUM(H123-F123) -> -55087050
A75: ▸ Juros pagos sobre depósitos | B75: =SUM(B76) -> -18987416 | C75: =IFERROR(SUM((D75/B75)-1),0) -> 0.024724217 | D75: =SUM(D76) -> -19456865 | E75: =IFERROR(SUM((F75/D75)-1),0) -> -0.14657089 | F75: =SUM(F76) -> -16605055 | G75: =IFERROR(SUM((H75/F75)-1),0) -> 0.17007044 | H75: =SUM(H76) -> -19429084
A76: ↳ Recursos de clientes | B76: =B125 -> -18987416 | C76: =IFERROR(SUM((D76/B76)-1),0) -> 0.024724217 | D76: =SUM(D125-B125) -> -19456865 | E76: =IFERROR(SUM((F76/D76)-1),0) -> -0.14657089 | F76: =SUM(F125-D125) -> -16605055 | G76: =IFERROR(SUM((H76/F76)-1),0) -> 0.17007044 | H76: =SUM(H125-F125) -> -19429084
B77: =B126
A78: Captação no mercado | B78: =SUM(B79:B80) -> -21802649 | C78: =IFERROR(SUM((D78/B78)-1),0) -> 0.18732756 | D78: =SUM(D79:D80) -> -25886886 | E78: =IFERROR(SUM((F78/D78)-1),0) -> -0.59400416 | F78: =SUM(F79:F80) -> -10509968 | G78: =IFERROR(SUM((H78/F78)-1),0) -> 1.3638733 | H78: =SUM(H79:H80) -> -24844233
A79: ↳ Recursos de instituições financeiras | B79: =B128 -> -23372314 | C79: =IFERROR(SUM((D79/B79)-1),0) -> 0.091571292 | D79: =SUM(D128-B128) -> -25512547 | E79: =IFERROR(SUM((F79/D79)-1),0) -> -0.73313488 | F79: =SUM(F128-D128) -> -6808409 | G79: =IFERROR(SUM((H79/F79)-1),0) -> 3.0796555 | H79: =SUM(H128-F128) -> -27775963
A80: ↳ Outras despesas de captação | B80: =B129 -> 1569665 | C80: =IFERROR(SUM((D80/B80)-1),0) -> -1.2384834 | D80: =SUM(D129-B129) -> -374339 | E80: =IFERROR(SUM((F80/D80)-1),0) -> 8.8882537 | F80: =SUM(F129-D129) -> -3701559 | G80: =IFERROR(SUM((H80/F80)-1),0) -> -1.7920257 | H80: =SUM(H129-F129) -> 2931730
B81: =B130
A82: Instrumentos de dívida | B82: =SUM(B83) -> -9453576 | C82: =IFERROR(SUM((D82/B82)-1),0) -> -0.068709238 | D82: =SUM(D83) -> -8804028 | E82: =IFERROR(SUM((F82/D82)-1),0) -> 0.40387014 | F82: =SUM(F83) -> -12359712 | G82: =IFERROR(SUM((H82/F82)-1),0) -> -0.12508212 | H82: =SUM(H83) -> -10813733
A83: ↳ Emissões de títulos e valores mobiliários | B83: =B132 -> -9453576 | C83: =IFERROR(SUM((D83/B83)-1),0) -> -0.068709238 | D83: =SUM(D132-B132) -> -8804028 | E83: =IFERROR(SUM((F83/D83)-1),0) -> 0.40387014 | F83: =SUM(F132-D132) -> -12359712 | G83: =IFERROR(SUM((H83/F83)-1),0) -> -0.12508212 | H83: =SUM(H132-F132) -> -10813733
B84: =B133
A85: Resultado da intermediação financeira (NII) | B85: =SUM(B64,B74) -> 24827467 | C85: =IFERROR(SUM((D85/B85)-1),0) -> 0.15081486 | D85: =SUM(D64,D74) -> 28571818 | E85: =IFERROR(SUM((F85/D85)-1),0) -> -0.18016813 | F85: =SUM(F64,F74) -> 23424087 | G85: =IFERROR(SUM((H85/F85)-1),0) -> 0.2216305 | H85: =SUM(H64,H74) -> 28615579
B86: =B135
A87: Perdas de crédito esperadas (PCLD) | B87: =B136 -> -16843154 | C87: =IFERROR(SUM((D87/B87)-1),0) -> 0.13219383 | D87: =SUM(D136-B136) -> -19069715 | E87: =IFERROR(SUM((F87/D87)-1),0) -> -0.41182461 | F87: =SUM(F136-D136) -> -11216337 | G87: =IFERROR(SUM((H87/F87)-1),0) -> 0.71699718 | H87: =SUM(H136-F136) -> -19258419
A88: Resultado financeiro após crédito | B88: =SUM(B85,B87) -> 7984313 | C88: =IFERROR(SUM((D88/B88)-1),0) -> 0.19009651 | D88: =SUM(D85,D87) -> 9502103 | E88: =IFERROR(SUM((F88/D88)-1),0) -> 0.28474191 | F88: =SUM(F85,F87) -> 12207750 | G88: =IFERROR(SUM((H88/F88)-1),0) -> -0.23350658 | H88: =SUM(H85,H87) -> 9357160
B89: =B138
A90: Receitas de serviços | B90: =B139 -> 8821279 | C90: =IFERROR(SUM((D90/B90)-1),0) -> 0.034455208 | D90: =SUM(D139-B139) -> 9125218 | E90: =IFERROR(SUM((F90/D90)-1),0) -> -0.11980514 | F90: =SUM(F139-D139) -> 8031970 | G90: =IFERROR(SUM((H90/F90)-1),0) -> 0.099928909 | H90: =SUM(H139-F139) -> 8834596
B91: =B140
A92: Despesas administrativas | B92: =SUM(B93:B95) -> -12838954 | C92: =IFERROR(SUM((D92/B92)-1),0) -> 0.0038324773 | D92: =SUM(D93:D95) -> -12888159 | E92: =IFERROR(SUM((F92/D92)-1),0) -> -0.08932455 | F92: =SUM(F93:F95) -> -11736930 | G92: =IFERROR(SUM((H92/F92)-1),0) -> 0.083492106 | H92: =SUM(H93:H95) -> -12716871
A93: ▸ Despesas de pessoal | B93: =B142 -> -6781843 | C93: =IFERROR(SUM((D93/B93)-1),0) -> -0.00014170189 | D93: =SUM(D142-B142) -> -6780882 | E93: =IFERROR(SUM((F93/D93)-1),0) -> -0.085018291 | F93: =SUM(F142-D142) -> -6204383 | G93: =IFERROR(SUM((H93/F93)-1),0) -> 0.04274446 | H93: =SUM(H142-F142) -> -6469586
A94: ▸ Outras despesas administrativas | B94: =B143 -> -3726189 | C94: =IFERROR(SUM((D94/B94)-1),0) -> 0.016181681 | D94: =SUM(D143-B143) -> -3786485 | E94: =IFERROR(SUM((F94/D94)-1),0) -> -0.060990338 | F94: =SUM(F143-D143) -> -3555546 | G94: =IFERROR(SUM((H94/F94)-1),0) -> 0.099233985 | H94: =SUM(H143-F143) -> -3908377
A95: ▸ Despesas tributárias | B95: =B144 -> -2330922 | C95: =IFERROR(SUM((D95/B95)-1),0) -> -0.0043459198 | D95: =SUM(D144-B144) -> -2320792 | E95: =IFERROR(SUM((F95/D95)-1),0) -> -0.14813521 | F95: =SUM(F144-D144) -> -1977001 | G95: =IFERROR(SUM((H95/F95)-1),0) -> 0.18305858 | H95: =SUM(H144-F144) -> -2338908
B96: =B145
A97: Outras receitas/despesas operacionais | B97: =SUM(B98:B99) -> 657836 | C97: =IFERROR(SUM((D97/B97)-1),0) -> -1.1289835 | D97: =SUM(D98:D99) -> -84850 | E97: =IFERROR(SUM((F97/D97)-1),0) -> -24.968509 | F97: =SUM(F98:F99) -> 2033728 | G97: =IFERROR(SUM((H97/F97)-1),0) -> -0.47074535 | H97: =SUM(H98:H99) -> 1076360
A98: ▸ Resultado de participações | B98: =B147 -> 1793243 | C98: =IFERROR(SUM((D98/B98)-1),0) -> 0.16280058 | D98: =SUM(D147-B147) -> 2085184 | E98: =IFERROR(SUM((F98/D98)-1),0) -> -0.044090593 | F98: =SUM(F147-D147) -> 1993247 | G98: =IFERROR(SUM((H98/F98)-1),0) -> 0.22662018 | H98: =SUM(H147-F147) -> 2444957
A99: ▸ Outras receitas/despesas | B99: =B148 -> -1135407 | C99: =IFERROR(SUM((D99/B99)-1),0) -> 0.91123888 | D99: =SUM(D148-B148) -> -2170034 | E99: =IFERROR(SUM((F99/D99)-1),0) -> -1.0186545 | F99: =SUM(F148-D148) -> 40481 | G99: =IFERROR(SUM((H99/F99)-1),0) -> -34.808379 | H99: =SUM(H148-F148) -> -1368597
B100: =B149
A101: Provisões operacionais | B101: =B150 -> -2631989 | C101: =IFERROR(SUM((D101/B101)-1),0) -> 0.087489347 | D101: =SUM(D150-B150) -> -2862260 | E101: =IFERROR(SUM((F101/D101)-1),0) -> 0.22398734 | F101: =SUM(F150-D150) -> -3503370 | G101: =IFERROR(SUM((H101/F101)-1),0) -> -0.0063792862 | H101: =SUM(H150-F150) -> -3481021
B102: =B151
A103: Resultado operacional | B103: =SUM(B88,B90,B92,B97,B101) -> 1992485 | C103: =IFERROR(SUM((D103/B103)-1),0) -> 0.40129135 | D103: =SUM(D88,D90,D92,D97,D101) -> 2792052 | E103: =IFERROR(SUM((F103/D103)-1),0) -> 1.5189889 | F103: =SUM(F88,F90,F92,F97,F101) -> 7033148 | G103: =IFERROR(SUM((H103/F103)-1),0) -> -0.56346376 | H103: =SUM(H88,H90,H92,H97,H101) -> 3070224
...

Sheet ITUB3
B1: Feito | C1: 46058 | D1: Atual | E1: 46238 | F1: Não | G1: 46058 | H1: Não | I1: 46058 | J1: Ultimo_Balanco | K1: {=IFERROR(INDEX('Indicadores_Ações'!$A$10:$L$23, MATCH($J$2, 'Indicadores_Ações'!$A$10:$A$23, 0), MATCH('Indicadores_Ações'!$B$9, 'Indicadores_Ações'!$A$9:$L$9, 0)),"")} -> 46203
A2: Balanço Patrimonial | C2: ▸ | J2: ITUB3 | K2: =IFERROR(__xludf.DUMMYFUNCTION("(GOOGLEFINANCE(""BVMF:"" & J2))"),45.86) -> 45.86 | L2: {=IFERROR(INDEX(Indicador_Ações[], MATCH($J$2, Indicador_Ações[Stock], 0), MATCH(Indicador_Ações[[#HEADERS],[qtd_acao]], Indicador_Ações[#HEADERS], 0)),"")} -> 11026900000 | M2: Numero_Papel
A3: Ano | B3: 1_T | C3: AH% (2/1) | D3: 2_T | E3: AH% (3/2) | F3: 3_T | G3: AH% (4/3) | H3: 4_T | J3: BP | K3: 1000000 | L3: =K13/K4 -> 0.043900992 | M3: Margem financeira (NII / Ativo médio) | N3: RF | O3: ='Indicadores_Ações'!$B$3 -> 0.139
A4: Liquidez imediata | B4: =SUM(B5:B6) -> 396857 | C4: =IFERROR(SUM((D4/B4)-1),0) -> -0.12336686 | D4: =SUM(D5:D6) -> 347898 | E4: =IFERROR(SUM((F4/D4)-1),0) -> 0.061147233 | F4: =SUM(F5:F6) -> 369171 | G4: =IFERROR(SUM((H4/F4)-1),0) -> 0.022648041 | H4: =SUM(H5:H6) -> 377532 | J4: Ativo | K4: =SUM(B26,D26,F26,H26)/4*K3 -> 2932097750000 | L4: =K25/SUM(K13,K18) -> 0.24671578 | M4: MARGEM LÍQUIDA | N4: Beta (B) | O4: =K26 -> 1
A5: ▸Disponibilidades | B5: 39723 | C5: =IFERROR(SUM((D5/B5)-1),0) -> -0.11006218 | D5: 35351 | E5: =IFERROR(SUM((F5/D5)-1),0) -> -0.027778564 | F5: 34369 | G5: =IFERROR(SUM((H5/F5)-1),0) -> 0.080741366 | H5: 37144 | J5: Valor_de_mercado/Firma | K5: =K2*L2 -> 505693634000 | L5: =K19/K15 -> 0.37181238 | M5: MARGEM OPERACIONAL | N5: RM | O5: =O3+0.01 -> 0.149
A6: ▸Aplicações interfinanceiras de liquidez | B6: 357134 | C6: =IFERROR(SUM((D6/B6)-1),0) -> -0.1248467 | D6: 312547 | E6: =IFERROR(SUM((F6/D6)-1),0) -> 0.071205291 | F6: 334802 | G6: =IFERROR(SUM((H6/F6)-1),0) -> 0.016684488 | H6: 340388 | J6: Patrimônio líq | K6: {=IFERROR(INDEX(Indicador_Ações[], MATCH($J$2, Indicador_Ações[Stock], 0), MATCH(Indicador_Ações[[#HEADERS],[patrimonio_liquido]], Indicador_Ações[#HEADERS], 0)),"")} -> 207648000000 | L6: =ABS(K22/SUM(K13,K18)) -> 0.35668011 | M6: Índice de eficiência | N6: KE | O6: =O3+O4*(O5-O3) -> 0.149
J7: Capital de terceiros (equiv. Dívida bruta) | L7: =K25/L2 -> 4.227208 | M7: LPA | N7: Excess Return
A8: Ativos financeiros | B8: =SUM(B9) -> 1061659 | C8: =IFERROR(SUM((D8/B8)-1),0) -> 0.059377823 | D8: =SUM(D9) -> 1124698 | E8: =IFERROR(SUM((F8/D8)-1),0) -> -0.10786985 | F8: =SUM(F9) -> 1003377 | G8: =IFERROR(SUM((H8/F8)-1),0) -> -0.0046343498 | H8: =SUM(H9) -> 998727 | J8: Captação Total Media ≈ Dív bruta | K8: =SUM(SUM(B28,D28,F28,H28),SUM(B31,D31,F31,H31),SUM(B35,D35,F35,H35),SUM(B38,D38,F38,H38))/4*K3 -> 2326822000000 | L8: =K19/L2 -> 6.3706028 | M8: ROPA | N8: g | O8: =L12*(1-L10) -> 0.071423756
A9: ▸Títulos e Valores Mobiliários e Derivativos | B9: 1061659 | C9: =IFERROR(SUM((D9/B9)-1),0) -> 0.059377823 | D9: 1124698 | E9: =IFERROR(SUM((F9/D9)-1),0) -> -0.10786985 | F9: 1003377 | G9: =IFERROR(SUM((H9/F9)-1),0) -> -0.0046343498 | H9: 998727 | J9: Qualidade da carteira (equiv. Dív líq) | L9: {=IFERROR(INDEX(L23*K3,0)/L2,"")} -> 2.8822244 | M9: DPA Liquido | N9: PL_Proj | O9: =K6*(1+O8) -> 222479000000
J10: Carteira Crédito Media ≈ Dív líq | K10: =SUM(B15,D15,F15,H15)/4*K3 -> 1064922250000 | L10: =L9/L7 -> 0.68182696 | M10: PAYOUT | N10: Roe_Proj | O10: 0.22
